Workbook
Name SegmentaçãodeDados_Categoria: #N/A
Name SegmentaçãodeDados_Categoria1: #N/A
Name SegmentaçãodeDados_Fornecedor: #N/A
Name SegmentaçãodeDados_Mês_Falta: #N/A
Name SegmentaçãodeDados_Unidade: #N/A
Name SegmentaçãodeDados_Unidade1: #N/A

Sheet Planilha1
A1: Mês de referência para faturamento | B1: 45689
A3: Contagem de Contrato | B3: Rótulos de Coluna
A4: Rótulos de Linha | B4: Verzani | C4: Total Geral
A5: Campo Limpo | B5: 5 | C5: 5
A6: Limpeza | B6: 1 | C6: 1
A7: Manutenção | B7: 1 | C7: 1
A8: PMOC | B8: 1 | C8: 1
A9: Portaria | B9: 1 | C9: 1
A10: Vigilância | B10: 1 | C10: 1
A11: Shopping Parque Dom Pedro | B11: 6 | C11: 6
A12: Limpeza | B12: 1 | C12: 1
A13: Manutenção | B13: 1 | C13: 1
A14: PMOC | B14: 1 | C14: 1
A15: Portaria | B15: 1 | C15: 1
A16: Vigilância | B16: 1 | C16: 1
... A20: Total Geral | B20: 12 | C20: 12

Sheet Planilha2

Sheet Planilha4

Sheet Planilha5
A4: Soma de Desconto SLA Mês
A5: -291042.2

Sheet tabShoppingsEmails
A1: Shopping | B1: E-mails consolidados | C1: E-mails teste
A2: Amazonas Shopping | B2: andrezza.gaona@allos.co; karen.lima@allos.co; larissa.enes@allos.co; roberto.filho@allos.co; gregori.saavedra@allos.co; pedro.mendes@allos.co
A3: Shopping da Bahia | B3: leidiane.santos@allos.co; antonio.carvalho@allos.co; jose.azevedo@allos.co; jose.fortes@allos.co; mauricio.cerqueira@allos.co; joeval.souza@allos.co; adolfo.klein@allos.co; adson.santos@allos.co; gilson.souza@allos.co
A4: Bangu Shopping | B4: alex.costa@allos.co; victor.fortunato@allos.co; valeria.grajauskas@allos.co; nathally.santos@allos.co; paulo.assis@allos.co; michele.ramos@allos.co; teste@allos.co
A5: Boulevard Bauru | B5: kelly.bezerrra@boulevardshoppingbauru.com.br; yumi.leite@boulevardshoppingbauru.com.br; murillo.rosa@boulevardshoppingbauru.com.br; fabio.correa@boulevardshoppingbauru.com.br; higor.carneiro@boulevardshoppingbauru.com.br
A6: Boulevard Belém | B6: yugnarley.cintra@allos.co; jose.alfaia@allos.co; joelma.muniz@allos.co; jaqueline.silva@allos.co; alan.rodriguez@allos.co; favacho.junior@allos.co; ana.deoliveira@allos.co
A7: Boulevard BH | B7: carla.costa@allos.co; carla.mairinck@allos.co; davidson.pelolungo@allos.co; mariana.almeida@allos.co; denilson.sanches@allos.co; cassio.costa@allos.co; maressa.oliveira@allos.co
A8: Shopping Campo Grande | B8: wilson.lobo@allos.co; murillo.meyer@allos.co; alexandre.ramos@allos.co; ludimila.machado@allos.co
A9: Shopping Campo Limpo | B9: vania.assis@allos.co; gabriela.queiroz@allos.co; camila.pontes@allos.co; fabio.gurjao@allos.co; silvia.machado@allos.co; ricardo.santos@allos.co; fabio.correa@allos.co
A10: Carioca Shopping | B10: david.souza@allos.co; bruna.wanzeler@allos.co; priscilla.souza@allos.co; julio.spinelli@allos.co; andressa.vieira@allos.co; gd_geop.cariocashopping@allos.co; alessandro.gomes@allos.co
A11: Cariri Shopping | B11: rafaela.portilho@caririshopping.com.br; brenda.brito@caririshopping.com.br; vitoria.silva@caririshopping.com.br; emilly.santos@caririshopping.com.br; ana.andrade@caririshopping.com.br; jesualdo.farias@caririshopping.com.br
A12: Catuaí Shopping Londrina | B12: willian.elsner@allos.co; erminia.wada@allos.co; everton.stock@allos.co; giovani.junior@allos.co; tienne.rezende@allos.co
A13: Catuaí Shopping Maringá | B13: sandra.sakamoto@allos.co; marcelo.mizuta@allos.co; emerson.junior@allos.co; daniela.aldrovande@allos.co; lindomar.freitas@allos.co; jonas.godeny@allos.co elaine.oliveira@allos.co
... A50: Shopping Villa Lobos | B50: renan.mattos@allos.co; rita.silva@allos.co; kathleen.hoveler@allos.co; wellington.novaes@allos.co;alberto.oliveira@allos.co

Sheet Faturamento SP2
A1: Data de Envio | B1: Enviou/Retornou a Medição? | C1: Unidade | D1: Categoria | E1: Fornecedor | F1: HC Organograma | G1: HC Planilha | H1: Dias Faltas | I1: Horas Atrasos | J1: Valor Planilha | K1: Desconto de faltas solicitado pelo fornecedor | L1: Desconto Falta Validado Atlas | M1: Desconto de atrasos solicitado pelo fornecedor | N1: Desconto Atrasos Validado Atlas | O1: Desconto SLA Mês | P1: Desconto SLA Retroativo | Q1: Desconto Equipamentos | R1: Prêmio Assiduidade | S1: Outros descontos | T1: Vai descontar SLA? | U1: Valor mensal final | V1: Taxa de prorrogação do prazo pagamento | W1: Valor mensal com prorrogação do prazo pagamento | X1: Retroativo de dissídio | Y1: Parcela (x/x) | Z1: Mês de referência para faturamento | AA1: Mês de emissão da NF | AB1: Extras Solicitado pelo fornecedor | AC1: Valor extras validado Atlas | AD1: Valor NF Extra | AE1: NF enviada sistema? | AF1: Valor NF | AG1: NF ok? | AH1: SEFIP Enviada Sistema? | AI1: Saving Faltas | AJ1: Saving Extras | AK1: Deduções Totais | AL1: Observações | AM1: E-mail
B2: Sim | C2: Shopping Villagio Caxias | D2: Limpeza | E2: GPS | F2: 25 | G2: 30 | H2: 169 | I2: 0 | J2: =209575.27 -> 209575.27 | K2: 0 | L2: -32713.7 | M2: 0 | N2: 0 | O2: -2095.75 | P2: 0 | Q2: 0 | R2: =208154.6-J2 -> -1420.67 | S2: 0 | T2: Sim | U2: =(J2+L2+Q2+R2+S2+N2)+IF(T2="Sim",O2+P2,0) -> 173345.15 | W2: =IF(J2="","",U2*(1+V2)) -> 173345.15 | Z2: 45658 | AA2: {=IFERROR( IF( _xlfn.XLOOKUP( 1, ( ('Condição de Faturamento'!$A$2:$A$1000 = Tabela1[[#This Row],[Unidade]]) * ('Condição de Faturamento'!$B$2:$B$1000 = Tabela1[[#This Row],[Categoria]]) * ('Condição de Faturamento'!$C$2:$C$1000 = Tabela1[[#This Row],[Fornecedor]]) ), 'Condição de Faturamento'!$D$2:$D$1000 ) = "Emissão no mês da prestação do serviço", Tabela1[[#This Row],[Mês de referência para faturamento]], DATE( YEAR(Tabela1[[#This Row],[Mês de referência para faturamento]]), MONTH(Tabela1[[#This Row],[Mês de referência para faturamento]]) + 1, DAY(Tabela1[[#This Row],[Mês de referência para faturamento]]) ) ), DATE( YEAR(Tabela1[[#This Row],[Mês de referência para faturamento]]), MONTH(Tabela1[[#This Row],[Mês de referência para faturamento]]) + 1, DAY(Tabela1[[#This Row],[Mês de referência para faturamento]]) ) )} -> 45689 | AI2: =K2-L2 -> 32713.7 | AJ2: =AB2-AC2 -> 0 | AK2: =J2-U2 -> 36230.12 | AM2: =_xlfn.XLOOKUP(Tabela1[[#This Row],[Unidade]],tabShoppingsEmails[Shopping],tabShoppingsEmails[E-mails consolidados]) -> patricia.benvenuti@allos.co; ludmila.fachin@allos.co; emerson.silveira@allos.co; bruna.zanella@allos.co; wallace.nascimento@allos.co; juliana.slomp@allos.co
B3: Sim | C3: Shopping Villagio Caxias | D3: Limpeza | E3: GPS | F3: 25 | G3: 30 | H3: 128 | I3: 0 | J3: =209575.27 -> 209575.27 | K3: 0 | L3: -25078.52 | M3: 0 | N3: 0 | O3: -2095.75 | P3: 0 | Q3: 0 | R3: =208509.76-J3 -> -1065.51 | S3: 0 | T3: Sim | U3: =(J3+L3+Q3+R3+S3+N3)+IF(T3="Sim",O3+P3,0) -> 181335.49 | W3: =IF(J3="","",U3*(1+V3)) -> 181335.49 | Z3: 45689 | AA3: {=IFERROR( IF( _xlfn.XLOOKUP( 1, ( ('Condição de Faturamento'!$A$2:$A$1000 = Tabela1[[#This Row],[Unidade]]) * ('Condição de Faturamento'!$B$2:$B$1000 = Tabela1[[#This Row],[Categoria]]) * ('Condição de Faturamento'!$C$2:$C$1000 = Tabela1[[#This Row],[Fornecedor]]) ), 'Condição de Faturamento'!$D$2:$D$1000 ) = "Emissão no mês da prestação do serviço", Tabela1[[#This Row],[Mês de referência para faturamento]], DATE( YEAR(Tabela1[[#This Row],[Mês de referência para faturamento]]), MONTH(Tabela1[[#This Row],[Mês de referência para faturamento]]) + 1, DAY(Tabela1[[#This Row],[Mês de referência para faturamento]]) ) ), DATE( YEAR(Tabela1[[#This Row],[Mês de referência para faturamento]]), MONTH(Tabela1[[#This Row],[Mês de referência para faturamento]]) + 1, DAY(Tabela1[[#This Row],[Mês de referência para faturamento]]) ) )} -> 45717 | AI3: =K3-L3 -> 25078.52 | AJ3: =AB3-AC3 -> 0 | AK3: =J3-U3 -> 28239.78 | AM3: =_xlfn.XLOOKUP(Tabela1[[#This Row],[Unidade]],tabShoppingsEmails[Shopping],tabShoppingsEmails[E-mails consolidados]) -> patricia.benvenuti@allos.co; ludmila.fachin@allos.co; emerson.silveira@allos.co; bruna.zanella@allos.co; wallace.nascimento@allos.co; juliana.slomp@allos.co
B4: Sim | C4: Shopping Villagio Caxias | D4: Limpeza | E4: GPS | F4: 25 | G4: 30 | H4: 68 | I4: 0 | J4: 222827.16 | K4: 0 | L4: -15434.14 | M4: 0 | N4: 0 | O4: -2599.65 | P4: 0 | Q4: 0 | R4: =221288.13-J4 -> -1539.03 | S4: 0 | T4: Sim | U4: =(J4+L4+Q4+R4+S4+N4)+IF(T4="Sim",O4+P4,0) -> 203254.34 | W4: =IF(J4="","",U4*(1+V4)) -> 203254.34 | X4: 22427.211 | Y4: 1.1 | Z4: 45717 | AA4: {=IFERROR( IF( _xlfn.XLOOKUP( 1, ( ('Condição de Faturamento'!$A$2:$A$1000 = Tabela1[[#This Row],[Unidade]]) * ('Condição de Faturamento'!$B$2:$B$1000 = Tabela1[[#This Row],[Categoria]]) * ('Condição de Faturamento'!$C$2:$C$1000 = Tabela1[[#This Row],[Fornecedor]]) ), 'Condição de Faturamento'!$D$2:$D$1000 ) = "Emissão no mês da prestação do serviço", Tabela1[[#This Row],[Mês de referência para faturamento]], DATE( YEAR(Tabela1[[#This Row],[Mês de referência para faturamento]]), MONTH(Tabela1[[#This Row],[Mês de referência para faturamento]]) + 1, DAY(Tabela1[[#This Row],[Mês de referência para faturamento]]) ) ), DATE( YEAR(Tabela1[[#This Row],[Mês de referência para faturamento]]), MONTH(Tabela1[[#This Row],[Mês de referência para faturamento]]) + 1, DAY(Tabela1[[#This Row],[Mês de referência para faturamento]]) ) )} -> 45748 | AB4: 4131.1831 | AC4: 4131.1831 | AI4: =K4-L4 -> 15434.14 | AJ4: =AB4-AC4 -> 0 | AK4: =J4-U4 -> 19572.82 | AM4: =_xlfn.XLOOKUP(Tabela1[[#This Row],[Unidade]],tabShoppingsEmails[Shopping],tabShoppingsEmails[E-mails consolidados]) -> patricia.benvenuti@allos.co; ludmila.fachin@allos.co; emerson.silveira@allos.co; bruna.zanella@allos.co; wallace.nascimento@allos.co; juliana.slomp@allos.co
B5: Sim | C5: Shopping Villagio Caxias | D5: Limpeza | E5: GPS | F5: 25 | G5: 30 | H5: 66 | I5: 0 | J5: 222827.16 | K5: 0 | L5: -14428.83 | M5: 0 | N5: 0 | O5: -2971.03 | P5: 0 | Q5: 0 | R5: =222353.61-J5 -> -473.55 | S5: 0 | T5: Sim | U5: =(J5+L5+Q5+R5+S5+N5)+IF(T5="Sim",O5+P5,0) -> 204953.75 | W5: =IF(J5="","",U5*(1+V5)) -> 204953.75 | Z5: 45748 | AA5: {=IFERROR( IF( _xlfn.XLOOKUP( 1, ( ('Condição de Faturamento'!$A$2:$A$1000 = Tabela1[[#This Row],[Unidade]]) * ('Condição de Faturamento'!$B$2:$B$1000 = Tabela1[[#This Row],[Categoria]]) * ('Condição de Faturamento'!$C$2:$C$1000 = Tabela1[[#This Row],[Fornecedor]]) ), 'Condição de Faturamento'!$D$2:$D$1000 ) = "Emissão no mês da prestação do serviço", Tabela1[[#This Row],[Mês de referência para faturamento]], DATE( YEAR(Tabela1[[#This Row],[Mês de referência para faturamento]]), MONTH(Tabela1[[#This Row],[Mês de referência para faturamento]]) + 1, DAY(Tabela1[[#This Row],[Mês de referência para faturamento]]) ) ), DATE( YEAR(Tabela1[[#This Row],[Mês de referência para faturamento]]), MONTH(Tabela1[[#This Row],[Mês de referência para faturamento]]) + 1, DAY(Tabela1[[#This Row],[Mês de referência para faturamento]]) ) )} -> 45778 | AB5: 7190.6889 | AC5: 7190.6889 | AI5: =K5-L5 -> 14428.83 | AJ5: =AB5-AC5 -> 0 | AK5: =J5-U5 -> 17873.41 | AM5: =_xlfn.XLOOKUP(Tabela1[[#This Row],[Unidade]],tabShoppingsEmails[Shopping],tabShoppingsEmails[E-mails consolidados]) -> patricia.benvenuti@allos.co; ludmila.fachin@allos.co; emerson.silveira@allos.co; bruna.zanella@allos.co; wallace.nascimento@allos.co; juliana.slomp@allos.co
A6: 45817 | B6: Sim | C6: Shopping Villagio Caxias | D6: Limpeza | E6: GPS | F6: 25 | G6: 30 | H6: 94 | I6: 0 | J6: 222827.16 | K6: 0 | L6: -20485.66 | M6: 0 | N6: 0 | O6: -2971.03 | P6: 0 | Q6: 0 | R6: =221880.06-Tabela1[[#This Row],[Valor Planilha]] -> -947.1 | S6: -3278.08 | T6: Sim | U6: =(J6+L6+Q6+R6+S6+N6)+IF(T6="Sim",O6+P6,0) -> 195145.29 | W6: =IF(J6="","",U6*(1+V6)) -> 195145.29 | Z6: 45778 | AA6: {=IFERROR( IF( _xlfn.XLOOKUP( 1, ( ('Condição de Faturamento'!$A$2:$A$1000 = Tabela1[[#This Row],[Unidade]]) * ('Condição de Faturamento'!$B$2:$B$1000 = Tabela1[[#This Row],[Categoria]]) * ('Condição de Faturamento'!$C$2:$C$1000 = Tabela1[[#This Row],[Fornecedor]]) ), 'Condição de Faturamento'!$D$2:$D$1000 ) = "Emissão no mês da prestação do serviço", Tabela1[[#This Row],[Mês de referência para faturamento]], DATE( YEAR(Tabela1[[#This Row],[Mês de referência para faturamento]]), MONTH(Tabela1[[#This Row],[Mês de referência para faturamento]]) + 1, DAY(Tabela1[[#This Row],[Mês de referência para faturamento]]) ) ), DATE( YEAR(Tabela1[[#This Row],[Mês de referência para faturamento]]), MONTH(Tabela1[[#This Row],[Mês de referência para faturamento]]) + 1, DAY(Tabela1[[#This Row],[Mês de referência para faturamento]]) ) )} -> 45809 | AB6: 6243.8189 | AC6: 6243.8189 | AI6: =K6-L6 -> 20485.66 | AJ6: =AB6-AC6 -> 0 | AK6: =J6-U6 -> 27681.87 | AM6: =_xlfn.XLOOKUP(Tabela1[[#This Row],[Unidade]],tabShoppingsEmails[Shopping],tabShoppingsEmails[E-mails consolidados]) -> patricia.benvenuti@allos.co; ludmila.fachin@allos.co; emerson.silveira@allos.co; bruna.zanella@allos.co; wallace.nascimento@allos.co; juliana.slomp@allos.co
A7: 45842 | B7: Sim | C7: Shopping Villagio Caxias | D7: Limpeza | E7: GPS | F7: 25 | G7: 30 | H7: 63 | I7: 0 | J7: 222827.16 | K7: 0 | L7: -13312.08 | M7: 0 | N7: 0 | O7: -2228.27 | P7: 0 | Q7: 0 | R7: =222116.84-Tabela1[[#This Row],[Valor Planilha]] -> -710.32 | S7: 0 | T7: Sim | U7: =(J7+L7+Q7+R7+S7+N7)+IF(T7="Sim",O7+P7,0) -> 206576.49 | W7: =IF(J7="","",U7*(1+V7)) -> 206576.49 | Z7: 45809 | AA7: {=IFERROR( IF( _xlfn.XLOOKUP( 1, ( ('Condição de Faturamento'!$A$2:$A$1000 = Tabela1[[#This Row],[Unidade]]) * ('Condição de Faturamento'!$B$2:$B$1000 = Tabela1[[#This Row],[Categoria]]) * ('Condição de Faturamento'!$C$2:$C$1000 = Tabela1[[#This Row],[Fornecedor]]) ), 'Condição de Faturamento'!$D$2:$D$1000 ) = "Emissão no mês da prestação do serviço", Tabela1[[#This Row],[Mês de referência para faturamento]], DATE( YEAR(Tabela1[[#This Row],[Mês de referência para faturamento]]), MONTH(Tabela1[[#This Row],[Mês de referência para faturamento]]) + 1, DAY(Tabela1[[#This Row],[Mês de referência para faturamento]]) ) ), DATE( YEAR(Tabela1[[#This Row],[Mês de referência para faturamento]]), MONTH(Tabela1[[#This Row],[Mês de referência para faturamento]]) + 1, DAY(Tabela1[[#This Row],[Mês de referência para faturamento]]) ) )} -> 45839 | AB7: 3165.6615 | AC7: 3165.6615 | AI7: =K7-L7 -> 13312.08 | AJ7: =AB7-AC7 -> 0 | AK7: =J7-U7 -> 16250.67 | AM7: =_xlfn.XLOOKUP(Tabela1[[#This Row],[Unidade]],tabShoppingsEmails[Shopping],tabShoppingsEmails[E-mails consolidados]) -> patricia.benvenuti@allos.co; ludmila.fachin@allos.co; emerson.silveira@allos.co; bruna.zanella@allos.co; wallace.nascimento@allos.co; juliana.slomp@allos.co
A8: 45874 | B8: Sim | C8: Shopping Villagio Caxias | D8: Limpeza | E8: GPS | F8: 25 | G8: 30 | H8: 74 | I8: 5.66 | J8: 222827.16 | K8: 0 | L8: -15515.18 | M8: 0 | N8: -199.3452 | O8: -2228.27 | P8: 0 | Q8: 0 | R8: =221288.13-Tabela1[[#This Row],[Valor Planilha]] -> -1539.03 | S8: 0 | T8: Sim | U8: =(J8+L8+Q8+R8+S8+N8)+IF(T8="Sim",O8+P8,0) -> 203345.33 | W8: =IF(J8="","",U8*(1+V8)) -> 203345.33 | Z8: 45839 | AA8: {=IFERROR( IF( _xlfn.XLOOKUP( 1, ( ('Condição de Faturamento'!$A$2:$A$1000 = Tabela1[[#This Row],[Unidade]]) * ('Condição de Faturamento'!$B$2:$B$1000 = Tabela1[[#This Row],[Categoria]]) * ('Condição de Faturamento'!$C$2:$C$1000 = Tabela1[[#This Row],[Fornecedor]]) ), 'Condição de Faturamento'!$D$2:$D$1000 ) = "Emissão no mês da prestação do serviço", Tabela1[[#This Row],[Mês de referência para faturamento]], DATE( YEAR(Tabela1[[#This Row],[Mês de referência para faturamento]]), MONTH(Tabela1[[#This Row],[Mês de referência para faturamento]]) + 1, DAY(Tabela1[[#This Row],[Mês de referência para faturamento]]) ) ), DATE( YEAR(Tabela1[[#This Row],[Mês de referência para faturamento]]), MONTH(Tabela1[[#This Row],[Mês de referência para faturamento]]) + 1, DAY(Tabela1[[#This Row],[Mês de referência para faturamento]]) ) )} -> 45870 | AB8: 3241.2739 | AC8: 3241.2739 | AI8: =K8-L8 -> 15515.18 | AJ8: =AB8-AC8 -> 0 | AK8: =J8-U8 -> 19481.825 | AM8: =_xlfn.XLOOKUP(Tabela1[[#This Row],[Unidade]],tabShoppingsEmails[Shopping],tabShoppingsEmails[E-mails consolidados]) -> patricia.benvenuti@allos.co; ludmila.fachin@allos.co; emerson.silveira@allos.co; bruna.zanella@allos.co; wallace.nascimento@allos.co; juliana.slomp@allos.co
A9: 45908 | B9: Sim | C9: Shopping Villagio Caxias | D9: Limpeza | E9: GPS | F9: 25 | G9: 30 | H9: 96 | I9: 0 | J9: 222827.16 | K9: 0 | L9: -19896.09 | M9: 0 | N9: 0 | O9: -2228.27 | P9: 0 | Q9: 0 | R9: =221761.66-Tabela1[[#This Row],[Valor Planilha]] -> -1065.5 | S9: 0 | T9: Sim | U9: =(J9+L9+Q9+R9+S9+N9)+IF(T9="Sim",O9+P9,0) -> 199637.3 | W9: =IF(J9="","",U9*(1+V9)) -> 199637.3 | Z9: 45870 | AA9: {=IFERROR( IF( _xlfn.XLOOKUP( 1, ( ('Condição de Faturamento'!$A$2:$A$1000 = Tabela1[[#This Row],[Unidade]]) * ('Condição de Faturamento'!$B$2:$B$1000 = Tabela1[[#This Row],[Categoria]]) * ('Condição de Faturamento'!$C$2:$C$1000 = Tabela1[[#This Row],[Fornecedor]]) ), 'Condição de Faturamento'!$D$2:$D$1000 ) = "Emissão no mês da prestação do serviço", Tabela1[[#This Row],[Mês de referência para faturamento]], DATE( YEAR(Tabela1[[#This Row],[Mês de referência para faturamento]]), MONTH(Tabela1[[#This Row],[Mês de referência para faturamento]]) + 1, DAY(Tabela1[[#This Row],[Mês de referência para faturamento]]) ) ), DATE( YEAR(Tabela1[[#This Row],[Mês de referência para faturamento]]), MONTH(Tabela1[[#This Row],[Mês de referência para faturamento]]) + 1, DAY(Tabela1[[#This Row],[Mês de referência para faturamento]]) ) )} -> 45901 | AB9: 2201.1872 | AC9: 2201.1872 | AI9: =K9-L9 -> 19896.09 | AJ9: =AB9-AC9 -> 0 | AK9: =J9-U9 -> 23189.86 | AM9: =_xlfn.XLOOKUP(Tabela1[[#This Row],[Unidade]],tabShoppingsEmails[Shopping],tabShoppingsEmails[E-mails consolidados]) -> patricia.benvenuti@allos.co; ludmila.fachin@allos.co; emerson.silveira@allos.co; bruna.zanella@allos.co; wallace.nascimento@allos.co; juliana.slomp@allos.co
A10: 45936 | B10: Sim | C10: Shopping Villagio Caxias | D10: Limpeza | E10: GPS | F10: 25 | G10: 30 | H10: 12 | I10: 3.33 | J10: 222827.16 | K10: 0 | L10: -2534.43 | M10: 0 | N10: -112.2126 | O10: -2599.65 | P10: 0 | Q10: 0 | R10: =221761.66-Tabela1[[#This Row],[Valor Planilha]] -> -1065.5 | S10: 0 | T10: Sim | U10: =(J10+L10+Q10+R10+S10+N10)+IF(T10="Sim",O10+P10,0) -> 216515.37 | W10: =IF(J10="","",U10*(1+V10)) -> 216515.37 | Z10: 45901 | AA10: {=IFERROR( IF( _xlfn.XLOOKUP( 1, ( ('Condição de Faturamento'!$A$2:$A$1000 = Tabela1[[#This Row],[Unidade]]) * ('Condição de Faturamento'!$B$2:$B$1000 = Tabela1[[#This Row],[Categoria]]) * ('Condição de Faturamento'!$C$2:$C$1000 = Tabela1[[#This Row],[Fornecedor]]) ), 'Condição de Faturamento'!$D$2:$D$1000 ) = "Emissão no mês da prestação do serviço", Tabela1[[#This Row],[Mês de referência para faturamento]], DATE( YEAR(Tabela1[[#This Row],[Mês de referência para faturamento]]), MONTH(Tabela1[[#This Row],[Mês de referência para faturamento]]) + 1, DAY(Tabela1[[#This Row],[Mês de referência para faturamento]]) ) ), DATE( YEAR(Tabela1[[#This Row],[Mês de referência para faturamento]]), MONTH(Tabela1[[#This Row],[Mês de referência para faturamento]]) + 1, DAY(Tabela1[[#This Row],[Mês de referência para faturamento]]) ) )} -> 45931 | AB10: 3300.189 | AC10: 3300.189 | AI10: =K10-L10 -> 2534.43 | AJ10: =AB10-AC10 -> 0 | AK10: =J10-U10 -> 6311.7926 | AM10: =_xlfn.XLOOKUP(Tabela1[[#This Row],[Unidade]],tabShoppingsEmails[Shopping],tabShoppingsEmails[E-mails consolidados]) -> patricia.benvenuti@allos.co; ludmila.fachin@allos.co; emerson.silveira@allos.co; bruna.zanella@allos.co; wallace.nascimento@allos.co; juliana.slomp@allos.co
C11: Shopping Villagio Caxias | D11: Limpeza | E11: GPS | F11: 25 | U11: =(J11+L11+Q11+R11+S11+N11)+IF(T11="Sim",O11+P11,0) -> 0 | W11: =IF(J11="","",U11*(1+V11)) | Z11: 45931 | AA11: {=IFERROR( IF( _xlfn.XLOOKUP( 1, ( ('Condição de Faturamento'!$A$2:$A$1000 = Tabela1[[#This Row],[Unidade]]) * ('Condição de Faturamento'!$B$2:$B$1000 = Tabela1[[#This Row],[Categoria]]) * ('Condição de Faturamento'!$C$2:$C$1000 = Tabela1[[#This Row],[Fornecedor]]) ), 'Condição de Faturamento'!$D$2:$D$1000 ) = "Emissão no mês da prestação do serviço", Tabela1[[#This Row],[Mês de referência para faturamento]], DATE( YEAR(Tabela1[[#This Row],[Mês de referência para faturamento]]), MONTH(Tabela1[[#This Row],[Mês de referência para faturamento]]) + 1, DAY(Tabela1[[#This Row],[Mês de referência para faturamento]]) ) ), DATE( YEAR(Tabela1[[#This Row],[Mês de referência para faturamento]]), MONTH(Tabela1[[#This Row],[Mês de referência para faturamento]]) + 1, DAY(Tabela1[[#This Row],[Mês de referência para faturamento]]) ) )} -> 45962 | AI11: =K11-L11 -> 0 | AJ11: =AB11-AC11 -> 0 | AK11: =J11-U11 -> 0 | AM11: =_xlfn.XLOOKUP(Tabela1[[#This Row],[Unidade]],tabShoppingsEmails[Shopping],tabShoppingsEmails[E-mails consolidados]) -> patricia.benvenuti@allos.co; ludmila.fachin@allos.co; emerson.silveira@allos.co; bruna.zanella@allos.co; wallace.nascimento@allos.co; juliana.slomp@allos.co
C12: Shopping Villagio Caxias | D12: Limpeza | E12: GPS | F12: 25 | U12: =(J12+L12+Q12+R12+S12+N12)+IF(T12="Sim",O12+P12,0) -> 0 | W12: =IF(J12="","",U12*(1+V12)) | Z12: 45962 | AA12: {=IFERROR( IF( _xlfn.XLOOKUP( 1, ( ('Condição de Faturamento'!$A$2:$A$1000 = Tabela1[[#This Row],[Unidade]]) * ('Condição de Faturamento'!$B$2:$B$1000 = Tabela1[[#This Row],[Categoria]]) * ('Condição de Faturamento'!$C$2:$C$1000 = Tabela1[[#This Row],[Fornecedor]]) ), 'Condição de Faturamento'!$D$2:$D$1000 ) = "Emissão no mês da prestação do serviço", Tabela1[[#This Row],[Mês de referência para faturamento]], DATE( YEAR(Tabela1[[#This Row],[Mês de referência para faturamento]]), MONTH(Tabela1[[#This Row],[Mês de referência para faturamento]]) + 1, DAY(Tabela1[[#This Row],[Mês de referência para faturamento]]) ) ), DATE( YEAR(Tabela1[[#This Row],[Mês de referência para faturamento]]), MONTH(Tabela1[[#This Row],[Mês de referência para faturamento]]) + 1, DAY(Tabela1[[#This Row],[Mês de referência para faturamento]]) ) )} -> 45992 | AI12: =K12-L12 -> 0 | AJ12: =AB12-AC12 -> 0 | AK12: =J12-U12 -> 0 | AM12: =_xlfn.XLOOKUP(Tabela1[[#This Row],[Unidade]],tabShoppingsEmails[Shopping],tabShoppingsEmails[E-mails consolidados]) -> patricia.benvenuti@allos.co; ludmila.fachin@allos.co; emerson.silveira@allos.co; bruna.zanella@allos.co; wallace.nascimento@allos.co; juliana.slomp@allos.co
C13: Shopping Villagio Caxias | D13: Limpeza | E13: GPS | F13: 25 | U13: =(J13+L13+Q13+R13+S13+N13)+IF(T13="Sim",O13+P13,0) -> 0 | W13: =IF(J13="","",U13*(1+V13)) | Z13: 45992 | AA13: {=IFERROR( IF( _xlfn.XLOOKUP( 1, ( ('Condição de Faturamento'!$A$2:$A$1000 = Tabela1[[#This Row],[Unidade]]) * ('Condição de Faturamento'!$B$2:$B$1000 = Tabela1[[#This Row],[Categoria]]) * ('Condição de Faturamento'!$C$2:$C$1000 = Tabela1[[#This Row],[Fornecedor]]) ), 'Condição de Faturamento'!$D$2:$D$1000 ) = "Emissão no mês da prestação do serviço", Tabela1[[#This Row],[Mês de referência para faturamento]], DATE( YEAR(Tabela1[[#This Row],[Mês de referência para faturamento]]), MONTH(Tabela1[[#This Row],[Mês de referência para faturamento]]) + 1, DAY(Tabela1[[#This Row],[Mês de referência para faturamento]]) ) ), DATE( YEAR(Tabela1[[#This Row],[Mês de referência para faturamento]]), MONTH(Tabela1[[#This Row],[Mês de referência para faturamento]]) + 1, DAY(Tabela1[[#This Row],[Mês de referência para faturamento]]) ) )} -> 46023 | AI13: =K13-L13 -> 0 | AJ13: =AB13-AC13 -> 0 | AK13: =J13-U13 -> 0 | AM13: =_xlfn.XLOOKUP(Tabela1[[#This Row],[Unidade]],tabShoppingsEmails[Shopping],tabShoppingsEmails[E-mails consolidados]) -> patricia.benvenuti@allos.co; ludmila.fachin@allos.co; emerson.silveira@allos.co; bruna.zanella@allos.co; wallace.nascimento@allos.co; juliana.slomp@allos.co
B14: Não | C14: Shopping Villagio Caxias | D14: Resíduos | E14: Recicla Engenharia | F14: 3 | G14: 3 | H14: infomação pendente | I14: infomação pendente | J14: 65000 | K14: 0 | M14: 0 | O14: preenchimento pendente | P14: 0 | Q14: 0 | R14: 0 | S14: 0 | U14: =(J14+L14+Q14+R14+S14+N14)+IF(T14="Sim",O14+P14,0) -> 65000 | W14: =IF(J14="","",U14*(1+V14)) -> 65000 | Z14: 45870 | AA14: {=IFERROR( IF( _xlfn.XLOOKUP( 1, ( ('Condição de Faturamento'!$A$2:$A$1000 = Tabela1[[#This Row],[Unidade]]) * ('Condição de Faturamento'!$B$2:$B$1000 = Tabela1[[#This Row],[Categoria]]) * ('Condição de Faturamento'!$C$2:$C$1000 = Tabela1[[#This Row],[Fornecedor]]) ), 'Condição de Faturamento'!$D$2:$D$1000 ) = "Emissão no mês da prestação do serviço", Tabela1[[#This Row],[Mês de referência para faturamento]], DATE( YEAR(Tabela1[[#This Row],[Mês de referência para faturamento]]), MONTH(Tabela1[[#This Row],[Mês de referência para faturamento]]) + 1, DAY(Tabela1[[#This Row],[Mês de referência para faturamento]]) ) ), DATE( YEAR(Tabela1[[#This Row],[Mês de referência para faturamento]]), MONTH(Tabela1[[#This Row],[Mês de referência para faturamento]]) + 1, DAY(Tabela1[[#This Row],[Mês de referência para faturamento]]) ) )} -> 45901 | AI14: =K14-L14 -> 0 | AJ14: =AB14-AC14 -> 0 | AK14: =J14-U14 -> 0 | AM14: =_xlfn.XLOOKUP(Tabela1[[#This Row],[Unidade]],tabShoppingsEmails[Shopping],tabShoppingsEmails[E-mails consolidados]) -> patricia.benvenuti@allos.co; ludmila.fachin@allos.co; emerson.silveira@allos.co; bruna.zanella@allos.co; wallace.nascimento@allos.co; juliana.slomp@allos.co
B15: Não | C15: Shopping Villagio Caxias | D15: Resíduos | E15: Recicla Engenharia | F15: 3 | G15: 3 | H15: infomação pendente | I15: infomação pendente | J15: 65000 | O15: preenchimento pendente | Q15: 0 | R15: 0 | S15: 0 | T15: Não | U15: =(J15+L15+Q15+R15+S15+N15)+IF(T15="Sim",O15+P15,0) -> 65000 | W15: =IF(J15="","",U15*(1+V15)) -> 65000 | Z15: 45901 | AA15: {=IFERROR( IF( _xlfn.XLOOKUP( 1, ( ('Condição de Faturamento'!$A$2:$A$1000 = Tabela1[[#This Row],[Unidade]]) * ('Condição de Faturamento'!$B$2:$B$1000 = Tabela1[[#This Row],[Categoria]]) * ('Condição de Faturamento'!$C$2:$C$1000 = Tabela1[[#This Row],[Fornecedor]]) ), 'Condição de Faturamento'!$D$2:$D$1000 ) = "Emissão no mês da prestação do serviço", Tabela1[[#This Row],[Mês de referência para faturamento]], DATE( YEAR(Tabela1[[#This Row],[Mês de referência para faturamento]]), MONTH(Tabela1[[#This Row],[Mês de referência para faturamento]]) + 1, DAY(Tabela1[[#This Row],[Mês de referência para faturamento]]) ) ), DATE( YEAR(Tabela1[[#This Row],[Mês de referência para faturamento]]), MONTH(Tabela1[[#This Row],[Mês de referência para faturamento]]) + 1, DAY(Tabela1[[#This Row],[Mês de referência para faturamento]]) ) )} -> 45931 | AI15: =K15-L15 -> 0 | AJ15: =AB15-AC15 -> 0 | AK15: =J15-U15 -> 0 | AM15: =_xlfn.XLOOKUP(Tabela1[[#This Row],[Unidade]],tabShoppingsEmails[Shopping],tabShoppingsEmails[E-mails consolidados]) -> patricia.benvenuti@allos.co; ludmila.fachin@allos.co; emerson.silveira@allos.co; bruna.zanella@allos.co; wallace.nascimento@allos.co; juliana.slomp@allos.co
C16: Shopping Villagio Caxias | D16: Resíduos | E16: Recicla Engenharia | F16: 3 | G16: 3 | U16: =(J16+L16+Q16+R16+S16+N16)+IF(T16="Sim",O16+P16,0) -> 0 | Z16: 45931 | AA16: {=IFERROR( IF( _xlfn.XLOOKUP( 1, ( ('Condição de Faturamento'!$A$2:$A$1000 = Tabela1[[#This Row],[Unidade]]) * ('Condição de Faturamento'!$B$2:$B$1000 = Tabela1[[#This Row],[Categoria]]) * ('Condição de Faturamento'!$C$2:$C$1000 = Tabela1[[#This Row],[Fornecedor]]) ), 'Condição de Faturamento'!$D$2:$D$1000 ) = "Emissão no mês da prestação do serviço", Tabela1[[#This Row],[Mês de referência para faturamento]], DATE( YEAR(Tabela1[[#This Row],[Mês de referência para faturamento]]), MONTH(Tabela1[[#This Row],[Mês de referência para faturamento]]) + 1, DAY(Tabela1[[#This Row],[Mês de referência para faturamento]]) ) ), DATE( YEAR(Tabela1[[#This Row],[Mês de referência para faturamento]]), MONTH(Tabela1[[#This Row],[Mês de referência para faturamento]]) + 1, DAY(Tabela1[[#This Row],[Mês de referência para faturamento]]) ) )} -> 45962 | AI16: =K16-L16 -> 0 | AJ16: =AB16-AC16 -> 0 | AK16: =J16-U16 -> 0 | AM16: =_xlfn.XLOOKUP(Tabela1[[#This Row],[Unidade]],tabShoppingsEmails[Shopping],tabShoppingsEmails[E-mails consolidados]) -> patricia.benvenuti@allos.co; ludmila.fachin@allos.co; emerson.silveira@allos.co; bruna.zanella@allos.co; wallace.nascimento@allos.co; juliana.slomp@allos.co
C17: Shopping Villagio Caxias | D17: Resíduos | E17: Recicla Engenharia | F17: 3 | G17: 3 | U17: =(J17+L17+Q17+R17+S17+N17)+IF(T17="Sim",O17+P17,0) -> 0 | Z17: 45962 | AA17: {=IFERROR( IF( _xlfn.XLOOKUP( 1, ( ('Condição de Faturamento'!$A$2:$A$1000 = Tabela1[[#This Row],[Unidade]]) * ('Condição de Faturamento'!$B$2:$B$1000 = Tabela1[[#This Row],[Categoria]]) * ('Condição de Faturamento'!$C$2:$C$1000 = Tabela1[[#This Row],[Fornecedor]]) ), 'Condição de Faturamento'!$D$2:$D$1000 ) = "Emissão no mês da prestação do serviço", Tabela1[[#This Row],[Mês de referência para faturamento]], DATE( YEAR(Tabela1[[#This Row],[Mês de referência para faturamento]]), MONTH(Tabela1[[#This Row],[Mês de referência para faturamento]]) + 1, DAY(Tabela1[[#This Row],[Mês de referência para faturamento]]) ) ), DATE( YEAR(Tabela1[[#This Row],[Mês de referência para faturamento]]), MONTH(Tabela1[[#This Row],[Mês de referência para faturamento]]) + 1, DAY(Tabela1[[#This Row],[Mês de referência para faturamento]]) ) )} -> 45992 | AI17: =K17-L17 -> 0 | AJ17: =AB17-AC17 -> 0 | AK17: =J17-U17 -> 0 | AM17: =_xlfn.XLOOKUP(Tabela1[[#This Row],[Unidade]],tabShoppingsEmails[Shopping],tabShoppingsEmails[E-mails consolidados]) -> patricia.benvenuti@allos.co; ludmila.fachin@allos.co; emerson.silveira@allos.co; bruna.zanella@allos.co; wallace.nascimento@allos.co; juliana.slomp@allos.co
C18: Shopping Villagio Caxias | D18: Resíduos | E18: Recicla Engenharia | F18: 3 | G18: 3 | U18: =(J18+L18+Q18+R18+S18+N18)+IF(T18="Sim",O18+P18,0) -> 0 | Z18: 45992 | AA18: {=IFERROR( IF( _xlfn.XLOOKUP( 1, ( ('Condição de Faturamento'!$A$2:$A$1000 = Tabela1[[#This Row],[Unidade]]) * ('Condição de Faturamento'!$B$2:$B$1000 = Tabela1[[#This Row],[Categoria]]) * ('Condição de Faturamento'!$C$2:$C$1000 = Tabela1[[#This Row],[Fornecedor]]) ), 'Condição de Faturamento'!$D$2:$D$1000 ) = "Emissão no mês da prestação do serviço", Tabela1[[#This Row],[Mês de referência para faturamento]], DATE( YEAR(Tabela1[[#This Row],[Mês de referência para faturamento]]), MONTH(Tabela1[[#This Row],[Mês de referência para faturamento]]) + 1, DAY(Tabela1[[#This Row],[Mês de referência para faturamento]]) ) ), DATE( YEAR(Tabela1[[#This Row],[Mês de referência para faturamento]]), MONTH(Tabela1[[#This Row],[Mês de referência para faturamento]]) + 1, DAY(Tabela1[[#This Row],[Mês de referência para faturamento]]) ) )} -> 46023 | AI18: =K18-L18 -> 0 | AJ18: =AB18-AC18 -> 0 | AK18: =J18-U18 -> 0 | AM18: =_xlfn.XLOOKUP(Tabela1[[#This Row],[Unidade]],tabShoppingsEmails[Shopping],tabShoppingsEmails[E-mails consolidados]) -> patricia.benvenuti@allos.co; ludmila.fachin@allos.co; emerson.silveira@allos.co; bruna.zanella@allos.co; wallace.nascimento@allos.co; juliana.slomp@allos.co
B19: Sim | C19: Shopping Villagio Caxias | D19: Portaria | E19: Veper | F19: 8 | G19: 8 | H19: 0 | I19: 7.42 | J19: 36468.39 | K19: 0 | L19: 0 | M19: 0 | N19: -149.6248 | O19: 0 | P19: 0 | Q19: 0 | R19: 0 | S19: 0 | T19: Sim | U19: =(J19+L19+Q19+R19+S19+N19)+IF(T19="Sim",O19+P19,0) -> 36318.765 | W19: =IF(J19="","",U19*(1+V19)) -> 36318.765 | Z19: 45658 | AA19: {=IFERROR( IF( _xlfn.XLOOKUP( 1, ( ('Condição de Faturamento'!$A$2:$A$1000 = Tabela1[[#This Row],[Unidade]]) * ('Condição de Faturamento'!$B$2:$B$1000 = Tabela1[[#This Row],[Categoria]]) * ('Condição de Faturamento'!$C$2:$C$1000 = Tabela1[[#This Row],[Fornecedor]]) ), 'Condição de Faturamento'!$D$2:$D$1000 ) = "Emissão no mês da prestação do serviço", Tabela1[[#This Row],[Mês de referência para faturamento]], DATE( YEAR(Tabela1[[#This Row],[Mês de referência para faturamento]]), MONTH(Tabela1[[#This Row],[Mês de referência para faturamento]]) + 1, DAY(Tabela1[[#This Row],[Mês de referência para faturamento]]) ) ), DATE( YEAR(Tabela1[[#This Row],[Mês de referência para faturamento]]), MONTH(Tabela1[[#This Row],[Mês de referência para faturamento]]) + 1, DAY(Tabela1[[#This Row],[Mês de referência para faturamento]]) ) )} -> 45689 | AI19: =K19-L19 -> 0 | AJ19: =AB19-AC19 -> 0 | AK19: =J19-U19 -> 149.6248 | AM19: =_xlfn.XLOOKUP(Tabela1[[#This Row],[Unidade]],tabShoppingsEmails[Shopping],tabShoppingsEmails[E-mails consolidados]) -> patricia.benvenuti@allos.co; ludmila.fachin@allos.co; emerson.silveira@allos.co; bruna.zanella@allos.co; wallace.nascimento@allos.co; juliana.slomp@allos.co
B20: Sim | C20: Shopping Villagio Caxias | D20: Portaria | E20: Veper | F20: 8 | G20: 8 | H20: 0 | I20: 19.5 | J20: 36468.39 | K20: 0 | L20: 0 | M20: 0 | N20: -400.42 | O20: -364.68 | P20: 0 | Q20: 0 | R20: 0 | S20: 0 | T20: Sim | U20: =(J20+L20+Q20+R20+S20+N20)+IF(T20="Sim",O20+P20,0) -> 35703.29 | W20: =IF(J20="","",U20*(1+V20)) -> 35703.29 | Z20: 45689 | AA20: {=IFERROR( IF( _xlfn.XLOOKUP( 1, ( ('Condição de Faturamento'!$A$2:$A$1000 = Tabela1[[#This Row],[Unidade]]) * ('Condição de Faturamento'!$B$2:$B$1000 = Tabela1[[#This Row],[Categoria]]) * ('Condição de Faturamento'!$C$2:$C$1000 = Tabela1[[#This Row],[Fornecedor]]) ), 'Condição de Faturamento'!$D$2:$D$1000 ) = "Emissão no mês da prestação do serviço", Tabela1[[#This Row],[Mês de referência para faturamento]], DATE( YEAR(Tabela1[[#This Row],[Mês de referência para faturamento]]), MONTH(Tabela1[[#This Row],[Mês de referência para faturamento]]) + 1, DAY(Tabela1[[#This Row],[Mês de referência para faturamento]]) ) ), DATE( YEAR(Tabela1[[#This Row],[Mês de referência para faturamento]]), MONTH(Tabela1[[#This Row],[Mês de referência para faturamento]]) + 1, DAY(Tabela1[[#This Row],[Mês de referência para faturamento]]) ) )} -> 45717 | AI20: =K20-L20 -> 0 | AJ20: =AB20-AC20 -> 0 | AK20: =J20-U20 -> 765.1 | AM20: =_xlfn.XLOOKUP(Tabela1[[#This Row],[Unidade]],tabShoppingsEmails[Shopping],tabShoppingsEmails[E-mails consolidados]) -> patricia.benvenuti@allos.co; ludmila.fachin@allos.co; emerson.silveira@allos.co; bruna.zanella@allos.co; wallace.nascimento@allos.co; juliana.slomp@allos.co
B21: Sim | C21: Shopping Villagio Caxias | D21: Portaria | E21: Veper | F21: 8 | G21: 8 | H21: 0 | I21: 41.48 | J21: 42452.35 | K21: 0 | L21: 0 | M21: 0 | N21: -992.51533 | O21: -424.52 | P21: 0 | Q21: 0 | R21: =38712.3743513944-J21 -> -3739.9756 | S21: 0 | T21: Sim | U21: =(J21+L21+Q21+R21+S21+N21)+IF(T21="Sim",O21+P21,0) -> 37295.339 | W21: =IF(J21="","",U21*(1+V21)) -> 37295.339 | Z21: 45717 | AA21: {=IFERROR( IF( _xlfn.XLOOKUP( 1, ( ('Condição de Faturamento'!$A$2:$A$1000 = Tabela1[[#This Row],[Unidade]]) * ('Condição de Faturamento'!$B$2:$B$1000 = Tabela1[[#This Row],[Categoria]]) * ('Condição de Faturamento'!$C$2:$C$1000 = Tabela1[[#This Row],[Fornecedor]]) ), 'Condição de Faturamento'!$D$2:$D$1000 ) = "Emissão no mês da prestação do serviço", Tabela1[[#This Row],[Mês de referência para faturamento]], DATE( YEAR(Tabela1[[#This Row],[Mês de referência para faturamento]]), MONTH(Tabela1[[#This Row],[Mês de referência para faturamento]]) + 1, DAY(Tabela1[[#This Row],[Mês de referência para faturamento]]) ) ), DATE( YEAR(Tabela1[[#This Row],[Mês de referência para faturamento]]), MONTH(Tabela1[[#This Row],[Mês de referência para faturamento]]) + 1, DAY(Tabela1[[#This Row],[Mês de referência para faturamento]]) ) )} -> 45748 | AI21: =K21-L21 -> 0 | AJ21: =AB21-AC21 -> 0 | AK21: =J21-U21 -> 5157.011 | AM21: =_xlfn.XLOOKUP(Tabela1[[#This Row],[Unidade]],tabShoppingsEmails[Shopping],tabShoppingsEmails[E-mails consolidados]) -> patricia.benvenuti@allos.co; ludmila.fachin@allos.co; emerson.silveira@allos.co; bruna.zanella@allos.co; wallace.nascimento@allos.co; juliana.slomp@allos.co
A22: 45722 | B22: Sim | C22: Shopping Villagio Caxias | D22: Portaria | E22: Veper | F22: 8 | G22: 8 | H22: 0 | I22: 2.01 | J22: 42452.35 | K22: 0 | L22: 0 | M22: 0 | N22: -48.400133 | O22: -212.26 | P22: 0 | Q22: 0 | R22: =39460.3692248094-Tabela1[[#This Row],[Valor Planilha]] -> -2991.9808 | S22: 0 | T22: Sim | U22: =(J22+L22+Q22+R22+S22+N22)+IF(T22="Sim",O22+P22,0) -> 39199.709 | W22: =IF(J22="","",U22*(1+V22)) -> 39199.709 | Z22: 45748 | AA22: {=IFERROR( IF( _xlfn.XLOOKUP( 1, ( ('Condição de Faturamento'!$A$2:$A$1000 = Tabela1[[#This Row],[Unidade]]) * ('Condição de Faturamento'!$B$2:$B$1000 = Tabela1[[#This Row],[Categoria]]) * ('Condição de Faturamento'!$C$2:$C$1000 = Tabela1[[#This Row],[Fornecedor]]) ), 'Condição de Faturamento'!$D$2:$D$1000 ) = "Emissão no mês da prestação do serviço", Tabela1[[#This Row],[Mês de referência para faturamento]], DATE( YEAR(Tabela1[[#This Row],[Mês de referência para faturamento]]), MONTH(Tabela1[[#This Row],[Mês de referência para faturamento]]) + 1, DAY(Tabela1[[#This Row],[Mês de referência para faturamento]]) ) ), DATE( YEAR(Tabela1[[#This Row],[Mês de referência para faturamento]]), MONTH(Tabela1[[#This Row],[Mês de referência para faturamento]]) + 1, DAY(Tabela1[[#This Row],[Mês de referência para faturamento]]) ) )} -> 45778 | AI22: =K22-L22 -> 0 | AJ22: =AB22-AC22 -> 0 | AK22: =J22-U22 -> 3252.6409 | AM22: =_xlfn.XLOOKUP(Tabela1[[#This Row],[Unidade]],tabShoppingsEmails[Shopping],tabShoppingsEmails[E-mails consolidados]) -> patricia.benvenuti@allos.co; ludmila.fachin@allos.co; emerson.silveira@allos.co; bruna.zanella@allos.co; wallace.nascimento@allos.co; juliana.slomp@allos.co
A23: 45811 | B23: Sim | C23: Shopping Villagio Caxias | D23: Portaria | E23: Veper | F23: 8 | G23: 8 | H23: 0 | I23: 0 | J23: 46399.92 | K23: 0 | L23: 0 | M23: 0 | N23: 0 | O23: -232 | P23: 0 | Q23: 0 | R23: =44903.9300710717-Tabela1[[#This Row],[Valor Planilha]] -> -1495.9897 | S23: 0 | T23: Sim | U23: =(J23+L23+Q23+R23+S23+N23)+IF(T23="Sim",O23+P23,0) -> 44671.93 | W23: =IF(J23="","",U23*(1+V23)) -> 44671.93 | X23: 13806.448 | Y23: 1.1 | Z23: 45778 | AA23: {=IFERROR( IF( _xlfn.XLOOKUP( 1, ( ('Condição de Faturamento'!$A$2:$A$1000 = Tabela1[[#This Row],[Unidade]]) * ('Condição de Faturamento'!$B$2:$B$1000 = Tabela1[[#This Row],[Categoria]]) * ('Condição de Faturamento'!$C$2:$C$1000 = Tabela1[[#This Row],[Fornecedor]]) ), 'Condição de Faturamento'!$D$2:$D$1000 ) = "Emissão no mês da prestação do serviço", Tabela1[[#This Row],[Mês de referência para faturamento]], DATE( YEAR(Tabela1[[#This Row],[Mês de referência para faturamento]]), MONTH(Tabela1[[#This Row],[Mês de referência para faturamento]]) + 1, DAY(Tabela1[[#This Row],[Mês de referência para faturamento]]) ) ), DATE( YEAR(Tabela1[[#This Row],[Mês de referência para faturamento]]), MONTH(Tabela1[[#This Row],[Mês de referência para faturamento]]) + 1, DAY(Tabela1[[#This Row],[Mês de referência para faturamento]]) ) )} -> 45809 | AI23: =K23-L23 -> 0 | AJ23: =AB23-AC23 -> 0 | AK23: =J23-U23 -> 1727.9897 | AM23: =_xlfn.XLOOKUP(Tabela1[[#This Row],[Unidade]],tabShoppingsEmails[Shopping],tabShoppingsEmails[E-mails consolidados]) -> patricia.benvenuti@allos.co; ludmila.fachin@allos.co; emerson.silveira@allos.co; bruna.zanella@allos.co; wallace.nascimento@allos.co; juliana.slomp@allos.co
A24: 45841 | B24: Sim | C24: Shopping Villagio Caxias | D24: Portaria | E24: Veper | F24: 8 | G24: 8 | H24: 0 | I24: 21.77 | J24: 46399.92 | K24: 0 | L24: 0 | M24: 0 | N24: -569.85133 | O24: -464 | P24: 0 | Q24: 0 | R24: =45651.9249444867-Tabela1[[#This Row],[Valor Planilha]] -> -747.99487 | S24: 0 | T24: Sim | U24: =(J24+L24+Q24+R24+S24+N24)+IF(T24="Sim",O24+P24,0) -> 44618.074 | W24: =IF(J24="","",U24*(1+V24)) -> 44618.074 | Z24: 45809 | AA24: {=IFERROR( IF( _xlfn.XLOOKUP( 1, ( ('Condição de Faturamento'!$A$2:$A$1000 = Tabela1[[#This Row],[Unidade]]) * ('Condição de Faturamento'!$B$2:$B$1000 = Tabela1[[#This Row],[Categoria]]) * ('Condição de Faturamento'!$C$2:$C$1000 = Tabela1[[#This Row],[Fornecedor]]) ), 'Condição de Faturamento'!$D$2:$D$1000 ) = "Emissão no mês da prestação do serviço", Tabela1[[#This Row],[Mês de referência para faturamento]], DATE( YEAR(Tabela1[[#This Row],[Mês de referência para faturamento]]), MONTH(Tabela1[[#This Row],[Mês de referência para faturamento]]) + 1, DAY(Tabela1[[#This Row],[Mês de referência para faturamento]]) ) ), DATE( YEAR(Tabela1[[#This Row],[Mês de referência para faturamento]]), MONTH(Tabela1[[#This Row],[Mês de referência para faturamento]]) + 1, DAY(Tabela1[[#This Row],[Mês de referência para faturamento]]) ) )} -> 45839 | AI24: =K24-L24 -> 0 | AJ24: =AB24-AC24 -> 0 | AK24: =J24-U24 -> 1781.8462 | AM24: =_xlfn.XLOOKUP(Tabela1[[#This Row],[Unidade]],tabShoppingsEmails[Shopping],tabShoppingsEmails[E-mails consolidados]) -> patricia.benvenuti@allos.co; ludmila.fachin@allos.co; emerson.silveira@allos.co; bruna.zanella@allos.co; wallace.nascimento@allos.co; juliana.slomp@allos.co
A25: 45876 | B25: Sim | C25: Shopping Villagio Caxias | D25: Portaria | E25: Protesul | F25: 8 | G25: 8 | H25: 0 | I25: 3 | J25: 51048.21 | K25: 0 | L25: 0 | M25: 0 | N25: -98.26 | O25: 0 | P25: 0 | Q25: 0 | R25: 0 | S25: 0 | T25: Sim | U25: =(J25+L25+Q25+R25+S25+N25)+IF(T25="Sim",O25+P25,0) -> 50949.95 | W25: =IF(J25="","",U25*(1+V25)) -> 50949.95 | Z25: 45839 | AA25: {=IFERROR( IF( _xlfn.XLOOKUP( 1, ( ('Condição de Faturamento'!$A$2:$A$1000 = Tabela1[[#This Row],[Unidade]]) * ('Condição de Faturamento'!$B$2:$B$1000 = Tabela1[[#This Row],[Categoria]]) * ('Condição de Faturamento'!$C$2:$C$1000 = Tabela1[[#This Row],[Fornecedor]]) ), 'Condição de Faturamento'!$D$2:$D$1000 ) = "Emissão no mês da prestação do serviço", Tabela1[[#This Row],[Mês de referência para faturamento]], DATE( YEAR(Tabela1[[#This Row],[Mês de referência para faturamento]]), MONTH(Tabela1[[#This Row],[Mês de referência para faturamento]]) + 1, DAY(Tabela1[[#This Row],[Mês de referência para faturamento]]) ) ), DATE( YEAR(Tabela1[[#This Row],[Mês de referência para faturamento]]), MONTH(Tabela1[[#This Row],[Mês de referência para faturamento]]) + 1, DAY(Tabela1[[#This Row],[Mês de referência para faturamento]]) ) )} -> 45870 | AI25: =K25-L25 -> 0 | AJ25: =AB25-AC25 -> 0 | AK25: =J25-U25 -> 98.26 | AM25: =_xlfn.XLOOKUP(Tabela1[[#This Row],[Unidade]],tabShoppingsEmails[Shopping],tabShoppingsEmails[E-mails consolidados]) -> patricia.benvenuti@allos.co; ludmila.fachin@allos.co; emerson.silveira@allos.co; bruna.zanella@allos.co; wallace.nascimento@allos.co; juliana.slomp@allos.co
A26: 45904 | B26: Sim | C26: Shopping Villagio Caxias | D26: Portaria | E26: Protesul | F26: 8 | G26: 8 | H26: 0 | I26: 8.27 | J26: 51048.21 | K26: 0 | L26: 0 | M26: 0 | N26: -281.49 | O26: -510.48 | P26: 0 | Q26: 0 | R26: 0 | S26: 0 | T26: Sim | U26: =(J26+L26+Q26+R26+S26+N26)+IF(T26="Sim",O26+P26,0) -> 50256.24 | W26: =IF(J26="","",U26*(1+V26)) -> 50256.24 | Z26: 45870 | AA26: {=IFERROR( IF( _xlfn.XLOOKUP( 1, ( ('Condição de Faturamento'!$A$2:$A$1000 = Tabela1[[#This Row],[Unidade]]) * ('Condição de Faturamento'!$B$2:$B$1000 = Tabela1[[#This Row],[Categoria]]) * ('Condição de Faturamento'!$C$2:$C$1000 = Tabela1[[#This Row],[Fornecedor]]) ), 'Condição de Faturamento'!$D$2:$D$1000 ) = "Emissão no mês da prestação do serviço", Tabela1[[#This Row],[Mês de referência para faturamento]], DATE( YEAR(Tabela1[[#This Row],[Mês de referência para faturamento]]), MONTH(Tabela1[[#This Row],[Mês de referência para faturamento]]) + 1, DAY(Tabela1[[#This Row],[Mês de referência para faturamento]]) ) ), DATE( YEAR(Tabela1[[#This Row],[Mês de referência para faturamento]]), MONTH(Tabela1[[#This Row],[Mês de referência para faturamento]]) + 1, DAY(Tabela1[[#This Row],[Mês de referência para faturamento]]) ) )} -> 45901 | AI26: =K26-L26 -> 0 | AJ26: =AB26-AC26 -> 0 | AK26: =J26-U26 -> 791.97 | AM26: =_xlfn.XLOOKUP(Tabela1[[#This Row],[Unidade]],tabShoppingsEmails[Shopping],tabShoppingsEmails[E-mails consolidados]) -> patricia.benvenuti@allos.co; ludmila.fachin@allos.co; emerson.silveira@allos.co; bruna.zanella@allos.co; wallace.nascimento@allos.co; juliana.slomp@allos.co
A27: 45931 | B27: Sim | C27: Shopping Villagio Caxias | D27: Portaria | E27: Protesul | F27: 8 | G27: 8 | H27: 0 | I27: 0.23 | J27: 51048.21 | K27: 0 | L27: 0 | M27: 0 | N27: -182.9252 | O27: -255.24 | P27: 0 | Q27: 0 | R27: 0 | S27: 0 | T27: Sim | U27: =(J27+L27+Q27+R27+S27+N27)+IF(T27="Sim",O27+P27,0) -> 50610.045 | W27: =IF(J27="","",U27*(1+V27)) -> 50610.045 | Z27: 45901 | AA27: {=IFERROR( IF( _xlfn.XLOOKUP( 1, ( ('Condição de Faturamento'!$A$2:$A$1000 = Tabela1[[#This Row],[Unidade]]) * ('Condição de Faturamento'!$B$2:$B$1000 = Tabela1[[#This Row],[Categoria]]) * ('Condição de Faturamento'!$C$2:$C$1000 = Tabela1[[#This Row],[Fornecedor]]) ), 'Condição de Faturamento'!$D$2:$D$1000 ) = "Emissão no mês da prestação do serviço", Tabela1[[#This Row],[Mês de referência para faturamento]], DATE( YEAR(Tabela1[[#This Row],[Mês de referência para faturamento]]), MONTH(Tabela1[[#This Row],[Mês de referência para faturamento]]) + 1, DAY(Tabela1[[#This Row],[Mês de referência para faturamento]]) ) ), DATE( YEAR(Tabela1[[#This Row],[Mês de referência para faturamento]]), MONTH(Tabela1[[#This Row],[Mês de referência para faturamento]]) + 1, DAY(Tabela1[[#This Row],[Mês de referência para faturamento]]) ) )} -> 45931 | AI27: =K27-L27 -> 0 | AJ27: =AB27-AC27 -> 0 | AK27: =J27-U27 -> 438.1652 | AM27: =_xlfn.XLOOKUP(Tabela1[[#This Row],[Unidade]],tabShoppingsEmails[Shopping],tabShoppingsEmails[E-mails consolidados]) -> patricia.benvenuti@allos.co; ludmila.fachin@allos.co; emerson.silveira@allos.co; bruna.zanella@allos.co; wallace.nascimento@allos.co; juliana.slomp@allos.co
C28: Shopping Villagio Caxias | D28: Portaria | E28: Protesul | F28: 8 | U28: =(J28+L28+Q28+R28+S28+N28)+IF(T28="Sim",O28+P28,0) -> 0 | W28: =IF(J28="","",U28*(1+V28)) | Z28: 45931 | AA28: {=IFERROR( IF( _xlfn.XLOOKUP( 1, ( ('Condição de Faturamento'!$A$2:$A$1000 = Tabela1[[#This Row],[Unidade]]) * ('Condição de Faturamento'!$B$2:$B$1000 = Tabela1[[#This Row],[Categoria]]) * ('Condição de Faturamento'!$C$2:$C$1000 = Tabela1[[#This Row],[Fornecedor]]) ), 'Condição de Faturamento'!$D$2:$D$1000 ) = "Emissão no mês da prestação do serviço", Tabela1[[#This Row],[Mês de referência para faturamento]], DATE( YEAR(Tabela1[[#This Row],[Mês de referência para faturamento]]), MONTH(Tabela1[[#This Row],[Mês de referência para faturamento]]) + 1, DAY(Tabela1[[#This Row],[Mês de referência para faturamento]]) ) ), DATE( YEAR(Tabela1[[#This Row],[Mês de referência para faturamento]]), MONTH(Tabela1[[#This Row],[Mês de referência para faturamento]]) + 1, DAY(Tabela1[[#This Row],[Mês de referência para faturamento]]) ) )} -> 45962 | AI28: =K28-L28 -> 0 | AJ28: =AB28-AC28 -> 0 | AK28: =J28-U28 -> 0 | AM28: =_xlfn.XLOOKUP(Tabela1[[#This Row],[Unidade]],tabShoppingsEmails[Shopping],tabShoppingsEmails[E-mails consolidados]) -> patricia.benvenuti@allos.co; ludmila.fachin@allos.co; emerson.silveira@allos.co; bruna.zanella@allos.co; wallace.nascimento@allos.co; juliana.slomp@allos.co
C29: Shopping Villagio Caxias | D29: Portaria | E29: Protesul | F29: 8 | U29: =(J29+L29+Q29+R29+S29+N29)+IF(T29="Sim",O29+P29,0) -> 0 | W29: =IF(J29="","",U29*(1+V29)) | Z29: 45962 | AA29: {=IFERROR( IF( _xlfn.XLOOKUP( 1, ( ('Condição de Faturamento'!$A$2:$A$1000 = Tabela1[[#This Row],[Unidade]]) * ('Condição de Faturamento'!$B$2:$B$1000 = Tabela1[[#This Row],[Categoria]]) * ('Condição de Faturamento'!$C$2:$C$1000 = Tabela1[[#This Row],[Fornecedor]]) ), 'Condição de Faturamento'!$D$2:$D$1000 ) = "Emissão no mês da prestação do serviço", Tabela1[[#This Row],[Mês de referência para faturamento]], DATE( YEAR(Tabela1[[#This Row],[Mês de referência para faturamento]]), MONTH(Tabela1[[#This Row],[Mês de referência para faturamento]]) + 1, DAY(Tabela1[[#This Row],[Mês de referência para faturamento]]) ) ), DATE( YEAR(Tabela1[[#This Row],[Mês de referência para faturamento]]), MONTH(Tabela1[[#This Row],[Mês de referência para faturamento]]) + 1, DAY(Tabela1[[#This Row],[Mês de referência para faturamento]]) ) )} -> 45992 | AI29: =K29-L29 -> 0 | AJ29: =AB29-AC29 -> 0 | AK29: =J29-U29 -> 0 | AM29: =_xlfn.XLOOKUP(Tabela1[[#This Row],[Unidade]],tabShoppingsEmails[Shopping],tabShoppingsEmails[E-mails consolidados]) -> patricia.benvenuti@allos.co; ludmila.fachin@allos.co; emerson.silveira@allos.co; bruna.zanella@allos.co; wallace.nascimento@allos.co; juliana.slomp@allos.co
C30: Shopping Villagio Caxias | D30: Portaria | E30: Protesul | F30: 8 | U30: =(J30+L30+Q30+R30+S30+N30)+IF(T30="Sim",O30+P30,0) -> 0 | W30: =IF(J30="","",U30*(1+V30)) | Z30: 45992 | AA30: {=IFERROR( IF( _xlfn.XLOOKUP( 1, ( ('Condição de Faturamento'!$A$2:$A$1000 = Tabela1[[#This Row],[Unidade]]) * ('Condição de Faturamento'!$B$2:$B$1000 = Tabela1[[#This Row],[Categoria]]) * ('Condição de Faturamento'!$C$2:$C$1000 = Tabela1[[#This Row],[Fornecedor]]) ), 'Condição de Faturamento'!$D$2:$D$1000 ) = "Emissão no mês da prestação do serviço", Tabela1[[#This Row],[Mês de referência para faturamento]], DATE( YEAR(Tabela1[[#This Row],[Mês de referência para faturamento]]), MONTH(Tabela1[[#This Row],[Mês de referência para faturamento]]) + 1, DAY(Tabela1[[#This Row],[Mês de referência para faturamento]]) ) ), DATE( YEAR(Tabela1[[#This Row],[Mês de referência para faturamento]]), MONTH(Tabela1[[#This Row],[Mês de referência para faturamento]]) + 1, DAY(Tabela1[[#This Row],[Mês de referência para faturamento]]) ) )} -> 46023 | AI30: =K30-L30 -> 0 | AJ30: =AB30-AC30 -> 0 | AK30: =J30-U30 -> 0 | AM30: =_xlfn.XLOOKUP(Tabela1[[#This Row],[Unidade]],tabShoppingsEmails[Shopping],tabShoppingsEmails[E-mails consolidados]) -> patricia.benvenuti@allos.co; ludmila.fachin@allos.co; emerson.silveira@allos.co; bruna.zanella@allos.co; wallace.nascimento@allos.co; juliana.slomp@allos.co
B31: Sim | C31: Shopping Villagio Caxias | D31: Vigilância | E31: Veper | F31: 12 | G31: 12 | H31: 0 | I31: 1.6 | J31: 76454.99 | K31: 0 | L31: 0 | M31: 0 | N31: -42.016 | O31: -382.32 | P31: 0 | Q31: 0 | R31: 0 | S31: 0 | T31: Sim | U31: =(J31+L31+Q31+R31+S31+N31)+IF(T31="Sim",O31+P31,0) -> 76030.654 | W31: =IF(J31="","",U31*(1+V31)) -> 76030.654 | Z31: 45658 | AA31: {=IFERROR( IF( _xlfn.XLOOKUP( 1, ( ('Condição de Faturamento'!$A$2:$A$1000 = Tabela1[[#This Row],[Unidade]]) * ('Condição de Faturamento'!$B$2:$B$1000 = Tabela1[[#This Row],[Categoria]]) * ('Condição de Faturamento'!$C$2:$C$1000 = Tabela1[[#This Row],[Fornecedor]]) ), 'Condição de Faturamento'!$D$2:$D$1000 ) = "Emissão no mês da prestação do serviço", Tabela1[[#This Row],[Mês de referência para faturamento]], DATE( YEAR(Tabela1[[#This Row],[Mês de referência para faturamento]]), MONTH(Tabela1[[#This Row],[Mês de referência para faturamento]]) + 1, DAY(Tabela1[[#This Row],[Mês de referência para faturamento]]) ) ), DATE( YEAR(Tabela1[[#This Row],[Mês de referência para faturamento]]), MONTH(Tabela1[[#This Row],[Mês de referência para faturamento]]) + 1, DAY(Tabela1[[#This Row],[Mês de referência para faturamento]]) ) )} -> 45689 | AI31: =K31-L31 -> 0 | AJ31: =AB31-AC31 -> 0 | AK31: =J31-U31 -> 424.336 | AM31: =_xlfn.XLOOKUP(Tabela1[[#This Row],[Unidade]],tabShoppingsEmails[Shopping],tabShoppingsEmails[E-mails consolidados]) -> patricia.benvenuti@allos.co; ludmila.fachin@allos.co; emerson.silveira@allos.co; bruna.zanella@allos.co; wallace.nascimento@allos.co; juliana.slomp@allos.co
B32: Sim | C32: Shopping Villagio Caxias | D32: Vigilância | E32: Veper | F32: 12 | G32: 12 | H32: 0 | I32: 1.9666667 | J32: 76454.99 | K32: 0 | L32: 0 | M32: 0 | N32: -51.644667 | O32: -1146.97 | P32: 0 | Q32: 0 | R32: 0 | S32: 0 | T32: Sim | U32: =(J32+L32+Q32+R32+S32+N32)+IF(T32="Sim",O32+P32,0) -> 75256.376 | W32: =IF(J32="","",U32*(1+V32)) -> 75256.376 | Z32: 45689 | AA32: {=IFERROR( IF( _xlfn.XLOOKUP( 1, ( ('Condição de Faturamento'!$A$2:$A$1000 = Tabela1[[#This Row],[Unidade]]) * ('Condição de Faturamento'!$B$2:$B$1000 = Tabela1[[#This Row],[Categoria]]) * ('Condição de Faturamento'!$C$2:$C$1000 = Tabela1[[#This Row],[Fornecedor]]) ), 'Condição de Faturamento'!$D$2:$D$1000 ) = "Emissão no mês da prestação do serviço", Tabela1[[#This Row],[Mês de referência para faturamento]], DATE( YEAR(Tabela1[[#This Row],[Mês de referência para faturamento]]), MONTH(Tabela1[[#This Row],[Mês de referência para faturamento]]) + 1, DAY(Tabela1[[#This Row],[Mês de referência para faturamento]]) ) ), DATE( YEAR(Tabela1[[#This Row],[Mês de referência para faturamento]]), MONTH(Tabela1[[#This Row],[Mês de referência para faturamento]]) + 1, DAY(Tabela1[[#This Row],[Mês de referência para faturamento]]) ) )} -> 45717 | AB32: 1394.6804 | AC32: 1394.6804 | AI32: =K32-L32 -> 0 | AJ32: =AB32-AC32 -> 0 | AK32: =J32-U32 -> 1198.6147 | AM32: =_xlfn.XLOOKUP(Tabela1[[#This Row],[Unidade]],tabShoppingsEmails[Shopping],tabShoppingsEmails[E-mails consolidados]) -> patricia.benvenuti@allos.co; ludmila.fachin@allos.co; emerson.silveira@allos.co; bruna.zanella@allos.co; wallace.nascimento@allos.co; juliana.slomp@allos.co
B33: Sim | C33: Shopping Villagio Caxias | D33: Vigilância | E33: Veper | F33: 12 | G33: 12 | H33: 0 | I33: 3.08 | J33: 76454.99 | K33: 0 | L33: 0 | M33: 0 | N33: -80.968333 | O33: -1146.97 | P33: 0 | Q33: 0 | R33: 0 | S33: 0 | T33: Sim | U33: =(J33+L33+Q33+R33+S33+N33)+IF(T33="Sim",O33+P33,0) -> 75227.052 | W33: =IF(J33="","",U33*(1+V33)) -> 75227.052 | Z33: 45717 | AA33: {=IFERROR( IF( _xlfn.XLOOKUP( 1, ( ('Condição de Faturamento'!$A$2:$A$1000 = Tabela1[[#This Row],[Unidade]]) * ('Condição de Faturamento'!$B$2:$B$1000 = Tabela1[[#This Row],[Categoria]]) * ('Condição de Faturamento'!$C$2:$C$1000 = Tabela1[[#This Row],[Fornecedor]]) ), 'Condição de Faturamento'!$D$2:$D$1000 ) = "Emissão no mês da prestação do serviço", Tabela1[[#This Row],[Mês de referência para faturamento]], DATE( YEAR(Tabela1[[#This Row],[Mês de referência para faturamento]]), MONTH(Tabela1[[#This Row],[Mês de referência para faturamento]]) + 1, DAY(Tabela1[[#This Row],[Mês de referência para faturamento]]) ) ), DATE( YEAR(Tabela1[[#This Row],[Mês de referência para faturamento]]), MONTH(Tabela1[[#This Row],[Mês de referência para faturamento]]) + 1, DAY(Tabela1[[#This Row],[Mês de referência para faturamento]]) ) )} -> 45748 | AB33: 2801.2911 | AC33: 2801.2911 | AI33: =K33-L33 -> 0 | AJ33: =AB33-AC33 -> 0 | AK33: =J33-U33 -> 1227.9383 | AM33: =_xlfn.XLOOKUP(Tabela1[[#This Row],[Unidade]],tabShoppingsEmails[Shopping],tabShoppingsEmails[E-mails consolidados]) -> patricia.benvenuti@allos.co; ludmila.fachin@allos.co; emerson.silveira@allos.co; bruna.zanella@allos.co; wallace.nascimento@allos.co; juliana.slomp@allos.co
B34: Sim | C34: Shopping Villagio Caxias | D34: Vigilância | E34: Veper | F34: 12 | G34: 12 | H34: 0 | I34: 2 | J34: 76454.99 | K34: 0 | L34: 0 | M34: 0 | N34: -57.86 | O34: 0 | P34: 0 | Q34: 0 | R34: 0 | S34: 0 | T34: Sim | U34: =(J34+L34+Q34+R34+S34+N34)+IF(T34="Sim",O34+P34,0) -> 76397.13 | W34: =IF(J34="","",U34*(1+V34)) -> 76397.13 | Z34: 45748 | AA34: {=IFERROR( IF( _xlfn.XLOOKUP( 1, ( ('Condição de Faturamento'!$A$2:$A$1000 = Tabela1[[#This Row],[Unidade]]) * ('Condição de Faturamento'!$B$2:$B$1000 = Tabela1[[#This Row],[Categoria]]) * ('Condição de Faturamento'!$C$2:$C$1000 = Tabela1[[#This Row],[Fornecedor]]) ), 'Condição de Faturamento'!$D$2:$D$1000 ) = "Emissão no mês da prestação do serviço", Tabela1[[#This Row],[Mês de referência para faturamento]], DATE( YEAR(Tabela1[[#This Row],[Mês de referência para faturamento]]), MONTH(Tabela1[[#This Row],[Mês de referência para faturamento]]) + 1, DAY(Tabela1[[#This Row],[Mês de referência para faturamento]]) ) ), DATE( YEAR(Tabela1[[#This Row],[Mês de referência para faturamento]]), MONTH(Tabela1[[#This Row],[Mês de referência para faturamento]]) + 1, DAY(Tabela1[[#This Row],[Mês de referência para faturamento]]) ) )} -> 45778 | AB34: 1672.2473 | AC34: 1672.2473 | AI34: =K34-L34 -> 0 | AJ34: =AB34-AC34 -> 0 | AK34: =J34-U34 -> 57.86 | AM34: =_xlfn.XLOOKUP(Tabela1[[#This Row],[Unidade]],tabShoppingsEmails[Shopping],tabShoppingsEmails[E-mails consolidados]) -> patricia.benvenuti@allos.co; ludmila.fachin@allos.co; emerson.silveira@allos.co; bruna.zanella@allos.co; wallace.nascimento@allos.co; juliana.slomp@allos.co
A35: 45811 | B35: sim | C35: Shopping Villagio Caxias | D35: Vigilância | E35: Veper | F35: 12 | G35: 12 | H35: 0 | I35: 12.5 | J35: 83872.722 | K35: 0 | L35: 0 | M35: 0 | N35: -397.25 | O35: -838.73 | P35: 0 | Q35: 0 | R35: 0 | S35: 0 | T35: Sim | U35: =(J35+L35+Q35+R35+S35+N35)+IF(T35="Sim",O35+P35,0) -> 82636.742 | W35: =IF(J35="","",U35*(1+V35)) -> 82636.742 | X35: 7574.3612 | Y35: 1.1 | Z35: 45778 | AA35: {=IFERROR( IF( _xlfn.XLOOKUP( 1, ( ('Condição de Faturamento'!$A$2:$A$1000 = Tabela1[[#This Row],[Unidade]]) * ('Condição de Faturamento'!$B$2:$B$1000 = Tabela1[[#This Row],[Categoria]]) * ('Condição de Faturamento'!$C$2:$C$1000 = Tabela1[[#This Row],[Fornecedor]]) ), 'Condição de Faturamento'!$D$2:$D$1000 ) = "Emissão no mês da prestação do serviço", Tabela1[[#This Row],[Mês de referência para faturamento]], DATE( YEAR(Tabela1[[#This Row],[Mês de referência para faturamento]]), MONTH(Tabela1[[#This Row],[Mês de referência para faturamento]]) + 1, DAY(Tabela1[[#This Row],[Mês de referência para faturamento]]) ) ), DATE( YEAR(Tabela1[[#This Row],[Mês de referência para faturamento]]), MONTH(Tabela1[[#This Row],[Mês de referência para faturamento]]) + 1, DAY(Tabela1[[#This Row],[Mês de referência para faturamento]]) ) )} -> 45809 | AB35: 800.34888 | AC35: 800.34888 | AI35: =K35-L35 -> 0 | AJ35: =AB35-AC35 -> 0 | AK35: =J35-U35 -> 1235.98 | AM35: =_xlfn.XLOOKUP(Tabela1[[#This Row],[Unidade]],tabShoppingsEmails[Shopping],tabShoppingsEmails[E-mails consolidados]) -> patricia.benvenuti@allos.co; ludmila.fachin@allos.co; emerson.silveira@allos.co; bruna.zanella@allos.co; wallace.nascimento@allos.co; juliana.slomp@allos.co
A36: 45841 | B36: Sim | C36: Shopping Villagio Caxias | D36: Vigilância | E36: Veper | F36: 12 | G36: 12 | H36: 0 | I36: 0.67 | J36: 83872.722 | K36: 0 | L36: 0 | M36: 0 | N36: -19.293333 | O36: 0 | P36: 0 | Q36: 0 | R36: 0 | S36: 0 | T36: Sim | U36: =(J36+L36+Q36+R36+S36+N36)+IF(T36="Sim",O36+P36,0) -> 83853.429 | W36: =IF(J36="","",U36*(1+V36)) -> 83853.429 | Z36: 45809 | AA36: {=IFERROR( IF( _xlfn.XLOOKUP( 1, ( ('Condição de Faturamento'!$A$2:$A$1000 = Tabela1[[#This Row],[Unidade]]) * ('Condição de Faturamento'!$B$2:$B$1000 = Tabela1[[#This Row],[Categoria]]) * ('Condição de Faturamento'!$C$2:$C$1000 = Tabela1[[#This Row],[Fornecedor]]) ), 'Condição de Faturamento'!$D$2:$D$1000 ) = "Emissão no mês da prestação do serviço", Tabela1[[#This Row],[Mês de referência para faturamento]], DATE( YEAR(Tabela1[[#This Row],[Mês de referência para faturamento]]), MONTH(Tabela1[[#This Row],[Mês de referência para faturamento]]) + 1, DAY(Tabela1[[#This Row],[Mês de referência para faturamento]]) ) ), DATE( YEAR(Tabela1[[#This Row],[Mês de referência para faturamento]]), MONTH(Tabela1[[#This Row],[Mês de referência para faturamento]]) + 1, DAY(Tabela1[[#This Row],[Mês de referência para faturamento]]) ) )} -> 45839 | AI36: =K36-L36 -> 0 | AJ36: =AB36-AC36 -> 0 | AK36: =J36-U36 -> 19.293333 | AM36: =_xlfn.XLOOKUP(Tabela1[[#This Row],[Unidade]],tabShoppingsEmails[Shopping],tabShoppingsEmails[E-mails consolidados]) -> patricia.benvenuti@allos.co; ludmila.fachin@allos.co; emerson.silveira@allos.co; bruna.zanella@allos.co; wallace.nascimento@allos.co; juliana.slomp@allos.co
A37: 45876 | B37: Sim | C37: Shopping Villagio Caxias | D37: Vigilância | E37: Protesul | F37: 12 | G37: 12 | H37: 0 | I37: 0.066666667 | J37: 92375.52 | K37: 0 | L37: 0 | M37: 0 | N37: -2.338 | O37: 0 | P37: 0 | Q37: 0 | R37: 0 | S37: 0 | T37: Sim | U37: =(J37+L37+Q37+R37+S37+N37)+IF(T37="Sim",O37+P37,0) -> 92373.182 | W37: =IF(J37="","",U37*(1+V37)) -> 92373.182 | Z37: 45839 | AA37: {=IFERROR( IF( _xlfn.XLOOKUP( 1, ( ('Condição de Faturamento'!$A$2:$A$1000 = Tabela1[[#This Row],[Unidade]]) * ('Condição de Faturamento'!$B$2:$B$1000 = Tabela1[[#This Row],[Categoria]]) * ('Condição de Faturamento'!$C$2:$C$1000 = Tabela1[[#This Row],[Fornecedor]]) ), 'Condição de Faturamento'!$D$2:$D$1000 ) = "Emissão no mês da prestação do serviço", Tabela1[[#This Row],[Mês de referência para faturamento]], DATE( YEAR(Tabela1[[#This Row],[Mês de referência para faturamento]]), MONTH(Tabela1[[#This Row],[Mês de referência para faturamento]]) + 1, DAY(Tabela1[[#This Row],[Mês de referência para faturamento]]) ) ), DATE( YEAR(Tabela1[[#This Row],[Mês de referência para faturamento]]), MONTH(Tabela1[[#This Row],[Mês de referência para faturamento]]) + 1, DAY(Tabela1[[#This Row],[Mês de referência para faturamento]]) ) )} -> 45870 | AB37: 4488.4393 | AC37: 4488.4393 | AI37: =K37-L37 -> 0 | AJ37: =AB37-AC37 -> 0 | AK37: =J37-U37 -> 2.338 | AM37: =_xlfn.XLOOKUP(Tabela1[[#This Row],[Unidade]],tabShoppingsEmails[Shopping],tabShoppingsEmails[E-mails consolidados]) -> patricia.benvenuti@allos.co; ludmila.fachin@allos.co; emerson.silveira@allos.co; bruna.zanella@allos.co; wallace.nascimento@allos.co; juliana.slomp@allos.co
A38: 45904 | B38: Sim | C38: Shopping Villagio Caxias | D38: Vigilância | E38: Protesul | F38: 12 | G38: 12 | H38: 0 | I38: 2.9166667 | J38: 92375.52 | K38: 0 | L38: 0 | M38: 0 | N38: -102.2875 | O38: -1385.63 | P38: 0 | Q38: 0 | R38: 0 | S38: 0 | T38: Sim | U38: =(J38+L38+Q38+R38+S38+N38)+IF(T38="Sim",O38+P38,0) -> 90887.602 | W38: =IF(J38="","",U38*(1+V38)) -> 90887.602 | Z38: 45870 | AA38: {=IFERROR( IF( _xlfn.XLOOKUP( 1, ( ('Condição de Faturamento'!$A$2:$A$1000 = Tabela1[[#This Row],[Unidade]]) * ('Condição de Faturamento'!$B$2:$B$1000 = Tabela1[[#This Row],[Categoria]]) * ('Condição de Faturamento'!$C$2:$C$1000 = Tabela1[[#This Row],[Fornecedor]]) ), 'Condição de Faturamento'!$D$2:$D$1000 ) = "Emissão no mês da prestação do serviço", Tabela1[[#This Row],[Mês de referência para faturamento]], DATE( YEAR(Tabela1[[#This Row],[Mês de referência para faturamento]]), MONTH(Tabela1[[#This Row],[Mês de referência para faturamento]]) + 1, DAY(Tabela1[[#This Row],[Mês de referência para faturamento]]) ) ), DATE( YEAR(Tabela1[[#This Row],[Mês de referência para faturamento]]), MONTH(Tabela1[[#This Row],[Mês de referência para faturamento]]) + 1, DAY(Tabela1[[#This Row],[Mês de referência para faturamento]]) ) )} -> 45901 | AB38: 713.76768 | AC38: 713.76768 | AI38: =K38-L38 -> 0 | AJ38: =AB38-AC38 -> 0 | AK38: =J38-U38 -> 1487.9175 | AM38: =_xlfn.XLOOKUP(Tabela1[[#This Row],[Unidade]],tabShoppingsEmails[Shopping],tabShoppingsEmails[E-mails consolidados]) -> patricia.benvenuti@allos.co; ludmila.fachin@allos.co; emerson.silveira@allos.co; bruna.zanella@allos.co; wallace.nascimento@allos.co; juliana.slomp@allos.co
A39: 45931 | B39: Sim | C39: Shopping Villagio Caxias | D39: Vigilância | E39: Protesul | F39: 12 | G39: 12 | H39: 0 | I39: 4.78 | J39: 92375.52 | K39: 0 | L39: 0 | M39: 0 | N39: -8.0661 | O39: -923.76 | P39: 0 | Q39: 0 | R39: 0 | S39: 0 | T39: Sim | U39: =(J39+L39+Q39+R39+S39+N39)+IF(T39="Sim",O39+P39,0) -> 91443.694 | W39: =IF(J39="","",U39*(1+V39)) -> 91443.694 | Z39: 45901 | AA39: {=IFERROR( IF( _xlfn.XLOOKUP( 1, ( ('Condição de Faturamento'!$A$2:$A$1000 = Tabela1[[#This Row],[Unidade]]) * ('Condição de Faturamento'!$B$2:$B$1000 = Tabela1[[#This Row],[Categoria]]) * ('Condição de Faturamento'!$C$2:$C$1000 = Tabela1[[#This Row],[Fornecedor]]) ), 'Condição de Faturamento'!$D$2:$D$1000 ) = "Emissão no mês da prestação do serviço", Tabela1[[#This Row],[Mês de referência para faturamento]], DATE( YEAR(Tabela1[[#This Row],[Mês de referência para faturamento]]), MONTH(Tabela1[[#This Row],[Mês de referência para faturamento]]) + 1, DAY(Tabela1[[#This Row],[Mês de referência para faturamento]]) ) ), DATE( YEAR(Tabela1[[#This Row],[Mês de referência para faturamento]]), MONTH(Tabela1[[#This Row],[Mês de referência para faturamento]]) + 1, DAY(Tabela1[[#This Row],[Mês de referência para faturamento]]) ) )} -> 45931 | AB39: 1438.79 | AC39: 1438.79 | AI39: =K39-L39 -> 0 | AJ39: =AB39-AC39 -> 0 | AK39: =J39-U39 -> 931.8261 | AM39: =_xlfn.XLOOKUP(Tabela1[[#This Row],[Unidade]],tabShoppingsEmails[Shopping],tabShoppingsEmails[E-mails consolidados]) -> patricia.benvenuti@allos.co; ludmila.fachin@allos.co; emerson.silveira@allos.co; bruna.zanella@allos.co; wallace.nascimento@allos.co; juliana.slomp@allos.co
C40: Shopping Villagio Caxias | D40: Vigilância | E40: Protesul | F40: 12 | U40: =(J40+L40+Q40+R40+S40+N40)+IF(T40="Sim",O40+P40,0) -> 0 | W40: =IF(J40="","",U40*(1+V40)) | Z40: 45931 | AA40: {=IFERROR( IF( _xlfn.XLOOKUP( 1, ( ('Condição de Faturamento'!$A$2:$A$1000 = Tabela1[[#This Row],[Unidade]]) * ('Condição de Faturamento'!$B$2:$B$1000 = Tabela1[[#This Row],[Categoria]]) * ('Condição de Faturamento'!$C$2:$C$1000 = Tabela1[[#This Row],[Fornecedor]]) ), 'Condição de Faturamento'!$D$2:$D$1000 ) = "Emissão no mês da prestação do serviço", Tabela1[[#This Row],[Mês de referência para faturamento]], DATE( YEAR(Tabela1[[#This Row],[Mês de referência para faturamento]]), MONTH(Tabela1[[#This Row],[Mês de referência para faturamento]]) + 1, DAY(Tabela1[[#This Row],[Mês de referência para faturamento]]) ) ), DATE( YEAR(Tabela1[[#This Row],[Mês de referência para faturamento]]), MONTH(Tabela1[[#This Row],[Mês de referência para faturamento]]) + 1, DAY(Tabela1[[#This Row],[Mês de referência para faturamento]]) ) )} -> 45962 | AI40: =K40-L40 -> 0 | AJ40: =AB40-AC40 -> 0 | AK40: =J40-U40 -> 0 | AM40: =_xlfn.XLOOKUP(Tabela1[[#This Row],[Unidade]],tabShoppingsEmails[Shopping],tabShoppingsEmails[E-mails consolidados]) -> patricia.benvenuti@allos.co; ludmila.fachin@allos.co; emerson.silveira@allos.co; bruna.zanella@allos.co; wallace.nascimento@allos.co; juliana.slomp@allos.co
C41: Shopping Villagio Caxias | D41: Vigilância | E41: Protesul | F41: 12 | U41: =(J41+L41+Q41+R41+S41+N41)+IF(T41="Sim",O41+P41,0) -> 0 | W41: =IF(J41="","",U41*(1+V41)) | Z41: 45962 | AA41: {=IFERROR( IF( _xlfn.XLOOKUP( 1, ( ('Condição de Faturamento'!$A$2:$A$1000 = Tabela1[[#This Row],[Unidade]]) * ('Condição de Faturamento'!$B$2:$B$1000 = Tabela1[[#This Row],[Categoria]]) * ('Condição de Faturamento'!$C$2:$C$1000 = Tabela1[[#This Row],[Fornecedor]]) ), 'Condição de Faturamento'!$D$2:$D$1000 ) = "Emissão no mês da prestação do serviço", Tabela1[[#This Row],[Mês de referência para faturamento]], DATE( YEAR(Tabela1[[#This Row],[Mês de referência para faturamento]]), MONTH(Tabela1[[#This Row],[Mês de referência para faturamento]]) + 1, DAY(Tabela1[[#This Row],[Mês de referência para faturamento]]) ) ), DATE( YEAR(Tabela1[[#This Row],[Mês de referência para faturamento]]), MONTH(Tabela1[[#This Row],[Mês de referência para faturamento]]) + 1, DAY(Tabela1[[#This Row],[Mês de referência para faturamento]]) ) )} -> 45992 | AI41: =K41-L41 -> 0 | AJ41: =AB41-AC41 -> 0 | AK41: =J41-U41 -> 0 | AM41: =_xlfn.XLOOKUP(Tabela1[[#This Row],[Unidade]],tabShoppingsEmails[Shopping],tabShoppingsEmails[E-mails consolidados]) -> patricia.benvenuti@allos.co; ludmila.fachin@allos.co; emerson.silveira@allos.co; bruna.zanella@allos.co; wallace.nascimento@allos.co; juliana.slomp@allos.co
C42: Shopping Villagio Caxias | D42: Vigilância | E42: Protesul | F42: 12 | U42: =(J42+L42+Q42+R42+S42+N42)+IF(T42="Sim",O42+P42,0) -> 0 | W42: =IF(J42="","",U42*(1+V42)) | Z42: 45992 | AA42: {=IFERROR( IF( _xlfn.XLOOKUP( 1, ( ('Condição de Faturamento'!$A$2:$A$1000 = Tabela1[[#This Row],[Unidade]]) * ('Condição de Faturamento'!$B$2:$B$1000 = Tabela1[[#This Row],[Categoria]]) * ('Condição de Faturamento'!$C$2:$C$1000 = Tabela1[[#This Row],[Fornecedor]]) ), 'Condição de Faturamento'!$D$2:$D$1000 ) = "Emissão no mês da prestação do serviço", Tabela1[[#This Row],[Mês de referência para faturamento]], DATE( YEAR(Tabela1[[#This Row],[Mês de referência para faturamento]]), MONTH(Tabela1[[#This Row],[Mês de referência para faturamento]]) + 1, DAY(Tabela1[[#This Row],[Mês de referência para faturamento]]) ) ), DATE( YEAR(Tabela1[[#This Row],[Mês de referência para faturamento]]), MONTH(Tabela1[[#This Row],[Mês de referência para faturamento]]) + 1, DAY(Tabela1[[#This Row],[Mês de referência para faturamento]]) ) )} -> 46023 | AI42: =K42-L42 -> 0 | AJ42: =AB42-AC42 -> 0 | AK42: =J42-U42 -> 0 | AM42: =_xlfn.XLOOKUP(Tabela1[[#This Row],[Unidade]],tabShoppingsEmails[Shopping],tabShoppingsEmails[E-mails consolidados]) -> patricia.benvenuti@allos.co; ludmila.fachin@allos.co; emerson.silveira@allos.co; bruna.zanella@allos.co; wallace.nascimento@allos.co; juliana.slomp@allos.co
B43: Não | C43: Shopping Villa Lobos | D43: Limpeza | E43: Verzani | F43: 40 | G43: 43 | H43: informação pendente | I43: 0 | J43: 237725.81 | K43: 0 | M43: 0 | N43: 0 | O43: preenchimento pendente | P43: 0 | Q43: 0 | R43: 0 | S43: 0 | U43: =(J43+L43+Q43+R43+S43+N43)+IF(T43="Sim",O43+P43,0) -> 237725.81 | W43: =IF(J43="","",U43*(1+V43)) -> 237725.81 | Z43: 45658 | AA43: {=IFERROR( IF( _xlfn.XLOOKUP( 1, ( ('Condição de Faturamento'!$A$2:$A$1000 = Tabela1[[#This Row],[Unidade]]) * ('Condição de Faturamento'!$B$2:$B$1000 = Tabela1[[#This Row],[Categoria]]) * ('Condição de Faturamento'!$C$2:$C$1000 = Tabela1[[#This Row],[Fornecedor]]) ), 'Condição de Faturamento'!$D$2:$D$1000 ) = "Emissão no mês da prestação do serviço", Tabela1[[#This Row],[Mês de referência para faturamento]], DATE( YEAR(Tabela1[[#This Row],[Mês de referência para faturamento]]), MONTH(Tabela1[[#This Row],[Mês de referência para faturamento]]) + 1, DAY(Tabela1[[#This Row],[Mês de referência para faturamento]]) ) ), DATE( YEAR(Tabela1[[#This Row],[Mês de referência para faturamento]]), MONTH(Tabela1[[#This Row],[Mês de referência para faturamento]]) + 1, DAY(Tabela1[[#This Row],[Mês de referência para faturamento]]) ) )} -> 45689 | AI43: =K43-L43 -> 0 | AJ43: =AB43-AC43 -> 0 | AK43: =J43-U43 -> 0 | AM43: =_xlfn.XLOOKUP(Tabela1[[#This Row],[Unidade]],tabShoppingsEmails[Shopping],tabShoppingsEmails[E-mails consolidados]) -> renan.mattos@allos.co; rita.silva@allos.co; kathleen.hoveler@allos.co; wellington.novaes@allos.co;alberto.oliveira@allos.co
B44: Sim | C44: Shopping Villa Lobos | D44: Limpeza | E44: Verzani | F44: 40 | G44: 43 | H44: 5 | I44: 0 | J44: 237725.81 | K44: 0 | L44: -735.39 | M44: 0 | N44: 0 | O44: 0 | P44: 0 | Q44: 0 | R44: 0 | S44: 0 | T44: Sim | U44: =(J44+L44+Q44+R44+S44+N44)+IF(T44="Sim",O44+P44,0) -> 236990.42 | W44: =IF(J44="","",U44*(1+V44)) -> 236990.42 | Z44: 45689 | AA44: {=IFERROR( IF( _xlfn.XLOOKUP( 1, ( ('Condição de Faturamento'!$A$2:$A$1000 = Tabela1[[#This Row],[Unidade]]) * ('Condição de Faturamento'!$B$2:$B$1000 = Tabela1[[#This Row],[Categoria]]) * ('Condição de Faturamento'!$C$2:$C$1000 = Tabela1[[#This Row],[Fornecedor]]) ), 'Condição de Faturamento'!$D$2:$D$1000 ) = "Emissão no mês da prestação do serviço", Tabela1[[#This Row],[Mês de referência para faturamento]], DATE( YEAR(Tabela1[[#This Row],[Mês de referência para faturamento]]), MONTH(Tabela1[[#This Row],[Mês de referência para faturamento]]) + 1, DAY(Tabela1[[#This Row],[Mês de referência para faturamento]]) ) ), DATE( YEAR(Tabela1[[#This Row],[Mês de referência para faturamento]]), MONTH(Tabela1[[#This Row],[Mês de referência para faturamento]]) + 1, DAY(Tabela1[[#This Row],[Mês de referência para faturamento]]) ) )} -> 45717 | AI44: =K44-L44 -> 735.39 | AJ44: =AB44-AC44 -> 0 | AK44: =J44-U44 -> 735.39 | AM44: =_xlfn.XLOOKUP(Tabela1[[#This Row],[Unidade]],tabShoppingsEmails[Shopping],tabShoppingsEmails[E-mails consolidados]) -> renan.mattos@allos.co; rita.silva@allos.co; kathleen.hoveler@allos.co; wellington.novaes@allos.co;alberto.oliveira@allos.co
B45: Sim | C45: Shopping Villa Lobos | D45: Limpeza | E45: Verzani | F45: 40 | G45: 43 | H45: 23 | I45: 0 | J45: 237725.81 | K45: 0 | L45: -3965.17 | M45: 0 | N45: 0 | O45: -2773.47 | P45: 0 | Q45: 0 | R45: 0 | S45: 0 | T45: Sim | U45: =(J45+L45+Q45+R45+S45+N45)+IF(T45="Sim",O45+P45,0) -> 230987.17 | W45: =IF(J45="","",U45*(1+V45)) -> 230987.17 | Z45: 45717 | AA45: {=IFERROR( IF( _xlfn.XLOOKUP( 1, ( ('Condição de Faturamento'!$A$2:$A$1000 = Tabela1[[#This Row],[Unidade]]) * ('Condição de Faturamento'!$B$2:$B$1000 = Tabela1[[#This Row],[Categoria]]) * ('Condição de Faturamento'!$C$2:$C$1000 = Tabela1[[#This Row],[Fornecedor]]) ), 'Condição de Faturamento'!$D$2:$D$1000 ) = "Emissão no mês da prestação do serviço", Tabela1[[#This Row],[Mês de referência para faturamento]], DATE( YEAR(Tabela1[[#This Row],[Mês de referência para faturamento]]), MONTH(Tabela1[[#This Row],[Mês de referência para faturamento]]) + 1, DAY(Tabela1[[#This Row],[Mês de referência para faturamento]]) ) ), DATE( YEAR(Tabela1[[#This Row],[Mês de referência para faturamento]]), MONTH(Tabela1[[#This Row],[Mês de referência para faturamento]]) + 1, DAY(Tabela1[[#This Row],[Mês de referência para faturamento]]) ) )} -> 45748 | AI45: =K45-L45 -> 3965.17 | AJ45: =AB45-AC45 -> 0 | AK45: =J45-U45 -> 6738.64 | AM45: =_xlfn.XLOOKUP(Tabela1[[#This Row],[Unidade]],tabShoppingsEmails[Shopping],tabShoppingsEmails[E-mails consolidados]) -> renan.mattos@allos.co; rita.silva@allos.co; kathleen.hoveler@allos.co; wellington.novaes@allos.co;alberto.oliveira@allos.co
A46: 45791 | B46: Sim | C46: Shopping Villa Lobos | D46: Limpeza | E46: Verzani | F46: 40 | G46: 43 | H46: 83 | I46: 0 | J46: 237725.81 | K46: 0 | L46: -15191.88 | M46: 0 | N46: 0 | O46: -2773.47 | P46: 0 | Q46: 0 | R46: 0 | S46: 0 | T46: Sim | U46: =(J46+L46+Q46+R46+S46+N46)+IF(T46="Sim",O46+P46,0) -> 219760.46 | W46: =IF(J46="","",U46*(1+V46)) -> 219760.46 | Z46: 45748 | AA46: {=IFERROR( IF( _xlfn.XLOOKUP( 1, ( ('Condição de Faturamento'!$A$2:$A$1000 = Tabela1[[#This Row],[Unidade]]) * ('Condição de Faturamento'!$B$2:$B$1000 = Tabela1[[#This Row],[Categoria]]) * ('Condição de Faturamento'!$C$2:$C$1000 = Tabela1[[#This Row],[Fornecedor]]) ), 'Condição de Faturamento'!$D$2:$D$1000 ) = "Emissão no mês da prestação do serviço", Tabela1[[#This Row],[Mês de referência para faturamento]], DATE( YEAR(Tabela1[[#This Row],[Mês de referência para faturamento]]), MONTH(Tabela1[[#This Row],[Mês de referência para faturamento]]) + 1, DAY(Tabela1[[#This Row],[Mês de referência para faturamento]]) ) ), DATE( YEAR(Tabela1[[#This Row],[Mês de referência para faturamento]]), MONTH(Tabela1[[#This Row],[Mês de referência para faturamento]]) + 1, DAY(Tabela1[[#This Row],[Mês de referência para faturamento]]) ) )} -> 45778 | AI46: =K46-L46 -> 15191.88 | AJ46: =AB46-AC46 -> 0 | AK46: =J46-U46 -> 17965.35 | AM46: =_xlfn.XLOOKUP(Tabela1[[#This Row],[Unidade]],tabShoppingsEmails[Shopping],tabShoppingsEmails[E-mails consolidados]) -> renan.mattos@allos.co; rita.silva@allos.co; kathleen.hoveler@allos.co; wellington.novaes@allos.co;alberto.oliveira@allos.co
A47: 45821 | B47: Sim | C47: Shopping Villa Lobos | D47: Limpeza | E47: Verzani | F47: 40 | G47: 43 | H47: 40 | I47: 0 | J47: 269020.92 | K47: 0 | L47: -7274.72 | M47: 0 | N47: 0 | O47: -2690.21 | P47: 0 | Q47: 0 | R47: 0 | S47: 0 | T47: Sim | U47: =(J47+L47+Q47+R47+S47+N47)+IF(T47="Sim",O47+P47,0) -> 259055.99 | W47: =IF(J47="","",U47*(1+V47)) -> 259055.99 | Z47: 45778 | AA47: {=IFERROR( IF( _xlfn.XLOOKUP( 1, ( ('Condição de Faturamento'!$A$2:$A$1000 = Tabela1[[#This Row],[Unidade]]) * ('Condição de Faturamento'!$B$2:$B$1000 = Tabela1[[#This Row],[Categoria]]) * ('Condição de Faturamento'!$C$2:$C$1000 = Tabela1[[#This Row],[Fornecedor]]) ), 'Condição de Faturamento'!$D$2:$D$1000 ) = "Emissão no mês da prestação do serviço", Tabela1[[#This Row],[Mês de referência para faturamento]], DATE( YEAR(Tabela1[[#This Row],[Mês de referência para faturamento]]), MONTH(Tabela1[[#This Row],[Mês de referência para faturamento]]) + 1, DAY(Tabela1[[#This Row],[Mês de referência para faturamento]]) ) ), DATE( YEAR(Tabela1[[#This Row],[Mês de referência para faturamento]]), MONTH(Tabela1[[#This Row],[Mês de referência para faturamento]]) + 1, DAY(Tabela1[[#This Row],[Mês de referência para faturamento]]) ) )} -> 45809 | AI47: =K47-L47 -> 7274.72 | AJ47: =AB47-AC47 -> 0 | AK47: =J47-U47 -> 9964.93 | AM47: =_xlfn.XLOOKUP(Tabela1[[#This Row],[Unidade]],tabShoppingsEmails[Shopping],tabShoppingsEmails[E-mails consolidados]) -> renan.mattos@allos.co; rita.silva@allos.co; kathleen.hoveler@allos.co; wellington.novaes@allos.co;alberto.oliveira@allos.co
A48: 45841 | B48: Sim | C48: Shopping Villa Lobos | D48: Limpeza | E48: Verzani | F48: 40 | G48: 43 | H48: 71 | I48: 0 | J48: 269020.92 | K48: 0 | L48: -14198.88 | M48: 0 | N48: 0 | O48: -2690.21 | P48: 0 | Q48: 0 | R48: =265404.035735233-Tabela1[[#This Row],[Valor Planilha]] -> -3616.8866 | S48: 0 | T48: Sim | U48: =(J48+L48+Q48+R48+S48+N48)+IF(T48="Sim",O48+P48,0) -> 248514.95 | W48: =IF(J48="","",U48*(1+V48)) -> 248514.95 | Z48: 45809 | AA48: {=IFERROR( IF( _xlfn.XLOOKUP( 1, ( ('Condição de Faturamento'!$A$2:$A$1000 = Tabela1[[#This Row],[Unidade]]) * ('Condição de Faturamento'!$B$2:$B$1000 = Tabela1[[#This Row],[Categoria]]) * ('Condição de Faturamento'!$C$2:$C$1000 = Tabela1[[#This Row],[Fornecedor]]) ), 'Condição de Faturamento'!$D$2:$D$1000 ) = "Emissão no mês da prestação do serviço", Tabela1[[#This Row],[Mês de referência para faturamento]], DATE( YEAR(Tabela1[[#This Row],[Mês de referência para faturamento]]), MONTH(Tabela1[[#This Row],[Mês de referência para faturamento]]) + 1, DAY(Tabela1[[#This Row],[Mês de referência para faturamento]]) ) ), DATE( YEAR(Tabela1[[#This Row],[Mês de referência para faturamento]]), MONTH(Tabela1[[#This Row],[Mês de referência para faturamento]]) + 1, DAY(Tabela1[[#This Row],[Mês de referência para faturamento]]) ) )} -> 45839 | AI48: =K48-L48 -> 14198.88 | AJ48: =AB48-AC48 -> 0 | AK48: =J48-U48 -> 20505.977 | AM48: =_xlfn.XLOOKUP(Tabela1[[#This Row],[Unidade]],tabShoppingsEmails[Shopping],tabShoppingsEmails[E-mails consolidados]) -> renan.mattos@allos.co; rita.silva@allos.co; kathleen.hoveler@allos.co; wellington.novaes@allos.co;alberto.oliveira@allos.co
A49: 45873 | B49: Sim | C49: Shopping Villa Lobos | D49: Limpeza | E49: Verzani | F49: 40 | G49: 43 | H49: 86 | I49: 0 | J49: 269020.92 | K49: 0 | L49: -16723.36 | M49: 0 | N49: 0 | O49: -3362.76 | P49: 0 | Q49: 0 | R49: =266489.101703822-Tabela1[[#This Row],[Valor Planilha]] -> -2531.8206 | S49: -8075.58 | T49: Sim | U49: =(J49+L49+Q49+R49+S49+N49)+IF(T49="Sim",O49+P49,0) -> 238327.4 | W49: =IF(J49="","",U49*(1+V49)) -> 238327.4 | Z49: 45839 | AA49: {=IFERROR( IF( _xlfn.XLOOKUP( 1, ( ('Condição de Faturamento'!$A$2:$A$1000 = Tabela1[[#This Row],[Unidade]]) * ('Condição de Faturamento'!$B$2:$B$1000 = Tabela1[[#This Row],[Categoria]]) * ('Condição de Faturamento'!$C$2:$C$1000 = Tabela1[[#This Row],[Fornecedor]]) ), 'Condição de Faturamento'!$D$2:$D$1000 ) = "Emissão no mês da prestação do serviço", Tabela1[[#This Row],[Mês de referência para faturamento]], DATE( YEAR(Tabela1[[#This Row],[Mês de referência para faturamento]]), MONTH(Tabela1[[#This Row],[Mês de referência para faturamento]]) + 1, DAY(Tabela1[[#This Row],[Mês de referência para faturamento]]) ) ), DATE( YEAR(Tabela1[[#This Row],[Mês de referência para faturamento]]), MONTH(Tabela1[[#This Row],[Mês de referência para faturamento]]) + 1, DAY(Tabela1[[#This Row],[Mês de referência para faturamento]]) ) )} -> 45870 | AI49: =K49-L49 -> 16723.36 | AJ49: =AB49-AC49 -> 0 | AK49: =J49-U49 -> 30693.521 | AM49: =_xlfn.XLOOKUP(Tabela1[[#This Row],[Unidade]],tabShoppingsEmails[Shopping],tabShoppingsEmails[E-mails consolidados]) -> renan.mattos@allos.co; rita.silva@allos.co; kathleen.hoveler@allos.co; wellington.novaes@allos.co;alberto.oliveira@allos.co
A50: 45904 | B50: Sim | C50: Shopping Villa Lobos | D50: Limpeza | E50: Verzani | F50: 40 | G50: 43 | H50: 149 | I50: 0 | J50: 269020.92 | K50: 0 | L50: -26494.99 | M50: 0 | N50: 0 | O50: -2690.21 | P50: 0 | Q50: 0 | R50: =265765.724391429-Tabela1[[#This Row],[Valor Planilha]] -> -3255.1979 | S50: 0 | T50: Sim | U50: =(J50+L50+Q50+R50+S50+N50)+IF(T50="Sim",O50+P50,0) -> 236580.52 | W50: =IF(J50="","",U50*(1+V50)) -> 236580.52 | Z50: 45870 | AA50: {=IFERROR( IF( _xlfn.XLOOKUP( 1, ( ('Condição de Faturamento'!$A$2:$A$1000 = Tabela1[[#This Row],[Unidade]]) * ('Condição de Faturamento'!$B$2:$B$1000 = Tabela1[[#This Row],[Categoria]]) * ('Condição de Faturamento'!$C$2:$C$1000 = Tabela1[[#This Row],[Fornecedor]]) ), 'Condição de Faturamento'!$D$2:$D$1000 ) = "Emissão no mês da prestação do serviço", Tabela1[[#This Row],[Mês de referência para faturamento]], DATE( YEAR(Tabela1[[#This Row],[Mês de referência para faturamento]]), MONTH(Tabela1[[#This Row],[Mês de referência para faturamento]]) + 1, DAY(Tabela1[[#This Row],[Mês de referência para faturamento]]) ) ), DATE( YEAR(Tabela1[[#This Row],[Mês de referência para faturamento]]), MONTH(Tabela1[[#This Row],[Mês de referência para faturamento]]) + 1, DAY(Tabela1[[#This Row],[Mês de referência para faturamento]]) ) )} -> 45901 | AI50: =K50-L50 -> 26494.99 | AJ50: =AB50-AC50 -> 0 | AK50: =J50-U50 -> 32440.398 | AM50: =_xlfn.XLOOKUP(Tabela1[[#This Row],[Unidade]],tabShoppingsEmails[Shopping],tabShoppingsEmails[E-mails consolidados]) -> renan.mattos@allos.co; rita.silva@allos.co; kathleen.hoveler@allos.co; wellington.novaes@allos.co;alberto.oliveira@allos.co
A51: 45933 | B51: Sim | C51: Shopping Villa Lobos | D51: Limpeza | E51: Verzani | F51: 40 | G51: 43 | H51: 61 | I51: 0 | J51: 269020.92 | K51: 0 | L51: -12307.61 | M51: 0 | N51: 0 | O51: -3138.58 | P51: 0 | Q51: 0 | R51: -1808.44 | S51: 0 | T51: Sim | U51: =(J51+L51+Q51+R51+S51+N51)+IF(T51="Sim",O51+P51,0) -> 251766.29 | W51: =IF(J51="","",U51*(1+V51)) -> 251766.29 | Z51: 45901 | AA51: {=IFERROR( IF( _xlfn.XLOOKUP( 1, ( ('Condição de Faturamento'!$A$2:$A$1000 = Tabela1[[#This Row],[Unidade]]) * ('Condição de Faturamento'!$B$2:$B$1000 = Tabela1[[#This Row],[Categoria]]) * ('Condição de Faturamento'!$C$2:$C$1000 = Tabela1[[#This Row],[Fornecedor]]) ), 'Condição de Faturamento'!$D$2:$D$1000 ) = "Emissão no mês da prestação do serviço", Tabela1[[#This Row],[Mês de referência para faturamento]], DATE( YEAR(Tabela1[[#This Row],[Mês de referência para faturamento]]), MONTH(Tabela1[[#This Row],[Mês de referência para faturamento]]) + 1, DAY(Tabela1[[#This Row],[Mês de referência para faturamento]]) ) ), DATE( YEAR(Tabela1[[#This Row],[Mês de referência para faturamento]]), MONTH(Tabela1[[#This Row],[Mês de referência para faturamento]]) + 1, DAY(Tabela1[[#This Row],[Mês de referência para faturamento]]) ) )} -> 45931 | AI51: =K51-L51 -> 12307.61 | AJ51: =AB51-AC51 -> 0 | AK51: =J51-U51 -> 17254.63 | AM51: =_xlfn.XLOOKUP(Tabela1[[#This Row],[Unidade]],tabShoppingsEmails[Shopping],tabShoppingsEmails[E-mails consolidados]) -> renan.mattos@allos.co; rita.silva@allos.co; kathleen.hoveler@allos.co; wellington.novaes@allos.co;alberto.oliveira@allos.co
C52: Shopping Villa Lobos | D52: Limpeza | E52: Verzani | F52: 40 | U52: =(J52+L52+Q52+R52+S52+N52)+IF(T52="Sim",O52+P52,0) -> 0 | W52: =IF(J52="","",U52*(1+V52)) | Z52: 45931 | AA52: {=IFERROR( IF( _xlfn.XLOOKUP( 1, ( ('Condição de Faturamento'!$A$2:$A$1000 = Tabela1[[#This Row],[Unidade]]) * ('Condição de Faturamento'!$B$2:$B$1000 = Tabela1[[#This Row],[Categoria]]) * ('Condição de Faturamento'!$C$2:$C$1000 = Tabela1[[#This Row],[Fornecedor]]) ), 'Condição de Faturamento'!$D$2:$D$1000 ) = "Emissão no mês da prestação do serviço", Tabela1[[#This Row],[Mês de referência para faturamento]], DATE( YEAR(Tabela1[[#This Row],[Mês de referência para faturamento]]), MONTH(Tabela1[[#This Row],[Mês de referência para faturamento]]) + 1, DAY(Tabela1[[#This Row],[Mês de referência para faturamento]]) ) ), DATE( YEAR(Tabela1[[#This Row],[Mês de referência para faturamento]]), MONTH(Tabela1[[#This Row],[Mês de referência para faturamento]]) + 1, DAY(Tabela1[[#This Row],[Mês de referência para faturamento]]) ) )} -> 45962 | AI52: =K52-L52 -> 0 | AJ52: =AB52-AC52 -> 0 | AK52: =J52-U52 -> 0 | AM52: =_xlfn.XLOOKUP(Tabela1[[#This Row],[Unidade]],tabShoppingsEmails[Shopping],tabShoppingsEmails[E-mails consolidados]) -> renan.mattos@allos.co; rita.silva@allos.co; kathleen.hoveler@allos.co; wellington.novaes@allos.co;alberto.oliveira@allos.co
C53: Shopping Villa Lobos | D53: Limpeza | E53: Verzani | F53: 40 | U53: =(J53+L53+Q53+R53+S53+N53)+IF(T53="Sim",O53+P53,0) -> 0 | W53: =IF(J53="","",U53*(1+V53)) | Z53: 45962 | AA53: {=IFERROR( IF( _xlfn.XLOOKUP( 1, ( ('Condição de Faturamento'!$A$2:$A$1000 = Tabela1[[#This Row],[Unidade]]) * ('Condição de Faturamento'!$B$2:$B$1000 = Tabela1[[#This Row],[Categoria]]) * ('Condição de Faturamento'!$C$2:$C$1000 = Tabela1[[#This Row],[Fornecedor]]) ), 'Condição de Faturamento'!$D$2:$D$1000 ) = "Emissão no mês da prestação do serviço", Tabela1[[#This Row],[Mês de referência para faturamento]], DATE( YEAR(Tabela1[[#This Row],[Mês de referência para faturamento]]), MONTH(Tabela1[[#This Row],[Mês de referência para faturamento]]) + 1, DAY(Tabela1[[#This Row],[Mês de referência para faturamento]]) ) ), DATE( YEAR(Tabela1[[#This Row],[Mês de referência para faturamento]]), MONTH(Tabela1[[#This Row],[Mês de referência para faturamento]]) + 1, DAY(Tabela1[[#This Row],[Mês de referência para faturamento]]) ) )} -> 45992 | AI53: =K53-L53 -> 0 | AJ53: =AB53-AC53 -> 0 | AK53: =J53-U53 -> 0 | AM53: =_xlfn.XLOOKUP(Tabela1[[#This Row],[Unidade]],tabShoppingsEmails[Shopping],tabShoppingsEmails[E-mails consolidados]) -> renan.mattos@allos.co; rita.silva@allos.co; kathleen.hoveler@allos.co; wellington.novaes@allos.co;alberto.oliveira@allos.co
C54: Shopping Villa Lobos | D54: Limpeza | E54: Verzani | F54: 40 | U54: =(J54+L54+Q54+R54+S54+N54)+IF(T54="Sim",O54+P54,0) -> 0 | W54: =IF(J54="","",U54*(1+V54)) | Z54: 45992 | AA54: {=IFERROR( IF( _xlfn.XLOOKUP( 1, ( ('Condição de Faturamento'!$A$2:$A$1000 = Tabela1[[#This Row],[Unidade]]) * ('Condição de Faturamento'!$B$2:$B$1000 = Tabela1[[#This Row],[Categoria]]) * ('Condição de Faturamento'!$C$2:$C$1000 = Tabela1[[#This Row],[Fornecedor]]) ), 'Condição de Faturamento'!$D$2:$D$1000 ) = "Emissão no mês da prestação do serviço", Tabela1[[#This Row],[Mês de referência para faturamento]], DATE( YEAR(Tabela1[[#This Row],[Mês de referência para faturamento]]), MONTH(Tabela1[[#This Row],[Mês de referência para faturamento]]) + 1, DAY(Tabela1[[#This Row],[Mês de referência para faturamento]]) ) ), DATE( YEAR(Tabela1[[#This Row],[Mês de referência para faturamento]]), MONTH(Tabela1[[#This Row],[Mês de referência para faturamento]]) + 1, DAY(Tabela1[[#This Row],[Mês de referência para faturamento]]) ) )} -> 46023 | AI54: =K54-L54 -> 0 | AJ54: =AB54-AC54 -> 0 | AK54: =J54-U54 -> 0 | AM54: =_xlfn.XLOOKUP(Tabela1[[#This Row],[Unidade]],tabShoppingsEmails[Shopping],tabShoppingsEmails[E-mails consolidados]) -> renan.mattos@allos.co; rita.silva@allos.co; kathleen.hoveler@allos.co; wellington.novaes@allos.co;alberto.oliveira@allos.co
B55: Não | C55: Shopping Villa Lobos | D55: Portaria | E55: GR | F55: 23 | G55: 23 | H55: informação pendente | I55: 0 | J55: 99311.15 | K55: 0 | M55: 0 | N55: 0 | O55: preenchimento pendente | P55: 0 | Q55: 0 | R55: 0 | S55: 0 | U55: =(J55+L55+Q55+R55+S55+N55)+IF(T55="Sim",O55+P55,0) -> 99311.15 | W55: =IF(J55="","",U55*(1+V55)) -> 99311.15 | Z55: 45658 | AA55: {=IFERROR( IF( _xlfn.XLOOKUP( 1, ( ('Condição de Faturamento'!$A$2:$A$1000 = Tabela1[[#This Row],[Unidade]]) * ('Condição de Faturamento'!$B$2:$B$1000 = Tabela1[[#This Row],[Categoria]]) * ('Condição de Faturamento'!$C$2:$C$1000 = Tabela1[[#This Row],[Fornecedor]]) ), 'Condição de Faturamento'!$D$2:$D$1000 ) = "Emissão no mês da prestação do serviço", Tabela1[[#This Row],[Mês de referência para faturamento]], DATE( YEAR(Tabela1[[#This Row],[Mês de referência para faturamento]]), MONTH(Tabela1[[#This Row],[Mês de referência para faturamento]]) + 1, DAY(Tabela1[[#This Row],[Mês de referência para faturamento]]) ) ), DATE( YEAR(Tabela1[[#This Row],[Mês de referência para faturamento]]), MONTH(Tabela1[[#This Row],[Mês de referência para faturamento]]) + 1, DAY(Tabela1[[#This Row],[Mês de referência para faturamento]]) ) )} -> 45689 | AI55: =K55-L55 -> 0 | AJ55: =AB55-AC55 -> 0 | AK55: =J55-U55 -> 0 | AM55: =_xlfn.XLOOKUP(Tabela1[[#This Row],[Unidade]],tabShoppingsEmails[Shopping],tabShoppingsEmails[E-mails consolidados]) -> renan.mattos@allos.co; rita.silva@allos.co; kathleen.hoveler@allos.co; wellington.novaes@allos.co;alberto.oliveira@allos.co
B56: Não | C56: Shopping Villa Lobos | D56: Portaria | E56: GR | F56: 23 | G56: 23 | H56: informação pendente | I56: 0 | J56: 99311.15 | K56: 0 | M56: 0 | N56: 0 | O56: preenchimento pendente | P56: 0 | Q56: 0 | R56: 0 | S56: 0 | U56: =(J56+L56+Q56+R56+S56+N56)+IF(T56="Sim",O56+P56,0) -> 99311.15 | W56: =IF(J56="","",U56*(1+V56)) -> 99311.15 | Z56: 45689 | AA56: {=IFERROR( IF( _xlfn.XLOOKUP( 1, ( ('Condição de Faturamento'!$A$2:$A$1000 = Tabela1[[#This Row],[Unidade]]) * ('Condição de Faturamento'!$B$2:$B$1000 = Tabela1[[#This Row],[Categoria]]) * ('Condição de Faturamento'!$C$2:$C$1000 = Tabela1[[#This Row],[Fornecedor]]) ), 'Condição de Faturamento'!$D$2:$D$1000 ) = "Emissão no mês da prestação do serviço", Tabela1[[#This Row],[Mês de referência para faturamento]], DATE( YEAR(Tabela1[[#This Row],[Mês de referência para faturamento]]), MONTH(Tabela1[[#This Row],[Mês de referência para faturamento]]) + 1, DAY(Tabela1[[#This Row],[Mês de referência para faturamento]]) ) ), DATE( YEAR(Tabela1[[#This Row],[Mês de referência para faturamento]]), MONTH(Tabela1[[#This Row],[Mês de referência para faturamento]]) + 1, DAY(Tabela1[[#This Row],[Mês de referência para faturamento]]) ) )} -> 45717 | AI56: =K56-L56 -> 0 | AJ56: =AB56-AC56 -> 0 | AK56: =J56-U56 -> 0 | AM56: =_xlfn.XLOOKUP(Tabela1[[#This Row],[Unidade]],tabShoppingsEmails[Shopping],tabShoppingsEmails[E-mails consolidados]) -> renan.mattos@allos.co; rita.silva@allos.co; kathleen.hoveler@allos.co; wellington.novaes@allos.co;alberto.oliveira@allos.co
B57: Não | C57: Shopping Villa Lobos | D57: Portaria | E57: GR | F57: 23 | G57: 23 | H57: informação pendente | I57: 0 | J57: 99311.15 | K57: 0 | M57: 0 | N57: 0 | O57: preenchimento pendente | P57: 0 | Q57: 0 | R57: 0 | S57: 0 | U57: =(J57+L57+Q57+R57+S57+N57)+IF(T57="Sim",O57+P57,0) -> 99311.15 | W57: =IF(J57="","",U57*(1+V57)) -> 99311.15 | Z57: 45717 | AA57: {=IFERROR( IF( _xlfn.XLOOKUP( 1, ( ('Condição de Faturamento'!$A$2:$A$1000 = Tabela1[[#This Row],[Unidade]]) * ('Condição de Faturamento'!$B$2:$B$1000 = Tabela1[[#This Row],[Categoria]]) * ('Condição de Faturamento'!$C$2:$C$1000 = Tabela1[[#This Row],[Fornecedor]]) ), 'Condição de Faturamento'!$D$2:$D$1000 ) = "Emissão no mês da prestação do serviço", Tabela1[[#This Row],[Mês de referência para faturamento]], DATE( YEAR(Tabela1[[#This Row],[Mês de referência para faturamento]]), MONTH(Tabela1[[#This Row],[Mês de referência para faturamento]]) + 1, DAY(Tabela1[[#This Row],[Mês de referência para faturamento]]) ) ), DATE( YEAR(Tabela1[[#This Row],[Mês de referência para faturamento]]), MONTH(Tabela1[[#This Row],[Mês de referência para faturamento]]) + 1, DAY(Tabela1[[#This Row],[Mês de referência para faturamento]]) ) )} -> 45748 | AI57: =K57-L57 -> 0 | AJ57: =AB57-AC57 -> 0 | AK57: =J57-U57 -> 0 | AM57: =_xlfn.XLOOKUP(Tabela1[[#This Row],[Unidade]],tabShoppingsEmails[Shopping],tabShoppingsEmails[E-mails consolidados]) -> renan.mattos@allos.co; rita.silva@allos.co; kathleen.hoveler@allos.co; wellington.novaes@allos.co;alberto.oliveira@allos.co
B58: Sim | C58: Shopping Villa Lobos | D58: Portaria | E58: GR | F58: 23 | G58: 25 | H58: 0 | I58: 261.5 | J58: 127372.29 | K58: 0 | L58: 0 | M58: 0 | N58: -6663.02 | O58: preenchimento pendente | P58: 0 | Q58: 0 | R58: 0 | S58: 0 | U58: =(J58+L58+Q58+R58+S58+N58)+IF(T58="Sim",O58+P58,0) -> 120709.27 | W58: =IF(J58="","",U58*(1+V58)) -> 120709.27 | Z58: 45748 | AA58: {=IFERROR( IF( _xlfn.XLOOKUP( 1, ( ('Condição de Faturamento'!$A$2:$A$1000 = Tabela1[[#This Row],[Unidade]]) * ('Condição de Faturamento'!$B$2:$B$1000 = Tabela1[[#This Row],[Categoria]]) * ('Condição de Faturamento'!$C$2:$C$1000 = Tabela1[[#This Row],[Fornecedor]]) ), 'Condição de Faturamento'!$D$2:$D$1000 ) = "Emissão no mês da prestação do serviço", Tabela1[[#This Row],[Mês de referência para faturamento]], DATE( YEAR(Tabela1[[#This Row],[Mês de referência para faturamento]]), MONTH(Tabela1[[#This Row],[Mês de referência para faturamento]]) + 1, DAY(Tabela1[[#This Row],[Mês de referência para faturamento]]) ) ), DATE( YEAR(Tabela1[[#This Row],[Mês de referência para faturamento]]), MONTH(Tabela1[[#This Row],[Mês de referência para faturamento]]) + 1, DAY(Tabela1[[#This Row],[Mês de referência para faturamento]]) ) )} -> 45778 | AI58: =K58-L58 -> 0 | AJ58: =AB58-AC58 -> 0 | AK58: =J58-U58 -> 6663.02 | AM58: =_xlfn.XLOOKUP(Tabela1[[#This Row],[Unidade]],tabShoppingsEmails[Shopping],tabShoppingsEmails[E-mails consolidados]) -> renan.mattos@allos.co; rita.silva@allos.co; kathleen.hoveler@allos.co; wellington.novaes@allos.co;alberto.oliveira@allos.co
A59: 45818 | B59: Sim | C59: Shopping Villa Lobos | D59: Portaria | E59: GR | F59: 23 | G59: 25 | H59: 16 | I59: 112.5 | J59: 127372.29 | K59: 0 | L59: -2663.27 | M59: 0 | N59: -2870.4 | O59: preenchimento pendente | P59: 0 | Q59: 0 | R59: 0 | S59: 0 | U59: =(J59+L59+Q59+R59+S59+N59)+IF(T59="Sim",O59+P59,0) -> 121838.62 | W59: =IF(J59="","",U59*(1+V59)) -> 121838.62 | Z59: 45778 | AA59: {=IFERROR( IF( _xlfn.XLOOKUP( 1, ( ('Condição de Faturamento'!$A$2:$A$1000 = Tabela1[[#This Row],[Unidade]]) * ('Condição de Faturamento'!$B$2:$B$1000 = Tabela1[[#This Row],[Categoria]]) * ('Condição de Faturamento'!$C$2:$C$1000 = Tabela1[[#This Row],[Fornecedor]]) ), 'Condição de Faturamento'!$D$2:$D$1000 ) = "Emissão no mês da prestação do serviço", Tabela1[[#This Row],[Mês de referência para faturamento]], DATE( YEAR(Tabela1[[#This Row],[Mês de referência para faturamento]]), MONTH(Tabela1[[#This Row],[Mês de referência para faturamento]]) + 1, DAY(Tabela1[[#This Row],[Mês de referência para faturamento]]) ) ), DATE( YEAR(Tabela1[[#This Row],[Mês de referência para faturamento]]), MONTH(Tabela1[[#This Row],[Mês de referência para faturamento]]) + 1, DAY(Tabela1[[#This Row],[Mês de referência para faturamento]]) ) )} -> 45809 | AB59: 147.41241 | AC59: 147.41241 | AI59: =K59-L59 -> 2663.27 | AJ59: =AB59-AC59 -> 0 | AK59: =J59-U59 -> 5533.67 | AM59: =_xlfn.XLOOKUP(Tabela1[[#This Row],[Unidade]],tabShoppingsEmails[Shopping],tabShoppingsEmails[E-mails consolidados]) -> renan.mattos@allos.co; rita.silva@allos.co; kathleen.hoveler@allos.co; wellington.novaes@allos.co;alberto.oliveira@allos.co
A60: 45842 | B60: Sim | C60: Shopping Villa Lobos | D60: Portaria | E60: GR | F60: 23 | G60: 25 | H60: 7 | I60: 117.33 | J60: 127372.29 | K60: 0 | L60: -1132.64 | M60: 0 | N60: -2997.5434 | O60: preenchimento pendente | P60: 0 | Q60: 0 | R60: 0 | S60: 0 | U60: =(J60+L60+Q60+R60+S60+N60)+IF(T60="Sim",O60+P60,0) -> 123242.11 | W60: =IF(J60="","",U60*(1+V60)) -> 123242.11 | Z60: 45809 | AA60: {=IFERROR( IF( _xlfn.XLOOKUP( 1, ( ('Condição de Faturamento'!$A$2:$A$1000 = Tabela1[[#This Row],[Unidade]]) * ('Condição de Faturamento'!$B$2:$B$1000 = Tabela1[[#This Row],[Categoria]]) * ('Condição de Faturamento'!$C$2:$C$1000 = Tabela1[[#This Row],[Fornecedor]]) ), 'Condição de Faturamento'!$D$2:$D$1000 ) = "Emissão no mês da prestação do serviço", Tabela1[[#This Row],[Mês de referência para faturamento]], DATE( YEAR(Tabela1[[#This Row],[Mês de referência para faturamento]]), MONTH(Tabela1[[#This Row],[Mês de referência para faturamento]]) + 1, DAY(Tabela1[[#This Row],[Mês de referência para faturamento]]) ) ), DATE( YEAR(Tabela1[[#This Row],[Mês de referência para faturamento]]), MONTH(Tabela1[[#This Row],[Mês de referência para faturamento]]) + 1, DAY(Tabela1[[#This Row],[Mês de referência para faturamento]]) ) )} -> 45839 | AB60: 165.83896 | AC60: 165.83896 | AI60: =K60-L60 -> 1132.64 | AJ60: =AB60-AC60 -> 0 | AK60: =J60-U60 -> 4130.1834 | AM60: =_xlfn.XLOOKUP(Tabela1[[#This Row],[Unidade]],tabShoppingsEmails[Shopping],tabShoppingsEmails[E-mails consolidados]) -> renan.mattos@allos.co; rita.silva@allos.co; kathleen.hoveler@allos.co; wellington.novaes@allos.co;alberto.oliveira@allos.co
A61: 45874 | B61: Sim | C61: Shopping Villa Lobos | D61: Portaria | E61: GR | F61: 23 | G61: 25 | H61: 5 | I61: 109 | J61: 127372.29 | K61: 0 | L61: -806.24 | M61: 0 | N61: -2810.87 | O61: preenchimento pendente | P61: 0 | Q61: 0 | R61: 0 | S61: 0 | U61: =(J61+L61+Q61+R61+S61+N61)+IF(T61="Sim",O61+P61,0) -> 123755.18 | W61: =IF(J61="","",U61*(1+V61)) -> 123755.18 | Z61: 45839 | AA61: {=IFERROR( IF( _xlfn.XLOOKUP( 1, ( ('Condição de Faturamento'!$A$2:$A$1000 = Tabela1[[#This Row],[Unidade]]) * ('Condição de Faturamento'!$B$2:$B$1000 = Tabela1[[#This Row],[Categoria]]) * ('Condição de Faturamento'!$C$2:$C$1000 = Tabela1[[#This Row],[Fornecedor]]) ), 'Condição de Faturamento'!$D$2:$D$1000 ) = "Emissão no mês da prestação do serviço", Tabela1[[#This Row],[Mês de referência para faturamento]], DATE( YEAR(Tabela1[[#This Row],[Mês de referência para faturamento]]), MONTH(Tabela1[[#This Row],[Mês de referência para faturamento]]) + 1, DAY(Tabela1[[#This Row],[Mês de referência para faturamento]]) ) ), DATE( YEAR(Tabela1[[#This Row],[Mês de referência para faturamento]]), MONTH(Tabela1[[#This Row],[Mês de referência para faturamento]]) + 1, DAY(Tabela1[[#This Row],[Mês de referência para faturamento]]) ) )} -> 45870 | AB61: 294.82482 | AC61: 294.82482 | AI61: =K61-L61 -> 806.24 | AJ61: =AB61-AC61 -> 0 | AK61: =J61-U61 -> 3617.11 | AM61: =_xlfn.XLOOKUP(Tabela1[[#This Row],[Unidade]],tabShoppingsEmails[Shopping],tabShoppingsEmails[E-mails consolidados]) -> renan.mattos@allos.co; rita.silva@allos.co; kathleen.hoveler@allos.co; wellington.novaes@allos.co;alberto.oliveira@allos.co
A62: 45906 | B62: Sim | C62: Shopping Villa Lobos | D62: Portaria | E62: GR | F62: 23 | G62: 25 | H62: 3 | I62: 110 | J62: 127372.29 | K62: 0 | L62: -482.28 | M62: 0 | N62: -2828.255 | O62: preenchimento pendente | P62: 0 | Q62: 0 | R62: 0 | S62: 0 | U62: =(J62+L62+Q62+R62+S62+N62)+IF(T62="Sim",O62+P62,0) -> 124061.76 | W62: =IF(J62="","",U62*(1+V62)) -> 124061.76 | Z62: 45870 | AA62: {=IFERROR( IF( _xlfn.XLOOKUP( 1, ( ('Condição de Faturamento'!$A$2:$A$1000 = Tabela1[[#This Row],[Unidade]]) * ('Condição de Faturamento'!$B$2:$B$1000 = Tabela1[[#This Row],[Categoria]]) * ('Condição de Faturamento'!$C$2:$C$1000 = Tabela1[[#This Row],[Fornecedor]]) ), 'Condição de Faturamento'!$D$2:$D$1000 ) = "Emissão no mês da prestação do serviço", Tabela1[[#This Row],[Mês de referência para faturamento]], DATE( YEAR(Tabela1[[#This Row],[Mês de referência para faturamento]]), MONTH(Tabela1[[#This Row],[Mês de referência para faturamento]]) + 1, DAY(Tabela1[[#This Row],[Mês de referência para faturamento]]) ) ), DATE( YEAR(Tabela1[[#This Row],[Mês de referência para faturamento]]), MONTH(Tabela1[[#This Row],[Mês de referência para faturamento]]) + 1, DAY(Tabela1[[#This Row],[Mês de referência para faturamento]]) ) )} -> 45901 | AB62: 128.98586 | AC62: 128.98586 | AI62: =K62-L62 -> 482.28 | AJ62: =AB62-AC62 -> 0 | AK62: =J62-U62 -> 3310.535 | AM62: =_xlfn.XLOOKUP(Tabela1[[#This Row],[Unidade]],tabShoppingsEmails[Shopping],tabShoppingsEmails[E-mails consolidados]) -> renan.mattos@allos.co; rita.silva@allos.co; kathleen.hoveler@allos.co; wellington.novaes@allos.co;alberto.oliveira@allos.co
A63: 45936 | B63: Sim | C63: Shopping Villa Lobos | D63: Portaria | E63: GR | F63: 23 | G63: 25 | H63: 8 | I63: 96 | J63: 127372.29 | K63: 0 | L63: -1303.16 | M63: 0 | N63: -2464.39 | O63: preenchimento pendente | P63: 0 | Q63: 0 | R63: 0 | S63: 0 | U63: =(J63+L63+Q63+R63+S63+N63)+IF(T63="Sim",O63+P63,0) -> 123604.74 | W63: =IF(J63="","",U63*(1+V63)) -> 123604.74 | Z63: 45901 | AA63: {=IFERROR( IF( _xlfn.XLOOKUP( 1, ( ('Condição de Faturamento'!$A$2:$A$1000 = Tabela1[[#This Row],[Unidade]]) * ('Condição de Faturamento'!$B$2:$B$1000 = Tabela1[[#This Row],[Categoria]]) * ('Condição de Faturamento'!$C$2:$C$1000 = Tabela1[[#This Row],[Fornecedor]]) ), 'Condição de Faturamento'!$D$2:$D$1000 ) = "Emissão no mês da prestação do serviço", Tabela1[[#This Row],[Mês de referência para faturamento]], DATE( YEAR(Tabela1[[#This Row],[Mês de referência para faturamento]]), MONTH(Tabela1[[#This Row],[Mês de referência para faturamento]]) + 1, DAY(Tabela1[[#This Row],[Mês de referência para faturamento]]) ) ), DATE( YEAR(Tabela1[[#This Row],[Mês de referência para faturamento]]), MONTH(Tabela1[[#This Row],[Mês de referência para faturamento]]) + 1, DAY(Tabela1[[#This Row],[Mês de referência para faturamento]]) ) )} -> 45931 | AB63: 286.80184 | AC63: 286.80184 | AI63: =K63-L63 -> 1303.16 | AJ63: =AB63-AC63 -> 0 | AK63: =J63-U63 -> 3767.55 | AM63: =_xlfn.XLOOKUP(Tabela1[[#This Row],[Unidade]],tabShoppingsEmails[Shopping],tabShoppingsEmails[E-mails consolidados]) -> renan.mattos@allos.co; rita.silva@allos.co; kathleen.hoveler@allos.co; wellington.novaes@allos.co;alberto.oliveira@allos.co
C64: Shopping Villa Lobos | D64: Portaria | E64: GR | F64: 23 | U64: =(J64+L64+Q64+R64+S64+N64)+IF(T64="Sim",O64+P64,0) -> 0 | W64: =IF(J64="","",U64*(1+V64)) | Z64: 45931 | AA64: {=IFERROR( IF( _xlfn.XLOOKUP( 1, ( ('Condição de Faturamento'!$A$2:$A$1000 = Tabela1[[#This Row],[Unidade]]) * ('Condição de Faturamento'!$B$2:$B$1000 = Tabela1[[#This Row],[Categoria]]) * ('Condição de Faturamento'!$C$2:$C$1000 = Tabela1[[#This Row],[Fornecedor]]) ), 'Condição de Faturamento'!$D$2:$D$1000 ) = "Emissão no mês da prestação do serviço", Tabela1[[#This Row],[Mês de referência para faturamento]], DATE( YEAR(Tabela1[[#This Row],[Mês de referência para faturamento]]), MONTH(Tabela1[[#This Row],[Mês de referência para faturamento]]) + 1, DAY(Tabela1[[#This Row],[Mês de referência para faturamento]]) ) ), DATE( YEAR(Tabela1[[#This Row],[Mês de referência para faturamento]]), MONTH(Tabela1[[#This Row],[Mês de referência para faturamento]]) + 1, DAY(Tabela1[[#This Row],[Mês de referência para faturamento]]) ) )} -> 45962 | AI64: =K64-L64 -> 0 | AJ64: =AB64-AC64 -> 0 | AK64: =J64-U64 -> 0 | AM64: =_xlfn.XLOOKUP(Tabela1[[#This Row],[Unidade]],tabShoppingsEmails[Shopping],tabShoppingsEmails[E-mails consolidados]) -> renan.mattos@allos.co; rita.silva@allos.co; kathleen.hoveler@allos.co; wellington.novaes@allos.co;alberto.oliveira@allos.co
C65: Shopping Villa Lobos | D65: Portaria | E65: GR | F65: 23 | U65: =(J65+L65+Q65+R65+S65+N65)+IF(T65="Sim",O65+P65,0) -> 0 | W65: =IF(J65="","",U65*(1+V65)) | Z65: 45962 | AA65: {=IFERROR( IF( _xlfn.XLOOKUP( 1, ( ('Condição de Faturamento'!$A$2:$A$1000 = Tabela1[[#This Row],[Unidade]]) * ('Condição de Faturamento'!$B$2:$B$1000 = Tabela1[[#This Row],[Categoria]]) * ('Condição de Faturamento'!$C$2:$C$1000 = Tabela1[[#This Row],[Fornecedor]]) ), 'Condição de Faturamento'!$D$2:$D$1000 ) = "Emissão no mês da prestação do serviço", Tabela1[[#This Row],[Mês de referência para faturamento]], DATE( YEAR(Tabela1[[#This Row],[Mês de referência para faturamento]]), MONTH(Tabela1[[#This Row],[Mês de referência para faturamento]]) + 1, DAY(Tabela1[[#This Row],[Mês de referência para faturamento]]) ) ), DATE( YEAR(Tabela1[[#This Row],[Mês de referência para faturamento]]), MONTH(Tabela1[[#This Row],[Mês de referência para faturamento]]) + 1, DAY(Tabela1[[#This Row],[Mês de referência para faturamento]]) ) )} -> 45992 | AI65: =K65-L65 -> 0 | AJ65: =AB65-AC65 -> 0 | AK65: =J65-U65 -> 0 | AM65: =_xlfn.XLOOKUP(Tabela1[[#This Row],[Unidade]],tabShoppingsEmails[Shopping],tabShoppingsEmails[E-mails consolidados]) -> renan.mattos@allos.co; rita.silva@allos.co; kathleen.hoveler@allos.co; wellington.novaes@allos.co;alberto.oliveira@allos.co
C66: Shopping Villa Lobos | D66: Portaria | E66: GR | F66: 23 | U66: =(J66+L66+Q66+R66+S66+N66)+IF(T66="Sim",O66+P66,0) -> 0 | W66: =IF(J66="","",U66*(1+V66)) | Z66: 45992 | AA66: {=IFERROR( IF( _xlfn.XLOOKUP( 1, ( ('Condição de Faturamento'!$A$2:$A$1000 = Tabela1[[#This Row],[Unidade]]) * ('Condição de Faturamento'!$B$2:$B$1000 = Tabela1[[#This Row],[Categoria]]) * ('Condição de Faturamento'!$C$2:$C$1000 = Tabela1[[#This Row],[Fornecedor]]) ), 'Condição de Faturamento'!$D$2:$D$1000 ) = "Emissão no mês da prestação do serviço", Tabela1[[#This Row],[Mês de referência para faturamento]], DATE( YEAR(Tabela1[[#This Row],[Mês de referência para faturamento]]), MONTH(Tabela1[[#This Row],[Mês de referência para faturamento]]) + 1, DAY(Tabela1[[#This Row],[Mês de referência para faturamento]]) ) ), DATE( YEAR(Tabela1[[#This Row],[Mês de referência para faturamento]]), MONTH(Tabela1[[#This Row],[Mês de referência para faturamento]]) + 1, DAY(Tabela1[[#This Row],[Mês de referência para faturamento]]) ) )} -> 46023 | AI66: =K66-L66 -> 0 | AJ66: =AB66-AC66 -> 0 | AK66: =J66-U66 -> 0 | AM66: =_xlfn.XLOOKUP(Tabela1[[#This Row],[Unidade]],tabShoppingsEmails[Shopping],tabShoppingsEmails[E-mails consolidados]) -> renan.mattos@allos.co; rita.silva@allos.co; kathleen.hoveler@allos.co; wellington.novaes@allos.co;alberto.oliveira@allos.co
B67: Não | C67: Shopping Villa Lobos | D67: Vigilância | E67: GR | F67: 2 | G67: 2 | H67: informação pendente | I67: 0 | J67: 12940.01 | K67: 0 | M67: 0 | N67: 0 | O67: preenchimento pendente | P67: 0 | Q67: 0 | R67: 0 | S67: 0 | U67: =(J67+L67+Q67+R67+S67+N67)+IF(T67="Sim",O67+P67,0) -> 12940.01 | W67: =IF(J67="","",U67*(1+V67)) -> 12940.01 | Z67: 45658 | AA67: {=IFERROR( IF( _xlfn.XLOOKUP( 1, ( ('Condição de Faturamento'!$A$2:$A$1000 = Tabela1[[#This Row],[Unidade]]) * ('Condição de Faturamento'!$B$2:$B$1000 = Tabela1[[#This Row],[Categoria]]) * ('Condição de Faturamento'!$C$2:$C$1000 = Tabela1[[#This Row],[Fornecedor]]) ), 'Condição de Faturamento'!$D$2:$D$1000 ) = "Emissão no mês da prestação do serviço", Tabela1[[#This Row],[Mês de referência para faturamento]], DATE( YEAR(Tabela1[[#This Row],[Mês de referência para faturamento]]), MONTH(Tabela1[[#This Row],[Mês de referência para faturamento]]) + 1, DAY(Tabela1[[#This Row],[Mês de referência para faturamento]]) ) ), DATE( YEAR(Tabela1[[#This Row],[Mês de referência para faturamento]]), MONTH(Tabela1[[#This Row],[Mês de referência para faturamento]]) + 1, DAY(Tabela1[[#This Row],[Mês de referência para faturamento]]) ) )} -> 45689 | AI67: =K67-L67 -> 0 | AJ67: =AB67-AC67 -> 0 | AK67: =J67-U67 -> 0 | AM67: =_xlfn.XLOOKUP(Tabela1[[#This Row],[Unidade]],tabShoppingsEmails[Shopping],tabShoppingsEmails[E-mails consolidados]) -> renan.mattos@allos.co; rita.silva@allos.co; kathleen.hoveler@allos.co; wellington.novaes@allos.co;alberto.oliveira@allos.co
B68: Não | C68: Shopping Villa Lobos | D68: Vigilância | E68: GR | F68: 2 | G68: 2 | H68: informação pendente | I68: 0 | J68: 12940.01 | K68: 0 | M68: 0 | N68: 0 | O68: preenchimento pendente | P68: 0 | Q68: 0 | R68: 0 | S68: 0 | U68: =(J68+L68+Q68+R68+S68+N68)+IF(T68="Sim",O68+P68,0) -> 12940.01 | W68: =IF(J68="","",U68*(1+V68)) -> 12940.01 | Z68: 45689 | AA68: {=IFERROR( IF( _xlfn.XLOOKUP( 1, ( ('Condição de Faturamento'!$A$2:$A$1000 = Tabela1[[#This Row],[Unidade]]) * ('Condição de Faturamento'!$B$2:$B$1000 = Tabela1[[#This Row],[Categoria]]) * ('Condição de Faturamento'!$C$2:$C$1000 = Tabela1[[#This Row],[Fornecedor]]) ), 'Condição de Faturamento'!$D$2:$D$1000 ) = "Emissão no mês da prestação do serviço", Tabela1[[#This Row],[Mês de referência para faturamento]], DATE( YEAR(Tabela1[[#This Row],[Mês de referência para faturamento]]), MONTH(Tabela1[[#This Row],[Mês de referência para faturamento]]) + 1, DAY(Tabela1[[#This Row],[Mês de referência para faturamento]]) ) ), DATE( YEAR(Tabela1[[#This Row],[Mês de referência para faturamento]]), MONTH(Tabela1[[#This Row],[Mês de referência para faturamento]]) + 1, DAY(Tabela1[[#This Row],[Mês de referência para faturamento]]) ) )} -> 45717 | AI68: =K68-L68 -> 0 | AJ68: =AB68-AC68 -> 0 | AK68: =J68-U68 -> 0 | AM68: =_xlfn.XLOOKUP(Tabela1[[#This Row],[Unidade]],tabShoppingsEmails[Shopping],tabShoppingsEmails[E-mails consolidados]) -> renan.mattos@allos.co; rita.silva@allos.co; kathleen.hoveler@allos.co; wellington.novaes@allos.co;alberto.oliveira@allos.co
B69: Não | C69: Shopping Villa Lobos | D69: Vigilância | E69: GR | F69: 2 | G69: 2 | H69: informação pendente | I69: 0 | J69: 12940.01 | K69: 0 | M69: 0 | N69: 0 | O69: preenchimento pendente | P69: 0 | Q69: 0 | R69: 0 | S69: 0 | U69: =(J69+L69+Q69+R69+S69+N69)+IF(T69="Sim",O69+P69,0) -> 12940.01 | W69: =IF(J69="","",U69*(1+V69)) -> 12940.01 | Z69: 45717 | AA69: {=IFERROR( IF( _xlfn.XLOOKUP( 1, ( ('Condição de Faturamento'!$A$2:$A$1000 = Tabela1[[#This Row],[Unidade]]) * ('Condição de Faturamento'!$B$2:$B$1000 = Tabela1[[#This Row],[Categoria]]) * ('Condição de Faturamento'!$C$2:$C$1000 = Tabela1[[#This Row],[Fornecedor]]) ), 'Condição de Faturamento'!$D$2:$D$1000 ) = "Emissão no mês da prestação do serviço", Tabela1[[#This Row],[Mês de referência para faturamento]], DATE( YEAR(Tabela1[[#This Row],[Mês de referência para faturamento]]), MONTH(Tabela1[[#This Row],[Mês de referência para faturamento]]) + 1, DAY(Tabela1[[#This Row],[Mês de referência para faturamento]]) ) ), DATE( YEAR(Tabela1[[#This Row],[Mês de referência para faturamento]]), MONTH(Tabela1[[#This Row],[Mês de referência para faturamento]]) + 1, DAY(Tabela1[[#This Row],[Mês de referência para faturamento]]) ) )} -> 45748 | AI69: =K69-L69 -> 0 | AJ69: =AB69-AC69 -> 0 | AK69: =J69-U69 -> 0 | AM69: =_xlfn.XLOOKUP(Tabela1[[#This Row],[Unidade]],tabShoppingsEmails[Shopping],tabShoppingsEmails[E-mails consolidados]) -> renan.mattos@allos.co; rita.silva@allos.co; kathleen.hoveler@allos.co; wellington.novaes@allos.co;alberto.oliveira@allos.co
B70: Sim | C70: Shopping Villa Lobos | D70: Vigilância | E70: GR | F70: 12 | G70: 12 | H70: 0 | I70: 69.5 | J70: 92569.71 | K70: 0 | L70: 0 | M70: 0 | N70: -2543.7 | O70: preenchimento pendente | P70: 0 | Q70: 0 | R70: 0 | S70: 0 | U70: =(J70+L70+Q70+R70+S70+N70)+IF(T70="Sim",O70+P70,0) -> 90026.01 | W70: =IF(J70="","",U70*(1+V70)) -> 90026.01 | Z70: 45748 | AA70: {=IFERROR( IF( _xlfn.XLOOKUP( 1, ( ('Condição de Faturamento'!$A$2:$A$1000 = Tabela1[[#This Row],[Unidade]]) * ('Condição de Faturamento'!$B$2:$B$1000 = Tabela1[[#This Row],[Categoria]]) * ('Condição de Faturamento'!$C$2:$C$1000 = Tabela1[[#This Row],[Fornecedor]]) ), 'Condição de Faturamento'!$D$2:$D$1000 ) = "Emissão no mês da prestação do serviço", Tabela1[[#This Row],[Mês de referência para faturamento]], DATE( YEAR(Tabela1[[#This Row],[Mês de referência para faturamento]]), MONTH(Tabela1[[#This Row],[Mês de referência para faturamento]]) + 1, DAY(Tabela1[[#This Row],[Mês de referência para faturamento]]) ) ), DATE( YEAR(Tabela1[[#This Row],[Mês de referência para faturamento]]), MONTH(Tabela1[[#This Row],[Mês de referência para faturamento]]) + 1, DAY(Tabela1[[#This Row],[Mês de referência para faturamento]]) ) )} -> 45778 | AI70: =K70-L70 -> 0 | AJ70: =AB70-AC70 -> 0 | AK70: =J70-U70 -> 2543.7 | AM70: =_xlfn.XLOOKUP(Tabela1[[#This Row],[Unidade]],tabShoppingsEmails[Shopping],tabShoppingsEmails[E-mails consolidados]) -> renan.mattos@allos.co; rita.silva@allos.co; kathleen.hoveler@allos.co; wellington.novaes@allos.co;alberto.oliveira@allos.co
A71: 45818 | B71: Sim | C71: Shopping Villa Lobos | D71: Vigilância | E71: GR | F71: 12 | G71: 12 | H71: 5 | I71: 35.5 | J71: 92569.71 | K71: 0 | L71: -1084.7 | M71: 0 | N71: -1231.895 | O71: preenchimento pendente | P71: 0 | Q71: 0 | R71: 0 | S71: 0 | U71: =(J71+L71+Q71+R71+S71+N71)+IF(T71="Sim",O71+P71,0) -> 90253.115 | W71: =IF(J71="","",U71*(1+V71)) -> 90253.115 | Z71: 45778 | AA71: {=IFERROR( IF( _xlfn.XLOOKUP( 1, ( ('Condição de Faturamento'!$A$2:$A$1000 = Tabela1[[#This Row],[Unidade]]) * ('Condição de Faturamento'!$B$2:$B$1000 = Tabela1[[#This Row],[Categoria]]) * ('Condição de Faturamento'!$C$2:$C$1000 = Tabela1[[#This Row],[Fornecedor]]) ), 'Condição de Faturamento'!$D$2:$D$1000 ) = "Emissão no mês da prestação do serviço", Tabela1[[#This Row],[Mês de referência para faturamento]], DATE( YEAR(Tabela1[[#This Row],[Mês de referência para faturamento]]), MONTH(Tabela1[[#This Row],[Mês de referência para faturamento]]) + 1, DAY(Tabela1[[#This Row],[Mês de referência para faturamento]]) ) ), DATE( YEAR(Tabela1[[#This Row],[Mês de referência para faturamento]]), MONTH(Tabela1[[#This Row],[Mês de referência para faturamento]]) + 1, DAY(Tabela1[[#This Row],[Mês de referência para faturamento]]) ) )} -> 45809 | AI71: =K71-L71 -> 1084.7 | AJ71: =AB71-AC71 -> 0 | AK71: =J71-U71 -> 2316.595 | AM71: =_xlfn.XLOOKUP(Tabela1[[#This Row],[Unidade]],tabShoppingsEmails[Shopping],tabShoppingsEmails[E-mails consolidados]) -> renan.mattos@allos.co; rita.silva@allos.co; kathleen.hoveler@allos.co; wellington.novaes@allos.co;alberto.oliveira@allos.co
A72: 45842 | B72: Sim | C72: Shopping Villa Lobos | D72: Vigilância | E72: GR | F72: 12 | G72: 12 | H72: 2 | I72: 27.5 | J72: 92569.71 | K72: 0 | L72: -447.81 | M72: 0 | N72: -981.085 | O72: preenchimento pendente | P72: 0 | Q72: 0 | R72: 0 | S72: 0 | U72: =(J72+L72+Q72+R72+S72+N72)+IF(T72="Sim",O72+P72,0) -> 91140.815 | W72: =IF(J72="","",U72*(1+V72)) -> 91140.815 | Z72: 45809 | AA72: {=IFERROR( IF( _xlfn.XLOOKUP( 1, ( ('Condição de Faturamento'!$A$2:$A$1000 = Tabela1[[#This Row],[Unidade]]) * ('Condição de Faturamento'!$B$2:$B$1000 = Tabela1[[#This Row],[Categoria]]) * ('Condição de Faturamento'!$C$2:$C$1000 = Tabela1[[#This Row],[Fornecedor]]) ), 'Condição de Faturamento'!$D$2:$D$1000 ) = "Emissão no mês da prestação do serviço", Tabela1[[#This Row],[Mês de referência para faturamento]], DATE( YEAR(Tabela1[[#This Row],[Mês de referência para faturamento]]), MONTH(Tabela1[[#This Row],[Mês de referência para faturamento]]) + 1, DAY(Tabela1[[#This Row],[Mês de referência para faturamento]]) ) ), DATE( YEAR(Tabela1[[#This Row],[Mês de referência para faturamento]]), MONTH(Tabela1[[#This Row],[Mês de referência para faturamento]]) + 1, DAY(Tabela1[[#This Row],[Mês de referência para faturamento]]) ) )} -> 45839 | AI72: =K72-L72 -> 447.81 | AJ72: =AB72-AC72 -> 0 | AK72: =J72-U72 -> 1428.895 | AM72: =_xlfn.XLOOKUP(Tabela1[[#This Row],[Unidade]],tabShoppingsEmails[Shopping],tabShoppingsEmails[E-mails consolidados]) -> renan.mattos@allos.co; rita.silva@allos.co; kathleen.hoveler@allos.co; wellington.novaes@allos.co;alberto.oliveira@allos.co
A73: 45874 | B73: Sim | C73: Shopping Villa Lobos | D73: Vigilância | E73: GR | F73: 12 | G73: 12 | H73: 1 | I73: 17 | J73: 92569.71 | K73: 0 | L73: -230.87 | M73: 0 | N73: -587.95 | O73: preenchimento pendente | P73: 0 | Q73: 0 | R73: 0 | S73: 0 | U73: =(J73+L73+Q73+R73+S73+N73)+IF(T73="Sim",O73+P73,0) -> 91750.89 | W73: =IF(J73="","",U73*(1+V73)) -> 91750.89 | Z73: 45839 | AA73: {=IFERROR( IF( _xlfn.XLOOKUP( 1, ( ('Condição de Faturamento'!$A$2:$A$1000 = Tabela1[[#This Row],[Unidade]]) * ('Condição de Faturamento'!$B$2:$B$1000 = Tabela1[[#This Row],[Categoria]]) * ('Condição de Faturamento'!$C$2:$C$1000 = Tabela1[[#This Row],[Fornecedor]]) ), 'Condição de Faturamento'!$D$2:$D$1000 ) = "Emissão no mês da prestação do serviço", Tabela1[[#This Row],[Mês de referência para faturamento]], DATE( YEAR(Tabela1[[#This Row],[Mês de referência para faturamento]]), MONTH(Tabela1[[#This Row],[Mês de referência para faturamento]]) + 1, DAY(Tabela1[[#This Row],[Mês de referência para faturamento]]) ) ), DATE( YEAR(Tabela1[[#This Row],[Mês de referência para faturamento]]), MONTH(Tabela1[[#This Row],[Mês de referência para faturamento]]) + 1, DAY(Tabela1[[#This Row],[Mês de referência para faturamento]]) ) )} -> 45870 | AI73: =K73-L73 -> 230.87 | AJ73: =AB73-AC73 -> 0 | AK73: =J73-U73 -> 818.82 | AM73: =_xlfn.XLOOKUP(Tabela1[[#This Row],[Unidade]],tabShoppingsEmails[Shopping],tabShoppingsEmails[E-mails consolidados]) -> renan.mattos@allos.co; rita.silva@allos.co; kathleen.hoveler@allos.co; wellington.novaes@allos.co;alberto.oliveira@allos.co
A74: 45906 | B74: Sim | C74: Shopping Villa Lobos | D74: Vigilância | E74: GR | F74: 12 | G74: 12 | H74: 0 | I74: 11 | J74: 92569.71 | K74: 0 | L74: 0 | M74: 0 | N74: -389.34 | O74: preenchimento pendente | P74: 0 | Q74: 0 | R74: 0 | S74: 0 | U74: =(J74+L74+Q74+R74+S74+N74)+IF(T74="Sim",O74+P74,0) -> 92180.37 | W74: =IF(J74="","",U74*(1+V74)) -> 92180.37 | Z74: 45870 | AA74: {=IFERROR( IF( _xlfn.XLOOKUP( 1, ( ('Condição de Faturamento'!$A$2:$A$1000 = Tabela1[[#This Row],[Unidade]]) * ('Condição de Faturamento'!$B$2:$B$1000 = Tabela1[[#This Row],[Categoria]]) * ('Condição de Faturamento'!$C$2:$C$1000 = Tabela1[[#This Row],[Fornecedor]]) ), 'Condição de Faturamento'!$D$2:$D$1000 ) = "Emissão no mês da prestação do serviço", Tabela1[[#This Row],[Mês de referência para faturamento]], DATE( YEAR(Tabela1[[#This Row],[Mês de referência para faturamento]]), MONTH(Tabela1[[#This Row],[Mês de referência para faturamento]]) + 1, DAY(Tabela1[[#This Row],[Mês de referência para faturamento]]) ) ), DATE( YEAR(Tabela1[[#This Row],[Mês de referência para faturamento]]), MONTH(Tabela1[[#This Row],[Mês de referência para faturamento]]) + 1, DAY(Tabela1[[#This Row],[Mês de referência para faturamento]]) ) )} -> 45901 | AI74: =K74-L74 -> 0 | AJ74: =AB74-AC74 -> 0 | AK74: =J74-U74 -> 389.34 | AM74: =_xlfn.XLOOKUP(Tabela1[[#This Row],[Unidade]],tabShoppingsEmails[Shopping],tabShoppingsEmails[E-mails consolidados]) -> renan.mattos@allos.co; rita.silva@allos.co; kathleen.hoveler@allos.co; wellington.novaes@allos.co;alberto.oliveira@allos.co
A75: 45936 | B75: Sim | C75: Shopping Villa Lobos | D75: Vigilância | E75: GR | F75: 12 | G75: 12 | H75: 3 | I75: 23.5 | J75: 92569.71 | K75: 0 | L75: -692.61 | M75: 0 | N75: -831.37 | O75: preenchimento pendente | P75: 0 | Q75: 0 | R75: 0 | S75: 0 | U75: =(J75+L75+Q75+R75+S75+N75)+IF(T75="Sim",O75+P75,0) -> 91045.73 | W75: =IF(J75="","",U75*(1+V75)) -> 91045.73 | Z75: 45901 | AA75: {=IFERROR( IF( _xlfn.XLOOKUP( 1, ( ('Condição de Faturamento'!$A$2:$A$1000 = Tabela1[[#This Row],[Unidade]]) * ('Condição de Faturamento'!$B$2:$B$1000 = Tabela1[[#This Row],[Categoria]]) * ('Condição de Faturamento'!$C$2:$C$1000 = Tabela1[[#This Row],[Fornecedor]]) ), 'Condição de Faturamento'!$D$2:$D$1000 ) = "Emissão no mês da prestação do serviço", Tabela1[[#This Row],[Mês de referência para faturamento]], DATE( YEAR(Tabela1[[#This Row],[Mês de referência para faturamento]]), MONTH(Tabela1[[#This Row],[Mês de referência para faturamento]]) + 1, DAY(Tabela1[[#This Row],[Mês de referência para faturamento]]) ) ), DATE( YEAR(Tabela1[[#This Row],[Mês de referência para faturamento]]), MONTH(Tabela1[[#This Row],[Mês de referência para faturamento]]) + 1, DAY(Tabela1[[#This Row],[Mês de referência para faturamento]]) ) )} -> 45931 | AI75: =K75-L75 -> 692.61 | AJ75: =AB75-AC75 -> 0 | AK75: =J75-U75 -> 1523.98 | AM75: =_xlfn.XLOOKUP(Tabela1[[#This Row],[Unidade]],tabShoppingsEmails[Shopping],tabShoppingsEmails[E-mails consolidados]) -> renan.mattos@allos.co; rita.silva@allos.co; kathleen.hoveler@allos.co; wellington.novaes@allos.co;alberto.oliveira@allos.co
C76: Shopping Villa Lobos | D76: Vigilância | E76: GR | F76: 12 | U76: =(J76+L76+Q76+R76+S76+N76)+IF(T76="Sim",O76+P76,0) -> 0 | W76: =IF(J76="","",U76*(1+V76)) | Z76: 45931 | AA76: {=IFERROR( IF( _xlfn.XLOOKUP( 1, ( ('Condição de Faturamento'!$A$2:$A$1000 = Tabela1[[#This Row],[Unidade]]) * ('Condição de Faturamento'!$B$2:$B$1000 = Tabela1[[#This Row],[Categoria]]) * ('Condição de Faturamento'!$C$2:$C$1000 = Tabela1[[#This Row],[Fornecedor]]) ), 'Condição de Faturamento'!$D$2:$D$1000 ) = "Emissão no mês da prestação do serviço", Tabela1[[#This Row],[Mês de referência para faturamento]], DATE( YEAR(Tabela1[[#This Row],[Mês de referência para faturamento]]), MONTH(Tabela1[[#This Row],[Mês de referência para faturamento]]) + 1, DAY(Tabela1[[#This Row],[Mês de referência para faturamento]]) ) ), DATE( YEAR(Tabela1[[#This Row],[Mês de referência para faturamento]]), MONTH(Tabela1[[#This Row],[Mês de referência para faturamento]]) + 1, DAY(Tabela1[[#This Row],[Mês de referência para faturamento]]) ) )} -> 45962 | AI76: =K76-L76 -> 0 | AJ76: =AB76-AC76 -> 0 | AK76: =J76-U76 -> 0 | AM76: =_xlfn.XLOOKUP(Tabela1[[#This Row],[Unidade]],tabShoppingsEmails[Shopping],tabShoppingsEmails[E-mails consolidados]) -> renan.mattos@allos.co; rita.silva@allos.co; kathleen.hoveler@allos.co; wellington.novaes@allos.co;alberto.oliveira@allos.co
C77: Shopping Villa Lobos | D77: Vigilância | E77: GR | F77: 12 | U77: =(J77+L77+Q77+R77+S77+N77)+IF(T77="Sim",O77+P77,0) -> 0 | W77: =IF(J77="","",U77*(1+V77)) | Z77: 45962 | AA77: {=IFERROR( IF( _xlfn.XLOOKUP( 1, ( ('Condição de Faturamento'!$A$2:$A$1000 = Tabela1[[#This Row],[Unidade]]) * ('Condição de Faturamento'!$B$2:$B$1000 = Tabela1[[#This Row],[Categoria]]) * ('Condição de Faturamento'!$C$2:$C$1000 = Tabela1[[#This Row],[Fornecedor]]) ), 'Condição de Faturamento'!$D$2:$D$1000 ) = "Emissão no mês da prestação do serviço", Tabela1[[#This Row],[Mês de referência para faturamento]], DATE( YEAR(Tabela1[[#This Row],[Mês de referência para faturamento]]), MONTH(Tabela1[[#This Row],[Mês de referência para faturamento]]) + 1, DAY(Tabela1[[#This Row],[Mês de referência para faturamento]]) ) ), DATE( YEAR(Tabela1[[#This Row],[Mês de referência para faturamento]]), MONTH(Tabela1[[#This Row],[Mês de referência para faturamento]]) + 1, DAY(Tabela1[[#This Row],[Mês de referência para faturamento]]) ) )} -> 45992 | AI77: =K77-L77 -> 0 | AJ77: =AB77-AC77 -> 0 | AK77: =J77-U77 -> 0 | AM77: =_xlfn.XLOOKUP(Tabela1[[#This Row],[Unidade]],tabShoppingsEmails[Shopping],tabShoppingsEmails[E-mails consolidados]) -> renan.mattos@allos.co; rita.silva@allos.co; kathleen.hoveler@allos.co; wellington.novaes@allos.co;alberto.oliveira@allos.co
C78: Shopping Villa Lobos | D78: Vigilância | E78: GR | F78: 12 | U78: =(J78+L78+Q78+R78+S78+N78)+IF(T78="Sim",O78+P78,0) -> 0 | W78: =IF(J78="","",U78*(1+V78)) | Z78: 45992 | AA78: {=IFERROR( IF( _xlfn.XLOOKUP( 1, ( ('Condição de Faturamento'!$A$2:$A$1000 = Tabela1[[#This Row],[Unidade]]) * ('Condição de Faturamento'!$B$2:$B$1000 = Tabela1[[#This Row],[Categoria]]) * ('Condição de Faturamento'!$C$2:$C$1000 = Tabela1[[#This Row],[Fornecedor]]) ), 'Condição de Faturamento'!$D$2:$D$1000 ) = "Emissão no mês da prestação do serviço", Tabela1[[#This Row],[Mês de referência para faturamento]], DATE( YEAR(Tabela1[[#This Row],[Mês de referência para faturamento]]), MONTH(Tabela1[[#This Row],[Mês de referência para faturamento]]) + 1, DAY(Tabela1[[#This Row],[Mês de referência para faturamento]]) ) ), DATE( YEAR(Tabela1[[#This Row],[Mês de referência para faturamento]]), MONTH(Tabela1[[#This Row],[Mês de referência para faturamento]]) + 1, DAY(Tabela1[[#This Row],[Mês de referência para faturamento]]) ) )} -> 46023 | AI78: =K78-L78 -> 0 | AJ78: =AB78-AC78 -> 0 | AK78: =J78-U78 -> 0 | AM78: =_xlfn.XLOOKUP(Tabela1[[#This Row],[Unidade]],tabShoppingsEmails[Shopping],tabShoppingsEmails[E-mails consolidados]) -> renan.mattos@allos.co; rita.silva@allos.co; kathleen.hoveler@allos.co; wellington.novaes@allos.co;alberto.oliveira@allos.co
C79: Shopping Villa Lobos | D79: PMOC | E79: Brasanitas | F79: 4 | G79: 2 | J79: =(16870.77/(365.25/12))*8 -> 4434.2065 | U79: =(J79+L79+Q79+R79+S79+N79)+IF(T79="Sim",O79+P79,0) -> 4434.2065 | W79: =IF(J79="","",U79*(1+V79)) -> 4434.2065 | Z79: 45931 | AA79: {=IFERROR( IF( _xlfn.XLOOKUP( 1, ( ('Condição de Faturamento'!$A$2:$A$1000 = Tabela1[[#This Row],[Unidade]]) * ('Condição de Faturamento'!$B$2:$B$1000 = Tabela1[[#This Row],[Categoria]]) * ('Condição de Faturamento'!$C$2:$C$1000 = Tabela1[[#This Row],[Fornecedor]]) ), 'Condição de Faturamento'!$D$2:$D$1000 ) = "Emissão no mês da prestação do serviço", Tabela1[[#This Row],[Mês de referência para faturamento]], DATE( YEAR(Tabela1[[#This Row],[Mês de referência para faturamento]]), MONTH(Tabela1[[#This Row],[Mês de referência para faturamento]]) + 1, DAY(Tabela1[[#This Row],[Mês de referência para faturamento]]) ) ), DATE( YEAR(Tabela1[[#This Row],[Mês de referência para faturamento]]), MONTH(Tabela1[[#This Row],[Mês de referência para faturamento]]) + 1, DAY(Tabela1[[#This Row],[Mês de referência para faturamento]]) ) )} -> 45962 | AI79: =K79-L79 -> 0 | AJ79: =AB79-AC79 -> 0 | AK79: =J79-U79 -> 0 | AM79: =_xlfn.XLOOKUP(Tabela1[[#This Row],[Unidade]],tabShoppingsEmails[Shopping],tabShoppingsEmails[E-mails consolidados]) -> renan.mattos@allos.co; rita.silva@allos.co; kathleen.hoveler@allos.co; wellington.novaes@allos.co;alberto.oliveira@allos.co
C80: Shopping Villa Lobos | D80: PMOC | E80: Brasanitas | F80: 4 | G80: 2 | J80: 16870.77 | U80: =(J80+L80+Q80+R80+S80+N80)+IF(T80="Sim",O80+P80,0) -> 16870.77 | W80: =IF(J80="","",U80*(1+V80)) -> 16870.77 | Z80: 45962 | AA80: {=IFERROR( IF( _xlfn.XLOOKUP( 1, ( ('Condição de Faturamento'!$A$2:$A$1000 = Tabela1[[#This Row],[Unidade]]) * ('Condição de Faturamento'!$B$2:$B$1000 = Tabela1[[#This Row],[Categoria]]) * ('Condição de Faturamento'!$C$2:$C$1000 = Tabela1[[#This Row],[Fornecedor]]) ), 'Condição de Faturamento'!$D$2:$D$1000 ) = "Emissão no mês da prestação do serviço", Tabela1[[#This Row],[Mês de referência para faturamento]], DATE( YEAR(Tabela1[[#This Row],[Mês de referência para faturamento]]), MONTH(Tabela1[[#This Row],[Mês de referência para faturamento]]) + 1, DAY(Tabela1[[#This Row],[Mês de referência para faturamento]]) ) ), DATE( YEAR(Tabela1[[#This Row],[Mês de referência para faturamento]]), MONTH(Tabela1[[#This Row],[Mês de referência para faturamento]]) + 1, DAY(Tabela1[[#This Row],[Mês de referência para faturamento]]) ) )} -> 45992 | AI80: =K80-L80 -> 0 | AJ80: =AB80-AC80 -> 0 | AK80: =J80-U80 -> 0 | AM80: =_xlfn.XLOOKUP(Tabela1[[#This Row],[Unidade]],tabShoppingsEmails[Shopping],tabShoppingsEmails[E-mails consolidados]) -> renan.mattos@allos.co; rita.silva@allos.co; kathleen.hoveler@allos.co; wellington.novaes@allos.co;alberto.oliveira@allos.co
C81: Shopping Villa Lobos | D81: PMOC | E81: Brasanitas | F81: 4 | G81: 2 | U81: =(J81+L81+Q81+R81+S81+N81)+IF(T81="Sim",O81+P81,0) -> 0 | W81: =IF(J81="","",U81*(1+V81)) | Z81: 45992 | AA81: {=IFERROR( IF( _xlfn.XLOOKUP( 1, ( ('Condição de Faturamento'!$A$2:$A$1000 = Tabela1[[#This Row],[Unidade]]) * ('Condição de Faturamento'!$B$2:$B$1000 = Tabela1[[#This Row],[Categoria]]) * ('Condição de Faturamento'!$C$2:$C$1000 = Tabela1[[#This Row],[Fornecedor]]) ), 'Condição de Faturamento'!$D$2:$D$1000 ) = "Emissão no mês da prestação do serviço", Tabela1[[#This Row],[Mês de referência para faturamento]], DATE( YEAR(Tabela1[[#This Row],[Mês de referência para faturamento]]), MONTH(Tabela1[[#This Row],[Mês de referência para faturamento]]) + 1, DAY(Tabela1[[#This Row],[Mês de referência para faturamento]]) ) ), DATE( YEAR(Tabela1[[#This Row],[Mês de referência para faturamento]]), MONTH(Tabela1[[#This Row],[Mês de referência para faturamento]]) + 1, DAY(Tabela1[[#This Row],[Mês de referência para faturamento]]) ) )} -> 46023 | AI81: =K81-L81 -> 0 | AJ81: =AB81-AC81 -> 0 | AK81: =J81-U81 -> 0 | AM81: =_xlfn.XLOOKUP(Tabela1[[#This Row],[Unidade]],tabShoppingsEmails[Shopping],tabShoppingsEmails[E-mails consolidados]) -> renan.mattos@allos.co; rita.silva@allos.co; kathleen.hoveler@allos.co; wellington.novaes@allos.co;alberto.oliveira@allos.co
B82: Sim | C82: Shopping Villa Lobos | D82: Manutenção | E82: Grupo Opus | F82: 29 | G82: 1 | H82: 0 | I82: 0 | J82: 8657.34 | K82: 0 | L82: 0 | M82: 0 | N82: 0 | O82: 0 | P82: 0 | Q82: 0 | R82: 0 | S82: 0 | T82: Sim | U82: =(J82+L82+Q82+R82+S82+N82)+IF(T82="Sim",O82+P82,0) -> 8657.34 | W82: =IF(J82="","",U82*(1+V82)) -> 8657.34 | Z82: 45658 | AA82: {=IFERROR( IF( _xlfn.XLOOKUP( 1, ( ('Condição de Faturamento'!$A$2:$A$1000 = Tabela1[[#This Row],[Unidade]]) * ('Condição de Faturamento'!$B$2:$B$1000 = Tabela1[[#This Row],[Categoria]]) * ('Condição de Faturamento'!$C$2:$C$1000 = Tabela1[[#This Row],[Fornecedor]]) ), 'Condição de Faturamento'!$D$2:$D$1000 ) = "Emissão no mês da prestação do serviço", Tabela1[[#This Row],[Mês de referência para faturamento]], DATE( YEAR(Tabela1[[#This Row],[Mês de referência para faturamento]]), MONTH(Tabela1[[#This Row],[Mês de referência para faturamento]]) + 1, DAY(Tabela1[[#This Row],[Mês de referência para faturamento]]) ) ), DATE( YEAR(Tabela1[[#This Row],[Mês de referência para faturamento]]), MONTH(Tabela1[[#This Row],[Mês de referência para faturamento]]) + 1, DAY(Tabela1[[#This Row],[Mês de referência para faturamento]]) ) )} -> 45689 | AI82: =K82-L82 -> 0 | AJ82: =AB82-AC82 -> 0 | AK82: =J82-U82 -> 0 | AM82: =_xlfn.XLOOKUP(Tabela1[[#This Row],[Unidade]],tabShoppingsEmails[Shopping],tabShoppingsEmails[E-mails consolidados]) -> renan.mattos@allos.co; rita.silva@allos.co; kathleen.hoveler@allos.co; wellington.novaes@allos.co;alberto.oliveira@allos.co
B83: Sim | C83: Shopping Villa Lobos | D83: Manutenção | E83: Grupo Opus | F83: 29 | G83: 1 | H83: 0 | I83: 0 | J83: 8657.34 | K83: 0 | L83: 0 | M83: 0 | N83: 0 | O83: 0 | P83: 0 | Q83: 0 | R83: 0 | S83: 0 | T83: Sim | U83: =(J83+L83+Q83+R83+S83+N83)+IF(T83="Sim",O83+P83,0) -> 8657.34 | W83: =IF(J83="","",U83*(1+V83)) -> 8657.34 | Z83: 45689 | AA83: {=IFERROR( IF( _xlfn.XLOOKUP( 1, ( ('Condição de Faturamento'!$A$2:$A$1000 = Tabela1[[#This Row],[Unidade]]) * ('Condição de Faturamento'!$B$2:$B$1000 = Tabela1[[#This Row],[Categoria]]) * ('Condição de Faturamento'!$C$2:$C$1000 = Tabela1[[#This Row],[Fornecedor]]) ), 'Condição de Faturamento'!$D$2:$D$1000 ) = "Emissão no mês da prestação do serviço", Tabela1[[#This Row],[Mês de referência para faturamento]], DATE( YEAR(Tabela1[[#This Row],[Mês de referência para faturamento]]), MONTH(Tabela1[[#This Row],[Mês de referência para faturamento]]) + 1, DAY(Tabela1[[#This Row],[Mês de referência para faturamento]]) ) ), DATE( YEAR(Tabela1[[#This Row],[Mês de referência para faturamento]]), MONTH(Tabela1[[#This Row],[Mês de referência para faturamento]]) + 1, DAY(Tabela1[[#This Row],[Mês de referência para faturamento]]) ) )} -> 45717 | AI83: =K83-L83 -> 0 | AJ83: =AB83-AC83 -> 0 | AK83: =J83-U83 -> 0 | AM83: =_xlfn.XLOOKUP(Tabela1[[#This Row],[Unidade]],tabShoppingsEmails[Shopping],tabShoppingsEmails[E-mails consolidados]) -> renan.mattos@allos.co; rita.silva@allos.co; kathleen.hoveler@allos.co; wellington.novaes@allos.co;alberto.oliveira@allos.co
B84: Sim | C84: Shopping Villa Lobos | D84: Manutenção | E84: Grupo Opus | F84: 29 | G84: 5 | H84: 31 | I84: 0 | J84: =8936.39+((33435/(365.25/12))*24) -> 35299.922 | K84: 0 | L84: -10724.72 | M84: 0 | N84: 0 | O84: -764.83 | P84: 0 | Q84: 0 | R84: 0 | S84: 0 | T84: Sim | U84: =(J84+L84+Q84+R84+S84+N84)+IF(T84="Sim",O84+P84,0) -> 23810.372 | W84: =IF(J84="","",U84*(1+V84)) -> 23810.372 | Z84: 45717 | AA84: {=IFERROR( IF( _xlfn.XLOOKUP( 1, ( ('Condição de Faturamento'!$A$2:$A$1000 = Tabela1[[#This Row],[Unidade]]) * ('Condição de Faturamento'!$B$2:$B$1000 = Tabela1[[#This Row],[Categoria]]) * ('Condição de Faturamento'!$C$2:$C$1000 = Tabela1[[#This Row],[Fornecedor]]) ), 'Condição de Faturamento'!$D$2:$D$1000 ) = "Emissão no mês da prestação do serviço", Tabela1[[#This Row],[Mês de referência para faturamento]], DATE( YEAR(Tabela1[[#This Row],[Mês de referência para faturamento]]), MONTH(Tabela1[[#This Row],[Mês de referência para faturamento]]) + 1, DAY(Tabela1[[#This Row],[Mês de referência para faturamento]]) ) ), DATE( YEAR(Tabela1[[#This Row],[Mês de referência para faturamento]]), MONTH(Tabela1[[#This Row],[Mês de referência para faturamento]]) + 1, DAY(Tabela1[[#This Row],[Mês de referência para faturamento]]) ) )} -> 45748 | AB84: 8177.07 | AC84: 8668 | AI84: =K84-L84 -> 10724.72 | AJ84: =AB84-AC84 -> -490.93 | AK84: =J84-U84 -> 11489.55 | AM84: =_xlfn.XLOOKUP(Tabela1[[#This Row],[Unidade]],tabShoppingsEmails[Shopping],tabShoppingsEmails[E-mails consolidados]) -> renan.mattos@allos.co; rita.silva@allos.co; kathleen.hoveler@allos.co; wellington.novaes@allos.co;alberto.oliveira@allos.co
B85: Sim | C85: Shopping Villa Lobos | D85: Manutenção | E85: Grupo Opus | F85: 29 | G85: 5 | H85: 0 | I85: 0 | J85: 42371.386 | K85: 0 | L85: 0 | M85: 0 | N85: 0 | O85: 0 | P85: 0 | Q85: 0 | R85: 0 | S85: 0 | T85: Sim | U85: =(J85+L85+Q85+R85+S85+N85)+IF(T85="Sim",O85+P85,0) -> 42371.386 | W85: =IF(J85="","",U85*(1+V85)) -> 42371.386 | Z85: 45748 | AA85: {=IFERROR( IF( _xlfn.XLOOKUP( 1, ( ('Condição de Faturamento'!$A$2:$A$1000 = Tabela1[[#This Row],[Unidade]]) * ('Condição de Faturamento'!$B$2:$B$1000 = Tabela1[[#This Row],[Categoria]]) * ('Condição de Faturamento'!$C$2:$C$1000 = Tabela1[[#This Row],[Fornecedor]]) ), 'Condição de Faturamento'!$D$2:$D$1000 ) = "Emissão no mês da prestação do serviço", Tabela1[[#This Row],[Mês de referência para faturamento]], DATE( YEAR(Tabela1[[#This Row],[Mês de referência para faturamento]]), MONTH(Tabela1[[#This Row],[Mês de referência para faturamento]]) + 1, DAY(Tabela1[[#This Row],[Mês de referência para faturamento]]) ) ), DATE( YEAR(Tabela1[[#This Row],[Mês de referência para faturamento]]), MONTH(Tabela1[[#This Row],[Mês de referência para faturamento]]) + 1, DAY(Tabela1[[#This Row],[Mês de referência para faturamento]]) ) )} -> 45778 | AI85: =K85-L85 -> 0 | AJ85: =AB85-AC85 -> 0 | AK85: =J85-U85 -> 0 | AM85: =_xlfn.XLOOKUP(Tabela1[[#This Row],[Unidade]],tabShoppingsEmails[Shopping],tabShoppingsEmails[E-mails consolidados]) -> renan.mattos@allos.co; rita.silva@allos.co; kathleen.hoveler@allos.co; wellington.novaes@allos.co;alberto.oliveira@allos.co
A86: 45066 | B86: Sim | C86: Shopping Villa Lobos | D86: Manutenção | E86: Grupo Opus | F86: 29 | G86: 5 | H86: 21 | I86: 0 | J86: 42371.386 | K86: -7177.12 | L86: -6677.62 | M86: 0 | N86: 0 | O86: -70.62 | P86: 0 | Q86: 0 | R86: 0 | S86: 0 | T86: Sim | U86: =(J86+L86+Q86+R86+S86+N86)+IF(T86="Sim",O86+P86,0) -> 35623.146 | W86: =IF(J86="","",U86*(1+V86)) -> 35623.146 | Z86: 45778 | AA86: {=IFERROR( IF( _xlfn.XLOOKUP( 1, ( ('Condição de Faturamento'!$A$2:$A$1000 = Tabela1[[#This Row],[Unidade]]) * ('Condição de Faturamento'!$B$2:$B$1000 = Tabela1[[#This Row],[Categoria]]) * ('Condição de Faturamento'!$C$2:$C$1000 = Tabela1[[#This Row],[Fornecedor]]) ), 'Condição de Faturamento'!$D$2:$D$1000 ) = "Emissão no mês da prestação do serviço", Tabela1[[#This Row],[Mês de referência para faturamento]], DATE( YEAR(Tabela1[[#This Row],[Mês de referência para faturamento]]), MONTH(Tabela1[[#This Row],[Mês de referência para faturamento]]) + 1, DAY(Tabela1[[#This Row],[Mês de referência para faturamento]]) ) ), DATE( YEAR(Tabela1[[#This Row],[Mês de referência para faturamento]]), MONTH(Tabela1[[#This Row],[Mês de referência para faturamento]]) + 1, DAY(Tabela1[[#This Row],[Mês de referência para faturamento]]) ) )} -> 45809 | AI86: =K86-L86 -> -499.5 | AJ86: =AB86-AC86 -> 0 | AK86: =J86-U86 -> 6748.24 | AM86: =_xlfn.XLOOKUP(Tabela1[[#This Row],[Unidade]],tabShoppingsEmails[Shopping],tabShoppingsEmails[E-mails consolidados]) -> renan.mattos@allos.co; rita.silva@allos.co; kathleen.hoveler@allos.co; wellington.novaes@allos.co;alberto.oliveira@allos.co
A87: 45831 | B87: Sim | C87: Shopping Villa Lobos | D87: Manutenção | E87: Grupo Opus | F87: 29 | G87: 5 | H87: 15 | I87: 0 | J87: 42371.386 | K87: -2883.9 | L87: -2883.9 | M87: 0 | N87: 0 | O87: -918.05 | P87: 0 | Q87: 0 | R87: 0 | S87: 0 | T87: Sim | U87: =(J87+L87+Q87+R87+S87+N87)+IF(T87="Sim",O87+P87,0) -> 38569.436 | W87: =IF(J87="","",U87*(1+V87)) -> 38569.436 | Z87: 45809 | AA87: {=IFERROR( IF( _xlfn.XLOOKUP( 1, ( ('Condição de Faturamento'!$A$2:$A$1000 = Tabela1[[#This Row],[Unidade]]) * ('Condição de Faturamento'!$B$2:$B$1000 = Tabela1[[#This Row],[Categoria]]) * ('Condição de Faturamento'!$C$2:$C$1000 = Tabela1[[#This Row],[Fornecedor]]) ), 'Condição de Faturamento'!$D$2:$D$1000 ) = "Emissão no mês da prestação do serviço", Tabela1[[#This Row],[Mês de referência para faturamento]], DATE( YEAR(Tabela1[[#This Row],[Mês de referência para faturamento]]), MONTH(Tabela1[[#This Row],[Mês de referência para faturamento]]) + 1, DAY(Tabela1[[#This Row],[Mês de referência para faturamento]]) ) ), DATE( YEAR(Tabela1[[#This Row],[Mês de referência para faturamento]]), MONTH(Tabela1[[#This Row],[Mês de referência para faturamento]]) + 1, DAY(Tabela1[[#This Row],[Mês de referência para faturamento]]) ) )} -> 45839 | AI87: =K87-L87 -> 0 | AJ87: =AB87-AC87 -> 0 | AK87: =J87-U87 -> 3801.95 | AM87: =_xlfn.XLOOKUP(Tabela1[[#This Row],[Unidade]],tabShoppingsEmails[Shopping],tabShoppingsEmails[E-mails consolidados]) -> renan.mattos@allos.co; rita.silva@allos.co; kathleen.hoveler@allos.co; wellington.novaes@allos.co;alberto.oliveira@allos.co
A88: 45859 | B88: Sim | C88: Shopping Villa Lobos | D88: Manutenção | E88: Grupo Opus | F88: 29 | G88: 5 | H88: 32 | I88: 0 | J88: 42371.386 | K88: -6397.74 | L88: -539.56 | M88: 0 | N88: 0 | O88: -70.62 | P88: 0 | Q88: 0 | R88: 0 | S88: =36513.2079859281-Tabela1[[#This Row],[Valor Planilha]] -> -5858.1776 | T88: Sim | U88: =(J88+L88+Q88+R88+S88+N88)+IF(T88="Sim",O88+P88,0) -> 35903.028 | W88: =IF(J88="","",U88*(1+V88)) -> 35903.028 | Z88: 45839 | AA88: {=IFERROR( IF( _xlfn.XLOOKUP( 1, ( ('Condição de Faturamento'!$A$2:$A$1000 = Tabela1[[#This Row],[Unidade]]) * ('Condição de Faturamento'!$B$2:$B$1000 = Tabela1[[#This Row],[Categoria]]) * ('Condição de Faturamento'!$C$2:$C$1000 = Tabela1[[#This Row],[Fornecedor]]) ), 'Condição de Faturamento'!$D$2:$D$1000 ) = "Emissão no mês da prestação do serviço", Tabela1[[#This Row],[Mês de referência para faturamento]], DATE( YEAR(Tabela1[[#This Row],[Mês de referência para faturamento]]), MONTH(Tabela1[[#This Row],[Mês de referência para faturamento]]) + 1, DAY(Tabela1[[#This Row],[Mês de referência para faturamento]]) ) ), DATE( YEAR(Tabela1[[#This Row],[Mês de referência para faturamento]]), MONTH(Tabela1[[#This Row],[Mês de referência para faturamento]]) + 1, DAY(Tabela1[[#This Row],[Mês de referência para faturamento]]) ) )} -> 45870 | AI88: =K88-L88 -> -5858.18 | AJ88: =AB88-AC88 -> 0 | AK88: =J88-U88 -> 6468.3576 | AM88: =_xlfn.XLOOKUP(Tabela1[[#This Row],[Unidade]],tabShoppingsEmails[Shopping],tabShoppingsEmails[E-mails consolidados]) -> renan.mattos@allos.co; rita.silva@allos.co; kathleen.hoveler@allos.co; wellington.novaes@allos.co;alberto.oliveira@allos.co
A89: 45890 | B89: Sim | C89: Shopping Villa Lobos | D89: Manutenção | E89: Grupo Opus | F89: 29 | G89: 5 | H89: 7 | I89: 0 | J89: 42371.386 | K89: -1423.34 | L89: -1423.34 | M89: 0 | N89: 0 | O89: -494.33 | P89: 0 | Q89: 0 | R89: 0 | S89: 0 | T89: Sim | U89: =(J89+L89+Q89+R89+S89+N89)+IF(T89="Sim",O89+P89,0) -> 40453.716 | W89: =IF(J89="","",U89*(1+V89)) -> 40453.716 | Z89: 45870 | AA89: {=IFERROR( IF( _xlfn.XLOOKUP( 1, ( ('Condição de Faturamento'!$A$2:$A$1000 = Tabela1[[#This Row],[Unidade]]) * ('Condição de Faturamento'!$B$2:$B$1000 = Tabela1[[#This Row],[Categoria]]) * ('Condição de Faturamento'!$C$2:$C$1000 = Tabela1[[#This Row],[Fornecedor]]) ), 'Condição de Faturamento'!$D$2:$D$1000 ) = "Emissão no mês da prestação do serviço", Tabela1[[#This Row],[Mês de referência para faturamento]], DATE( YEAR(Tabela1[[#This Row],[Mês de referência para faturamento]]), MONTH(Tabela1[[#This Row],[Mês de referência para faturamento]]) + 1, DAY(Tabela1[[#This Row],[Mês de referência para faturamento]]) ) ), DATE( YEAR(Tabela1[[#This Row],[Mês de referência para faturamento]]), MONTH(Tabela1[[#This Row],[Mês de referência para faturamento]]) + 1, DAY(Tabela1[[#This Row],[Mês de referência para faturamento]]) ) )} -> 45901 | AB89: 4538.29 | AC89: 4117.7617 | AI89: =K89-L89 -> 0 | AJ89: =AB89-AC89 -> 420.52825 | AK89: =J89-U89 -> 1917.67 | AM89: =_xlfn.XLOOKUP(Tabela1[[#This Row],[Unidade]],tabShoppingsEmails[Shopping],tabShoppingsEmails[E-mails consolidados]) -> renan.mattos@allos.co; rita.silva@allos.co; kathleen.hoveler@allos.co; wellington.novaes@allos.co;alberto.oliveira@allos.co
A90: 45917 | B90: Sim | C90: Shopping Villa Lobos | D90: Manutenção | E90: Grupo Opus | F90: 29 | G90: 5 | H90: 1 | I90: 0 | J90: 42371.386 | K90: 0 | L90: -289.69 | M90: 0 | N90: 0 | O90: -70.62 | P90: 0 | Q90: 0 | R90: 0 | S90: 0 | T90: Sim | U90: =(J90+L90+Q90+R90+S90+N90)+IF(T90="Sim",O90+P90,0) -> 42011.076 | W90: =IF(J90="","",U90*(1+V90)) -> 42011.076 | Z90: 45901 | AA90: {=IFERROR( IF( _xlfn.XLOOKUP( 1, ( ('Condição de Faturamento'!$A$2:$A$1000 = Tabela1[[#This Row],[Unidade]]) * ('Condição de Faturamento'!$B$2:$B$1000 = Tabela1[[#This Row],[Categoria]]) * ('Condição de Faturamento'!$C$2:$C$1000 = Tabela1[[#This Row],[Fornecedor]]) ), 'Condição de Faturamento'!$D$2:$D$1000 ) = "Emissão no mês da prestação do serviço", Tabela1[[#This Row],[Mês de referência para faturamento]], DATE( YEAR(Tabela1[[#This Row],[Mês de referência para faturamento]]), MONTH(Tabela1[[#This Row],[Mês de referência para faturamento]]) + 1, DAY(Tabela1[[#This Row],[Mês de referência para faturamento]]) ) ), DATE( YEAR(Tabela1[[#This Row],[Mês de referência para faturamento]]), MONTH(Tabela1[[#This Row],[Mês de referência para faturamento]]) + 1, DAY(Tabela1[[#This Row],[Mês de referência para faturamento]]) ) )} -> 45931 | AI90: =K90-L90 -> 289.69 | AJ90: =AB90-AC90 -> 0 | AK90: =J90-U90 -> 360.31 | AM90: =_xlfn.XLOOKUP(Tabela1[[#This Row],[Unidade]],tabShoppingsEmails[Shopping],tabShoppingsEmails[E-mails consolidados]) -> renan.mattos@allos.co; rita.silva@allos.co; kathleen.hoveler@allos.co; wellington.novaes@allos.co;alberto.oliveira@allos.co
A91: 45953 | B91: Sim | C91: Shopping Villa Lobos | D91: Manutenção | E91: Grupo Opus | F91: 29 | G91: 5 | H91: 18 | I91: 0 | J91: =(42371.3856003551/(365.25/12))*22 -> 30625.724 | L91: -384.52 | N91: 0 | O91: preenchimento pendente | Q91: 0 | R91: 0 | S91: -3328.63 | T91: Não | U91: =(J91+L91+Q91+R91+S91+N91)+IF(T91="Sim",O91+P91,0) -> 26912.574 | W91: =IF(J91="","",U91*(1+V91)) -> 26912.574 | Z91: 45931 | AA91: {=IFERROR( IF( _xlfn.XLOOKUP( 1, ( ('Condição de Faturamento'!$A$2:$A$1000 = Tabela1[[#This Row],[Unidade]]) * ('Condição de Faturamento'!$B$2:$B$1000 = Tabela1[[#This Row],[Categoria]]) * ('Condição de Faturamento'!$C$2:$C$1000 = Tabela1[[#This Row],[Fornecedor]]) ), 'Condição de Faturamento'!$D$2:$D$1000 ) = "Emissão no mês da prestação do serviço", Tabela1[[#This Row],[Mês de referência para faturamento]], DATE( YEAR(Tabela1[[#This Row],[Mês de referência para faturamento]]), MONTH(Tabela1[[#This Row],[Mês de referência para faturamento]]) + 1, DAY(Tabela1[[#This Row],[Mês de referência para faturamento]]) ) ), DATE( YEAR(Tabela1[[#This Row],[Mês de referência para faturamento]]), MONTH(Tabela1[[#This Row],[Mês de referência para faturamento]]) + 1, DAY(Tabela1[[#This Row],[Mês de referência para faturamento]]) ) )} -> 45962 | AI91: =K91-L91 -> 384.52 | AJ91: =AB91-AC91 -> 0 | AK91: =J91-U91 -> 3713.15 | AM91: =_xlfn.XLOOKUP(Tabela1[[#This Row],[Unidade]],tabShoppingsEmails[Shopping],tabShoppingsEmails[E-mails consolidados]) -> renan.mattos@allos.co; rita.silva@allos.co; kathleen.hoveler@allos.co; wellington.novaes@allos.co;alberto.oliveira@allos.co
C92: Shopping Villa Lobos | D92: Manutenção | E92: Brasanitas | F92: 29 | G92: 11 | J92: =(84915.13/(365.25/12))*8 -> 22318.556 | U92: =(J92+L92+Q92+R92+S92+N92)+IF(T92="Sim",O92+P92,0) -> 22318.556 | W92: =IF(J92="","",U92*(1+V92)) -> 22318.556 | Z92: 45931 | AA92: {=IFERROR( IF( _xlfn.XLOOKUP( 1, ( ('Condição de Faturamento'!$A$2:$A$1000 = Tabela1[[#This Row],[Unidade]]) * ('Condição de Faturamento'!$B$2:$B$1000 = Tabela1[[#This Row],[Categoria]]) * ('Condição de Faturamento'!$C$2:$C$1000 = Tabela1[[#This Row],[Fornecedor]]) ), 'Condição de Faturamento'!$D$2:$D$1000 ) = "Emissão no mês da prestação do serviço", Tabela1[[#This Row],[Mês de referência para faturamento]], DATE( YEAR(Tabela1[[#This Row],[Mês de referência para faturamento]]), MONTH(Tabela1[[#This Row],[Mês de referência para faturamento]]) + 1, DAY(Tabela1[[#This Row],[Mês de referência para faturamento]]) ) ), DATE( YEAR(Tabela1[[#This Row],[Mês de referência para faturamento]]), MONTH(Tabela1[[#This Row],[Mês de referência para faturamento]]) + 1, DAY(Tabela1[[#This Row],[Mês de referência para faturamento]]) ) )} -> 45962 | AI92: =K92-L92 -> 0 | AJ92: =AB92-AC92 -> 0 | AK92: =J92-U92 -> 0 | AM92: =_xlfn.XLOOKUP(Tabela1[[#This Row],[Unidade]],tabShoppingsEmails[Shopping],tabShoppingsEmails[E-mails consolidados]) -> renan.mattos@allos.co; rita.silva@allos.co; kathleen.hoveler@allos.co; wellington.novaes@allos.co;alberto.oliveira@allos.co
C93: Shopping Villa Lobos | D93: Manutenção | E93: Brasanitas | F93: 29 | G93: 11 | J93: 84915.129 | U93: =(J93+L93+Q93+R93+S93+N93)+IF(T93="Sim",O93+P93,0) -> 84915.129 | W93: =IF(J93="","",U93*(1+V93)) -> 84915.129 | Z93: 45962 | AA93: {=IFERROR( IF( _xlfn.XLOOKUP( 1, ( ('Condição de Faturamento'!$A$2:$A$1000 = Tabela1[[#This Row],[Unidade]]) * ('Condição de Faturamento'!$B$2:$B$1000 = Tabela1[[#This Row],[Categoria]]) * ('Condição de Faturamento'!$C$2:$C$1000 = Tabela1[[#This Row],[Fornecedor]]) ), 'Condição de Faturamento'!$D$2:$D$1000 ) = "Emissão no mês da prestação do serviço", Tabela1[[#This Row],[Mês de referência para faturamento]], DATE( YEAR(Tabela1[[#This Row],[Mês de referência para faturamento]]), MONTH(Tabela1[[#This Row],[Mês de referência para faturamento]]) + 1, DAY(Tabela1[[#This Row],[Mês de referência para faturamento]]) ) ), DATE( YEAR(Tabela1[[#This Row],[Mês de referência para faturamento]]), MONTH(Tabela1[[#This Row],[Mês de referência para faturamento]]) + 1, DAY(Tabela1[[#This Row],[Mês de referência para faturamento]]) ) )} -> 45992 | AI93: =K93-L93 -> 0 | AJ93: =AB93-AC93 -> 0 | AK93: =J93-U93 -> 0 | AM93: =_xlfn.XLOOKUP(Tabela1[[#This Row],[Unidade]],tabShoppingsEmails[Shopping],tabShoppingsEmails[E-mails consolidados]) -> renan.mattos@allos.co; rita.silva@allos.co; kathleen.hoveler@allos.co; wellington.novaes@allos.co;alberto.oliveira@allos.co
C94: Shopping Villa Lobos | D94: Manutenção | E94: Brasanitas | F94: 29 | G94: 11 | U94: =(J94+L94+Q94+R94+S94+N94)+IF(T94="Sim",O94+P94,0) -> 0 | W94: =IF(J94="","",U94*(1+V94)) | Z94: 45992 | AA94: {=IFERROR( IF( _xlfn.XLOOKUP( 1, ( ('Condição de Faturamento'!$A$2:$A$1000 = Tabela1[[#This Row],[Unidade]]) * ('Condição de Faturamento'!$B$2:$B$1000 = Tabela1[[#This Row],[Categoria]]) * ('Condição de Faturamento'!$C$2:$C$1000 = Tabela1[[#This Row],[Fornecedor]]) ), 'Condição de Faturamento'!$D$2:$D$1000 ) = "Emissão no mês da prestação do serviço", Tabela1[[#This Row],[Mês de referência para faturamento]], DATE( YEAR(Tabela1[[#This Row],[Mês de referência para faturamento]]), MONTH(Tabela1[[#This Row],[Mês de referência para faturamento]]) + 1, DAY(Tabela1[[#This Row],[Mês de referência para faturamento]]) ) ), DATE( YEAR(Tabela1[[#This Row],[Mês de referência para faturamento]]), MONTH(Tabela1[[#This Row],[Mês de referência para faturamento]]) + 1, DAY(Tabela1[[#This Row],[Mês de referência para faturamento]]) ) )} -> 46023 | AI94: =K94-L94 -> 0 | AJ94: =AB94-AC94 -> 0 | AK94: =J94-U94 -> 0 | AM94: =_xlfn.XLOOKUP(Tabela1[[#This Row],[Unidade]],tabShoppingsEmails[Shopping],tabShoppingsEmails[E-mails consolidados]) -> renan.mattos@allos.co; rita.silva@allos.co; kathleen.hoveler@allos.co; wellington.novaes@allos.co;alberto.oliveira@allos.co
B95: Sim | C95: Shopping Piracicaba | D95: Brigada de Incêndio | E95: Brasanitas | F95: 13 | G95: 13 | H95: 0 | I95: 0 | J95: 118217.4 | K95: 0 | L95: 0 | M95: 0 | N95: 0 | O95: preenchimento pendente | P95: 0 | Q95: 0 | R95: 0 | S95: 0 | U95: =(J95+L95+Q95+R95+S95+N95)+IF(T95="Sim",O95+P95,0) -> 118217.4 | W95: =IF(J95="","",U95*(1+V95)) -> 118217.4 | Z95: 45658 | AA95: {=IFERROR( IF( _xlfn.XLOOKUP( 1, ( ('Condição de Faturamento'!$A$2:$A$1000 = Tabela1[[#This Row],[Unidade]]) * ('Condição de Faturamento'!$B$2:$B$1000 = Tabela1[[#This Row],[Categoria]]) * ('Condição de Faturamento'!$C$2:$C$1000 = Tabela1[[#This Row],[Fornecedor]]) ), 'Condição de Faturamento'!$D$2:$D$1000 ) = "Emissão no mês da prestação do serviço", Tabela1[[#This Row],[Mês de referência para faturamento]], DATE( YEAR(Tabela1[[#This Row],[Mês de referência para faturamento]]), MONTH(Tabela1[[#This Row],[Mês de referência para faturamento]]) + 1, DAY(Tabela1[[#This Row],[Mês de referência para faturamento]]) ) ), DATE( YEAR(Tabela1[[#This Row],[Mês de referência para faturamento]]), MONTH(Tabela1[[#This Row],[Mês de referência para faturamento]]) + 1, DAY(Tabela1[[#This Row],[Mês de referência para faturamento]]) ) )} -> 45689 | AB95: 7289.8 | AC95: 6450.1333 | AD95: 6450.1333 | AI95: =K95-L95 -> 0 | AJ95: =AB95-AC95 -> 839.66668 | AK95: =J95-U95 -> 0 | AM95: =_xlfn.XLOOKUP(Tabela1[[#This Row],[Unidade]],tabShoppingsEmails[Shopping],tabShoppingsEmails[E-mails consolidados]) -> ricardo.vieira@allos.co; enzo.cremasco@allos.co; vinicius.esteves@allos.co; lais.medeiros@allos.co; filipe.cordeiro@allos.co
B96: Sim | C96: Shopping Piracicaba | D96: Brigada de Incêndio | E96: Brasanitas | F96: 13 | G96: 13 | H96: 0 | I96: 0 | J96: 118217.4 | K96: 0 | L96: 0 | M96: 0 | N96: 0 | O96: preenchimento pendente | P96: 0 | Q96: 0 | R96: 0 | S96: 0 | U96: =(J96+L96+Q96+R96+S96+N96)+IF(T96="Sim",O96+P96,0) -> 118217.4 | W96: =IF(J96="","",U96*(1+V96)) -> 118217.4 | Z96: 45689 | AA96: {=IFERROR( IF( _xlfn.XLOOKUP( 1, ( ('Condição de Faturamento'!$A$2:$A$1000 = Tabela1[[#This Row],[Unidade]]) * ('Condição de Faturamento'!$B$2:$B$1000 = Tabela1[[#This Row],[Categoria]]) * ('Condição de Faturamento'!$C$2:$C$1000 = Tabela1[[#This Row],[Fornecedor]]) ), 'Condição de Faturamento'!$D$2:$D$1000 ) = "Emissão no mês da prestação do serviço", Tabela1[[#This Row],[Mês de referência para faturamento]], DATE( YEAR(Tabela1[[#This Row],[Mês de referência para faturamento]]), MONTH(Tabela1[[#This Row],[Mês de referência para faturamento]]) + 1, DAY(Tabela1[[#This Row],[Mês de referência para faturamento]]) ) ), DATE( YEAR(Tabela1[[#This Row],[Mês de referência para faturamento]]), MONTH(Tabela1[[#This Row],[Mês de referência para faturamento]]) + 1, DAY(Tabela1[[#This Row],[Mês de referência para faturamento]]) ) )} -> 45717 | AB96: 2452.1717 | AC96: 2452.1717 | AI96: =K96-L96 -> 0 | AJ96: =AB96-AC96 -> 0 | AK96: =J96-U96 -> 0 | AL96: Promoção de um bombeiro diurno comum (07:00 às 19:00) para líder (10:00 às 22:00) - a fim de evitar a demanda de serviços extra | AM96: =_xlfn.XLOOKUP(Tabela1[[#This Row],[Unidade]],tabShoppingsEmails[Shopping],tabShoppingsEmails[E-mails consolidados]) -> ricardo.vieira@allos.co; enzo.cremasco@allos.co; vinicius.esteves@allos.co; lais.medeiros@allos.co; filipe.cordeiro@allos.co
B97: Sim | C97: Shopping Piracicaba | D97: Brigada de Incêndio | E97: Brasanitas | F97: 13 | G97: 13 | H97: 0 | I97: 0 | J97: 125748.43 | K97: 0 | L97: 0 | M97: 0 | N97: 0 | O97: preenchimento pendente | P97: 0 | Q97: 0 | R97: 0 | S97: 0 | U97: =(J97+L97+Q97+R97+S97+N97)+IF(T97="Sim",O97+P97,0) -> 125748.43 | W97: =IF(J97="","",U97*(1+V97)) -> 125748.43 | X97: 33671.26 | Y97: 1.1 | Z97: 45717 | AA97: {=IFERROR( IF( _xlfn.XLOOKUP( 1, ( ('Condição de Faturamento'!$A$2:$A$1000 = Tabela1[[#This Row],[Unidade]]) * ('Condição de Faturamento'!$B$2:$B$1000 = Tabela1[[#This Row],[Categoria]]) * ('Condição de Faturamento'!$C$2:$C$1000 = Tabela1[[#This Row],[Fornecedor]]) ), 'Condição de Faturamento'!$D$2:$D$1000 ) = "Emissão no mês da prestação do serviço", Tabela1[[#This Row],[Mês de referência para faturamento]], DATE( YEAR(Tabela1[[#This Row],[Mês de referência para faturamento]]), MONTH(Tabela1[[#This Row],[Mês de referência para faturamento]]) + 1, DAY(Tabela1[[#This Row],[Mês de referência para faturamento]]) ) ), DATE( YEAR(Tabela1[[#This Row],[Mês de referência para faturamento]]), MONTH(Tabela1[[#This Row],[Mês de referência para faturamento]]) + 1, DAY(Tabela1[[#This Row],[Mês de referência para faturamento]]) ) )} -> 45748 | AB97: 2262.75 | AC97: 3013.344 | AI97: =K97-L97 -> 0 | AJ97: =AB97-AC97 -> -750.59405 | AK97: =J97-U97 -> 0 | AM97: =_xlfn.XLOOKUP(Tabela1[[#This Row],[Unidade]],tabShoppingsEmails[Shopping],tabShoppingsEmails[E-mails consolidados]) -> ricardo.vieira@allos.co; enzo.cremasco@allos.co; vinicius.esteves@allos.co; lais.medeiros@allos.co; filipe.cordeiro@allos.co
B98: Sim | C98: Shopping Piracicaba | D98: Brigada de Incêndio | E98: Brasanitas | F98: 13 | G98: 13 | H98: 0 | I98: 0 | J98: 125748.43 | K98: 0 | L98: 0 | M98: 0 | N98: 0 | O98: preenchimento pendente | P98: 0 | Q98: 0 | R98: 0 | S98: 0 | U98: =(J98+L98+Q98+R98+S98+N98)+IF(T98="Sim",O98+P98,0) -> 125748.43 | W98: =IF(J98="","",U98*(1+V98)) -> 125748.43 | Z98: 45748 | AA98: {=IFERROR( IF( _xlfn.XLOOKUP( 1, ( ('Condição de Faturamento'!$A$2:$A$1000 = Tabela1[[#This Row],[Unidade]]) * ('Condição de Faturamento'!$B$2:$B$1000 = Tabela1[[#This Row],[Categoria]]) * ('Condição de Faturamento'!$C$2:$C$1000 = Tabela1[[#This Row],[Fornecedor]]) ), 'Condição de Faturamento'!$D$2:$D$1000 ) = "Emissão no mês da prestação do serviço", Tabela1[[#This Row],[Mês de referência para faturamento]], DATE( YEAR(Tabela1[[#This Row],[Mês de referência para faturamento]]), MONTH(Tabela1[[#This Row],[Mês de referência para faturamento]]) + 1, DAY(Tabela1[[#This Row],[Mês de referência para faturamento]]) ) ), DATE( YEAR(Tabela1[[#This Row],[Mês de referência para faturamento]]), MONTH(Tabela1[[#This Row],[Mês de referência para faturamento]]) + 1, DAY(Tabela1[[#This Row],[Mês de referência para faturamento]]) ) )} -> 45778 | AI98: =K98-L98 -> 0 | AJ98: =AB98-AC98 -> 0 | AK98: =J98-U98 -> 0 | AM98: =_xlfn.XLOOKUP(Tabela1[[#This Row],[Unidade]],tabShoppingsEmails[Shopping],tabShoppingsEmails[E-mails consolidados]) -> ricardo.vieira@allos.co; enzo.cremasco@allos.co; vinicius.esteves@allos.co; lais.medeiros@allos.co; filipe.cordeiro@allos.co
A99: 45816 | B99: Sim | C99: Shopping Piracicaba | D99: Brigada de Incêndio | E99: Brasanitas | F99: 13 | G99: 13 | H99: 0 | I99: 0 | J99: 125748.43 | K99: 0 | L99: 0 | M99: 0 | N99: 0 | O99: preenchimento pendente | P99: 0 | Q99: 0 | R99: 0 | S99: 0 | U99: =(J99+L99+Q99+R99+S99+N99)+IF(T99="Sim",O99+P99,0) -> 125748.43 | W99: =IF(J99="","",U99*(1+V99)) -> 125748.43 | Z99: 45778 | AA99: {=IFERROR( IF( _xlfn.XLOOKUP( 1, ( ('Condição de Faturamento'!$A$2:$A$1000 = Tabela1[[#This Row],[Unidade]]) * ('Condição de Faturamento'!$B$2:$B$1000 = Tabela1[[#This Row],[Categoria]]) * ('Condição de Faturamento'!$C$2:$C$1000 = Tabela1[[#This Row],[Fornecedor]]) ), 'Condição de Faturamento'!$D$2:$D$1000 ) = "Emissão no mês da prestação do serviço", Tabela1[[#This Row],[Mês de referência para faturamento]], DATE( YEAR(Tabela1[[#This Row],[Mês de referência para faturamento]]), MONTH(Tabela1[[#This Row],[Mês de referência para faturamento]]) + 1, DAY(Tabela1[[#This Row],[Mês de referência para faturamento]]) ) ), DATE( YEAR(Tabela1[[#This Row],[Mês de referência para faturamento]]), MONTH(Tabela1[[#This Row],[Mês de referência para faturamento]]) + 1, DAY(Tabela1[[#This Row],[Mês de referência para faturamento]]) ) )} -> 45809 | AB99: 1133.89 | AC99: 1143.5434 | AI99: =K99-L99 -> 0 | AJ99: =AB99-AC99 -> -9.6533758 | AK99: =J99-U99 -> 0 | AM99: =_xlfn.XLOOKUP(Tabela1[[#This Row],[Unidade]],tabShoppingsEmails[Shopping],tabShoppingsEmails[E-mails consolidados]) -> ricardo.vieira@allos.co; enzo.cremasco@allos.co; vinicius.esteves@allos.co; lais.medeiros@allos.co; filipe.cordeiro@allos.co
A100: 45852 | B100: Sim | C100: Shopping Piracicaba | D100: Brigada de Incêndio | E100: Brasanitas | F100: 13 | G100: 13 | H100: 0 | I100: 0 | J100: 125748.43 | K100: 0 | L100: 0 | M100: 0 | N100: 0 | O100: preenchimento pendente | P100: 0 | Q100: 0 | R100: 0 | S100: 0 | U100: =(J100+L100+Q100+R100+S100+N100)+IF(T100="Sim",O100+P100,0) -> 125748.43 | W100: =IF(J100="","",U100*(1+V100)) -> 125748.43 | Z100: 45809 | AA100: {=IFERROR( IF( _xlfn.XLOOKUP( 1, ( ('Condição de Faturamento'!$A$2:$A$1000 = Tabela1[[#This Row],[Unidade]]) * ('Condição de Faturamento'!$B$2:$B$1000 = Tabela1[[#This Row],[Categoria]]) * ('Condição de Faturamento'!$C$2:$C$1000 = Tabela1[[#This Row],[Fornecedor]]) ), 'Condição de Faturamento'!$D$2:$D$1000 ) = "Emissão no mês da prestação do serviço", Tabela1[[#This Row],[Mês de referência para faturamento]], DATE( YEAR(Tabela1[[#This Row],[Mês de referência para faturamento]]), MONTH(Tabela1[[#This Row],[Mês de referência para faturamento]]) + 1, DAY(Tabela1[[#This Row],[Mês de referência para faturamento]]) ) ), DATE( YEAR(Tabela1[[#This Row],[Mês de referência para faturamento]]), MONTH(Tabela1[[#This Row],[Mês de referência para faturamento]]) + 1, DAY(Tabela1[[#This Row],[Mês de referência para faturamento]]) ) )} -> 45839 | AI100: =K100-L100 -> 0 | AJ100: =AB100-AC100 -> 0 | AK100: =J100-U100 -> 0 | AM100: =_xlfn.XLOOKUP(Tabela1[[#This Row],[Unidade]],tabShoppingsEmails[Shopping],tabShoppingsEmails[E-mails consolidados]) -> ricardo.vieira@allos.co; enzo.cremasco@allos.co; vinicius.esteves@allos.co; lais.medeiros@allos.co; filipe.cordeiro@allos.co
...

Sheet Reajuste SP2
A1: Fornecedor | B1: Unidade | C1: Categoria | D1: Mês Referência Relatório - Mês que o reajuste foi validado pelas partes | E1: Data Reajuste do Contrato | F1: Status | G1: Valor 2024 | H1: Valor 2025 | I1: Reajuste | J1: % Reajuste | K1: Retroativo Fornecedor | L1: Retroativo Atlas | M1: Diferença | N1: Valor 2025 Fornecedor | O1: Valor 2025 Revisão Atlas | P1: Diferença Atlas-Fornecedor | Q1: Diferença Anual | R1: CCT Vinculada | S1: Observação
A2: Protege | B2: Boulevard Bauru | C2: Vigilância | D2: 45689 | E2: 45658 | F2: OK | G2: 34335.283 | H2: 35907.222 | I2: =IFERROR(IF(G2>0,H2-G2,""),"") -> 1571.9399 | J2: =IFERROR(IF(I2>0,I2/G2,""),"") -> 0.045782058 | M2: =K2-L2 -> 0 | N2: =34335.28*1.0676 -> 36656.345 | O2: =H2 -> 35907.222 | P2: =N2-O2 -> 749.12253 | Q2: =P2*12 -> 8989.4704
A3: Grupo Opus | B3: Boulevard Bauru | C3: PMOC | D3: 45689 | E3: 45658 | F3: OK | G3: 10325.122 | H3: 11759.612 | I3: =IFERROR(IF(G3>0,H3-G3,""),"") -> 1434.4902 | J3: =IFERROR(IF(I3>0,I3/G3,""),"") -> 0.13893204 | M3: =K3-L3 -> 0 | N3: 11809.66 | O3: =H3 -> 11759.612 | P3: =N3-O3 -> 50.047958 | Q3: =P3*12 -> 600.5755
A4: Brasanitas | B4: Boulevard Bauru | C4: Limpeza | D4: 45717 | E4: 45658 | F4: OK | G4: 155512.86 | H4: 176536.01 | I4: =IFERROR(IF(G4>0,H4-G4,""),"") -> 21023.16 | J4: =IFERROR(IF(I4>0,I4/G4,""),"") -> 0.13518599 | K4: 40642.57 | L4: 40638.364 | M4: =K4-L4 -> 4.2063417 | N4: 176565.69 | O4: 176536.01 | P4: =N4-O4 -> 29.675095 | Q4: =P4*12 -> 356.10114
A5: Protege | B5: Boulevard Bauru | C5: Portaria | D5: 45806 | E5: 45658 | F5: OK | G5: 83530.593 | H5: 91480.113 | I5: =IFERROR(IF(G5>0,H5-G5,""),"") -> 7949.5198 | J5: =IFERROR(IF(I5>0,I5/G5,""),"") -> 0.095168961 | M5: =K5-L5 -> 0 | N5: =83530.59*1.0923 -> 91240.463 | O5: 91480.113 | P5: =N5-O5 -> -239.64962 | Q5: =P5*12 -> -2875.7954
A6: GSBRU | B6: Boulevard Bauru | C6: Jardinagem | E6: 45658 | F6: Em revisão | G6: 11284.105 | H6: 12775.877 | I6: =IFERROR(IF(G6>0,H6-G6,""),"") -> 1491.7717 | J6: =IFERROR(IF(I6>0,I6/G6,""),"") -> 0.13220115 | M6: =K6-L6 -> 0 | P6: =N6-O6 -> 0 | Q6: =P6*12 -> 0 | R6: SINDVERDE
A7: GSBRU | B7: Boulevard Bauru | C7: Jardinagem | D7: 45784 | E7: 45658 | F7: OK | G7: 10551.92 | H7: 13168.11 | I7: =IFERROR(IF(G7>0,H7-G7,""),"") -> 2616.19 | J7: =IFERROR(IF(I7>0,I7/G7,""),"") -> 0.24793497 | M7: =K7-L7 -> 0 | P7: =N7-O7 -> 0 | Q7: =P7*12 -> 0 | R7: SEAC
A8: Grupo JLR | B8: Franca Shopping | C8: Portaria | D8: 45658 | E8: 45658 | F8: OK | G8: 35564.92 | H8: 41266.277 | I8: =IFERROR(IF(G8>0,H8-G8,""),"") -> 5701.3567 | J8: =IFERROR(IF(I8>0,I8/G8,""),"") -> 0.16030844 | M8: =K8-L8 -> 0 | N8: 41409.59 | O8: =H8 -> 41266.277 | P8: =N8-O8 -> 143.31329 | Q8: =P8*12 -> 1719.7595
A9: Grupo JLR | B9: Franca Shopping | C9: Vigilância | D9: 45658 | E9: 45658 | F9: OK | G9: 57456.903 | H9: 60347.759 | I9: =IFERROR(IF(G9>0,H9-G9,""),"") -> 2890.8568 | J9: =IFERROR(IF(I9>0,I9/G9,""),"") -> 0.050313482 | M9: =K9-L9 -> 0 | N9: 62583.83 | O9: =H9 -> 60347.759 | P9: =N9-O9 -> 2236.0706 | Q9: =P9*12 -> 26832.847
A10: Grupo Altum | B10: Franca Shopping | C10: Brigada de Incêndio | D10: 45689 | E10: 45536 | F10: OK | G10: 72766.91 | H10: 75838.912 | I10: =IFERROR(IF(G10>0,H10-G10,""),"") -> 3072.0016 | J10: =IFERROR(IF(I10>0,I10/G10,""),"") -> 0.042217013 | M10: =K10-L10 -> 0 | N10: 77126.12 | O10: =H10 -> 75838.912 | P10: =N10-O10 -> 1287.2084 | Q10: =P10*12 -> 15446.501
A11: Império | B11: Franca Shopping | C11: Segregação de resíduos | D11: 45717 | E11: 45658 | F11: OK | G11: 19299.996 | H11: 25076.04 | I11: =IFERROR(IF(G11>0,H11-G11,""),"") -> 5776.0445 | J11: =IFERROR(IF(I11>0,I11/G11,""),"") -> 0.29927699 | M11: =K11-L11 -> 0 | N11: 25382.14 | O11: 25076.04 | P11: =N11-O11 -> 306.1 | Q11: =P11*12 -> 3673.2
A12: Paisagismo Ouro | B12: Franca Shopping | C12: Jardinagem | D12: 45717 | E12: 45658 | F12: OK | G12: 12000 | H12: 13063.75 | I12: =IFERROR(IF(G12>0,H12-G12,""),"") -> 1063.75 | J12: =IFERROR(IF(I12>0,I12/G12,""),"") -> 0.088645833 | K12: 2127.5 | L12: =2*I12 -> 2127.5 | M12: =K12-L12 -> 0 | N12: 12354.03 | O12: 12680.5 | P12: =N12-O12 -> -326.47 | Q12: =P12*12 -> -3917.64
A13: Brasanitas | B13: Franca Shopping | C13: Limpeza | D13: 45748 | E13: 45658 | F13: OK | G13: 121717.27 | H13: 137750.83 | I13: =IFERROR(IF(G13>0,H13-G13,""),"") -> 16033.558 | J13: =IFERROR(IF(I13>0,I13/G13,""),"") -> 0.13172788 | K13: 29053.076 | L13: 29053.076 | M13: =K13-L13 -> 0 | N13: 138014.8 | O13: 137750.83 | P13: =N13-O13 -> 263.97372 | Q13: =P13*12 -> 3167.6846
A14: Grupo JLR | B14: Praça Nova Araçatuba | C14: Portaria | D14: 45748 | E14: 45658 | F14: OK | G14: 45909.13 | H14: 53032.732 | I14: =IFERROR(IF(G14>0,H14-G14,""),"") -> 7123.6024 | J14: =IFERROR(IF(I14>0,I14/G14,""),"") -> 0.15516744 | M14: =K14-L14 -> 0 | N14: 53210.04 | O14: =H14 -> 53032.732 | P14: =N14-O14 -> 177.30752 | Q14: =P14*12 -> 2127.6902
A15: Grupo JLR | B15: Praça Nova Araçatuba | C15: Vigilância | D15: 45748 | E15: 45658 | F15: OK | G15: 20013.241 | H15: 21040.094 | I15: =IFERROR(IF(G15>0,H15-G15,""),"") -> 1026.8538 | J15: =IFERROR(IF(I15>0,I15/G15,""),"") -> 0.051308722 | M15: =K15-L15 -> 0 | N15: 21590.9 | O15: =H15 -> 21040.094 | P15: =N15-O15 -> 550.8056 | Q15: =P15*12 -> 6609.6672
A16: Medmais | B16: Praça Nova Araçatuba | C16: Brigada de Incêndio | D16: 45717 | E16: 45536 | F16: OK | G16: 75347.43 | H16: 78212.74 | I16: =IFERROR(IF(G16>0,H16-G16,""),"") -> 2865.31 | J16: =IFERROR(IF(I16>0,I16/G16,""),"") -> 0.038027973 | M16: =K16-L16 -> 0 | N16: 78212.74 | O16: =H16 -> 78212.74 | P16: =N16-O16 -> 0 | Q16: =P16*12 -> 0
A17: Grupo Altum | B17: Praça Nova Araçatuba | C17: Limpeza | D17: 45782 | E17: 45658 | F17: OK | G17: 119660.06 | H17: 134737.91 | I17: =IFERROR(IF(G17>0,H17-G17,""),"") -> 15077.846 | J17: =IFERROR(IF(I17>0,I17/G17,""),"") -> 0.12600567 | M17: =K17-L17 -> 0 | N17: 134106.02 | O17: 134737.91 | P17: =N17-O17 -> -631.89 | Q17: =P17*12 -> -7582.68
A18: Grupo Altum | B18: Praça Nova Araçatuba | C18: Resíduos | D18: 45786 | E18: 45658 | F18: OK | G18: 5633.47 | H18: 6395.9274 | I18: =IFERROR(IF(G18>0,H18-G18,""),"") -> 762.45737 | J18: =IFERROR(IF(I18>0,I18/G18,""),"") -> 0.13534418 | M18: =K18-L18 -> 0 | P18: =N18-O18 -> 0 | Q18: =P18*12 -> 0
A19: Masstin | B19: Praça Nova Araçatuba | C19: PMOC | D19: 45813 | E19: 45796 | F19: OK | G19: 8541.5691 | H19: 9060.1932 | I19: =IFERROR(IF(G19>0,H19-G19,""),"") -> 518.62415 | J19: =IFERROR(IF(I19>0,I19/G19,""),"") -> 0.060717668 | K19: 891.44162 | L19: 891.44162 | M19: =K19-L19 -> 0 | N19: 8959.45 | O19: 9060.1932 | P19: =N19-O19 -> -100.74322 | Q19: =P19*12 -> -1208.9187 | R19: SINDEPRESTEM
A20: Grupo Opus | B20: Praça Nova Santa Maria | C20: PMOC | D20: 45689 | E20: 45658 | F20: OK | G20: 12074.58 | H20: 13035.73 | I20: =IFERROR(IF(G20>0,H20-G20,""),"") -> 961.15 | J20: =IFERROR(IF(I20>0,I20/G20,""),"") -> 0.079601112 | M20: =K20-L20 -> 0 | N20: 13127.19 | O20: =H20 -> 13035.73 | P20: =N20-O20 -> 91.46 | Q20: =P20*12 -> 1097.52
A21: SulClean | B21: Praça Nova Santa Maria | C21: Limpeza | D21: 45689 | E21: 45658 | F21: OK | G21: 126086.29 | H21: 134301.81 | I21: =IFERROR(IF(G21>0,H21-G21,""),"") -> 8215.5228 | J21: =IFERROR(IF(I21>0,I21/G21,""),"") -> 0.065157939 | M21: =K21-L21 -> 0 | N21: 134285.59 | O21: =H21 -> 134301.81 | P21: =N21-O21 -> -16.223842 | Q21: =P21*12 -> -194.6861
A22: SulClean | B22: Praça Nova Santa Maria | C22: Brigada de Incêndio | D22: 45717 | E22: 45505 | F22: OK | G22: 72432.51 | H22: 78887.1 | I22: =IFERROR(IF(G22>0,H22-G22,""),"") -> 6454.59 | J22: =IFERROR(IF(I22>0,I22/G22,""),"") -> 0.089111781 | M22: =K22-L22 -> 0 | N22: 79125.37 | O22: 78887.1 | P22: =N22-O22 -> 238.27 | Q22: =P22*12 -> 2859.24
A23: SulClean | B23: Praça Nova Santa Maria | C23: Portaria | D23: 45748 | E23: 45689 | F23: OK | G23: 58515.534 | H23: 64680.616 | I23: =IFERROR(IF(G23>0,H23-G23,""),"") -> 6165.0823 | J23: =IFERROR(IF(I23>0,I23/G23,""),"") -> 0.10535805 | K23: 6165.0819 | L23: 6165.0819 | M23: =K23-L23 -> 0 | N23: 64680.56 | O23: 64680.616 | P23: =N23-O23 -> -0.056017417 | Q23: =P23*12 -> -0.672209
A24: SulClean | B24: Praça Nova Santa Maria | C24: Vigilância | D24: 45748 | E24: 45689 | F24: OK | G24: 7746.1869 | H24: 8056.8166 | I24: =IFERROR(IF(G24>0,H24-G24,""),"") -> 310.62966 | J24: =IFERROR(IF(I24>0,I24/G24,""),"") -> 0.040100976 | K24: 310.62978 | L24: 310.62978 | M24: =K24-L24 -> 0 | N24: 8056.81 | O24: 8056.8166 | P24: =N24-O24 -> -0.0065599416 | Q24: =P24*12 -> -0.078719299
A25: Verzani | B25: Shopping Campo Limpo | C25: Limpeza | D25: 45658 | E25: 45658 | F25: OK | G25: 211937.49 | H25: 241415.96 | I25: =IFERROR(IF(G25>0,H25-G25,""),"") -> 29478.47 | J25: =IFERROR(IF(I25>0,I25/G25,""),"") -> 0.1390904 | M25: =K25-L25 -> 0 | N25: 242753.13 | O25: =H25 -> 241415.96 | P25: =N25-O25 -> 1337.17 | Q25: =P25*12 -> 16046.04
A26: Verzani | B26: Shopping Campo Limpo | C26: Manutenção | D26: 45748 | E26: 45658 | F26: OK | G26: 81966.71 | H26: 87154.114 | I26: =IFERROR(IF(G26>0,H26-G26,""),"") -> 5187.4041 | J26: =IFERROR(IF(I26>0,I26/G26,""),"") -> 0.063286719 | M26: =K26-L26 -> 0 | N26: 86440.14 | O26: 87154.114 | P26: =N26-O26 -> -713.97413 | Q26: =P26*12 -> -8567.6895
A27: Verzani | B27: Shopping Campo Limpo | C27: PMOC | D27: 45748 | E27: 45658 | F27: OK | G27: 6792.59 | H27: 7318.1483 | I27: =IFERROR(IF(G27>0,H27-G27,""),"") -> 525.55827 | J27: =IFERROR(IF(I27>0,I27/G27,""),"") -> 0.077372294 | M27: =K27-L27 -> 0 | N27: 7267.15 | O27: 7318.1483 | P27: =N27-O27 -> -50.998267 | Q27: =P27*12 -> -611.97921
A28: Verzani | B28: Shopping Campo Limpo | C28: Portaria | D28: 45717 | E28: 45658 | F28: OK | G28: 99497.14 | H28: 109422.91 | I28: =IFERROR(IF(G28>0,H28-G28,""),"") -> 9925.77 | J28: =IFERROR(IF(I28>0,I28/G28,""),"") -> 0.09975935 | K28: 29400.499 | L28: 29400.499 | M28: =K28-L28 -> 0 | N28: 114180.33 | O28: 109422.91 | P28: =N28-O28 -> 4757.42 | Q28: =P28*12 -> 57089.04
A29: Verzani | B29: Shopping Campo Limpo | C29: Vigilância | D29: 45717 | E29: 45658 | F29: OK | G29: 110625.48 | H29: 116800.64 | I29: =IFERROR(IF(G29>0,H29-G29,""),"") -> 6175.1589 | J29: =IFERROR(IF(I29>0,I29/G29,""),"") -> 0.055820403 | K29: 18307.161 | L29: 18307.161 | M29: =K29-L29 -> 0 | N29: 120689.78 | O29: 116800.64 | P29: =N29-O29 -> 3889.1354 | Q29: =P29*12 -> 46669.625
A30: Marcia Novaes Paisagismo | B30: Shopping Parque Dom Pedro | C30: Jardinagem | D30: 45717 | E30: 45536 | F30: OK | G30: 69218.122 | H30: 72503.407 | I30: =IFERROR(IF(G30>0,H30-G30,""),"") -> 3285.2851 | J30: =IFERROR(IF(I30>0,I30/G30,""),"") -> 0.047462788 | L30: 21116.387 | M30: =K30-L30 -> -21116.387 | N30: 74505.84 | O30: 72503.407 | P30: =N30-O30 -> 2002.4327 | Q30: =P30*12 -> 24029.192
A31: Verzani | B31: Shopping Parque Dom Pedro | C31: Portaria | D31: 45905 | E31: 45658 | F31: OK | G31: 154589.28 | H31: 164656.52 | I31: =IFERROR(IF(G31>0,H31-G31,""),"") -> 10067.237 | J31: =IFERROR(IF(I31>0,I31/G31,""),"") -> 0.065122475 | L31: 66441.885 | M31: =K31-L31 -> -66441.885 | N31: 170453.49 | O31: 164656.52 | P31: =N31-O31 -> 5796.9708 | Q31: =P31*12 -> 69563.649
A32: Verzani | B32: Shopping Parque Dom Pedro | C32: Vigilância | D32: 45905 | E32: 45658 | F32: OK | G32: 377185.17 | H32: 393334.73 | I32: =IFERROR(IF(G32>0,H32-G32,""),"") -> 16149.556 | J32: =IFERROR(IF(I32>0,I32/G32,""),"") -> 0.042815988 | L32: 110114.65 | M32: =K32-L32 -> -110114.65 | N32: 410996.98 | O32: 393334.73 | P32: =N32-O32 -> 17662.251 | Q32: =P32*12 -> 211947.01
A33: Verzani | B33: Shopping Parque Dom Pedro | C33: Vigilância - Joalheria | D33: 45905 | E33: 45658 | F33: OK | G33: 53520.76 | H33: 55962.86 | I33: =IFERROR(IF(G33>0,H33-G33,""),"") -> 2442.0993 | J33: =IFERROR(IF(I33>0,I33/G33,""),"") -> 0.045629009 | L33: 15156.094 | M33: =K33-L33 -> -15156.094 | N33: 58742.73 | O33: 55962.86 | P33: =N33-O33 -> 2779.8704 | Q33: =P33*12 -> 33358.445
A34: Verzani | B34: Shopping Parque Dom Pedro | C34: Manutenção | D34: 45791 | E34: 45658 | F34: OK | G34: 206270.62 | H34: 219322.2 | I34: =IFERROR(IF(G34>0,H34-G34,""),"") -> 13051.576 | J34: =IFERROR(IF(I34>0,I34/G34,""),"") -> 0.06327404 | M34: =K34-L34 -> 0 | N34: 221049.92 | O34: 219322.2 | P34: =N34-O34 -> 1727.7215 | Q34: =P34*12 -> 20732.658 | R34: SINDEPRESTEM
A35: Verzani | B35: Shopping Parque Dom Pedro | C35: PMOC | D35: 45791 | E35: 45658 | F35: OK | G35: 29222.155 | H35: 31114.221 | I35: =IFERROR(IF(G35>0,H35-G35,""),"") -> 1892.0664 | J35: =IFERROR(IF(I35>0,I35/G35,""),"") -> 0.06474767 | M35: =K35-L35 -> 0 | N35: 30629.42 | O35: 31114.221 | P35: =N35-O35 -> -484.80136 | Q35: =P35*12 -> -5817.6163 | R35: SINDEPRESTEM
A36: Verzani | B36: Shopping Parque Dom Pedro | C36: Limpeza | D36: 45748 | E36: 45658 | F36: OK | G36: 662121.23 | H36: 737757.84 | I36: =IFERROR(IF(G36>0,H36-G36,""),"") -> 75636.606 | J36: =IFERROR(IF(I36>0,I36/G36,""),"") -> 0.11423377 | L36: 265250.49 | M36: =K36-L36 -> -265250.49 | N36: 737890.43 | O36: 737757.84 | P36: =N36-O36 -> 132.59447 | Q36: =P36*12 -> 1591.1336
A37: Brasanitas | B37: Shopping Piracicaba | C37: Limpeza | D37: 45689 | E37: 45658 | F37: OK | G37: 273951.5 | H37: 308969.1 | I37: =IFERROR(IF(G37>0,H37-G37,""),"") -> 35017.6 | J37: =IFERROR(IF(I37>0,I37/G37,""),"") -> 0.12782409 | K37: 43074.035 | L37: 43074.035 | M37: =K37-L37 -> 0 | N37: 309630.3 | O37: =H37 -> 308969.1 | P37: =N37-O37 -> 661.2 | Q37: =P37*12 -> 7934.4
A38: Grupo JLR | B38: Shopping Piracicaba | C38: Portaria | D38: 45689 | E38: 45658 | F38: OK | G38: 46333.245 | H38: 50681.681 | I38: =IFERROR(IF(G38>0,H38-G38,""),"") -> 4348.4364 | J38: =IFERROR(IF(I38>0,I38/G38,""),"") -> 0.093851326 | M38: =K38-L38 -> 0 | N38: 51218.14 | O38: =H38 -> 50681.681 | P38: =N38-O38 -> 536.45891 | Q38: =P38*12 -> 6437.5069
A39: Grupo JLR | B39: Shopping Piracicaba | C39: Vigilância | D39: 45689 | E39: 45658 | F39: OK | G39: 62347.233 | H39: 65079.286 | I39: =IFERROR(IF(G39>0,H39-G39,""),"") -> 2732.0524 | J39: =IFERROR(IF(I39>0,I39/G39,""),"") -> 0.043819946 | M39: =K39-L39 -> 0 | N39: 68473.52 | O39: =H39 -> 65079.286 | P39: =N39-O39 -> 3394.2343 | Q39: =P39*12 -> 40730.812
A40: Brasanitas | B40: Shopping Piracicaba | C40: Manutenção | D40: 45689 | E40: 45658 | F40: OK | G40: 111363.54 | H40: 120959.33 | I40: =IFERROR(IF(G40>0,H40-G40,""),"") -> 9595.7831 | J40: =IFERROR(IF(I40>0,I40/G40,""),"") -> 0.086166287 | K40: 10937.91 | L40: 9066.5744 | M40: =K40-L40 -> 1871.3356 | N40: 121106.9 | O40: 120959.33 | P40: =N40-O40 -> 147.57234 | Q40: =P40*12 -> 1770.8681
A41: Brasanitas | B41: Shopping Piracicaba | C41: PMOC | D41: 45689 | E41: 45658 | F41: OK | G41: 20705.858 | H41: 22722.122 | I41: =IFERROR(IF(G41>0,H41-G41,""),"") -> 2016.2631 | J41: =IFERROR(IF(I41>0,I41/G41,""),"") -> 0.097376458 | K41: 1989.08 | L41: 1988.5957 | M41: =K41-L41 -> 0.48427475 | N41: 22762.26 | O41: 22722.122 | P41: =N41-O41 -> 40.138499 | Q41: =P41*12 -> 481.66198
A42: Brasanitas | B42: Shopping Piracicaba | C42: Brigada de Incêndio | D42: 45748 | E42: 45536 | F42: OK | G42: 120827.58 | H42: 125748.43 | I42: =IFERROR(IF(G42>0,H42-G42,""),"") -> 4920.85 | J42: =IFERROR(IF(I42>0,I42/G42,""),"") -> 0.040726215 | L42: 33671.26 | M42: =K42-L42 -> -33671.26 | N42: 125847.04 | O42: 125748.43 | P42: =N42-O42 -> 98.61 | Q42: =P42*12 -> 1183.32
A43: Grupo Opus | B43: Shopping Villa Lobos | C43: Manutenção | E43: 45658 | F43: Em revisão | G43: 8657.34 | H43: 9353.21 | I43: =IFERROR(IF(G43>0,H43-G43,""),"") -> 695.87 | J43: =IFERROR(IF(I43>0,I43/G43,""),"") -> 0.080379193 | M43: =K43-L43 -> 0 | N43: 9352.78 | O43: =H43 -> 9353.21 | P43: =N43-O43 -> -0.43 | Q43: =P43*12 -> -5.16
A44: Verzani | B44: Shopping Villa Lobos | C44: Limpeza | D44: 45824 | E44: 45658 | F44: OK | G44: 237725.81 | H44: 269020.92 | I44: =IFERROR(IF(G44>0,H44-G44,""),"") -> 31295.108 | J44: =IFERROR(IF(I44>0,I44/G44,""),"") -> 0.13164371 | M44: =K44-L44 -> 0 | N44: 268986.8 | O44: =H44 -> 269020.92 | P44: =N44-O44 -> -34.122297 | Q44: =P44*12 -> -409.46757
A45: GR | B45: Shopping Villa Lobos | C45: Portaria | E45: 45658 | F45: Em revisão | G45: 99311.15 | I45: =IFERROR(IF(G45>0,H45-G45,""),"") -> -99311.15 | J45: =IFERROR(IF(I45>0,I45/G45,""),"") | M45: =K45-L45 -> 0 | P45: =N45-O45 -> 0 | Q45: =P45*12 -> 0
A46: GR | B46: Shopping Villa Lobos | C46: Vigilância | E46: 45658 | F46: Em revisão | G46: 12940.01 | I46: =IFERROR(IF(G46>0,H46-G46,""),"") -> -12940.01 | J46: =IFERROR(IF(I46>0,I46/G46,""),"") | M46: =K46-L46 -> 0 | P46: =N46-O46 -> 0 | Q46: =P46*12 -> 0
A47: GPS | B47: Shopping Villagio Caxias | C47: Limpeza | D47: 45717 | E47: 45658 | F47: OK | G47: 209575.27 | H47: 222827.16 | I47: =IFERROR(IF(G47>0,H47-G47,""),"") -> 13251.89 | J47: =IFERROR(IF(I47>0,I47/G47,""),"") -> 0.063232127 | L47: 22427.211 | M47: =K47-L47 -> -22427.211 | N47: =G47*1.0684 -> 223910.22 | O47: 222827.16 | P47: =N47-O47 -> 1083.0585 | Q47: =P47*12 -> 12996.702
A48: Veper | B48: Shopping Villagio Caxias | C48: Portaria | D48: 45811 | E48: 45658 | F48: OK | G48: 42452.35 | H48: 46399.92 | I48: =IFERROR(IF(G48>0,H48-G48,""),"") -> 3947.5698 | J48: =IFERROR(IF(I48>0,I48/G48,""),"") -> 0.092988252 | K48: 55232.77 | L48: 13806.448 | M48: =K48-L48 -> 41426.322 | N48: 46412.35 | O48: 46399.92 | P48: =N48-O48 -> 12.430182 | Q48: =P48*12 -> 149.16219
A49: Veper | B49: Shopping Villagio Caxias | C49: Vigilância | D49: 45810 | E49: 45748 | F49: OK | G49: 76454.99 | H49: 83872.722 | I49: =IFERROR(IF(G49>0,H49-G49,""),"") -> 7417.7316 | J49: =IFERROR(IF(I49>0,I49/G49,""),"") -> 0.097020896 | K49: 7572.73 | L49: 7574.3612 | M49: =K49-L49 -> -1.6311753 | N49: 84033.68 | O49: 83872.722 | P49: =N49-O49 -> 160.95815 | Q49: =P49*12 -> 1931.4978
A50: Seleto | B50: Shopping Campo Limpo | C50: Jardinagem | D50: 45824 | E50: 45717 | F50: OK | G50: 10685.98 | H50: 11280.682 | I50: =IFERROR(IF(G50>0,H50-G50,""),"") -> 594.70186 | J50: =IFERROR(IF(I50>0,I50/G50,""),"") -> 0.055652534 | M50: =K50-L50 -> 0 | N50: 11292.04 | O50: 11280.682 | P50: =N50-O50 -> 11.358136 | Q50: =P50*12 -> 136.29763 | R50: SINDVERDE

Sheet Config
B1: Acompanhamento Descontos
B2: Acompanhamento Extras
B3: Controles Sistema
B4: Saving Extras

Sheet Fornecedor
A1: Fornecedor
A2: Action Fire
A3: Agro Rio
A4: AgroGarden
A5: Agrotexas
A6: Ambi Verde
A7: AMPLA Resgate Treinamentos
A8: Art Garden
A9: Artemp
A10: Auto Park
A11: BM Serviços de Jardinagem
A12: Brasanitas
... A91: Ambiente Verde

Sheet Unidade
A1: Unidade | B1: Regional UF | C1: Regional PS | D1: Regional RS | E1: Cluster | F1: Portifólio
A2: Boulevard Bauru | B2: SP2 | C2: André L. | D2: Nath | E2: 1 | F2: Administrado
A3: Franca Shopping | B3: SP2 | C3: André L. | D3: Nath | E3: 1 | F3: Próprio
A4: Praça Nova Araçatuba | B4: SP2 | C4: André L. | D4: Nath | E4: 1 | F4: Administrado
A5: Praça Nova Santa Maria | B5: SP2 | C5: André L. | D5: Nath | E5: 1 | F5: Administrado
A6: Shopping Campo Limpo | B6: SP2 | C6: André L. | D6: Nath | E6: 2 | F6: Próprio
A7: Shopping Parque Dom Pedro | B7: SP2 | C7: André L. | D7: Nath | E7: 4 | F7: Próprio
A8: Shopping Piracicaba | B8: SP2 | C8: André L. | D8: Nath | E8: 3 | F8: Próprio
A9: Shopping Villa Lobos | B9: SP2 | C9: André L. | D9: Nath | E9: 3 | F9: Próprio
A10: Shopping Villagio Caxias | B10: SP2 | C10: André L. | D10: Nath | E10: 2 | F10: Próprio

Sheet HC
A1: Cluster | B1: Categoria | C1: HC_Min | D1: HC_Max
A2: 1 | B2: Manutenção | C2: 12 | D2: 18
A3: 2 | B3: Manutenção | C3: 16 | D3: 21
A4: 3 | B4: Manutenção | C4: 21 | D4: 29
A5: 4 | B5: Manutenção | C5: 27 | D5: 38
A6: 1 | B6: PMOC | C6: 2 | D6: 2
A7: 2 | B7: PMOC | C7: 2 | D7: 3
A8: 3 | B8: PMOC | C8: 3 | D8: 4
A9: 4 | B9: PMOC | C9: 5 | D9: 7

Sheet Categoria
A1: SP2
A2: Brigada de Incêndio
A3: Estacionamento
A4: Jardinagem
A5: Limpeza
A6: Manutenção
A7: Manutenção - Planejador
A8: PMOC
A9: Portaria
A10: Resíduos
A11: Vigilância
A12: Vigilância - Extras Joalheria
A13: Composteira

Sheet Faltas e atrasos | Cálculos_ant
B2: Praça Nova Araçatuba- nov/24 | C2: Função | D2: Escala | E2: Horário entrada | F2: Horário saída | G2: Quantidade de dias | H2: Valor dia/falta | I2: Total
C3: Bonbeiro Civil | D3: 12x36 | E3: 0.41666667 | F3: 0.91666667 | H3: 329.23 | I3: =H3*G3 -> 0
C4: Bonbeiro Civil | D4: 12x36 | E4: 0.91666667 | F4: 0.41666667 | G4: 1 | H4: 349.94 | I4: =H4*G4 -> 349.94
G5: =SUM(G3:G4) -> 1 | I5: =SUM(I3:I4) -> 349.94
B7: Parque Dom Pedro - nov/24 | C7: Função | D7: Escala | E7: Horário entrada | F7: Horário saída | G7: Quantidade de dias | H7: Valor hora/falta | I7: Total
C8: Jardineiro | D8: 5x1 | E8: 0.33333333 | F8: 0.68055556 | G8: 41 | H8: 152.79 | I8: =H8*G8 -> 6264.39
G9: =SUM(G8:G8) -> 41 | I9: =SUM(I8:I8) -> 6264.39
B11: bauru - nov/24 | C11: Função | D11: Escala | E11: Horário entrada | F11: Horário saída | G11: Quantidade de dias | H11: Valor dia/falta | I11: Total
C12: Jardineiro | D12: 5x2 | E12: 0.29166667 | F12: 0.7 | H12: 160.87 | I12: =H12*G12 -> 0
C13: Aux de jardinagem | D13: 5x2 | E13: 0.29166667 | F13: 0.7 | G13: 1 | H13: 154.58 | I13: =H13*G13 -> 154.58
G14: =SUM(G12:G13) -> 1 | I14: =SUM(I12:I13) -> 154.58
B16: franca - nov/24 | C16: Função | D16: Escala | E16: Horário entrada | F16: Horário saída | G16: Quantidade de dias | H16: Valor dia/falta | I16: Total
C17: Orientador de Tráfego | D17: 12x36 | E17: 0.45833333 | F17: 0.95833333 | G17: 2 | H17: 120.82 | I17: =H17*G17 -> 241.64
C18: Operador de Estacionamento Sênior (Lider) | D18: 5x1 | E18: 0.375 | F18: 0.72222222 | G18: 1 | H18: 186.43 | I18: =H18*G18 -> 186.43
G19: =SUM(G17:G18) -> 3 | I19: =SUM(I17:I18) -> 428.07
B21: Piracicaba - nov/24 | C21: Função | D21: Escala | E21: Horário entrada | F21: Horário saída | G21: Quantidade de dias | H21: Valor dia/falta | I21: Total
C22: Porteiro | D22: 6X1 | E22: 0.29166667 | F22: 0.625 | H22: 156.81 | I22: =G22*H22 -> 0
C23: Porteiro | D23: 12X36 | E23: 0.29166667 | F23: 0.79166667 | H23: 146.67 | I23: =G23*H23 -> 0
C24: Porteiro | D24: 12x36 | E24: 0.375 | F24: 0.875 | G24: 1 | H24: 146.67 | I24: =G24*H24 -> 146.67
C25: Porteiro | D25: 12x36 | E25: 0.79166667 | F25: 0.29166667 | H25: 161.01 | I25: =G25*H25 -> 0
G26: =SUBTOTAL(9,G22:G25) -> 1 | I26: =SUBTOTAL(9,I22:I25) -> 146.67
B28: piracicaba - nov/24 | C28: Função | D28: Escala | E28: Horário entrada | F28: Horário saída | G28: Quantidade de dias | H28: Valor dia/falta | I28: Total
C29: Vigilante | D29: 12x36 | E29: 0.41666667 | F29: 0.91666667 | H29: 201.98 | I29: =H29*G29 -> 0
C30: Vigilante | D30: 12x36 | E30: 0.79166667 | F30: 0.29166667 | H30: 222.15 | I30: =H30*G30 -> 0
C31: Vigilante | D31: 12x36 | E31: 0.5 | F31: 0 | H31: 208.7 | I31: =H31*G31 -> 0
C32: Vigilante Líder | D32: 6x1 | E32: 0.61111111 | F32: 0.95833333 | H32: 239.28 | I32: =H32*G32 -> 0
G33: =SUM(G29:G32) -> 0 | I33: =SUM(I29:I32) -> 0
B35: piracicaba - nov/24 | C35: Função | D35: Escala | E35: Horário entrada | F35: Horário saída | G35: Quantidade de horas | H35: Valor hora/falta | I35: Total
C36: Agente de portaria | D36: 12x36 | E36: 0.79166667 | F36: 0.29166667 | H36: 22.28 | I36: =H36*G36 -> 0
C37: Agente de portaria | D37: 6x1 | E37: 0.29166667 | F37: 0.63888889 | H37: 21.69 | I37: =H37*G37 -> 0
C38: Agente de portaria | D38: 12x36 | E38: 0.29166667 | F38: 0.79166667 | H38: 20.29 | I38: =H38*G38 -> 0
C39: Agente de portaria | D39: 12x36 | E39: 0.375 | F39: 0.875 | H39: 20.29 | I39: =H39*G39 -> 0
C40: Agente de portaria | D40: 12x36 | E40: 0.375 | F40: 0.875 | G40: 3.6 | H40: 20.29 | I40: =H40*G40 -> 73.044
G41: =SUM(G36:G40) -> 3.6 | I41: =SUM(I36:I40) -> 73.044
B43: piracicaba - nov/24 | C43: Função | D43: Escala | E43: Horário entrada | F43: Horário saída | G43: Quantidade de horas | H43: Valor hora/falta | I43: Total
C44: Vigilante | D44: 12x36 | E44: 0.41666667 | F44: 0.91666667 | G44: 1.13 | H44: 27.94 | I44: =H44*G44 -> 31.5722
C45: Vigilante | D45: 12x36 | E45: 0.79166667 | F45: 0.29166667 | H45: 30.74 | I45: =H45*G45 -> 0
C46: Vigilante | D46: 12x36 | E46: 0.5 | F46: 0 | H46: 28.87 | I46: =H46*G46 -> 0
C47: Vigilante Líder | D47: 6x1 | E47: 0.61111111 | F47: 0.95833333 | H47: 33.11 | I47: =H47*G47 -> 0
G48: =SUM(G44:G47) -> 1.13 | I48: =SUM(I44:I47) -> 31.5722
B50: bauru - nov/24 | C50: Função | D50: Escala | E50: Horário entrada | F50: Horário saída | G50: Quantidade de dias | H50: Valor dia/falta | I50: Total
C51: BANHEIRISTA | D51: 12x36 | E51: 0.27083333 | F51: 0.77083333 | G51: 20 | H51: 166.04 | I51: =H51*G51 -> 3320.8
C52: BANHEIRISTA | D52: 12x36 | E52: 0.4375 | F52: 0.9375 | G52: 15 | H52: 167.24 | I52: =H52*G52 -> 2508.6
C53: COLETOR | D53: 5x1 | E53: 0.27083333 | F53: 0.61805556 | G53: 1 | H53: 175.05 | I53: =H53*G53 -> 175.05
C54: COLETOR | D54: 5x1 | E54: 0.59027778 | F54: 0.9375 | G54: 1 | H54: 177.22 | I54: =H54*G54 -> 177.22
C55: AGENTE DE LIMPEZA | D55: 5x1 | E55: 0.27083333 | F55: 0.61805556 | G55: 29 | H55: 137.51 | I55: =H55*G55 -> 3987.79
C56: AGENTE DE LIMPEZA | D56: 5x1 | E56: 0.59027778 | F56: 0.9375 | G56: 28 | H56: 139.11 | I56: =H56*G56 -> 3895.08
C57: OPERADOR DE MÁQUINA | D57: 5x1 | E57: 0.27083333 | F57: 0.61805556 | H57: 181.51 | I57: =H57*G57 -> 0
C58: LIMPADOR DE VIDRO | D58: 5x1 | E58: 0.27083333 | F58: 0.61805556 | G58: 1 | H58: 169.22 | I58: =H58*G58 -> 169.22
C59: LÍDER DE LIMPEZA | D59: 5x1 | E59: 0.27083333 | F59: 0.61805556 | H59: 169.09 | I59: =H59*G59 -> 0
G60: =SUM(G51:G59) -> 95 | I60: =SUM(I51:I59) -> 14233.76
B62: PDP - nov/24 | C62: Função | D62: Escala | E62: Horário entrada | F62: Horário saída | G62: Quantidade de horas | H62: Valor hora/falta | I62: Total
C63: Vigilante | D63: 12x36 | E63: 0.79166667 | F63: 0.29166667 | G63: 151.5 | H63: 32.35 | I63: =H63*G63 -> 4901.025
C64: Vigilante | D64: 12x36 | E64: 0.29166667 | F64: 0.79166667 | G64: 151.5 | H64: 29.63 | I64: =H64*G64 -> 4488.945
G65: =SUM(G63:G64) -> 303 | I65: =SUM(I63:I64) -> 9389.97
B67: PDP - nov/24 | C67: Função | D67: Escala | E67: Horário entrada | F67: Horário saída | G67: Quantidade de horas | H67: Valor hora/falta | I67: Total
C68: Porteiro | D68: 12x36 | E68: 0.29166667 | F68: 0.79166667 | G68: 174.75 | H68: 20.88 | I68: =H68*G68 -> 3648.78
C69: Porteiro | D69: 12x36 | E69: 0.79166667 | F69: 0.29166667 | G69: 174.75 | H69: 22.83 | I69: =H69*G69 -> 3989.5425
G70: =SUM(G68:G69) -> 349.5 | I70: =SUM(I68:I69) -> 7638.3225
B72: PDP - nov/24 | C72: Função | D72: Escala | E72: Horário entrada | F72: Horário saída | G72: Quantidade de horas | H72: Valor hora/falta | I72: Total
C73: Vigilante joalheria | D73: 12x36 | E73: 0.45833333 | F73: 0.95833333 | G73: 12 | H73: 35.25 | I73: =H73*G73 -> 423
G74: =SUM(G73:G73) -> 12 | I74: =SUM(I73:I73) -> 423
B76: santa maria - nov/24 | C76: Função | D76: Escala | E76: Horário entrada | F76: Horário saída | G76: Quantidade de dias | H76: Valor dia/falta | I76: Total
C77: Mecânico de refrigeração | D77: 6x1 | E77: 0.29166667 | F77: 0.63888889 | H77: 209.86 | I77: =H77*G77 -> 0
C78: Auxiliar de refrigeração | D78: 6x1 | E78: 0.29166667 | F78: 0.63888889 | G78: 3 | H78: 131.48 | I78: =H78*G78 -> 394.44
G79: =SUM(G77:G78) -> 3 | I79: =SUM(I77:I78) -> 394.44
B81: piracicaba - nov/24 | C81: Função | D81: Escala | E81: Horário entrada | F81: Horário saída | G81: Quantidade de dias | H81: Valor dia/falta | I81: Total
C82: Supervisor | D82: 5x2 | E82: 0.33333333 | F82: 0.74166667 | G82: 3 | H82: 272.07 | I82: =G82*H82 -> 816.21
C83: Supervisor | D83: 5x2 | E83: 0.54166667 | F83: 0.95 | H83: 274.35 | I83: =G83*H83 -> 0
C84: Auxiliar de Manutenção | D84: 6x1 | E84: 0.33333333 | F84: 0.68055556 | G84: 3 | H84: 152.13 | I84: =G84*H84 -> 456.39
C85: Auxiliar de Manutenção | D85: 5x2 | E85: 0.91666667 | F85: 0.325 | G85: 22 | H85: 212 | I85: =G85*H85 -> 4664
C86: Eletricista | D86: 12x36 | E86: 0.79166667 | F86: 0.29166667 | H86: 268.09 | I86: =G86*H86 -> 0
C87: Eletricista II | D87: 12x36 | E87: 0.29166667 | F87: 0.79166667 | H87: 304.14 | I87: =G87*H87 -> 0
C88: Eletricista | D88: 6x1 | E88: 0.29166667 | F88: 0.63888889 | G88: 2 | H88: 226.3 | I88: =G88*H88 -> 452.6
C89: Bombeiro Hidráulico | D89: 12x36 | E89: 0.29166667 | F89: 0.79166667 | G89: 3 | H89: 161.92 | I89: =G89*H89 -> 485.76
C90: Pintor | D90: 5x2 | E90: 0.91666667 | F90: 0.325 | G90: 1 | H90: 212 | I90: =G90*H90 -> 212
C91: Civil | D91: 12x36 | E91: 0.79166667 | F91: 0.29166667 | G91: 2 | H91: 158.66 | I91: =G91*H91 -> 317.32
C92: Planejamento/Almoxarife* | D92: 5x2 | E92: 0.33333333 | F92: 0.74166667 | H92: 171.92 | I92: =G92*H92 -> 0
G93: =SUM(G82:G92) -> 36 | I93: =SUM(I82:I92) -> 7404.28
B95: piracicaba - nov/24 | C95: Função | D95: Escala | E95: Horário entrada | F95: Horário saída | G95: Quantidade de dias | H95: Valor dia/falta | I95: Total
C96: SUP DE OPERAÇÕES I | D96: 6x1 | E96: 0.33333333 | F96: 0.68055556 | H96: 307.33 | I96: =G96*H96 -> 0
C97: ENCARREGADO II | D97: 6x1 | E97: 0.91666667 | F97: 0.25 | G97: 13 | H97: 250.36 | I97: =G97*H97 -> 3254.68
C98: OPERADOR DE MAQUINAS | D98: 6x1 | E98: 0.91666667 | F98: 0.25 | H98: 170.32 | I98: =G98*H98 -> 0
C99: SERVENTE LIMPEZA | D99: 6x1 | E99: 0.41666667 | F99: 0.76388889 | H99: 145.83 | I99: =G99*H99 -> 0
C100: SERVENTE LIMPEZA | D100: 12X36 | E100: 0.41666667 | F100: 0.91666667 | G100: 1 | H100: 134.02 | I100: =G100*H100 -> 134.02
C101: AGENTE DE HIGIENIZAÇÃO I40 | D101: 12X36 | E101: 0.41666667 | F101: 0.91666667 | H101: 173.31 | I101: =G101*H101 -> 0
C102: AUX SERVIÇOS GERAIS P30 | D102: 12X36 | E102: 0.41666667 | F102: 0.91666667 | H102: 167.2 | I102: =G102*H102 -> 0
C103: LIMPADOR VIDRO | D103: 6X1 | E103: 0.25 | F103: 0.59722222 | H103: 156.11 | I103: =G103*H103 -> 0
C104: SERVENTE LIMPEZA | D104: 5x1 | E104: 0.91666667 | F104: 0.25 | G104: 32 | H104: 166.65 | I104: =G104*H104 -> 5332.8
C105: AGENTE DE HIGIENIZAÇÃO I40 | D105: 6X1 | E105: 0.91666667 | F105: 0.25 | H105: 213.34 | I105: =G105*H105 -> 0
G106: =SUBTOTAL(9,G96:G105) -> 46 | I106: =SUBTOTAL(9,I96:I105) -> 8721.5
B108: PDP - nov/24 | C108: Função | D108: Escala | E108: Horário entrada | F108: Horário saída | G108: Quantidade de dias | H108: Valor dia/falta | I108: Total
C109: Supervisor | D109: 6x1 | E109: 0.375 | F109: 0.72222222 | H109: 437.92 | I109: =H109*G109 -> 0
C110: Encarregado | D110: 5x1 | E110: 0.25 | F110: 0.59722222 | H110: 202.15 | I110: =H110*G110 -> 0
C111: Encarregado | D111: 5x1 | E111: 0.56944444 | F111: 0.91666667 | H111: 202.15 | I111: =H111*G111 -> 0
C112: Agente de Limpeza | D112: 5x1 | E112: 0.56944444 | F112: 0.91666667 | G112: 33 | H112: 145.5 | I112: =H112*G112 -> 4801.5
C113: Agente de Limpeza Líder | D113: 5x1 | E113: 0.25 | F113: 0.59722222 | G113: 26 | H113: 186.33 | I113: =H113*G113 -> 4844.58
C114: Agente de Limpeza Líder | D114: 5x1 | E114: 0.56944444 | F114: 0.91666667 | H114: 168.4 | I114: =H114*G114 -> 0
C115: Limpador de Vidro em Altura | D115: 5x1 | E115: 0.25 | F115: 0.59722222 | H115: 192.65 | I115: =H115*G115 -> 0
C116: Agente de Limpeza | D116: 5x1 | E116: 0.25 | F116: 0.59722222 | G116: 27 | H116: 145.5 | I116: =H116*G116 -> 3928.5
...

Sheet Faltas e atrasos | Cálculo
B1: Unidade | C1: Categoria | D1: Fornecedor | E1: Mês Falta | F1: Função | G1: Escala | H1: Horário entrada | I1: Horário saída | J1: Quantidade de horas | K1: Valor hora/falta | L1: Total Atrasos | M1: Quantidade de dias | N1: Valor dia/falta | O1: Total Faltas
B2: Shopping Villagio Caxias | C2: Portaria | D2: Veper | E2: 45658 | F2: Porteiro | G2: 12x36 | H2: 0.29166667 | I2: 0.79166667 | J2: 3 | K2: 19.76 | L2: =J2*K2 -> 59.28 | M2: 0 | O2: =M2*N2 -> 0
B3: Shopping Villagio Caxias | C3: Portaria | D3: Veper | E3: 45658 | F3: Porteiro | G3: 12x36 | H3: 0.5 | I3: 0 | J3: 4.42 | K3: 20.44 | L3: =J3*K3 -> 90.3448 | M3: 0 | O3: =M3*N3 -> 0
B4: Shopping Villagio Caxias | C4: Portaria | D4: Veper | E4: 45658 | F4: Porteiro | G4: 5x2 | H4: 0.33333333 | I4: 0.58333333 | J4: 0 | K4: 19.62 | L4: =J4*K4 -> 0 | M4: 0 | O4: =M4*N4 -> 0
B5: Shopping Villagio Caxias | C5: Portaria | D5: Veper | E5: 45658 | F5: Porteiro | G5: 6x1 | H5: 0.79166667 | I5: 0.041666667 | J5: 0 | K5: 21.36 | L5: =J5*K5 -> 0 | M5: 0 | O5: =M5*N5 -> 0
B6: Shopping Villagio Caxias | C6: Vigilância | D6: Veper | E6: 45658 | F6: Vigilante | G6: 12x36 | H6: 0.375 | I6: 0.875 | J6: 0.11666667 | K6: 26.26 | L6: =J6*K6 -> 3.0636667 | M6: 0 | O6: =M6*N6 -> 0
B7: Shopping Villagio Caxias | C7: Vigilância | D7: Veper | E7: 45658 | F7: Vigilante | G7: 12x36 | H7: 0.41666667 | I7: 0.91666667 | J7: 0.55 | K7: 26.26 | L7: =J7*K7 -> 14.443 | M7: 0 | O7: =M7*N7 -> 0
B8: Shopping Villagio Caxias | C8: Vigilância | D8: Veper | E8: 45658 | F8: Vigilante | G8: 12x36 | H8: 0.33333333 | I8: 0.83333333 | J8: 0 | K8: 26.26 | L8: =J8*K8 -> 0 | M8: 0 | O8: =M8*N8 -> 0
B9: Shopping Villagio Caxias | C9: Vigilância | D9: Veper | E9: 45658 | F9: Vigilante | G9: 12x36 | H9: 0.29166667 | I9: 0.79166667 | J9: 0.93333333 | K9: 26.26 | L9: =J9*K9 -> 24.509333 | M9: 0 | O9: =M9*N9 -> 0
B10: Shopping Parque Dom Pedro | C10: Jardinagem | D10: Marcia Novaes Paisagismo | E10: 45658 | F10: Jardineiro | G10: 5x1 | H10: 0.33333333 | I10: 0.68055556 | J10: 0 | L10: =J10*K10 -> 0 | M10: 18 | N10: 152.79 | O10: =M10*N10 -> 2750.22
B11: Praça Nova Araçatuba | C11: Brigada de Incêndio | D11: Medmais | E11: 45658 | F11: Bonbeiro Civil | G11: 12x36 | H11: 0.25 | I11: 0.75 | J11: 6.25 | K11: 45.55 | L11: =J11*K11 -> 284.6875 | M11: 0 | N11: 329.23 | O11: =M11*N11 -> 0
B12: Praça Nova Araçatuba | C12: Brigada de Incêndio | D12: Medmais | E12: 45658 | F12: Bonbeiro Civil | G12: 12x36 | H12: 0.75 | I12: 0.25 | J12: 6 | K12: 48.42 | L12: =J12*K12 -> 290.52 | M12: 0 | N12: 349.94 | O12: =M12*N12 -> 0
B13: Shopping Villagio Caxias | C13: Limpeza | D13: GPS | E13: 45658 | F13: Auxiliar de Limpeza 2º turno - 40% Insalubridade | G13: 5x1 | H13: 0.47916667 | I13: 0.82638889 | J13: 0 | L13: =J13*K13 -> 0 | M13: 3 | N13: 216.44 | O13: =M13*N13 -> 649.32
B14: Shopping Villagio Caxias | C14: Limpeza | D14: GPS | E14: 45658 | F14: Auxiliar de Limpeza 2º turno - 20% Insalubridade | G14: 5x1 | H14: 0.47916667 | I14: 0.82638889 | J14: 0 | L14: =J14*K14 -> 0 | M14: 165 | N14: 192.88 | O14: =M14*N14 -> 31825.2
B15: Shopping Villagio Caxias | C15: Limpeza | D15: GPS | E15: 45658 | F15: Auxiliar de Limpeza 3º turno - 40% Insalubridade | G15: 5x1 | H15: 0.8125 | I15: 0.15972222 | J15: 0 | L15: =J15*K15 -> 0 | M15: 0 | N15: 241.71 | O15: =M15*N15 -> 0
B16: Shopping Villagio Caxias | C16: Limpeza | D16: GPS | E16: 45658 | F16: Auxiliar de Limpeza 3º turno - 20% Insalubridade | G16: 5x1 | H16: 0.8125 | I16: 0.15972222 | J16: 0 | L16: =J16*K16 -> 0 | M16: 0 | N16: 214.54 | O16: =M16*N16 -> 0
B17: Shopping Villagio Caxias | C17: Limpeza | D17: GPS | E17: 45658 | F17: Auxiliar de Limpeza 2º turno - 20% Insalubridade | G17: 5x1 | H17: 0.60069444 | I17: 0.94791667 | J17: 0 | L17: =J17*K17 -> 0 | M17: 0 | N17: 196.57 | O17: =M17*N17 -> 0
B18: Shopping Villagio Caxias | C18: Limpeza | D18: GPS | E18: 45658 | F18: Líder 1º turno | G18: 5x1 | H18: 0.29166667 | I18: 0.63888889 | J18: 0 | L18: =J18*K18 -> 0 | M18: 0 | N18: 239.18 | O18: =M18*N18 -> 0
B19: Shopping Villagio Caxias | C19: Limpeza | D19: GPS | E19: 45658 | F19: Líder 2º turno | G19: 5x1 | H19: 0.47916667 | I19: 0.82638889 | J19: 0 | L19: =J19*K19 -> 0 | M19: 1 | N19: 239.18 | O19: =M19*N19 -> 239.18
B20: Shopping Villagio Caxias | C20: Limpeza | D20: GPS | E20: 45658 | F20: Líder 3º turno | G20: 5x1 | H20: 0.8125 | I20: 0.15972222 | J20: 0 | L20: =J20*K20 -> 0 | M20: 0 | N20: 268.05 | O20: =M20*N20 -> 0
B21: Franca Shopping | C21: Limpeza | D21: Brasanitas | E21: 45658 | F21: Líder | G21: 12x36 | H21: 0.45833333 | I21: 0.95833333 | J21: 0 | L21: =J21*K21 -> 0 | M21: 1 | N21: 155.2 | O21: =M21*N21 -> 155.2
B22: Franca Shopping | C22: Limpeza | D22: Brasanitas | E22: 45658 | F22: Agente de asseio | G22: 5x1 | H22: 0.27777778 | I22: 0.625 | J22: 0 | L22: =J22*K22 -> 0 | M22: 36 | N22: 162.55 | O22: =M22*N22 -> 5851.8
B23: Franca Shopping | C23: Limpeza | D23: Brasanitas | E23: 45658 | F23: Agente de asseio | G23: 5x1 | H23: 0.61111111 | I23: 0.95833333 | J23: 0 | L23: =J23*K23 -> 0 | M23: 30 | N23: 166.68 | O23: =M23*N23 -> 5000.4
B24: Franca Shopping | C24: Limpeza | D24: Brasanitas | E24: 45658 | F24: Agente de higienização | G24: 5x1 | H24: 0.29166667 | I24: 0.63888889 | J24: 0 | L24: =J24*K24 -> 0 | M24: 0 | N24: 207.83 | O24: =M24*N24 -> 0
B25: Franca Shopping | C25: Limpeza | D25: Brasanitas | E25: 45658 | F25: Agente de higienização | G25: 5x1 | H25: 0.61111111 | I25: 0.95833333 | J25: 0 | L25: =J25*K25 -> 0 | M25: 7 | N25: 213.42 | O25: =M25*N25 -> 1493.94
B26: Shopping Piracicaba | C26: Portaria | D26: Grupo JLR | E26: 45658 | F26: Porteiro | G26: 12x36 | H26: 0.79166667 | I26: 0.29166667 | J26: 0 | K26: 24.35 | L26: =J26*K26 -> 0 | M26: 6 | N26: 176 | O26: =M26*N26 -> 1056
B27: Shopping Piracicaba | C27: Portaria | D27: Grupo JLR | E27: 45658 | F27: Porteiro | G27: 6x1 | H27: 0.29166667 | I27: 0.63888889 | J27: 0 | K27: 23.69 | L27: =J27*K27 -> 0 | M27: 0 | N27: 171.26 | O27: =M27*N27 -> 0
B28: Shopping Piracicaba | C28: Portaria | D28: Grupo JLR | E28: 45658 | F28: Porteiro | G28: 12x36 | H28: 0.29166667 | I28: 0.79166667 | J28: 0 | K28: 22.23 | L28: =J28*K28 -> 0 | M28: 0 | N28: 160.67 | O28: =M28*N28 -> 0
B29: Shopping Piracicaba | C29: Portaria | D29: Grupo JLR | E29: 45658 | F29: Porteiro | G29: 12x36 | H29: 0.375 | I29: 0.875 | J29: 0 | K29: 22.23 | L29: =J29*K29 -> 0 | M29: 6 | N29: 160.67 | O29: =M29*N29 -> 964.02
B30: Shopping Piracicaba | C30: Vigilância | D30: Grupo JLR | E30: 45658 | F30: Vigilante | G30: 12x36 | H30: 0.41666667 | I30: 0.91666667 | J30: 0 | K30: 29.26 | L30: =J30*K30 -> 0 | M30: 1 | N30: 211.46 | O30: =M30*N30 -> 211.46
B31: Shopping Piracicaba | C31: Vigilância | D31: Grupo JLR | E31: 45658 | F31: Vigilante | G31: 12x36 | H31: 0.79166667 | I31: 0.29166667 | J31: 0 | K31: 32.19 | L31: =J31*K31 -> 0 | M31: 0 | N31: 232.65 | O31: =M31*N31 -> 0
B32: Shopping Piracicaba | C32: Vigilância | D32: Grupo JLR | E32: 45658 | F32: Vigilante | G32: 12x36 | H32: 0.5 | I32: 0 | J32: 0 | K32: 30.23 | L32: =J32*K32 -> 0 | M32: 0 | N32: 218.52 | O32: =M32*N32 -> 0
B33: Shopping Piracicaba | C33: Vigilância | D33: Grupo JLR | E33: 45658 | F33: Vigilante Líder | G33: 6x1 | H33: 0.61111111 | I33: 0.95833333 | J33: 0 | K33: 34.66 | L33: =J33*K33 -> 0 | M33: 0 | N33: 250.49 | O33: =M33*N33 -> 0
B34: Boulevard Bauru | C34: PMOC | D34: Grupo Opus | E34: 45658 | F34: Mecânico de refrigeração | G34: 6x1 | H34: 0.29166667 | I34: 0.63888889 | J34: 0 | L34: =J34*K34 -> 0 | M34: 0 | N34: 196.47 | O34: =M34*N34 -> 0
B35: Boulevard Bauru | C35: PMOC | D35: Grupo Opus | E35: 45658 | F35: Auxiliar de refrigeração | G35: 6x1 | H35: 0.29166667 | I35: 0.63888889 | J35: 0 | L35: =J35*K35 -> 0 | M35: 1 | N35: 152.36 | O35: =M35*N35 -> 152.36
B36: Praça Nova Santa Maria | C36: PMOC | D36: Grupo Opus | E36: 45658 | F36: Mecânico de refrigeração | G36: 6x1 | H36: 0.29166667 | I36: 0.63888889 | J36: 0 | L36: =J36*K36 -> 0 | M36: 3 | N36: 214.55 | O36: =M36*N36 -> 643.65
B37: Praça Nova Santa Maria | C37: PMOC | D37: Grupo Opus | E37: 45658 | F37: Auxiliar de refrigeração | G37: 6x1 | H37: 0.29166667 | I37: 0.63888889 | J37: 0 | L37: =J37*K37 -> 0 | M37: 2 | N37: 140.8 | O37: =M37*N37 -> 281.6
B38: Shopping Parque Dom Pedro | C38: Vigilância | D38: Verzani | E38: 45658 | F38: Vigilante | G38: 12x36 | H38: 0.79166667 | I38: 0.29166667 | J38: 22.5 | K38: 32.35 | L38: =J38*K38 -> 727.875 | M38: 0 | O38: =M38*N38 -> 0
B39: Shopping Parque Dom Pedro | C39: Vigilância | D39: Verzani | E39: 45658 | F39: Vigilante | G39: 12x36 | H39: 0.29166667 | I39: 0.79166667 | J39: 22.5 | K39: 29.63 | L39: =J39*K39 -> 666.675 | M39: 0 | O39: =M39*N39 -> 0
B40: Shopping Parque Dom Pedro | C40: Portaria | D40: Verzani | E40: 45658 | F40: Porteiro | G40: 12x36 | H40: 0.29166667 | I40: 0.79166667 | J40: 111 | K40: 20.88 | L40: =J40*K40 -> 2317.68 | M40: 0 | O40: =M40*N40 -> 0
B41: Shopping Parque Dom Pedro | C41: Portaria | D41: Verzani | E41: 45658 | F41: Porteiro | G41: 12x36 | H41: 0.79166667 | I41: 0.29166667 | J41: 111 | K41: 22.83 | L41: =J41*K41 -> 2534.13 | M41: 0 | O41: =M41*N41 -> 0
B42: Shopping Parque Dom Pedro | C42: Vigilância - Extras Joalheria | D42: Verzani | E42: 45658 | F42: Vigilante joalheria | G42: 12x36 | H42: 0.45833333 | I42: 0.95833333 | J42: 108 | K42: 35.25 | L42: =J42*K42 -> 3807 | M42: 0 | O42: =M42*N42 -> 0
B43: Shopping Piracicaba | C43: Manutenção | D43: Brasanitas | E43: 45658 | F43: Supervisor | G43: 5x2 | H43: 0.33333333 | I43: 0.74166667 | J43: 0 | L43: =J43*K43 -> 0 | M43: 0 | N43: 278.82 | O43: =M43*N43 -> 0
B44: Shopping Piracicaba | C44: Manutenção | D44: Brasanitas | E44: 45658 | F44: Supervisor | G44: 5x2 | H44: 0.54166667 | I44: 0.95 | J44: 0 | L44: =J44*K44 -> 0 | M44: 0 | N44: 281.76 | O44: =M44*N44 -> 0
B45: Shopping Piracicaba | C45: Manutenção | D45: Brasanitas | E45: 45658 | F45: Auxiliar de Manutenção | G45: 6x1 | H45: 0.33333333 | I45: 0.68055556 | J45: 0 | L45: =J45*K45 -> 0 | M45: 3 | N45: 155.33 | O45: =M45*N45 -> 465.99
B46: Shopping Piracicaba | C46: Manutenção | D46: Brasanitas | E46: 45658 | F46: Auxiliar de Manutenção | G46: 5x2 | H46: 0.91666667 | I46: 0.325 | J46: 0 | L46: =J46*K46 -> 0 | M46: 27 | N46: 215.74 | O46: =M46*N46 -> 5824.98
B47: Shopping Piracicaba | C47: Manutenção | D47: Brasanitas | E47: 45658 | F47: Eletricista | G47: 12x36 | H47: 0.79166667 | I47: 0.29166667 | J47: 0 | L47: =J47*K47 -> 0 | M47: 0 | N47: 274.37 | O47: =M47*N47 -> 0
B48: Shopping Piracicaba | C48: Manutenção | D48: Brasanitas | E48: 45658 | F48: Eletricista II | G48: 12x36 | H48: 0.29166667 | I48: 0.79166667 | J48: 0 | L48: =J48*K48 -> 0 | M48: 0 | N48: 311.7 | O48: =M48*N48 -> 0
B49: Shopping Piracicaba | C49: Manutenção | D49: Brasanitas | E49: 45658 | F49: Eletricista | G49: 6x1 | H49: 0.29166667 | I49: 0.63888889 | J49: 0 | L49: =J49*K49 -> 0 | M49: 0 | N49: 231.95 | O49: =M49*N49 -> 0
B50: Shopping Piracicaba | C50: Manutenção | D50: Brasanitas | E50: 45658 | F50: Bombeiro Hidráulico | G50: 12x36 | H50: 0.29166667 | I50: 0.79166667 | J50: 0 | L50: =J50*K50 -> 0 | M50: 0 | N50: 165.91 | O50: =M50*N50 -> 0
B51: Shopping Piracicaba | C51: Manutenção | D51: Brasanitas | E51: 45658 | F51: Pintor | G51: 5x2 | H51: 0.91666667 | I51: 0.325 | J51: 0 | L51: =J51*K51 -> 0 | M51: 38 | N51: 215.74 | O51: =M51*N51 -> 8198.12
B52: Shopping Piracicaba | C52: Manutenção | D52: Brasanitas | E52: 45658 | F52: Civil | G52: 12x36 | H52: 0.79166667 | I52: 0.29166667 | J52: 0 | L52: =J52*K52 -> 0 | M52: 2 | N52: 162.55 | O52: =M52*N52 -> 325.1
B53: Shopping Piracicaba | C53: Manutenção | D53: Brasanitas | E53: 45658 | F53: Planejamento/Almoxarife* | G53: 5x2 | H53: 0.33333333 | I53: 0.74166667 | J53: 0 | L53: =J53*K53 -> 0 | M53: 0 | N53: 176 | O53: =M53*N53 -> 0
B54: Shopping Piracicaba | C54: PMOC | D54: Brasanitas | E54: 45658 | F54: Mecânico de Refrigeração | G54: 12x36 | H54: 0.29166667 | I54: 0.79166667 | J54: 0 | L54: =J54*K54 -> 0 | M54: 1 | N54: 284.13 | O54: =M54*N54 -> 284.13
... B79: Shopping Parque Dom Pedro | C79: Limpeza | D79: Verzani | E79: 45658 | F79: Operador de Máquina de Limpeza Tripulada | G79: 5x1 | H79: 0.25 | I79: 0.59722222 | J79: 0 | L79: =J79*K79 -> 0 | M79: 0 | N79: 192.11 | O79: =M79*N79 -> 0
B80: Shopping Parque Dom Pedro | C80: Manutenção | D80: Verzani | E80: 45658 | F80: SUPERVISOR DE MANUTENÇÃO | G80: 5x2 | H80: 0.33333333 | I80: 0.74166667 | J80: 0.31 | K80: 97.3 | L80: =J80*K80 -> 30.163 | M80: 0 | N80: 703.25 | O80: =M80*N80 -> 0
B81: Shopping Parque Dom Pedro | C81: Manutenção | D81: Verzani | E81: 45658 | F81: ENCARREGADO DE MANUTENÇÃO | G81: 12x36 | H81: 0.25 | I81: 0.75 | J81: 0 | K81: 53.39 | L81: =J81*K81 -> 0 | M81: 0 | N81: 385.9 | O81: =M81*N81 -> 0
B82: Shopping Parque Dom Pedro | C82: Manutenção | D82: Verzani | E82: 45658 | F82: ENCARREGADO DE MANUTENÇÃO | G82: 12x36 | H82: 0.25 | I82: 0.75 | J82: 0 | K82: 53.39 | L82: =J82*K82 -> 0 | M82: 0 | N82: 385.9 | O82: =M82*N82 -> 0
B83: Shopping Parque Dom Pedro | C83: Manutenção | D83: Verzani | E83: 45658 | F83: ALMOXARIFE (AUX.) | G83: 5x2 | H83: 0.33333333 | I83: 0.74166667 | J83: 0 | K83: 31.23 | L83: =J83*K83 -> 0 | M83: 0 | N83: 225.73 | O83: =M83*N83 -> 0
B84: Shopping Parque Dom Pedro | C84: Manutenção | D84: Verzani | E84: 45658 | F84: PLANEJADOR (PCM) | G84: 5x2 | H84: 0.33333333 | I84: 0.74166667 | J84: 0 | K84: 39.03 | L84: =J84*K84 -> 0 | M84: 0 | N84: 282.13 | O84: =M84*N84 -> 0
