Workbook
Name SegmentaçãodeDados_Categoria: #N/A
Name SegmentaçãodeDados_Fornecedor: #N/A
Name SegmentaçãodeDados_Mês: #N/A
Name SegmentaçãodeDados_Unidade: #N/A

Sheet Infos Relatório
C1: 45292 | I1: 45323 | O1: 45352 | U1: 45383 | AA1: 45413 | AG1: 45444 | AM1: 45474 | AS1: 45505 | AY1: 45536 | BE1: 45566 | BK1: 45597 | BQ1: 45627
B2: Limpeza | C2: =C1 -> 45292 | I2: =I1 -> 45323 | O2: =O1 -> 45352 | U2: =U1 -> 45383 | AA2: =AA1 -> 45413 | AG2: =AG1 -> 45444 | AM2: =AM1 -> 45474 | AS2: =AS1 -> 45505 | AY2: =AY1 -> 45536 | BE2: =BE1 -> 45566 | BK2: =BK1 -> 45597 | BQ2: =BQ1 -> 45627
B3: Fornecedor | C3: Qtd Shopping | D3: HC Total | E3: Valor total contrato | F3: Desconto SLA Total | G3: Desconto médio % | H3: QTD de faltas | I3: Qtd Shopping | J3: HC Total | K3: Valor total contrato | L3: Desconto SLA Total | M3: Desconto médio % | N3: QTD de faltas | O3: Qtd Shopping | P3: HC Total | Q3: Valor total contrato | R3: Desconto SLA Total | S3: Desconto médio % | T3: QTD de faltas | U3: Qtd Shopping | V3: HC Total | W3: Valor total contrato | X3: Desconto SLA Total | Y3: Desconto médio % | Z3: QTD de faltas | AA3: Qtd Shopping | AB3: HC Total | AC3: Valor total contrato | AD3: Desconto SLA Total | AE3: Desconto médio % | AF3: QTD de faltas | AG3: Qtd Shopping | AH3: HC Total | AI3: Valor total contrato | AJ3: Desconto SLA Total | AK3: Desconto médio % | AL3: QTD de faltas | AM3: Qtd Shopping | AN3: HC Total | AO3: Valor total contrato | AP3: Desconto SLA Total | AQ3: Desconto médio % | AR3: QTD de faltas | AS3: Qtd Shopping | AT3: HC Total | AU3: Valor total contrato | AV3: Desconto SLA Total | AW3: Desconto médio % | AX3: QTD de faltas | AY3: Qtd Shopping | AZ3: HC Total | BA3: Valor total contrato | BB3: Desconto SLA Total | BC3: Desconto médio % | BD3: QTD de faltas | BE3: Qtd Shopping | BF3: HC Total | BG3: Valor total contrato | BH3: Desconto SLA Total | BI3: Desconto médio % | BJ3: QTD de faltas | BK3: Qtd Shopping | BL3: HC Total | BM3: Valor total contrato | BN3: Desconto SLA Total | BO3: Desconto médio % | BP3: QTD de faltas | BQ3: Qtd Shopping | BR3: HC Total | BS3: Valor total contrato | BT3: Desconto SLA Total | BU3: Desconto médio % | BV3: QTD de faltas
B4: Action Fire | C4: =COUNTIFS('Faturamento SP3'!$D$2:$D$692,'Infos Relatório'!$B$2,'Faturamento SP3'!$E$2:$E$692,'Infos Relatório'!$B4,'Faturamento SP3'!$Z$2:$Z$692,'Infos Relatório'!C$1) -> 0 | D4: =SUMIFS('Faturamento SP3'!$G$2:$G$692,'Faturamento SP3'!$D$2:$D$692,'Infos Relatório'!$B$2,'Faturamento SP3'!$E$2:$E$692,'Infos Relatório'!$B4,'Faturamento SP3'!$Z$2:$Z$692,'Infos Relatório'!C$1) -> 0 | E4: =SUMIFS('Faturamento SP3'!$J$2:$J$692,'Faturamento SP3'!$D$2:$D$692,'Infos Relatório'!$B$2,'Faturamento SP3'!$E$2:$E$692,'Infos Relatório'!$B4,'Faturamento SP3'!$Z$2:$Z$692,'Infos Relatório'!C$1) -> 0 | F4: =SUMIFS('Faturamento SP3'!$O$2:$O$692,'Faturamento SP3'!$D$2:$D$692,'Infos Relatório'!$B$2,'Faturamento SP3'!$E$2:$E$692,'Infos Relatório'!$B4,'Faturamento SP3'!$Z$2:$Z$692,'Infos Relatório'!C$1,'Faturamento SP3'!$T$2:$T$692,"Sim")+SUMIFS('Faturamento SP3'!$P$2:$P$692,'Faturamento SP3'!$D$2:$D$692,'Infos Relatório'!$B$2,'Faturamento SP3'!$E$2:$E$692,'Infos Relatório'!$B4,'Faturamento SP3'!$Z$2:$Z$692,'Infos Relatório'!C$1,'Faturamento SP3'!$T$2:$T$692,"Sim") -> 0 | G4: =F4/E4 -> #DIV/0! | H4: =SUMIFS('Faturamento SP3'!$H$2:$H$692,'Faturamento SP3'!$D$2:$D$692,'Infos Relatório'!$B$2,'Faturamento SP3'!$E$2:$E$692,'Infos Relatório'!$B4,'Faturamento SP3'!$Z$2:$Z$692,'Infos Relatório'!C$1) -> 0 | I4: =COUNTIFS('Faturamento SP3'!$D$2:$D$692,'Infos Relatório'!$B$2,'Faturamento SP3'!$E$2:$E$692,'Infos Relatório'!$B4,'Faturamento SP3'!$Z$2:$Z$692,'Infos Relatório'!I$1) -> 0 | J4: =SUMIFS('Faturamento SP3'!$G$2:$G$692,'Faturamento SP3'!$D$2:$D$692,'Infos Relatório'!$B$2,'Faturamento SP3'!$E$2:$E$692,'Infos Relatório'!$B4,'Faturamento SP3'!$Z$2:$Z$692,'Infos Relatório'!I$1) -> 0 | K4: =SUMIFS('Faturamento SP3'!$J$2:$J$692,'Faturamento SP3'!$D$2:$D$692,'Infos Relatório'!$B$2,'Faturamento SP3'!$E$2:$E$692,'Infos Relatório'!$B4,'Faturamento SP3'!$Z$2:$Z$692,'Infos Relatório'!I$1) -> 0 | L4: =SUMIFS('Faturamento SP3'!$O$2:$O$692,'Faturamento SP3'!$D$2:$D$692,'Infos Relatório'!$B$2,'Faturamento SP3'!$E$2:$E$692,'Infos Relatório'!$B4,'Faturamento SP3'!$Z$2:$Z$692,'Infos Relatório'!I$1,'Faturamento SP3'!$T$2:$T$692,"Sim")+SUMIFS('Faturamento SP3'!$P$2:$P$692,'Faturamento SP3'!$D$2:$D$692,'Infos Relatório'!$B$2,'Faturamento SP3'!$E$2:$E$692,'Infos Relatório'!$B4,'Faturamento SP3'!$Z$2:$Z$692,'Infos Relatório'!I$1,'Faturamento SP3'!$T$2:$T$692,"Sim") -> 0 | M4: =L4/K4 -> #DIV/0! | N4: =SUMIFS('Faturamento SP3'!$H$2:$H$692,'Faturamento SP3'!$D$2:$D$692,'Infos Relatório'!$B$2,'Faturamento SP3'!$E$2:$E$692,'Infos Relatório'!$B4,'Faturamento SP3'!$Z$2:$Z$692,'Infos Relatório'!I$1) -> 0 | O4: =COUNTIFS('Faturamento SP3'!$D$2:$D$692,'Infos Relatório'!$B$2,'Faturamento SP3'!$E$2:$E$692,'Infos Relatório'!$B4,'Faturamento SP3'!$Z$2:$Z$692,'Infos Relatório'!O$1) -> 0 | P4: =SUMIFS('Faturamento SP3'!$G$2:$G$692,'Faturamento SP3'!$D$2:$D$692,'Infos Relatório'!$B$2,'Faturamento SP3'!$E$2:$E$692,'Infos Relatório'!$B4,'Faturamento SP3'!$Z$2:$Z$692,'Infos Relatório'!O$1) -> 0 | Q4: =SUMIFS('Faturamento SP3'!$J$2:$J$692,'Faturamento SP3'!$D$2:$D$692,'Infos Relatório'!$B$2,'Faturamento SP3'!$E$2:$E$692,'Infos Relatório'!$B4,'Faturamento SP3'!$Z$2:$Z$692,'Infos Relatório'!O$1) -> 0 | R4: =SUMIFS('Faturamento SP3'!$O$2:$O$692,'Faturamento SP3'!$D$2:$D$692,'Infos Relatório'!$B$2,'Faturamento SP3'!$E$2:$E$692,'Infos Relatório'!$B4,'Faturamento SP3'!$Z$2:$Z$692,'Infos Relatório'!O$1,'Faturamento SP3'!$T$2:$T$692,"Sim")+SUMIFS('Faturamento SP3'!$P$2:$P$692,'Faturamento SP3'!$D$2:$D$692,'Infos Relatório'!$B$2,'Faturamento SP3'!$E$2:$E$692,'Infos Relatório'!$B4,'Faturamento SP3'!$Z$2:$Z$692,'Infos Relatório'!O$1,'Faturamento SP3'!$T$2:$T$692,"Sim") -> 0 | S4: =R4/Q4 -> #DIV/0! | T4: =SUMIFS('Faturamento SP3'!$H$2:$H$692,'Faturamento SP3'!$D$2:$D$692,'Infos Relatório'!$B$2,'Faturamento SP3'!$E$2:$E$692,'Infos Relatório'!$B4,'Faturamento SP3'!$Z$2:$Z$692,'Infos Relatório'!O$1) -> 0 | U4: =COUNTIFS('Faturamento SP3'!$D$2:$D$692,'Infos Relatório'!$B$2,'Faturamento SP3'!$E$2:$E$692,'Infos Relatório'!$B4,'Faturamento SP3'!$Z$2:$Z$692,'Infos Relatório'!U$1) -> 0 | V4: =SUMIFS('Faturamento SP3'!$G$2:$G$692,'Faturamento SP3'!$D$2:$D$692,'Infos Relatório'!$B$2,'Faturamento SP3'!$E$2:$E$692,'Infos Relatório'!$B4,'Faturamento SP3'!$Z$2:$Z$692,'Infos Relatório'!U$1) -> 0 | W4: =SUMIFS('Faturamento SP3'!$J$2:$J$692,'Faturamento SP3'!$D$2:$D$692,'Infos Relatório'!$B$2,'Faturamento SP3'!$E$2:$E$692,'Infos Relatório'!$B4,'Faturamento SP3'!$Z$2:$Z$692,'Infos Relatório'!U$1) -> 0 | X4: =SUMIFS('Faturamento SP3'!$O$2:$O$692,'Faturamento SP3'!$D$2:$D$692,'Infos Relatório'!$B$2,'Faturamento SP3'!$E$2:$E$692,'Infos Relatório'!$B4,'Faturamento SP3'!$Z$2:$Z$692,'Infos Relatório'!U$1,'Faturamento SP3'!$T$2:$T$692,"Sim")+SUMIFS('Faturamento SP3'!$P$2:$P$692,'Faturamento SP3'!$D$2:$D$692,'Infos Relatório'!$B$2,'Faturamento SP3'!$E$2:$E$692,'Infos Relatório'!$B4,'Faturamento SP3'!$Z$2:$Z$692,'Infos Relatório'!U$1,'Faturamento SP3'!$T$2:$T$692,"Sim") -> 0 | Y4: =X4/W4 -> #DIV/0! | Z4: =SUMIFS('Faturamento SP3'!$H$2:$H$692,'Faturamento SP3'!$D$2:$D$692,'Infos Relatório'!$B$2,'Faturamento SP3'!$E$2:$E$692,'Infos Relatório'!$B4,'Faturamento SP3'!$Z$2:$Z$692,'Infos Relatório'!U$1) -> 0 | AA4: =COUNTIFS('Faturamento SP3'!$D$2:$D$692,'Infos Relatório'!$B$2,'Faturamento SP3'!$E$2:$E$692,'Infos Relatório'!$B4,'Faturamento SP3'!$Z$2:$Z$692,'Infos Relatório'!AA$1) -> 0 | AB4: =SUMIFS('Faturamento SP3'!$G$2:$G$692,'Faturamento SP3'!$D$2:$D$692,'Infos Relatório'!$B$2,'Faturamento SP3'!$E$2:$E$692,'Infos Relatório'!$B4,'Faturamento SP3'!$Z$2:$Z$692,'Infos Relatório'!AA$1) -> 0 | AC4: =SUMIFS('Faturamento SP3'!$J$2:$J$692,'Faturamento SP3'!$D$2:$D$692,'Infos Relatório'!$B$2,'Faturamento SP3'!$E$2:$E$692,'Infos Relatório'!$B4,'Faturamento SP3'!$Z$2:$Z$692,'Infos Relatório'!AA$1) -> 0 | AD4: =SUMIFS('Faturamento SP3'!$O$2:$O$692,'Faturamento SP3'!$D$2:$D$692,'Infos Relatório'!$B$2,'Faturamento SP3'!$E$2:$E$692,'Infos Relatório'!$B4,'Faturamento SP3'!$Z$2:$Z$692,'Infos Relatório'!AA$1,'Faturamento SP3'!$T$2:$T$692,"Sim")+SUMIFS('Faturamento SP3'!$P$2:$P$692,'Faturamento SP3'!$D$2:$D$692,'Infos Relatório'!$B$2,'Faturamento SP3'!$E$2:$E$692,'Infos Relatório'!$B4,'Faturamento SP3'!$Z$2:$Z$692,'Infos Relatório'!AA$1,'Faturamento SP3'!$T$2:$T$692,"Sim") -> 0 | AE4: =AD4/AC4 -> #DIV/0! | AF4: =SUMIFS('Faturamento SP3'!$H$2:$H$692,'Faturamento SP3'!$D$2:$D$692,'Infos Relatório'!$B$2,'Faturamento SP3'!$E$2:$E$692,'Infos Relatório'!$B4,'Faturamento SP3'!$Z$2:$Z$692,'Infos Relatório'!AA$1) -> 0 | AG4: =COUNTIFS('Faturamento SP3'!$D$2:$D$692,'Infos Relatório'!$B$2,'Faturamento SP3'!$E$2:$E$692,'Infos Relatório'!$B4,'Faturamento SP3'!$Z$2:$Z$692,'Infos Relatório'!AG$1) -> 0 | AH4: =SUMIFS('Faturamento SP3'!$G$2:$G$692,'Faturamento SP3'!$D$2:$D$692,'Infos Relatório'!$B$2,'Faturamento SP3'!$E$2:$E$692,'Infos Relatório'!$B4,'Faturamento SP3'!$Z$2:$Z$692,'Infos Relatório'!AG$1) -> 0 | AI4: =SUMIFS('Faturamento SP3'!$J$2:$J$692,'Faturamento SP3'!$D$2:$D$692,'Infos Relatório'!$B$2,'Faturamento SP3'!$E$2:$E$692,'Infos Relatório'!$B4,'Faturamento SP3'!$Z$2:$Z$692,'Infos Relatório'!AG$1) -> 0 | AJ4: =SUMIFS('Faturamento SP3'!$O$2:$O$692,'Faturamento SP3'!$D$2:$D$692,'Infos Relatório'!$B$2,'Faturamento SP3'!$E$2:$E$692,'Infos Relatório'!$B4,'Faturamento SP3'!$Z$2:$Z$692,'Infos Relatório'!AG$1,'Faturamento SP3'!$T$2:$T$692,"Sim")+SUMIFS('Faturamento SP3'!$P$2:$P$692,'Faturamento SP3'!$D$2:$D$692,'Infos Relatório'!$B$2,'Faturamento SP3'!$E$2:$E$692,'Infos Relatório'!$B4,'Faturamento SP3'!$Z$2:$Z$692,'Infos Relatório'!AG$1,'Faturamento SP3'!$T$2:$T$692,"Sim") -> 0 | AK4: =AJ4/AI4 -> #DIV/0! | AL4: =SUMIFS('Faturamento SP3'!$H$2:$H$692,'Faturamento SP3'!$D$2:$D$692,'Infos Relatório'!$B$2,'Faturamento SP3'!$E$2:$E$692,'Infos Relatório'!$B4,'Faturamento SP3'!$Z$2:$Z$692,'Infos Relatório'!AG$1) -> 0 | AM4: =COUNTIFS('Faturamento SP3'!$D$2:$D$692,'Infos Relatório'!$B$2,'Faturamento SP3'!$E$2:$E$692,'Infos Relatório'!$B4,'Faturamento SP3'!$Z$2:$Z$692,'Infos Relatório'!AM$1) -> 0 | AN4: =SUMIFS('Faturamento SP3'!$G$2:$G$692,'Faturamento SP3'!$D$2:$D$692,'Infos Relatório'!$B$2,'Faturamento SP3'!$E$2:$E$692,'Infos Relatório'!$B4,'Faturamento SP3'!$Z$2:$Z$692,'Infos Relatório'!AM$1) -> 0 | AO4: =SUMIFS('Faturamento SP3'!$J$2:$J$692,'Faturamento SP3'!$D$2:$D$692,'Infos Relatório'!$B$2,'Faturamento SP3'!$E$2:$E$692,'Infos Relatório'!$B4,'Faturamento SP3'!$Z$2:$Z$692,'Infos Relatório'!AM$1) -> 0 | AP4: =SUMIFS('Faturamento SP3'!$O$2:$O$692,'Faturamento SP3'!$D$2:$D$692,'Infos Relatório'!$B$2,'Faturamento SP3'!$E$2:$E$692,'Infos Relatório'!$B4,'Faturamento SP3'!$Z$2:$Z$692,'Infos Relatório'!AM$1,'Faturamento SP3'!$T$2:$T$692,"Sim")+SUMIFS('Faturamento SP3'!$P$2:$P$692,'Faturamento SP3'!$D$2:$D$692,'Infos Relatório'!$B$2,'Faturamento SP3'!$E$2:$E$692,'Infos Relatório'!$B4,'Faturamento SP3'!$Z$2:$Z$692,'Infos Relatório'!AM$1,'Faturamento SP3'!$T$2:$T$692,"Sim") -> 0 | AQ4: =AP4/AO4 -> #DIV/0! | AR4: =SUMIFS('Faturamento SP3'!$H$2:$H$692,'Faturamento SP3'!$D$2:$D$692,'Infos Relatório'!$B$2,'Faturamento SP3'!$E$2:$E$692,'Infos Relatório'!$B4,'Faturamento SP3'!$Z$2:$Z$692,'Infos Relatório'!AM$1) -> 0 | AS4: =COUNTIFS('Faturamento SP3'!$D$2:$D$692,'Infos Relatório'!$B$2,'Faturamento SP3'!$E$2:$E$692,'Infos Relatório'!$B4,'Faturamento SP3'!$Z$2:$Z$692,'Infos Relatório'!AS$1) -> 0 | AT4: =SUMIFS('Faturamento SP3'!$G$2:$G$692,'Faturamento SP3'!$D$2:$D$692,'Infos Relatório'!$B$2,'Faturamento SP3'!$E$2:$E$692,'Infos Relatório'!$B4,'Faturamento SP3'!$Z$2:$Z$692,'Infos Relatório'!AS$1) -> 0 | AU4: =SUMIFS('Faturamento SP3'!$J$2:$J$692,'Faturamento SP3'!$D$2:$D$692,'Infos Relatório'!$B$2,'Faturamento SP3'!$E$2:$E$692,'Infos Relatório'!$B4,'Faturamento SP3'!$Z$2:$Z$692,'Infos Relatório'!AS$1) -> 0 | AV4: =SUMIFS('Faturamento SP3'!$O$2:$O$692,'Faturamento SP3'!$D$2:$D$692,'Infos Relatório'!$B$2,'Faturamento SP3'!$E$2:$E$692,'Infos Relatório'!$B4,'Faturamento SP3'!$Z$2:$Z$692,'Infos Relatório'!AS$1,'Faturamento SP3'!$T$2:$T$692,"Sim")+SUMIFS('Faturamento SP3'!$P$2:$P$692,'Faturamento SP3'!$D$2:$D$692,'Infos Relatório'!$B$2,'Faturamento SP3'!$E$2:$E$692,'Infos Relatório'!$B4,'Faturamento SP3'!$Z$2:$Z$692,'Infos Relatório'!AS$1,'Faturamento SP3'!$T$2:$T$692,"Sim") -> 0 | AW4: =AV4/AU4 -> #DIV/0! | AX4: =SUMIFS('Faturamento SP3'!$H$2:$H$692,'Faturamento SP3'!$D$2:$D$692,'Infos Relatório'!$B$2,'Faturamento SP3'!$E$2:$E$692,'Infos Relatório'!$B4,'Faturamento SP3'!$Z$2:$Z$692,'Infos Relatório'!AS$1) -> 0 | AY4: =COUNTIFS('Faturamento SP3'!$D$2:$D$692,'Infos Relatório'!$B$2,'Faturamento SP3'!$E$2:$E$692,'Infos Relatório'!$B4,'Faturamento SP3'!$Z$2:$Z$692,'Infos Relatório'!AY$1) -> 0 | AZ4: =SUMIFS('Faturamento SP3'!$G$2:$G$692,'Faturamento SP3'!$D$2:$D$692,'Infos Relatório'!$B$2,'Faturamento SP3'!$E$2:$E$692,'Infos Relatório'!$B4,'Faturamento SP3'!$Z$2:$Z$692,'Infos Relatório'!AY$1) -> 0 | BA4: =SUMIFS('Faturamento SP3'!$J$2:$J$692,'Faturamento SP3'!$D$2:$D$692,'Infos Relatório'!$B$2,'Faturamento SP3'!$E$2:$E$692,'Infos Relatório'!$B4,'Faturamento SP3'!$Z$2:$Z$692,'Infos Relatório'!AY$1) -> 0 | BB4: =SUMIFS('Faturamento SP3'!$O$2:$O$692,'Faturamento SP3'!$D$2:$D$692,'Infos Relatório'!$B$2,'Faturamento SP3'!$E$2:$E$692,'Infos Relatório'!$B4,'Faturamento SP3'!$Z$2:$Z$692,'Infos Relatório'!AY$1,'Faturamento SP3'!$T$2:$T$692,"Sim")+SUMIFS('Faturamento SP3'!$P$2:$P$692,'Faturamento SP3'!$D$2:$D$692,'Infos Relatório'!$B$2,'Faturamento SP3'!$E$2:$E$692,'Infos Relatório'!$B4,'Faturamento SP3'!$Z$2:$Z$692,'Infos Relatório'!AY$1,'Faturamento SP3'!$T$2:$T$692,"Sim") -> 0 | BC4: =BB4/BA4 -> #DIV/0! | BD4: =SUMIFS('Faturamento SP3'!$H$2:$H$692,'Faturamento SP3'!$D$2:$D$692,'Infos Relatório'!$B$2,'Faturamento SP3'!$E$2:$E$692,'Infos Relatório'!$B4,'Faturamento SP3'!$Z$2:$Z$692,'Infos Relatório'!AY$1) -> 0 | BE4: =COUNTIFS('Faturamento SP3'!$D$2:$D$692,'Infos Relatório'!$B$2,'Faturamento SP3'!$E$2:$E$692,'Infos Relatório'!$B4,'Faturamento SP3'!$Z$2:$Z$692,'Infos Relatório'!BE$1) -> 0 | BF4: =SUMIFS('Faturamento SP3'!$G$2:$G$692,'Faturamento SP3'!$D$2:$D$692,'Infos Relatório'!$B$2,'Faturamento SP3'!$E$2:$E$692,'Infos Relatório'!$B4,'Faturamento SP3'!$Z$2:$Z$692,'Infos Relatório'!BE$1) -> 0 | BG4: =SUMIFS('Faturamento SP3'!$J$2:$J$692,'Faturamento SP3'!$D$2:$D$692,'Infos Relatório'!$B$2,'Faturamento SP3'!$E$2:$E$692,'Infos Relatório'!$B4,'Faturamento SP3'!$Z$2:$Z$692,'Infos Relatório'!BE$1) -> 0 | BH4: =SUMIFS('Faturamento SP3'!$O$2:$O$692,'Faturamento SP3'!$D$2:$D$692,'Infos Relatório'!$B$2,'Faturamento SP3'!$E$2:$E$692,'Infos Relatório'!$B4,'Faturamento SP3'!$Z$2:$Z$692,'Infos Relatório'!BE$1,'Faturamento SP3'!$T$2:$T$692,"Sim")+SUMIFS('Faturamento SP3'!$P$2:$P$692,'Faturamento SP3'!$D$2:$D$692,'Infos Relatório'!$B$2,'Faturamento SP3'!$E$2:$E$692,'Infos Relatório'!$B4,'Faturamento SP3'!$Z$2:$Z$692,'Infos Relatório'!BE$1,'Faturamento SP3'!$T$2:$T$692,"Sim") -> 0 | BI4: =BH4/BG4 -> #DIV/0! | BJ4: =SUMIFS('Faturamento SP3'!$H$2:$H$692,'Faturamento SP3'!$D$2:$D$692,'Infos Relatório'!$B$2,'Faturamento SP3'!$E$2:$E$692,'Infos Relatório'!$B4,'Faturamento SP3'!$Z$2:$Z$692,'Infos Relatório'!BE$1) -> 0 | BK4: =COUNTIFS('Faturamento SP3'!$D$2:$D$692,'Infos Relatório'!$B$2,'Faturamento SP3'!$E$2:$E$692,'Infos Relatório'!$B4,'Faturamento SP3'!$Z$2:$Z$692,'Infos Relatório'!BK$1) -> 0 | BL4: =SUMIFS('Faturamento SP3'!$G$2:$G$692,'Faturamento SP3'!$D$2:$D$692,'Infos Relatório'!$B$2,'Faturamento SP3'!$E$2:$E$692,'Infos Relatório'!$B4,'Faturamento SP3'!$Z$2:$Z$692,'Infos Relatório'!BK$1) -> 0 | BM4: =SUMIFS('Faturamento SP3'!$J$2:$J$692,'Faturamento SP3'!$D$2:$D$692,'Infos Relatório'!$B$2,'Faturamento SP3'!$E$2:$E$692,'Infos Relatório'!$B4,'Faturamento SP3'!$Z$2:$Z$692,'Infos Relatório'!BK$1) -> 0 | BN4: =SUMIFS('Faturamento SP3'!$O$2:$O$692,'Faturamento SP3'!$D$2:$D$692,'Infos Relatório'!$B$2,'Faturamento SP3'!$E$2:$E$692,'Infos Relatório'!$B4,'Faturamento SP3'!$Z$2:$Z$692,'Infos Relatório'!BK$1,'Faturamento SP3'!$T$2:$T$692,"Sim")+SUMIFS('Faturamento SP3'!$P$2:$P$692,'Faturamento SP3'!$D$2:$D$692,'Infos Relatório'!$B$2,'Faturamento SP3'!$E$2:$E$692,'Infos Relatório'!$B4,'Faturamento SP3'!$Z$2:$Z$692,'Infos Relatório'!BK$1,'Faturamento SP3'!$T$2:$T$692,"Sim") -> 0 | BO4: =BN4/BM4 -> #DIV/0! | BP4: =SUMIFS('Faturamento SP3'!$H$2:$H$692,'Faturamento SP3'!$D$2:$D$692,'Infos Relatório'!$B$2,'Faturamento SP3'!$E$2:$E$692,'Infos Relatório'!$B4,'Faturamento SP3'!$Z$2:$Z$692,'Infos Relatório'!BK$1) -> 0 | BQ4: =COUNTIFS('Faturamento SP3'!$D$2:$D$692,'Infos Relatório'!$B$2,'Faturamento SP3'!$E$2:$E$692,'Infos Relatório'!$B4,'Faturamento SP3'!$Z$2:$Z$692,'Infos Relatório'!BQ$1) -> 0 | BR4: =SUMIFS('Faturamento SP3'!$G$2:$G$692,'Faturamento SP3'!$D$2:$D$692,'Infos Relatório'!$B$2,'Faturamento SP3'!$E$2:$E$692,'Infos Relatório'!$B4,'Faturamento SP3'!$Z$2:$Z$692,'Infos Relatório'!BQ$1) -> 0 | BS4: =SUMIFS('Faturamento SP3'!$J$2:$J$692,'Faturamento SP3'!$D$2:$D$692,'Infos Relatório'!$B$2,'Faturamento SP3'!$E$2:$E$692,'Infos Relatório'!$B4,'Faturamento SP3'!$Z$2:$Z$692,'Infos Relatório'!BQ$1) -> 0 | BT4: =SUMIFS('Faturamento SP3'!$O$2:$O$692,'Faturamento SP3'!$D$2:$D$692,'Infos Relatório'!$B$2,'Faturamento SP3'!$E$2:$E$692,'Infos Relatório'!$B4,'Faturamento SP3'!$Z$2:$Z$692,'Infos Relatório'!BQ$1,'Faturamento SP3'!$T$2:$T$692,"Sim")+SUMIFS('Faturamento SP3'!$P$2:$P$692,'Faturamento SP3'!$D$2:$D$692,'Infos Relatório'!$B$2,'Faturamento SP3'!$E$2:$E$692,'Infos Relatório'!$B4,'Faturamento SP3'!$Z$2:$Z$692,'Infos Relatório'!BQ$1,'Faturamento SP3'!$T$2:$T$692,"Sim") -> 0 | BU4: =BT4/BS4 -> #DIV/0! | BV4: =SUMIFS('Faturamento SP3'!$H$2:$H$692,'Faturamento SP3'!$D$2:$D$692,'Infos Relatório'!$B$2,'Faturamento SP3'!$E$2:$E$692,'Infos Relatório'!$B4,'Faturamento SP3'!$Z$2:$Z$692,'Infos Relatório'!BQ$1) -> 0
B5: Agro Rio | C5: =COUNTIFS('Faturamento SP3'!$D$2:$D$692,'Infos Relatório'!$B$2,'Faturamento SP3'!$E$2:$E$692,'Infos Relatório'!$B5,'Faturamento SP3'!$Z$2:$Z$692,'Infos Relatório'!C$1) -> 0 | D5: =SUMIFS('Faturamento SP3'!$G$2:$G$692,'Faturamento SP3'!$D$2:$D$692,'Infos Relatório'!$B$2,'Faturamento SP3'!$E$2:$E$692,'Infos Relatório'!$B5,'Faturamento SP3'!$Z$2:$Z$692,'Infos Relatório'!C$1) -> 0 | E5: =SUMIFS('Faturamento SP3'!$J$2:$J$692,'Faturamento SP3'!$D$2:$D$692,'Infos Relatório'!$B$2,'Faturamento SP3'!$E$2:$E$692,'Infos Relatório'!$B5,'Faturamento SP3'!$Z$2:$Z$692,'Infos Relatório'!C$1) -> 0 | F5: =SUMIFS('Faturamento SP3'!$O$2:$O$692,'Faturamento SP3'!$D$2:$D$692,'Infos Relatório'!$B$2,'Faturamento SP3'!$E$2:$E$692,'Infos Relatório'!$B5,'Faturamento SP3'!$Z$2:$Z$692,'Infos Relatório'!C$1,'Faturamento SP3'!$T$2:$T$692,"Sim")+SUMIFS('Faturamento SP3'!$P$2:$P$692,'Faturamento SP3'!$D$2:$D$692,'Infos Relatório'!$B$2,'Faturamento SP3'!$E$2:$E$692,'Infos Relatório'!$B5,'Faturamento SP3'!$Z$2:$Z$692,'Infos Relatório'!C$1,'Faturamento SP3'!$T$2:$T$692,"Sim") -> 0 | G5: =F5/E5 -> #DIV/0! | H5: =SUMIFS('Faturamento SP3'!$H$2:$H$692,'Faturamento SP3'!$D$2:$D$692,'Infos Relatório'!$B$2,'Faturamento SP3'!$E$2:$E$692,'Infos Relatório'!$B5,'Faturamento SP3'!$Z$2:$Z$692,'Infos Relatório'!C$1) -> 0 | I5: =COUNTIFS('Faturamento SP3'!$D$2:$D$692,'Infos Relatório'!$B$2,'Faturamento SP3'!$E$2:$E$692,'Infos Relatório'!$B5,'Faturamento SP3'!$Z$2:$Z$692,'Infos Relatório'!I$1) -> 0 | J5: =SUMIFS('Faturamento SP3'!$G$2:$G$692,'Faturamento SP3'!$D$2:$D$692,'Infos Relatório'!$B$2,'Faturamento SP3'!$E$2:$E$692,'Infos Relatório'!$B5,'Faturamento SP3'!$Z$2:$Z$692,'Infos Relatório'!I$1) -> 0 | K5: =SUMIFS('Faturamento SP3'!$J$2:$J$692,'Faturamento SP3'!$D$2:$D$692,'Infos Relatório'!$B$2,'Faturamento SP3'!$E$2:$E$692,'Infos Relatório'!$B5,'Faturamento SP3'!$Z$2:$Z$692,'Infos Relatório'!I$1) -> 0 | L5: =SUMIFS('Faturamento SP3'!$O$2:$O$692,'Faturamento SP3'!$D$2:$D$692,'Infos Relatório'!$B$2,'Faturamento SP3'!$E$2:$E$692,'Infos Relatório'!$B5,'Faturamento SP3'!$Z$2:$Z$692,'Infos Relatório'!I$1,'Faturamento SP3'!$T$2:$T$692,"Sim")+SUMIFS('Faturamento SP3'!$P$2:$P$692,'Faturamento SP3'!$D$2:$D$692,'Infos Relatório'!$B$2,'Faturamento SP3'!$E$2:$E$692,'Infos Relatório'!$B5,'Faturamento SP3'!$Z$2:$Z$692,'Infos Relatório'!I$1,'Faturamento SP3'!$T$2:$T$692,"Sim") -> 0 | M5: =L5/K5 -> #DIV/0! | N5: =SUMIFS('Faturamento SP3'!$H$2:$H$692,'Faturamento SP3'!$D$2:$D$692,'Infos Relatório'!$B$2,'Faturamento SP3'!$E$2:$E$692,'Infos Relatório'!$B5,'Faturamento SP3'!$Z$2:$Z$692,'Infos Relatório'!I$1) -> 0 | O5: =COUNTIFS('Faturamento SP3'!$D$2:$D$692,'Infos Relatório'!$B$2,'Faturamento SP3'!$E$2:$E$692,'Infos Relatório'!$B5,'Faturamento SP3'!$Z$2:$Z$692,'Infos Relatório'!O$1) -> 0 | P5: =SUMIFS('Faturamento SP3'!$G$2:$G$692,'Faturamento SP3'!$D$2:$D$692,'Infos Relatório'!$B$2,'Faturamento SP3'!$E$2:$E$692,'Infos Relatório'!$B5,'Faturamento SP3'!$Z$2:$Z$692,'Infos Relatório'!O$1) -> 0 | Q5: =SUMIFS('Faturamento SP3'!$J$2:$J$692,'Faturamento SP3'!$D$2:$D$692,'Infos Relatório'!$B$2,'Faturamento SP3'!$E$2:$E$692,'Infos Relatório'!$B5,'Faturamento SP3'!$Z$2:$Z$692,'Infos Relatório'!O$1) -> 0 | R5: =SUMIFS('Faturamento SP3'!$O$2:$O$692,'Faturamento SP3'!$D$2:$D$692,'Infos Relatório'!$B$2,'Faturamento SP3'!$E$2:$E$692,'Infos Relatório'!$B5,'Faturamento SP3'!$Z$2:$Z$692,'Infos Relatório'!O$1,'Faturamento SP3'!$T$2:$T$692,"Sim")+SUMIFS('Faturamento SP3'!$P$2:$P$692,'Faturamento SP3'!$D$2:$D$692,'Infos Relatório'!$B$2,'Faturamento SP3'!$E$2:$E$692,'Infos Relatório'!$B5,'Faturamento SP3'!$Z$2:$Z$692,'Infos Relatório'!O$1,'Faturamento SP3'!$T$2:$T$692,"Sim") -> 0 | S5: =R5/Q5 -> #DIV/0! | T5: =SUMIFS('Faturamento SP3'!$H$2:$H$692,'Faturamento SP3'!$D$2:$D$692,'Infos Relatório'!$B$2,'Faturamento SP3'!$E$2:$E$692,'Infos Relatório'!$B5,'Faturamento SP3'!$Z$2:$Z$692,'Infos Relatório'!O$1) -> 0 | U5: =COUNTIFS('Faturamento SP3'!$D$2:$D$692,'Infos Relatório'!$B$2,'Faturamento SP3'!$E$2:$E$692,'Infos Relatório'!$B5,'Faturamento SP3'!$Z$2:$Z$692,'Infos Relatório'!U$1) -> 0 | V5: =SUMIFS('Faturamento SP3'!$G$2:$G$692,'Faturamento SP3'!$D$2:$D$692,'Infos Relatório'!$B$2,'Faturamento SP3'!$E$2:$E$692,'Infos Relatório'!$B5,'Faturamento SP3'!$Z$2:$Z$692,'Infos Relatório'!U$1) -> 0 | W5: =SUMIFS('Faturamento SP3'!$J$2:$J$692,'Faturamento SP3'!$D$2:$D$692,'Infos Relatório'!$B$2,'Faturamento SP3'!$E$2:$E$692,'Infos Relatório'!$B5,'Faturamento SP3'!$Z$2:$Z$692,'Infos Relatório'!U$1) -> 0 | X5: =SUMIFS('Faturamento SP3'!$O$2:$O$692,'Faturamento SP3'!$D$2:$D$692,'Infos Relatório'!$B$2,'Faturamento SP3'!$E$2:$E$692,'Infos Relatório'!$B5,'Faturamento SP3'!$Z$2:$Z$692,'Infos Relatório'!U$1,'Faturamento SP3'!$T$2:$T$692,"Sim")+SUMIFS('Faturamento SP3'!$P$2:$P$692,'Faturamento SP3'!$D$2:$D$692,'Infos Relatório'!$B$2,'Faturamento SP3'!$E$2:$E$692,'Infos Relatório'!$B5,'Faturamento SP3'!$Z$2:$Z$692,'Infos Relatório'!U$1,'Faturamento SP3'!$T$2:$T$692,"Sim") -> 0 | Y5: =X5/W5 -> #DIV/0! | Z5: =SUMIFS('Faturamento SP3'!$H$2:$H$692,'Faturamento SP3'!$D$2:$D$692,'Infos Relatório'!$B$2,'Faturamento SP3'!$E$2:$E$692,'Infos Relatório'!$B5,'Faturamento SP3'!$Z$2:$Z$692,'Infos Relatório'!U$1) -> 0 | AA5: =COUNTIFS('Faturamento SP3'!$D$2:$D$692,'Infos Relatório'!$B$2,'Faturamento SP3'!$E$2:$E$692,'Infos Relatório'!$B5,'Faturamento SP3'!$Z$2:$Z$692,'Infos Relatório'!AA$1) -> 0 | AB5: =SUMIFS('Faturamento SP3'!$G$2:$G$692,'Faturamento SP3'!$D$2:$D$692,'Infos Relatório'!$B$2,'Faturamento SP3'!$E$2:$E$692,'Infos Relatório'!$B5,'Faturamento SP3'!$Z$2:$Z$692,'Infos Relatório'!AA$1) -> 0 | AC5: =SUMIFS('Faturamento SP3'!$J$2:$J$692,'Faturamento SP3'!$D$2:$D$692,'Infos Relatório'!$B$2,'Faturamento SP3'!$E$2:$E$692,'Infos Relatório'!$B5,'Faturamento SP3'!$Z$2:$Z$692,'Infos Relatório'!AA$1) -> 0 | AD5: =SUMIFS('Faturamento SP3'!$O$2:$O$692,'Faturamento SP3'!$D$2:$D$692,'Infos Relatório'!$B$2,'Faturamento SP3'!$E$2:$E$692,'Infos Relatório'!$B5,'Faturamento SP3'!$Z$2:$Z$692,'Infos Relatório'!AA$1,'Faturamento SP3'!$T$2:$T$692,"Sim")+SUMIFS('Faturamento SP3'!$P$2:$P$692,'Faturamento SP3'!$D$2:$D$692,'Infos Relatório'!$B$2,'Faturamento SP3'!$E$2:$E$692,'Infos Relatório'!$B5,'Faturamento SP3'!$Z$2:$Z$692,'Infos Relatório'!AA$1,'Faturamento SP3'!$T$2:$T$692,"Sim") -> 0 | AE5: =AD5/AC5 -> #DIV/0! | AF5: =SUMIFS('Faturamento SP3'!$H$2:$H$692,'Faturamento SP3'!$D$2:$D$692,'Infos Relatório'!$B$2,'Faturamento SP3'!$E$2:$E$692,'Infos Relatório'!$B5,'Faturamento SP3'!$Z$2:$Z$692,'Infos Relatório'!AA$1) -> 0 | AG5: =COUNTIFS('Faturamento SP3'!$D$2:$D$692,'Infos Relatório'!$B$2,'Faturamento SP3'!$E$2:$E$692,'Infos Relatório'!$B5,'Faturamento SP3'!$Z$2:$Z$692,'Infos Relatório'!AG$1) -> 0 | AH5: =SUMIFS('Faturamento SP3'!$G$2:$G$692,'Faturamento SP3'!$D$2:$D$692,'Infos Relatório'!$B$2,'Faturamento SP3'!$E$2:$E$692,'Infos Relatório'!$B5,'Faturamento SP3'!$Z$2:$Z$692,'Infos Relatório'!AG$1) -> 0 | AI5: =SUMIFS('Faturamento SP3'!$J$2:$J$692,'Faturamento SP3'!$D$2:$D$692,'Infos Relatório'!$B$2,'Faturamento SP3'!$E$2:$E$692,'Infos Relatório'!$B5,'Faturamento SP3'!$Z$2:$Z$692,'Infos Relatório'!AG$1) -> 0 | AJ5: =SUMIFS('Faturamento SP3'!$O$2:$O$692,'Faturamento SP3'!$D$2:$D$692,'Infos Relatório'!$B$2,'Faturamento SP3'!$E$2:$E$692,'Infos Relatório'!$B5,'Faturamento SP3'!$Z$2:$Z$692,'Infos Relatório'!AG$1,'Faturamento SP3'!$T$2:$T$692,"Sim")+SUMIFS('Faturamento SP3'!$P$2:$P$692,'Faturamento SP3'!$D$2:$D$692,'Infos Relatório'!$B$2,'Faturamento SP3'!$E$2:$E$692,'Infos Relatório'!$B5,'Faturamento SP3'!$Z$2:$Z$692,'Infos Relatório'!AG$1,'Faturamento SP3'!$T$2:$T$692,"Sim") -> 0 | AK5: =AJ5/AI5 -> #DIV/0! | AL5: =SUMIFS('Faturamento SP3'!$H$2:$H$692,'Faturamento SP3'!$D$2:$D$692,'Infos Relatório'!$B$2,'Faturamento SP3'!$E$2:$E$692,'Infos Relatório'!$B5,'Faturamento SP3'!$Z$2:$Z$692,'Infos Relatório'!AG$1) -> 0 | AM5: =COUNTIFS('Faturamento SP3'!$D$2:$D$692,'Infos Relatório'!$B$2,'Faturamento SP3'!$E$2:$E$692,'Infos Relatório'!$B5,'Faturamento SP3'!$Z$2:$Z$692,'Infos Relatório'!AM$1) -> 0 | AN5: =SUMIFS('Faturamento SP3'!$G$2:$G$692,'Faturamento SP3'!$D$2:$D$692,'Infos Relatório'!$B$2,'Faturamento SP3'!$E$2:$E$692,'Infos Relatório'!$B5,'Faturamento SP3'!$Z$2:$Z$692,'Infos Relatório'!AM$1) -> 0 | AO5: =SUMIFS('Faturamento SP3'!$J$2:$J$692,'Faturamento SP3'!$D$2:$D$692,'Infos Relatório'!$B$2,'Faturamento SP3'!$E$2:$E$692,'Infos Relatório'!$B5,'Faturamento SP3'!$Z$2:$Z$692,'Infos Relatório'!AM$1) -> 0 | AP5: =SUMIFS('Faturamento SP3'!$O$2:$O$692,'Faturamento SP3'!$D$2:$D$692,'Infos Relatório'!$B$2,'Faturamento SP3'!$E$2:$E$692,'Infos Relatório'!$B5,'Faturamento SP3'!$Z$2:$Z$692,'Infos Relatório'!AM$1,'Faturamento SP3'!$T$2:$T$692,"Sim")+SUMIFS('Faturamento SP3'!$P$2:$P$692,'Faturamento SP3'!$D$2:$D$692,'Infos Relatório'!$B$2,'Faturamento SP3'!$E$2:$E$692,'Infos Relatório'!$B5,'Faturamento SP3'!$Z$2:$Z$692,'Infos Relatório'!AM$1,'Faturamento SP3'!$T$2:$T$692,"Sim") -> 0 | AQ5: =AP5/AO5 -> #DIV/0! | AR5: =SUMIFS('Faturamento SP3'!$H$2:$H$692,'Faturamento SP3'!$D$2:$D$692,'Infos Relatório'!$B$2,'Faturamento SP3'!$E$2:$E$692,'Infos Relatório'!$B5,'Faturamento SP3'!$Z$2:$Z$692,'Infos Relatório'!AM$1) -> 0 | AS5: =COUNTIFS('Faturamento SP3'!$D$2:$D$692,'Infos Relatório'!$B$2,'Faturamento SP3'!$E$2:$E$692,'Infos Relatório'!$B5,'Faturamento SP3'!$Z$2:$Z$692,'Infos Relatório'!AS$1) -> 0 | AT5: =SUMIFS('Faturamento SP3'!$G$2:$G$692,'Faturamento SP3'!$D$2:$D$692,'Infos Relatório'!$B$2,'Faturamento SP3'!$E$2:$E$692,'Infos Relatório'!$B5,'Faturamento SP3'!$Z$2:$Z$692,'Infos Relatório'!AS$1) -> 0 | AU5: =SUMIFS('Faturamento SP3'!$J$2:$J$692,'Faturamento SP3'!$D$2:$D$692,'Infos Relatório'!$B$2,'Faturamento SP3'!$E$2:$E$692,'Infos Relatório'!$B5,'Faturamento SP3'!$Z$2:$Z$692,'Infos Relatório'!AS$1) -> 0 | AV5: =SUMIFS('Faturamento SP3'!$O$2:$O$692,'Faturamento SP3'!$D$2:$D$692,'Infos Relatório'!$B$2,'Faturamento SP3'!$E$2:$E$692,'Infos Relatório'!$B5,'Faturamento SP3'!$Z$2:$Z$692,'Infos Relatório'!AS$1,'Faturamento SP3'!$T$2:$T$692,"Sim")+SUMIFS('Faturamento SP3'!$P$2:$P$692,'Faturamento SP3'!$D$2:$D$692,'Infos Relatório'!$B$2,'Faturamento SP3'!$E$2:$E$692,'Infos Relatório'!$B5,'Faturamento SP3'!$Z$2:$Z$692,'Infos Relatório'!AS$1,'Faturamento SP3'!$T$2:$T$692,"Sim") -> 0 | AW5: =AV5/AU5 -> #DIV/0! | AX5: =SUMIFS('Faturamento SP3'!$H$2:$H$692,'Faturamento SP3'!$D$2:$D$692,'Infos Relatório'!$B$2,'Faturamento SP3'!$E$2:$E$692,'Infos Relatório'!$B5,'Faturamento SP3'!$Z$2:$Z$692,'Infos Relatório'!AS$1) -> 0 | AY5: =COUNTIFS('Faturamento SP3'!$D$2:$D$692,'Infos Relatório'!$B$2,'Faturamento SP3'!$E$2:$E$692,'Infos Relatório'!$B5,'Faturamento SP3'!$Z$2:$Z$692,'Infos Relatório'!AY$1) -> 0 | AZ5: =SUMIFS('Faturamento SP3'!$G$2:$G$692,'Faturamento SP3'!$D$2:$D$692,'Infos Relatório'!$B$2,'Faturamento SP3'!$E$2:$E$692,'Infos Relatório'!$B5,'Faturamento SP3'!$Z$2:$Z$692,'Infos Relatório'!AY$1) -> 0 | BA5: =SUMIFS('Faturamento SP3'!$J$2:$J$692,'Faturamento SP3'!$D$2:$D$692,'Infos Relatório'!$B$2,'Faturamento SP3'!$E$2:$E$692,'Infos Relatório'!$B5,'Faturamento SP3'!$Z$2:$Z$692,'Infos Relatório'!AY$1) -> 0 | BB5: =SUMIFS('Faturamento SP3'!$O$2:$O$692,'Faturamento SP3'!$D$2:$D$692,'Infos Relatório'!$B$2,'Faturamento SP3'!$E$2:$E$692,'Infos Relatório'!$B5,'Faturamento SP3'!$Z$2:$Z$692,'Infos Relatório'!AY$1,'Faturamento SP3'!$T$2:$T$692,"Sim")+SUMIFS('Faturamento SP3'!$P$2:$P$692,'Faturamento SP3'!$D$2:$D$692,'Infos Relatório'!$B$2,'Faturamento SP3'!$E$2:$E$692,'Infos Relatório'!$B5,'Faturamento SP3'!$Z$2:$Z$692,'Infos Relatório'!AY$1,'Faturamento SP3'!$T$2:$T$692,"Sim") -> 0 | BC5: =BB5/BA5 -> #DIV/0! | BD5: =SUMIFS('Faturamento SP3'!$H$2:$H$692,'Faturamento SP3'!$D$2:$D$692,'Infos Relatório'!$B$2,'Faturamento SP3'!$E$2:$E$692,'Infos Relatório'!$B5,'Faturamento SP3'!$Z$2:$Z$692,'Infos Relatório'!AY$1) -> 0 | BE5: =COUNTIFS('Faturamento SP3'!$D$2:$D$692,'Infos Relatório'!$B$2,'Faturamento SP3'!$E$2:$E$692,'Infos Relatório'!$B5,'Faturamento SP3'!$Z$2:$Z$692,'Infos Relatório'!BE$1) -> 0 | BF5: =SUMIFS('Faturamento SP3'!$G$2:$G$692,'Faturamento SP3'!$D$2:$D$692,'Infos Relatório'!$B$2,'Faturamento SP3'!$E$2:$E$692,'Infos Relatório'!$B5,'Faturamento SP3'!$Z$2:$Z$692,'Infos Relatório'!BE$1) -> 0 | BG5: =SUMIFS('Faturamento SP3'!$J$2:$J$692,'Faturamento SP3'!$D$2:$D$692,'Infos Relatório'!$B$2,'Faturamento SP3'!$E$2:$E$692,'Infos Relatório'!$B5,'Faturamento SP3'!$Z$2:$Z$692,'Infos Relatório'!BE$1) -> 0 | BH5: =SUMIFS('Faturamento SP3'!$O$2:$O$692,'Faturamento SP3'!$D$2:$D$692,'Infos Relatório'!$B$2,'Faturamento SP3'!$E$2:$E$692,'Infos Relatório'!$B5,'Faturamento SP3'!$Z$2:$Z$692,'Infos Relatório'!BE$1,'Faturamento SP3'!$T$2:$T$692,"Sim")+SUMIFS('Faturamento SP3'!$P$2:$P$692,'Faturamento SP3'!$D$2:$D$692,'Infos Relatório'!$B$2,'Faturamento SP3'!$E$2:$E$692,'Infos Relatório'!$B5,'Faturamento SP3'!$Z$2:$Z$692,'Infos Relatório'!BE$1,'Faturamento SP3'!$T$2:$T$692,"Sim") -> 0 | BI5: =BH5/BG5 -> #DIV/0! | BJ5: =SUMIFS('Faturamento SP3'!$H$2:$H$692,'Faturamento SP3'!$D$2:$D$692,'Infos Relatório'!$B$2,'Faturamento SP3'!$E$2:$E$692,'Infos Relatório'!$B5,'Faturamento SP3'!$Z$2:$Z$692,'Infos Relatório'!BE$1) -> 0 | BK5: =COUNTIFS('Faturamento SP3'!$D$2:$D$692,'Infos Relatório'!$B$2,'Faturamento SP3'!$E$2:$E$692,'Infos Relatório'!$B5,'Faturamento SP3'!$Z$2:$Z$692,'Infos Relatório'!BK$1) -> 0 | BL5: =SUMIFS('Faturamento SP3'!$G$2:$G$692,'Faturamento SP3'!$D$2:$D$692,'Infos Relatório'!$B$2,'Faturamento SP3'!$E$2:$E$692,'Infos Relatório'!$B5,'Faturamento SP3'!$Z$2:$Z$692,'Infos Relatório'!BK$1) -> 0 | BM5: =SUMIFS('Faturamento SP3'!$J$2:$J$692,'Faturamento SP3'!$D$2:$D$692,'Infos Relatório'!$B$2,'Faturamento SP3'!$E$2:$E$692,'Infos Relatório'!$B5,'Faturamento SP3'!$Z$2:$Z$692,'Infos Relatório'!BK$1) -> 0 | BN5: =SUMIFS('Faturamento SP3'!$O$2:$O$692,'Faturamento SP3'!$D$2:$D$692,'Infos Relatório'!$B$2,'Faturamento SP3'!$E$2:$E$692,'Infos Relatório'!$B5,'Faturamento SP3'!$Z$2:$Z$692,'Infos Relatório'!BK$1,'Faturamento SP3'!$T$2:$T$692,"Sim")+SUMIFS('Faturamento SP3'!$P$2:$P$692,'Faturamento SP3'!$D$2:$D$692,'Infos Relatório'!$B$2,'Faturamento SP3'!$E$2:$E$692,'Infos Relatório'!$B5,'Faturamento SP3'!$Z$2:$Z$692,'Infos Relatório'!BK$1,'Faturamento SP3'!$T$2:$T$692,"Sim") -> 0 | BO5: =BN5/BM5 -> #DIV/0! | BP5: =SUMIFS('Faturamento SP3'!$H$2:$H$692,'Faturamento SP3'!$D$2:$D$692,'Infos Relatório'!$B$2,'Faturamento SP3'!$E$2:$E$692,'Infos Relatório'!$B5,'Faturamento SP3'!$Z$2:$Z$692,'Infos Relatório'!BK$1) -> 0 | BQ5: =COUNTIFS('Faturamento SP3'!$D$2:$D$692,'Infos Relatório'!$B$2,'Faturamento SP3'!$E$2:$E$692,'Infos Relatório'!$B5,'Faturamento SP3'!$Z$2:$Z$692,'Infos Relatório'!BQ$1) -> 0 | BR5: =SUMIFS('Faturamento SP3'!$G$2:$G$692,'Faturamento SP3'!$D$2:$D$692,'Infos Relatório'!$B$2,'Faturamento SP3'!$E$2:$E$692,'Infos Relatório'!$B5,'Faturamento SP3'!$Z$2:$Z$692,'Infos Relatório'!BQ$1) -> 0 | BS5: =SUMIFS('Faturamento SP3'!$J$2:$J$692,'Faturamento SP3'!$D$2:$D$692,'Infos Relatório'!$B$2,'Faturamento SP3'!$E$2:$E$692,'Infos Relatório'!$B5,'Faturamento SP3'!$Z$2:$Z$692,'Infos Relatório'!BQ$1) -> 0 | BT5: =SUMIFS('Faturamento SP3'!$O$2:$O$692,'Faturamento SP3'!$D$2:$D$692,'Infos Relatório'!$B$2,'Faturamento SP3'!$E$2:$E$692,'Infos Relatório'!$B5,'Faturamento SP3'!$Z$2:$Z$692,'Infos Relatório'!BQ$1,'Faturamento SP3'!$T$2:$T$692,"Sim")+SUMIFS('Faturamento SP3'!$P$2:$P$692,'Faturamento SP3'!$D$2:$D$692,'Infos Relatório'!$B$2,'Faturamento SP3'!$E$2:$E$692,'Infos Relatório'!$B5,'Faturamento SP3'!$Z$2:$Z$692,'Infos Relatório'!BQ$1,'Faturamento SP3'!$T$2:$T$692,"Sim") -> 0 | BU5: =BT5/BS5 -> #DIV/0! | BV5: =SUMIFS('Faturamento SP3'!$H$2:$H$692,'Faturamento SP3'!$D$2:$D$692,'Infos Relatório'!$B$2,'Faturamento SP3'!$E$2:$E$692,'Infos Relatório'!$B5,'Faturamento SP3'!$Z$2:$Z$692,'Infos Relatório'!BQ$1) -> 0
B6: AgroGarden | C6: =COUNTIFS('Faturamento SP3'!$D$2:$D$692,'Infos Relatório'!$B$2,'Faturamento SP3'!$E$2:$E$692,'Infos Relatório'!$B6,'Faturamento SP3'!$Z$2:$Z$692,'Infos Relatório'!C$1) -> 0 | D6: =SUMIFS('Faturamento SP3'!$G$2:$G$692,'Faturamento SP3'!$D$2:$D$692,'Infos Relatório'!$B$2,'Faturamento SP3'!$E$2:$E$692,'Infos Relatório'!$B6,'Faturamento SP3'!$Z$2:$Z$692,'Infos Relatório'!C$1) -> 0 | E6: =SUMIFS('Faturamento SP3'!$J$2:$J$692,'Faturamento SP3'!$D$2:$D$692,'Infos Relatório'!$B$2,'Faturamento SP3'!$E$2:$E$692,'Infos Relatório'!$B6,'Faturamento SP3'!$Z$2:$Z$692,'Infos Relatório'!C$1) -> 0 | F6: =SUMIFS('Faturamento SP3'!$O$2:$O$692,'Faturamento SP3'!$D$2:$D$692,'Infos Relatório'!$B$2,'Faturamento SP3'!$E$2:$E$692,'Infos Relatório'!$B6,'Faturamento SP3'!$Z$2:$Z$692,'Infos Relatório'!C$1,'Faturamento SP3'!$T$2:$T$692,"Sim")+SUMIFS('Faturamento SP3'!$P$2:$P$692,'Faturamento SP3'!$D$2:$D$692,'Infos Relatório'!$B$2,'Faturamento SP3'!$E$2:$E$692,'Infos Relatório'!$B6,'Faturamento SP3'!$Z$2:$Z$692,'Infos Relatório'!C$1,'Faturamento SP3'!$T$2:$T$692,"Sim") -> 0 | G6: =F6/E6 -> #DIV/0! | H6: =SUMIFS('Faturamento SP3'!$H$2:$H$692,'Faturamento SP3'!$D$2:$D$692,'Infos Relatório'!$B$2,'Faturamento SP3'!$E$2:$E$692,'Infos Relatório'!$B6,'Faturamento SP3'!$Z$2:$Z$692,'Infos Relatório'!C$1) -> 0 | I6: =COUNTIFS('Faturamento SP3'!$D$2:$D$692,'Infos Relatório'!$B$2,'Faturamento SP3'!$E$2:$E$692,'Infos Relatório'!$B6,'Faturamento SP3'!$Z$2:$Z$692,'Infos Relatório'!I$1) -> 0 | J6: =SUMIFS('Faturamento SP3'!$G$2:$G$692,'Faturamento SP3'!$D$2:$D$692,'Infos Relatório'!$B$2,'Faturamento SP3'!$E$2:$E$692,'Infos Relatório'!$B6,'Faturamento SP3'!$Z$2:$Z$692,'Infos Relatório'!I$1) -> 0 | K6: =SUMIFS('Faturamento SP3'!$J$2:$J$692,'Faturamento SP3'!$D$2:$D$692,'Infos Relatório'!$B$2,'Faturamento SP3'!$E$2:$E$692,'Infos Relatório'!$B6,'Faturamento SP3'!$Z$2:$Z$692,'Infos Relatório'!I$1) -> 0 | L6: =SUMIFS('Faturamento SP3'!$O$2:$O$692,'Faturamento SP3'!$D$2:$D$692,'Infos Relatório'!$B$2,'Faturamento SP3'!$E$2:$E$692,'Infos Relatório'!$B6,'Faturamento SP3'!$Z$2:$Z$692,'Infos Relatório'!I$1,'Faturamento SP3'!$T$2:$T$692,"Sim")+SUMIFS('Faturamento SP3'!$P$2:$P$692,'Faturamento SP3'!$D$2:$D$692,'Infos Relatório'!$B$2,'Faturamento SP3'!$E$2:$E$692,'Infos Relatório'!$B6,'Faturamento SP3'!$Z$2:$Z$692,'Infos Relatório'!I$1,'Faturamento SP3'!$T$2:$T$692,"Sim") -> 0 | M6: =L6/K6 -> #DIV/0! | N6: =SUMIFS('Faturamento SP3'!$H$2:$H$692,'Faturamento SP3'!$D$2:$D$692,'Infos Relatório'!$B$2,'Faturamento SP3'!$E$2:$E$692,'Infos Relatório'!$B6,'Faturamento SP3'!$Z$2:$Z$692,'Infos Relatório'!I$1) -> 0 | O6: =COUNTIFS('Faturamento SP3'!$D$2:$D$692,'Infos Relatório'!$B$2,'Faturamento SP3'!$E$2:$E$692,'Infos Relatório'!$B6,'Faturamento SP3'!$Z$2:$Z$692,'Infos Relatório'!O$1) -> 0 | P6: =SUMIFS('Faturamento SP3'!$G$2:$G$692,'Faturamento SP3'!$D$2:$D$692,'Infos Relatório'!$B$2,'Faturamento SP3'!$E$2:$E$692,'Infos Relatório'!$B6,'Faturamento SP3'!$Z$2:$Z$692,'Infos Relatório'!O$1) -> 0 | Q6: =SUMIFS('Faturamento SP3'!$J$2:$J$692,'Faturamento SP3'!$D$2:$D$692,'Infos Relatório'!$B$2,'Faturamento SP3'!$E$2:$E$692,'Infos Relatório'!$B6,'Faturamento SP3'!$Z$2:$Z$692,'Infos Relatório'!O$1) -> 0 | R6: =SUMIFS('Faturamento SP3'!$O$2:$O$692,'Faturamento SP3'!$D$2:$D$692,'Infos Relatório'!$B$2,'Faturamento SP3'!$E$2:$E$692,'Infos Relatório'!$B6,'Faturamento SP3'!$Z$2:$Z$692,'Infos Relatório'!O$1,'Faturamento SP3'!$T$2:$T$692,"Sim")+SUMIFS('Faturamento SP3'!$P$2:$P$692,'Faturamento SP3'!$D$2:$D$692,'Infos Relatório'!$B$2,'Faturamento SP3'!$E$2:$E$692,'Infos Relatório'!$B6,'Faturamento SP3'!$Z$2:$Z$692,'Infos Relatório'!O$1,'Faturamento SP3'!$T$2:$T$692,"Sim") -> 0 | S6: =R6/Q6 -> #DIV/0! | T6: =SUMIFS('Faturamento SP3'!$H$2:$H$692,'Faturamento SP3'!$D$2:$D$692,'Infos Relatório'!$B$2,'Faturamento SP3'!$E$2:$E$692,'Infos Relatório'!$B6,'Faturamento SP3'!$Z$2:$Z$692,'Infos Relatório'!O$1) -> 0 | U6: =COUNTIFS('Faturamento SP3'!$D$2:$D$692,'Infos Relatório'!$B$2,'Faturamento SP3'!$E$2:$E$692,'Infos Relatório'!$B6,'Faturamento SP3'!$Z$2:$Z$692,'Infos Relatório'!U$1) -> 0 | V6: =SUMIFS('Faturamento SP3'!$G$2:$G$692,'Faturamento SP3'!$D$2:$D$692,'Infos Relatório'!$B$2,'Faturamento SP3'!$E$2:$E$692,'Infos Relatório'!$B6,'Faturamento SP3'!$Z$2:$Z$692,'Infos Relatório'!U$1) -> 0 | W6: =SUMIFS('Faturamento SP3'!$J$2:$J$692,'Faturamento SP3'!$D$2:$D$692,'Infos Relatório'!$B$2,'Faturamento SP3'!$E$2:$E$692,'Infos Relatório'!$B6,'Faturamento SP3'!$Z$2:$Z$692,'Infos Relatório'!U$1) -> 0 | X6: =SUMIFS('Faturamento SP3'!$O$2:$O$692,'Faturamento SP3'!$D$2:$D$692,'Infos Relatório'!$B$2,'Faturamento SP3'!$E$2:$E$692,'Infos Relatório'!$B6,'Faturamento SP3'!$Z$2:$Z$692,'Infos Relatório'!U$1,'Faturamento SP3'!$T$2:$T$692,"Sim")+SUMIFS('Faturamento SP3'!$P$2:$P$692,'Faturamento SP3'!$D$2:$D$692,'Infos Relatório'!$B$2,'Faturamento SP3'!$E$2:$E$692,'Infos Relatório'!$B6,'Faturamento SP3'!$Z$2:$Z$692,'Infos Relatório'!U$1,'Faturamento SP3'!$T$2:$T$692,"Sim") -> 0 | Y6: =X6/W6 -> #DIV/0! | Z6: =SUMIFS('Faturamento SP3'!$H$2:$H$692,'Faturamento SP3'!$D$2:$D$692,'Infos Relatório'!$B$2,'Faturamento SP3'!$E$2:$E$692,'Infos Relatório'!$B6,'Faturamento SP3'!$Z$2:$Z$692,'Infos Relatório'!U$1) -> 0 | AA6: =COUNTIFS('Faturamento SP3'!$D$2:$D$692,'Infos Relatório'!$B$2,'Faturamento SP3'!$E$2:$E$692,'Infos Relatório'!$B6,'Faturamento SP3'!$Z$2:$Z$692,'Infos Relatório'!AA$1) -> 0 | AB6: =SUMIFS('Faturamento SP3'!$G$2:$G$692,'Faturamento SP3'!$D$2:$D$692,'Infos Relatório'!$B$2,'Faturamento SP3'!$E$2:$E$692,'Infos Relatório'!$B6,'Faturamento SP3'!$Z$2:$Z$692,'Infos Relatório'!AA$1) -> 0 | AC6: =SUMIFS('Faturamento SP3'!$J$2:$J$692,'Faturamento SP3'!$D$2:$D$692,'Infos Relatório'!$B$2,'Faturamento SP3'!$E$2:$E$692,'Infos Relatório'!$B6,'Faturamento SP3'!$Z$2:$Z$692,'Infos Relatório'!AA$1) -> 0 | AD6: =SUMIFS('Faturamento SP3'!$O$2:$O$692,'Faturamento SP3'!$D$2:$D$692,'Infos Relatório'!$B$2,'Faturamento SP3'!$E$2:$E$692,'Infos Relatório'!$B6,'Faturamento SP3'!$Z$2:$Z$692,'Infos Relatório'!AA$1,'Faturamento SP3'!$T$2:$T$692,"Sim")+SUMIFS('Faturamento SP3'!$P$2:$P$692,'Faturamento SP3'!$D$2:$D$692,'Infos Relatório'!$B$2,'Faturamento SP3'!$E$2:$E$692,'Infos Relatório'!$B6,'Faturamento SP3'!$Z$2:$Z$692,'Infos Relatório'!AA$1,'Faturamento SP3'!$T$2:$T$692,"Sim") -> 0 | AE6: =AD6/AC6 -> #DIV/0! | AF6: =SUMIFS('Faturamento SP3'!$H$2:$H$692,'Faturamento SP3'!$D$2:$D$692,'Infos Relatório'!$B$2,'Faturamento SP3'!$E$2:$E$692,'Infos Relatório'!$B6,'Faturamento SP3'!$Z$2:$Z$692,'Infos Relatório'!AA$1) -> 0 | AG6: =COUNTIFS('Faturamento SP3'!$D$2:$D$692,'Infos Relatório'!$B$2,'Faturamento SP3'!$E$2:$E$692,'Infos Relatório'!$B6,'Faturamento SP3'!$Z$2:$Z$692,'Infos Relatório'!AG$1) -> 0 | AH6: =SUMIFS('Faturamento SP3'!$G$2:$G$692,'Faturamento SP3'!$D$2:$D$692,'Infos Relatório'!$B$2,'Faturamento SP3'!$E$2:$E$692,'Infos Relatório'!$B6,'Faturamento SP3'!$Z$2:$Z$692,'Infos Relatório'!AG$1) -> 0 | AI6: =SUMIFS('Faturamento SP3'!$J$2:$J$692,'Faturamento SP3'!$D$2:$D$692,'Infos Relatório'!$B$2,'Faturamento SP3'!$E$2:$E$692,'Infos Relatório'!$B6,'Faturamento SP3'!$Z$2:$Z$692,'Infos Relatório'!AG$1) -> 0 | AJ6: =SUMIFS('Faturamento SP3'!$O$2:$O$692,'Faturamento SP3'!$D$2:$D$692,'Infos Relatório'!$B$2,'Faturamento SP3'!$E$2:$E$692,'Infos Relatório'!$B6,'Faturamento SP3'!$Z$2:$Z$692,'Infos Relatório'!AG$1,'Faturamento SP3'!$T$2:$T$692,"Sim")+SUMIFS('Faturamento SP3'!$P$2:$P$692,'Faturamento SP3'!$D$2:$D$692,'Infos Relatório'!$B$2,'Faturamento SP3'!$E$2:$E$692,'Infos Relatório'!$B6,'Faturamento SP3'!$Z$2:$Z$692,'Infos Relatório'!AG$1,'Faturamento SP3'!$T$2:$T$692,"Sim") -> 0 | AK6: =AJ6/AI6 -> #DIV/0! | AL6: =SUMIFS('Faturamento SP3'!$H$2:$H$692,'Faturamento SP3'!$D$2:$D$692,'Infos Relatório'!$B$2,'Faturamento SP3'!$E$2:$E$692,'Infos Relatório'!$B6,'Faturamento SP3'!$Z$2:$Z$692,'Infos Relatório'!AG$1) -> 0 | AM6: =COUNTIFS('Faturamento SP3'!$D$2:$D$692,'Infos Relatório'!$B$2,'Faturamento SP3'!$E$2:$E$692,'Infos Relatório'!$B6,'Faturamento SP3'!$Z$2:$Z$692,'Infos Relatório'!AM$1) -> 0 | AN6: =SUMIFS('Faturamento SP3'!$G$2:$G$692,'Faturamento SP3'!$D$2:$D$692,'Infos Relatório'!$B$2,'Faturamento SP3'!$E$2:$E$692,'Infos Relatório'!$B6,'Faturamento SP3'!$Z$2:$Z$692,'Infos Relatório'!AM$1) -> 0 | AO6: =SUMIFS('Faturamento SP3'!$J$2:$J$692,'Faturamento SP3'!$D$2:$D$692,'Infos Relatório'!$B$2,'Faturamento SP3'!$E$2:$E$692,'Infos Relatório'!$B6,'Faturamento SP3'!$Z$2:$Z$692,'Infos Relatório'!AM$1) -> 0 | AP6: =SUMIFS('Faturamento SP3'!$O$2:$O$692,'Faturamento SP3'!$D$2:$D$692,'Infos Relatório'!$B$2,'Faturamento SP3'!$E$2:$E$692,'Infos Relatório'!$B6,'Faturamento SP3'!$Z$2:$Z$692,'Infos Relatório'!AM$1,'Faturamento SP3'!$T$2:$T$692,"Sim")+SUMIFS('Faturamento SP3'!$P$2:$P$692,'Faturamento SP3'!$D$2:$D$692,'Infos Relatório'!$B$2,'Faturamento SP3'!$E$2:$E$692,'Infos Relatório'!$B6,'Faturamento SP3'!$Z$2:$Z$692,'Infos Relatório'!AM$1,'Faturamento SP3'!$T$2:$T$692,"Sim") -> 0 | AQ6: =AP6/AO6 -> #DIV/0! | AR6: =SUMIFS('Faturamento SP3'!$H$2:$H$692,'Faturamento SP3'!$D$2:$D$692,'Infos Relatório'!$B$2,'Faturamento SP3'!$E$2:$E$692,'Infos Relatório'!$B6,'Faturamento SP3'!$Z$2:$Z$692,'Infos Relatório'!AM$1) -> 0 | AS6: =COUNTIFS('Faturamento SP3'!$D$2:$D$692,'Infos Relatório'!$B$2,'Faturamento SP3'!$E$2:$E$692,'Infos Relatório'!$B6,'Faturamento SP3'!$Z$2:$Z$692,'Infos Relatório'!AS$1) -> 0 | AT6: =SUMIFS('Faturamento SP3'!$G$2:$G$692,'Faturamento SP3'!$D$2:$D$692,'Infos Relatório'!$B$2,'Faturamento SP3'!$E$2:$E$692,'Infos Relatório'!$B6,'Faturamento SP3'!$Z$2:$Z$692,'Infos Relatório'!AS$1) -> 0 | AU6: =SUMIFS('Faturamento SP3'!$J$2:$J$692,'Faturamento SP3'!$D$2:$D$692,'Infos Relatório'!$B$2,'Faturamento SP3'!$E$2:$E$692,'Infos Relatório'!$B6,'Faturamento SP3'!$Z$2:$Z$692,'Infos Relatório'!AS$1) -> 0 | AV6: =SUMIFS('Faturamento SP3'!$O$2:$O$692,'Faturamento SP3'!$D$2:$D$692,'Infos Relatório'!$B$2,'Faturamento SP3'!$E$2:$E$692,'Infos Relatório'!$B6,'Faturamento SP3'!$Z$2:$Z$692,'Infos Relatório'!AS$1,'Faturamento SP3'!$T$2:$T$692,"Sim")+SUMIFS('Faturamento SP3'!$P$2:$P$692,'Faturamento SP3'!$D$2:$D$692,'Infos Relatório'!$B$2,'Faturamento SP3'!$E$2:$E$692,'Infos Relatório'!$B6,'Faturamento SP3'!$Z$2:$Z$692,'Infos Relatório'!AS$1,'Faturamento SP3'!$T$2:$T$692,"Sim") -> 0 | AW6: =AV6/AU6 -> #DIV/0! | AX6: =SUMIFS('Faturamento SP3'!$H$2:$H$692,'Faturamento SP3'!$D$2:$D$692,'Infos Relatório'!$B$2,'Faturamento SP3'!$E$2:$E$692,'Infos Relatório'!$B6,'Faturamento SP3'!$Z$2:$Z$692,'Infos Relatório'!AS$1) -> 0 | AY6: =COUNTIFS('Faturamento SP3'!$D$2:$D$692,'Infos Relatório'!$B$2,'Faturamento SP3'!$E$2:$E$692,'Infos Relatório'!$B6,'Faturamento SP3'!$Z$2:$Z$692,'Infos Relatório'!AY$1) -> 0 | AZ6: =SUMIFS('Faturamento SP3'!$G$2:$G$692,'Faturamento SP3'!$D$2:$D$692,'Infos Relatório'!$B$2,'Faturamento SP3'!$E$2:$E$692,'Infos Relatório'!$B6,'Faturamento SP3'!$Z$2:$Z$692,'Infos Relatório'!AY$1) -> 0 | BA6: =SUMIFS('Faturamento SP3'!$J$2:$J$692,'Faturamento SP3'!$D$2:$D$692,'Infos Relatório'!$B$2,'Faturamento SP3'!$E$2:$E$692,'Infos Relatório'!$B6,'Faturamento SP3'!$Z$2:$Z$692,'Infos Relatório'!AY$1) -> 0 | BB6: =SUMIFS('Faturamento SP3'!$O$2:$O$692,'Faturamento SP3'!$D$2:$D$692,'Infos Relatório'!$B$2,'Faturamento SP3'!$E$2:$E$692,'Infos Relatório'!$B6,'Faturamento SP3'!$Z$2:$Z$692,'Infos Relatório'!AY$1,'Faturamento SP3'!$T$2:$T$692,"Sim")+SUMIFS('Faturamento SP3'!$P$2:$P$692,'Faturamento SP3'!$D$2:$D$692,'Infos Relatório'!$B$2,'Faturamento SP3'!$E$2:$E$692,'Infos Relatório'!$B6,'Faturamento SP3'!$Z$2:$Z$692,'Infos Relatório'!AY$1,'Faturamento SP3'!$T$2:$T$692,"Sim") -> 0 | BC6: =BB6/BA6 -> #DIV/0! | BD6: =SUMIFS('Faturamento SP3'!$H$2:$H$692,'Faturamento SP3'!$D$2:$D$692,'Infos Relatório'!$B$2,'Faturamento SP3'!$E$2:$E$692,'Infos Relatório'!$B6,'Faturamento SP3'!$Z$2:$Z$692,'Infos Relatório'!AY$1) -> 0 | BE6: =COUNTIFS('Faturamento SP3'!$D$2:$D$692,'Infos Relatório'!$B$2,'Faturamento SP3'!$E$2:$E$692,'Infos Relatório'!$B6,'Faturamento SP3'!$Z$2:$Z$692,'Infos Relatório'!BE$1) -> 0 | BF6: =SUMIFS('Faturamento SP3'!$G$2:$G$692,'Faturamento SP3'!$D$2:$D$692,'Infos Relatório'!$B$2,'Faturamento SP3'!$E$2:$E$692,'Infos Relatório'!$B6,'Faturamento SP3'!$Z$2:$Z$692,'Infos Relatório'!BE$1) -> 0 | BG6: =SUMIFS('Faturamento SP3'!$J$2:$J$692,'Faturamento SP3'!$D$2:$D$692,'Infos Relatório'!$B$2,'Faturamento SP3'!$E$2:$E$692,'Infos Relatório'!$B6,'Faturamento SP3'!$Z$2:$Z$692,'Infos Relatório'!BE$1) -> 0 | BH6: =SUMIFS('Faturamento SP3'!$O$2:$O$692,'Faturamento SP3'!$D$2:$D$692,'Infos Relatório'!$B$2,'Faturamento SP3'!$E$2:$E$692,'Infos Relatório'!$B6,'Faturamento SP3'!$Z$2:$Z$692,'Infos Relatório'!BE$1,'Faturamento SP3'!$T$2:$T$692,"Sim")+SUMIFS('Faturamento SP3'!$P$2:$P$692,'Faturamento SP3'!$D$2:$D$692,'Infos Relatório'!$B$2,'Faturamento SP3'!$E$2:$E$692,'Infos Relatório'!$B6,'Faturamento SP3'!$Z$2:$Z$692,'Infos Relatório'!BE$1,'Faturamento SP3'!$T$2:$T$692,"Sim") -> 0 | BI6: =BH6/BG6 -> #DIV/0! | BJ6: =SUMIFS('Faturamento SP3'!$H$2:$H$692,'Faturamento SP3'!$D$2:$D$692,'Infos Relatório'!$B$2,'Faturamento SP3'!$E$2:$E$692,'Infos Relatório'!$B6,'Faturamento SP3'!$Z$2:$Z$692,'Infos Relatório'!BE$1) -> 0 | BK6: =COUNTIFS('Faturamento SP3'!$D$2:$D$692,'Infos Relatório'!$B$2,'Faturamento SP3'!$E$2:$E$692,'Infos Relatório'!$B6,'Faturamento SP3'!$Z$2:$Z$692,'Infos Relatório'!BK$1) -> 0 | BL6: =SUMIFS('Faturamento SP3'!$G$2:$G$692,'Faturamento SP3'!$D$2:$D$692,'Infos Relatório'!$B$2,'Faturamento SP3'!$E$2:$E$692,'Infos Relatório'!$B6,'Faturamento SP3'!$Z$2:$Z$692,'Infos Relatório'!BK$1) -> 0 | BM6: =SUMIFS('Faturamento SP3'!$J$2:$J$692,'Faturamento SP3'!$D$2:$D$692,'Infos Relatório'!$B$2,'Faturamento SP3'!$E$2:$E$692,'Infos Relatório'!$B6,'Faturamento SP3'!$Z$2:$Z$692,'Infos Relatório'!BK$1) -> 0 | BN6: =SUMIFS('Faturamento SP3'!$O$2:$O$692,'Faturamento SP3'!$D$2:$D$692,'Infos Relatório'!$B$2,'Faturamento SP3'!$E$2:$E$692,'Infos Relatório'!$B6,'Faturamento SP3'!$Z$2:$Z$692,'Infos Relatório'!BK$1,'Faturamento SP3'!$T$2:$T$692,"Sim")+SUMIFS('Faturamento SP3'!$P$2:$P$692,'Faturamento SP3'!$D$2:$D$692,'Infos Relatório'!$B$2,'Faturamento SP3'!$E$2:$E$692,'Infos Relatório'!$B6,'Faturamento SP3'!$Z$2:$Z$692,'Infos Relatório'!BK$1,'Faturamento SP3'!$T$2:$T$692,"Sim") -> 0 | BO6: =BN6/BM6 -> #DIV/0! | BP6: =SUMIFS('Faturamento SP3'!$H$2:$H$692,'Faturamento SP3'!$D$2:$D$692,'Infos Relatório'!$B$2,'Faturamento SP3'!$E$2:$E$692,'Infos Relatório'!$B6,'Faturamento SP3'!$Z$2:$Z$692,'Infos Relatório'!BK$1) -> 0 | BQ6: =COUNTIFS('Faturamento SP3'!$D$2:$D$692,'Infos Relatório'!$B$2,'Faturamento SP3'!$E$2:$E$692,'Infos Relatório'!$B6,'Faturamento SP3'!$Z$2:$Z$692,'Infos Relatório'!BQ$1) -> 0 | BR6: =SUMIFS('Faturamento SP3'!$G$2:$G$692,'Faturamento SP3'!$D$2:$D$692,'Infos Relatório'!$B$2,'Faturamento SP3'!$E$2:$E$692,'Infos Relatório'!$B6,'Faturamento SP3'!$Z$2:$Z$692,'Infos Relatório'!BQ$1) -> 0 | BS6: =SUMIFS('Faturamento SP3'!$J$2:$J$692,'Faturamento SP3'!$D$2:$D$692,'Infos Relatório'!$B$2,'Faturamento SP3'!$E$2:$E$692,'Infos Relatório'!$B6,'Faturamento SP3'!$Z$2:$Z$692,'Infos Relatório'!BQ$1) -> 0 | BT6: =SUMIFS('Faturamento SP3'!$O$2:$O$692,'Faturamento SP3'!$D$2:$D$692,'Infos Relatório'!$B$2,'Faturamento SP3'!$E$2:$E$692,'Infos Relatório'!$B6,'Faturamento SP3'!$Z$2:$Z$692,'Infos Relatório'!BQ$1,'Faturamento SP3'!$T$2:$T$692,"Sim")+SUMIFS('Faturamento SP3'!$P$2:$P$692,'Faturamento SP3'!$D$2:$D$692,'Infos Relatório'!$B$2,'Faturamento SP3'!$E$2:$E$692,'Infos Relatório'!$B6,'Faturamento SP3'!$Z$2:$Z$692,'Infos Relatório'!BQ$1,'Faturamento SP3'!$T$2:$T$692,"Sim") -> 0 | BU6: =BT6/BS6 -> #DIV/0! | BV6: =SUMIFS('Faturamento SP3'!$H$2:$H$692,'Faturamento SP3'!$D$2:$D$692,'Infos Relatório'!$B$2,'Faturamento SP3'!$E$2:$E$692,'Infos Relatório'!$B6,'Faturamento SP3'!$Z$2:$Z$692,'Infos Relatório'!BQ$1) -> 0
B7: Águias da Vida | C7: =COUNTIFS('Faturamento SP3'!$D$2:$D$692,'Infos Relatório'!$B$2,'Faturamento SP3'!$E$2:$E$692,'Infos Relatório'!$B7,'Faturamento SP3'!$Z$2:$Z$692,'Infos Relatório'!C$1) -> 0 | D7: =SUMIFS('Faturamento SP3'!$G$2:$G$692,'Faturamento SP3'!$D$2:$D$692,'Infos Relatório'!$B$2,'Faturamento SP3'!$E$2:$E$692,'Infos Relatório'!$B7,'Faturamento SP3'!$Z$2:$Z$692,'Infos Relatório'!C$1) -> 0 | E7: =SUMIFS('Faturamento SP3'!$J$2:$J$692,'Faturamento SP3'!$D$2:$D$692,'Infos Relatório'!$B$2,'Faturamento SP3'!$E$2:$E$692,'Infos Relatório'!$B7,'Faturamento SP3'!$Z$2:$Z$692,'Infos Relatório'!C$1) -> 0 | F7: =SUMIFS('Faturamento SP3'!$O$2:$O$692,'Faturamento SP3'!$D$2:$D$692,'Infos Relatório'!$B$2,'Faturamento SP3'!$E$2:$E$692,'Infos Relatório'!$B7,'Faturamento SP3'!$Z$2:$Z$692,'Infos Relatório'!C$1,'Faturamento SP3'!$T$2:$T$692,"Sim")+SUMIFS('Faturamento SP3'!$P$2:$P$692,'Faturamento SP3'!$D$2:$D$692,'Infos Relatório'!$B$2,'Faturamento SP3'!$E$2:$E$692,'Infos Relatório'!$B7,'Faturamento SP3'!$Z$2:$Z$692,'Infos Relatório'!C$1,'Faturamento SP3'!$T$2:$T$692,"Sim") -> 0 | G7: =F7/E7 -> #DIV/0! | H7: =SUMIFS('Faturamento SP3'!$H$2:$H$692,'Faturamento SP3'!$D$2:$D$692,'Infos Relatório'!$B$2,'Faturamento SP3'!$E$2:$E$692,'Infos Relatório'!$B7,'Faturamento SP3'!$Z$2:$Z$692,'Infos Relatório'!C$1) -> 0 | I7: =COUNTIFS('Faturamento SP3'!$D$2:$D$692,'Infos Relatório'!$B$2,'Faturamento SP3'!$E$2:$E$692,'Infos Relatório'!$B7,'Faturamento SP3'!$Z$2:$Z$692,'Infos Relatório'!I$1) -> 0 | J7: =SUMIFS('Faturamento SP3'!$G$2:$G$692,'Faturamento SP3'!$D$2:$D$692,'Infos Relatório'!$B$2,'Faturamento SP3'!$E$2:$E$692,'Infos Relatório'!$B7,'Faturamento SP3'!$Z$2:$Z$692,'Infos Relatório'!I$1) -> 0 | K7: =SUMIFS('Faturamento SP3'!$J$2:$J$692,'Faturamento SP3'!$D$2:$D$692,'Infos Relatório'!$B$2,'Faturamento SP3'!$E$2:$E$692,'Infos Relatório'!$B7,'Faturamento SP3'!$Z$2:$Z$692,'Infos Relatório'!I$1) -> 0 | L7: =SUMIFS('Faturamento SP3'!$O$2:$O$692,'Faturamento SP3'!$D$2:$D$692,'Infos Relatório'!$B$2,'Faturamento SP3'!$E$2:$E$692,'Infos Relatório'!$B7,'Faturamento SP3'!$Z$2:$Z$692,'Infos Relatório'!I$1,'Faturamento SP3'!$T$2:$T$692,"Sim")+SUMIFS('Faturamento SP3'!$P$2:$P$692,'Faturamento SP3'!$D$2:$D$692,'Infos Relatório'!$B$2,'Faturamento SP3'!$E$2:$E$692,'Infos Relatório'!$B7,'Faturamento SP3'!$Z$2:$Z$692,'Infos Relatório'!I$1,'Faturamento SP3'!$T$2:$T$692,"Sim") -> 0 | M7: =L7/K7 -> #DIV/0! | N7: =SUMIFS('Faturamento SP3'!$H$2:$H$692,'Faturamento SP3'!$D$2:$D$692,'Infos Relatório'!$B$2,'Faturamento SP3'!$E$2:$E$692,'Infos Relatório'!$B7,'Faturamento SP3'!$Z$2:$Z$692,'Infos Relatório'!I$1) -> 0 | O7: =COUNTIFS('Faturamento SP3'!$D$2:$D$692,'Infos Relatório'!$B$2,'Faturamento SP3'!$E$2:$E$692,'Infos Relatório'!$B7,'Faturamento SP3'!$Z$2:$Z$692,'Infos Relatório'!O$1) -> 0 | P7: =SUMIFS('Faturamento SP3'!$G$2:$G$692,'Faturamento SP3'!$D$2:$D$692,'Infos Relatório'!$B$2,'Faturamento SP3'!$E$2:$E$692,'Infos Relatório'!$B7,'Faturamento SP3'!$Z$2:$Z$692,'Infos Relatório'!O$1) -> 0 | Q7: =SUMIFS('Faturamento SP3'!$J$2:$J$692,'Faturamento SP3'!$D$2:$D$692,'Infos Relatório'!$B$2,'Faturamento SP3'!$E$2:$E$692,'Infos Relatório'!$B7,'Faturamento SP3'!$Z$2:$Z$692,'Infos Relatório'!O$1) -> 0 | R7: =SUMIFS('Faturamento SP3'!$O$2:$O$692,'Faturamento SP3'!$D$2:$D$692,'Infos Relatório'!$B$2,'Faturamento SP3'!$E$2:$E$692,'Infos Relatório'!$B7,'Faturamento SP3'!$Z$2:$Z$692,'Infos Relatório'!O$1,'Faturamento SP3'!$T$2:$T$692,"Sim")+SUMIFS('Faturamento SP3'!$P$2:$P$692,'Faturamento SP3'!$D$2:$D$692,'Infos Relatório'!$B$2,'Faturamento SP3'!$E$2:$E$692,'Infos Relatório'!$B7,'Faturamento SP3'!$Z$2:$Z$692,'Infos Relatório'!O$1,'Faturamento SP3'!$T$2:$T$692,"Sim") -> 0 | S7: =R7/Q7 -> #DIV/0! | T7: =SUMIFS('Faturamento SP3'!$H$2:$H$692,'Faturamento SP3'!$D$2:$D$692,'Infos Relatório'!$B$2,'Faturamento SP3'!$E$2:$E$692,'Infos Relatório'!$B7,'Faturamento SP3'!$Z$2:$Z$692,'Infos Relatório'!O$1) -> 0 | U7: =COUNTIFS('Faturamento SP3'!$D$2:$D$692,'Infos Relatório'!$B$2,'Faturamento SP3'!$E$2:$E$692,'Infos Relatório'!$B7,'Faturamento SP3'!$Z$2:$Z$692,'Infos Relatório'!U$1) -> 0 | V7: =SUMIFS('Faturamento SP3'!$G$2:$G$692,'Faturamento SP3'!$D$2:$D$692,'Infos Relatório'!$B$2,'Faturamento SP3'!$E$2:$E$692,'Infos Relatório'!$B7,'Faturamento SP3'!$Z$2:$Z$692,'Infos Relatório'!U$1) -> 0 | W7: =SUMIFS('Faturamento SP3'!$J$2:$J$692,'Faturamento SP3'!$D$2:$D$692,'Infos Relatório'!$B$2,'Faturamento SP3'!$E$2:$E$692,'Infos Relatório'!$B7,'Faturamento SP3'!$Z$2:$Z$692,'Infos Relatório'!U$1) -> 0 | X7: =SUMIFS('Faturamento SP3'!$O$2:$O$692,'Faturamento SP3'!$D$2:$D$692,'Infos Relatório'!$B$2,'Faturamento SP3'!$E$2:$E$692,'Infos Relatório'!$B7,'Faturamento SP3'!$Z$2:$Z$692,'Infos Relatório'!U$1,'Faturamento SP3'!$T$2:$T$692,"Sim")+SUMIFS('Faturamento SP3'!$P$2:$P$692,'Faturamento SP3'!$D$2:$D$692,'Infos Relatório'!$B$2,'Faturamento SP3'!$E$2:$E$692,'Infos Relatório'!$B7,'Faturamento SP3'!$Z$2:$Z$692,'Infos Relatório'!U$1,'Faturamento SP3'!$T$2:$T$692,"Sim") -> 0 | Y7: =X7/W7 -> #DIV/0! | Z7: =SUMIFS('Faturamento SP3'!$H$2:$H$692,'Faturamento SP3'!$D$2:$D$692,'Infos Relatório'!$B$2,'Faturamento SP3'!$E$2:$E$692,'Infos Relatório'!$B7,'Faturamento SP3'!$Z$2:$Z$692,'Infos Relatório'!U$1) -> 0 | AA7: =COUNTIFS('Faturamento SP3'!$D$2:$D$692,'Infos Relatório'!$B$2,'Faturamento SP3'!$E$2:$E$692,'Infos Relatório'!$B7,'Faturamento SP3'!$Z$2:$Z$692,'Infos Relatório'!AA$1) -> 0 | AB7: =SUMIFS('Faturamento SP3'!$G$2:$G$692,'Faturamento SP3'!$D$2:$D$692,'Infos Relatório'!$B$2,'Faturamento SP3'!$E$2:$E$692,'Infos Relatório'!$B7,'Faturamento SP3'!$Z$2:$Z$692,'Infos Relatório'!AA$1) -> 0 | AC7: =SUMIFS('Faturamento SP3'!$J$2:$J$692,'Faturamento SP3'!$D$2:$D$692,'Infos Relatório'!$B$2,'Faturamento SP3'!$E$2:$E$692,'Infos Relatório'!$B7,'Faturamento SP3'!$Z$2:$Z$692,'Infos Relatório'!AA$1) -> 0 | AD7: =SUMIFS('Faturamento SP3'!$O$2:$O$692,'Faturamento SP3'!$D$2:$D$692,'Infos Relatório'!$B$2,'Faturamento SP3'!$E$2:$E$692,'Infos Relatório'!$B7,'Faturamento SP3'!$Z$2:$Z$692,'Infos Relatório'!AA$1,'Faturamento SP3'!$T$2:$T$692,"Sim")+SUMIFS('Faturamento SP3'!$P$2:$P$692,'Faturamento SP3'!$D$2:$D$692,'Infos Relatório'!$B$2,'Faturamento SP3'!$E$2:$E$692,'Infos Relatório'!$B7,'Faturamento SP3'!$Z$2:$Z$692,'Infos Relatório'!AA$1,'Faturamento SP3'!$T$2:$T$692,"Sim") -> 0 | AE7: =AD7/AC7 -> #DIV/0! | AF7: =SUMIFS('Faturamento SP3'!$H$2:$H$692,'Faturamento SP3'!$D$2:$D$692,'Infos Relatório'!$B$2,'Faturamento SP3'!$E$2:$E$692,'Infos Relatório'!$B7,'Faturamento SP3'!$Z$2:$Z$692,'Infos Relatório'!AA$1) -> 0 | AG7: =COUNTIFS('Faturamento SP3'!$D$2:$D$692,'Infos Relatório'!$B$2,'Faturamento SP3'!$E$2:$E$692,'Infos Relatório'!$B7,'Faturamento SP3'!$Z$2:$Z$692,'Infos Relatório'!AG$1) -> 0 | AH7: =SUMIFS('Faturamento SP3'!$G$2:$G$692,'Faturamento SP3'!$D$2:$D$692,'Infos Relatório'!$B$2,'Faturamento SP3'!$E$2:$E$692,'Infos Relatório'!$B7,'Faturamento SP3'!$Z$2:$Z$692,'Infos Relatório'!AG$1) -> 0 | AI7: =SUMIFS('Faturamento SP3'!$J$2:$J$692,'Faturamento SP3'!$D$2:$D$692,'Infos Relatório'!$B$2,'Faturamento SP3'!$E$2:$E$692,'Infos Relatório'!$B7,'Faturamento SP3'!$Z$2:$Z$692,'Infos Relatório'!AG$1) -> 0 | AJ7: =SUMIFS('Faturamento SP3'!$O$2:$O$692,'Faturamento SP3'!$D$2:$D$692,'Infos Relatório'!$B$2,'Faturamento SP3'!$E$2:$E$692,'Infos Relatório'!$B7,'Faturamento SP3'!$Z$2:$Z$692,'Infos Relatório'!AG$1,'Faturamento SP3'!$T$2:$T$692,"Sim")+SUMIFS('Faturamento SP3'!$P$2:$P$692,'Faturamento SP3'!$D$2:$D$692,'Infos Relatório'!$B$2,'Faturamento SP3'!$E$2:$E$692,'Infos Relatório'!$B7,'Faturamento SP3'!$Z$2:$Z$692,'Infos Relatório'!AG$1,'Faturamento SP3'!$T$2:$T$692,"Sim") -> 0 | AK7: =AJ7/AI7 -> #DIV/0! | AL7: =SUMIFS('Faturamento SP3'!$H$2:$H$692,'Faturamento SP3'!$D$2:$D$692,'Infos Relatório'!$B$2,'Faturamento SP3'!$E$2:$E$692,'Infos Relatório'!$B7,'Faturamento SP3'!$Z$2:$Z$692,'Infos Relatório'!AG$1) -> 0 | AM7: =COUNTIFS('Faturamento SP3'!$D$2:$D$692,'Infos Relatório'!$B$2,'Faturamento SP3'!$E$2:$E$692,'Infos Relatório'!$B7,'Faturamento SP3'!$Z$2:$Z$692,'Infos Relatório'!AM$1) -> 0 | AN7: =SUMIFS('Faturamento SP3'!$G$2:$G$692,'Faturamento SP3'!$D$2:$D$692,'Infos Relatório'!$B$2,'Faturamento SP3'!$E$2:$E$692,'Infos Relatório'!$B7,'Faturamento SP3'!$Z$2:$Z$692,'Infos Relatório'!AM$1) -> 0 | AO7: =SUMIFS('Faturamento SP3'!$J$2:$J$692,'Faturamento SP3'!$D$2:$D$692,'Infos Relatório'!$B$2,'Faturamento SP3'!$E$2:$E$692,'Infos Relatório'!$B7,'Faturamento SP3'!$Z$2:$Z$692,'Infos Relatório'!AM$1) -> 0 | AP7: =SUMIFS('Faturamento SP3'!$O$2:$O$692,'Faturamento SP3'!$D$2:$D$692,'Infos Relatório'!$B$2,'Faturamento SP3'!$E$2:$E$692,'Infos Relatório'!$B7,'Faturamento SP3'!$Z$2:$Z$692,'Infos Relatório'!AM$1,'Faturamento SP3'!$T$2:$T$692,"Sim")+SUMIFS('Faturamento SP3'!$P$2:$P$692,'Faturamento SP3'!$D$2:$D$692,'Infos Relatório'!$B$2,'Faturamento SP3'!$E$2:$E$692,'Infos Relatório'!$B7,'Faturamento SP3'!$Z$2:$Z$692,'Infos Relatório'!AM$1,'Faturamento SP3'!$T$2:$T$692,"Sim") -> 0 | AQ7: =AP7/AO7 -> #DIV/0! | AR7: =SUMIFS('Faturamento SP3'!$H$2:$H$692,'Faturamento SP3'!$D$2:$D$692,'Infos Relatório'!$B$2,'Faturamento SP3'!$E$2:$E$692,'Infos Relatório'!$B7,'Faturamento SP3'!$Z$2:$Z$692,'Infos Relatório'!AM$1) -> 0 | AS7: =COUNTIFS('Faturamento SP3'!$D$2:$D$692,'Infos Relatório'!$B$2,'Faturamento SP3'!$E$2:$E$692,'Infos Relatório'!$B7,'Faturamento SP3'!$Z$2:$Z$692,'Infos Relatório'!AS$1) -> 0 | AT7: =SUMIFS('Faturamento SP3'!$G$2:$G$692,'Faturamento SP3'!$D$2:$D$692,'Infos Relatório'!$B$2,'Faturamento SP3'!$E$2:$E$692,'Infos Relatório'!$B7,'Faturamento SP3'!$Z$2:$Z$692,'Infos Relatório'!AS$1) -> 0 | AU7: =SUMIFS('Faturamento SP3'!$J$2:$J$692,'Faturamento SP3'!$D$2:$D$692,'Infos Relatório'!$B$2,'Faturamento SP3'!$E$2:$E$692,'Infos Relatório'!$B7,'Faturamento SP3'!$Z$2:$Z$692,'Infos Relatório'!AS$1) -> 0 | AV7: =SUMIFS('Faturamento SP3'!$O$2:$O$692,'Faturamento SP3'!$D$2:$D$692,'Infos Relatório'!$B$2,'Faturamento SP3'!$E$2:$E$692,'Infos Relatório'!$B7,'Faturamento SP3'!$Z$2:$Z$692,'Infos Relatório'!AS$1,'Faturamento SP3'!$T$2:$T$692,"Sim")+SUMIFS('Faturamento SP3'!$P$2:$P$692,'Faturamento SP3'!$D$2:$D$692,'Infos Relatório'!$B$2,'Faturamento SP3'!$E$2:$E$692,'Infos Relatório'!$B7,'Faturamento SP3'!$Z$2:$Z$692,'Infos Relatório'!AS$1,'Faturamento SP3'!$T$2:$T$692,"Sim") -> 0 | AW7: =AV7/AU7 -> #DIV/0! | AX7: =SUMIFS('Faturamento SP3'!$H$2:$H$692,'Faturamento SP3'!$D$2:$D$692,'Infos Relatório'!$B$2,'Faturamento SP3'!$E$2:$E$692,'Infos Relatório'!$B7,'Faturamento SP3'!$Z$2:$Z$692,'Infos Relatório'!AS$1) -> 0 | AY7: =COUNTIFS('Faturamento SP3'!$D$2:$D$692,'Infos Relatório'!$B$2,'Faturamento SP3'!$E$2:$E$692,'Infos Relatório'!$B7,'Faturamento SP3'!$Z$2:$Z$692,'Infos Relatório'!AY$1) -> 0 | AZ7: =SUMIFS('Faturamento SP3'!$G$2:$G$692,'Faturamento SP3'!$D$2:$D$692,'Infos Relatório'!$B$2,'Faturamento SP3'!$E$2:$E$692,'Infos Relatório'!$B7,'Faturamento SP3'!$Z$2:$Z$692,'Infos Relatório'!AY$1) -> 0 | BA7: =SUMIFS('Faturamento SP3'!$J$2:$J$692,'Faturamento SP3'!$D$2:$D$692,'Infos Relatório'!$B$2,'Faturamento SP3'!$E$2:$E$692,'Infos Relatório'!$B7,'Faturamento SP3'!$Z$2:$Z$692,'Infos Relatório'!AY$1) -> 0 | BB7: =SUMIFS('Faturamento SP3'!$O$2:$O$692,'Faturamento SP3'!$D$2:$D$692,'Infos Relatório'!$B$2,'Faturamento SP3'!$E$2:$E$692,'Infos Relatório'!$B7,'Faturamento SP3'!$Z$2:$Z$692,'Infos Relatório'!AY$1,'Faturamento SP3'!$T$2:$T$692,"Sim")+SUMIFS('Faturamento SP3'!$P$2:$P$692,'Faturamento SP3'!$D$2:$D$692,'Infos Relatório'!$B$2,'Faturamento SP3'!$E$2:$E$692,'Infos Relatório'!$B7,'Faturamento SP3'!$Z$2:$Z$692,'Infos Relatório'!AY$1,'Faturamento SP3'!$T$2:$T$692,"Sim") -> 0 | BC7: =BB7/BA7 -> #DIV/0! | BD7: =SUMIFS('Faturamento SP3'!$H$2:$H$692,'Faturamento SP3'!$D$2:$D$692,'Infos Relatório'!$B$2,'Faturamento SP3'!$E$2:$E$692,'Infos Relatório'!$B7,'Faturamento SP3'!$Z$2:$Z$692,'Infos Relatório'!AY$1) -> 0 | BE7: =COUNTIFS('Faturamento SP3'!$D$2:$D$692,'Infos Relatório'!$B$2,'Faturamento SP3'!$E$2:$E$692,'Infos Relatório'!$B7,'Faturamento SP3'!$Z$2:$Z$692,'Infos Relatório'!BE$1) -> 0 | BF7: =SUMIFS('Faturamento SP3'!$G$2:$G$692,'Faturamento SP3'!$D$2:$D$692,'Infos Relatório'!$B$2,'Faturamento SP3'!$E$2:$E$692,'Infos Relatório'!$B7,'Faturamento SP3'!$Z$2:$Z$692,'Infos Relatório'!BE$1) -> 0 | BG7: =SUMIFS('Faturamento SP3'!$J$2:$J$692,'Faturamento SP3'!$D$2:$D$692,'Infos Relatório'!$B$2,'Faturamento SP3'!$E$2:$E$692,'Infos Relatório'!$B7,'Faturamento SP3'!$Z$2:$Z$692,'Infos Relatório'!BE$1) -> 0 | BH7: =SUMIFS('Faturamento SP3'!$O$2:$O$692,'Faturamento SP3'!$D$2:$D$692,'Infos Relatório'!$B$2,'Faturamento SP3'!$E$2:$E$692,'Infos Relatório'!$B7,'Faturamento SP3'!$Z$2:$Z$692,'Infos Relatório'!BE$1,'Faturamento SP3'!$T$2:$T$692,"Sim")+SUMIFS('Faturamento SP3'!$P$2:$P$692,'Faturamento SP3'!$D$2:$D$692,'Infos Relatório'!$B$2,'Faturamento SP3'!$E$2:$E$692,'Infos Relatório'!$B7,'Faturamento SP3'!$Z$2:$Z$692,'Infos Relatório'!BE$1,'Faturamento SP3'!$T$2:$T$692,"Sim") -> 0 | BI7: =BH7/BG7 -> #DIV/0! | BJ7: =SUMIFS('Faturamento SP3'!$H$2:$H$692,'Faturamento SP3'!$D$2:$D$692,'Infos Relatório'!$B$2,'Faturamento SP3'!$E$2:$E$692,'Infos Relatório'!$B7,'Faturamento SP3'!$Z$2:$Z$692,'Infos Relatório'!BE$1) -> 0 | BK7: =COUNTIFS('Faturamento SP3'!$D$2:$D$692,'Infos Relatório'!$B$2,'Faturamento SP3'!$E$2:$E$692,'Infos Relatório'!$B7,'Faturamento SP3'!$Z$2:$Z$692,'Infos Relatório'!BK$1) -> 0 | BL7: =SUMIFS('Faturamento SP3'!$G$2:$G$692,'Faturamento SP3'!$D$2:$D$692,'Infos Relatório'!$B$2,'Faturamento SP3'!$E$2:$E$692,'Infos Relatório'!$B7,'Faturamento SP3'!$Z$2:$Z$692,'Infos Relatório'!BK$1) -> 0 | BM7: =SUMIFS('Faturamento SP3'!$J$2:$J$692,'Faturamento SP3'!$D$2:$D$692,'Infos Relatório'!$B$2,'Faturamento SP3'!$E$2:$E$692,'Infos Relatório'!$B7,'Faturamento SP3'!$Z$2:$Z$692,'Infos Relatório'!BK$1) -> 0 | BN7: =SUMIFS('Faturamento SP3'!$O$2:$O$692,'Faturamento SP3'!$D$2:$D$692,'Infos Relatório'!$B$2,'Faturamento SP3'!$E$2:$E$692,'Infos Relatório'!$B7,'Faturamento SP3'!$Z$2:$Z$692,'Infos Relatório'!BK$1,'Faturamento SP3'!$T$2:$T$692,"Sim")+SUMIFS('Faturamento SP3'!$P$2:$P$692,'Faturamento SP3'!$D$2:$D$692,'Infos Relatório'!$B$2,'Faturamento SP3'!$E$2:$E$692,'Infos Relatório'!$B7,'Faturamento SP3'!$Z$2:$Z$692,'Infos Relatório'!BK$1,'Faturamento SP3'!$T$2:$T$692,"Sim") -> 0 | BO7: =BN7/BM7 -> #DIV/0! | BP7: =SUMIFS('Faturamento SP3'!$H$2:$H$692,'Faturamento SP3'!$D$2:$D$692,'Infos Relatório'!$B$2,'Faturamento SP3'!$E$2:$E$692,'Infos Relatório'!$B7,'Faturamento SP3'!$Z$2:$Z$692,'Infos Relatório'!BK$1) -> 0 | BQ7: =COUNTIFS('Faturamento SP3'!$D$2:$D$692,'Infos Relatório'!$B$2,'Faturamento SP3'!$E$2:$E$692,'Infos Relatório'!$B7,'Faturamento SP3'!$Z$2:$Z$692,'Infos Relatório'!BQ$1) -> 0 | BR7: =SUMIFS('Faturamento SP3'!$G$2:$G$692,'Faturamento SP3'!$D$2:$D$692,'Infos Relatório'!$B$2,'Faturamento SP3'!$E$2:$E$692,'Infos Relatório'!$B7,'Faturamento SP3'!$Z$2:$Z$692,'Infos Relatório'!BQ$1) -> 0 | BS7: =SUMIFS('Faturamento SP3'!$J$2:$J$692,'Faturamento SP3'!$D$2:$D$692,'Infos Relatório'!$B$2,'Faturamento SP3'!$E$2:$E$692,'Infos Relatório'!$B7,'Faturamento SP3'!$Z$2:$Z$692,'Infos Relatório'!BQ$1) -> 0 | BT7: =SUMIFS('Faturamento SP3'!$O$2:$O$692,'Faturamento SP3'!$D$2:$D$692,'Infos Relatório'!$B$2,'Faturamento SP3'!$E$2:$E$692,'Infos Relatório'!$B7,'Faturamento SP3'!$Z$2:$Z$692,'Infos Relatório'!BQ$1,'Faturamento SP3'!$T$2:$T$692,"Sim")+SUMIFS('Faturamento SP3'!$P$2:$P$692,'Faturamento SP3'!$D$2:$D$692,'Infos Relatório'!$B$2,'Faturamento SP3'!$E$2:$E$692,'Infos Relatório'!$B7,'Faturamento SP3'!$Z$2:$Z$692,'Infos Relatório'!BQ$1,'Faturamento SP3'!$T$2:$T$692,"Sim") -> 0 | BU7: =BT7/BS7 -> #DIV/0! | BV7: =SUMIFS('Faturamento SP3'!$H$2:$H$692,'Faturamento SP3'!$D$2:$D$692,'Infos Relatório'!$B$2,'Faturamento SP3'!$E$2:$E$692,'Infos Relatório'!$B7,'Faturamento SP3'!$Z$2:$Z$692,'Infos Relatório'!BQ$1) -> 0
B8: AMPLA Resgate Treinamentos | C8: =COUNTIFS('Faturamento SP3'!$D$2:$D$692,'Infos Relatório'!$B$2,'Faturamento SP3'!$E$2:$E$692,'Infos Relatório'!$B8,'Faturamento SP3'!$Z$2:$Z$692,'Infos Relatório'!C$1) -> 0 | D8: =SUMIFS('Faturamento SP3'!$G$2:$G$692,'Faturamento SP3'!$D$2:$D$692,'Infos Relatório'!$B$2,'Faturamento SP3'!$E$2:$E$692,'Infos Relatório'!$B8,'Faturamento SP3'!$Z$2:$Z$692,'Infos Relatório'!C$1) -> 0 | E8: =SUMIFS('Faturamento SP3'!$J$2:$J$692,'Faturamento SP3'!$D$2:$D$692,'Infos Relatório'!$B$2,'Faturamento SP3'!$E$2:$E$692,'Infos Relatório'!$B8,'Faturamento SP3'!$Z$2:$Z$692,'Infos Relatório'!C$1) -> 0 | F8: =SUMIFS('Faturamento SP3'!$O$2:$O$692,'Faturamento SP3'!$D$2:$D$692,'Infos Relatório'!$B$2,'Faturamento SP3'!$E$2:$E$692,'Infos Relatório'!$B8,'Faturamento SP3'!$Z$2:$Z$692,'Infos Relatório'!C$1,'Faturamento SP3'!$T$2:$T$692,"Sim")+SUMIFS('Faturamento SP3'!$P$2:$P$692,'Faturamento SP3'!$D$2:$D$692,'Infos Relatório'!$B$2,'Faturamento SP3'!$E$2:$E$692,'Infos Relatório'!$B8,'Faturamento SP3'!$Z$2:$Z$692,'Infos Relatório'!C$1,'Faturamento SP3'!$T$2:$T$692,"Sim") -> 0 | G8: =F8/E8 -> #DIV/0! | H8: =SUMIFS('Faturamento SP3'!$H$2:$H$692,'Faturamento SP3'!$D$2:$D$692,'Infos Relatório'!$B$2,'Faturamento SP3'!$E$2:$E$692,'Infos Relatório'!$B8,'Faturamento SP3'!$Z$2:$Z$692,'Infos Relatório'!C$1) -> 0 | I8: =COUNTIFS('Faturamento SP3'!$D$2:$D$692,'Infos Relatório'!$B$2,'Faturamento SP3'!$E$2:$E$692,'Infos Relatório'!$B8,'Faturamento SP3'!$Z$2:$Z$692,'Infos Relatório'!I$1) -> 0 | J8: =SUMIFS('Faturamento SP3'!$G$2:$G$692,'Faturamento SP3'!$D$2:$D$692,'Infos Relatório'!$B$2,'Faturamento SP3'!$E$2:$E$692,'Infos Relatório'!$B8,'Faturamento SP3'!$Z$2:$Z$692,'Infos Relatório'!I$1) -> 0 | K8: =SUMIFS('Faturamento SP3'!$J$2:$J$692,'Faturamento SP3'!$D$2:$D$692,'Infos Relatório'!$B$2,'Faturamento SP3'!$E$2:$E$692,'Infos Relatório'!$B8,'Faturamento SP3'!$Z$2:$Z$692,'Infos Relatório'!I$1) -> 0 | L8: =SUMIFS('Faturamento SP3'!$O$2:$O$692,'Faturamento SP3'!$D$2:$D$692,'Infos Relatório'!$B$2,'Faturamento SP3'!$E$2:$E$692,'Infos Relatório'!$B8,'Faturamento SP3'!$Z$2:$Z$692,'Infos Relatório'!I$1,'Faturamento SP3'!$T$2:$T$692,"Sim")+SUMIFS('Faturamento SP3'!$P$2:$P$692,'Faturamento SP3'!$D$2:$D$692,'Infos Relatório'!$B$2,'Faturamento SP3'!$E$2:$E$692,'Infos Relatório'!$B8,'Faturamento SP3'!$Z$2:$Z$692,'Infos Relatório'!I$1,'Faturamento SP3'!$T$2:$T$692,"Sim") -> 0 | M8: =L8/K8 -> #DIV/0! | N8: =SUMIFS('Faturamento SP3'!$H$2:$H$692,'Faturamento SP3'!$D$2:$D$692,'Infos Relatório'!$B$2,'Faturamento SP3'!$E$2:$E$692,'Infos Relatório'!$B8,'Faturamento SP3'!$Z$2:$Z$692,'Infos Relatório'!I$1) -> 0 | O8: =COUNTIFS('Faturamento SP3'!$D$2:$D$692,'Infos Relatório'!$B$2,'Faturamento SP3'!$E$2:$E$692,'Infos Relatório'!$B8,'Faturamento SP3'!$Z$2:$Z$692,'Infos Relatório'!O$1) -> 0 | P8: =SUMIFS('Faturamento SP3'!$G$2:$G$692,'Faturamento SP3'!$D$2:$D$692,'Infos Relatório'!$B$2,'Faturamento SP3'!$E$2:$E$692,'Infos Relatório'!$B8,'Faturamento SP3'!$Z$2:$Z$692,'Infos Relatório'!O$1) -> 0 | Q8: =SUMIFS('Faturamento SP3'!$J$2:$J$692,'Faturamento SP3'!$D$2:$D$692,'Infos Relatório'!$B$2,'Faturamento SP3'!$E$2:$E$692,'Infos Relatório'!$B8,'Faturamento SP3'!$Z$2:$Z$692,'Infos Relatório'!O$1) -> 0 | R8: =SUMIFS('Faturamento SP3'!$O$2:$O$692,'Faturamento SP3'!$D$2:$D$692,'Infos Relatório'!$B$2,'Faturamento SP3'!$E$2:$E$692,'Infos Relatório'!$B8,'Faturamento SP3'!$Z$2:$Z$692,'Infos Relatório'!O$1,'Faturamento SP3'!$T$2:$T$692,"Sim")+SUMIFS('Faturamento SP3'!$P$2:$P$692,'Faturamento SP3'!$D$2:$D$692,'Infos Relatório'!$B$2,'Faturamento SP3'!$E$2:$E$692,'Infos Relatório'!$B8,'Faturamento SP3'!$Z$2:$Z$692,'Infos Relatório'!O$1,'Faturamento SP3'!$T$2:$T$692,"Sim") -> 0 | S8: =R8/Q8 -> #DIV/0! | T8: =SUMIFS('Faturamento SP3'!$H$2:$H$692,'Faturamento SP3'!$D$2:$D$692,'Infos Relatório'!$B$2,'Faturamento SP3'!$E$2:$E$692,'Infos Relatório'!$B8,'Faturamento SP3'!$Z$2:$Z$692,'Infos Relatório'!O$1) -> 0 | U8: =COUNTIFS('Faturamento SP3'!$D$2:$D$692,'Infos Relatório'!$B$2,'Faturamento SP3'!$E$2:$E$692,'Infos Relatório'!$B8,'Faturamento SP3'!$Z$2:$Z$692,'Infos Relatório'!U$1) -> 0 | V8: =SUMIFS('Faturamento SP3'!$G$2:$G$692,'Faturamento SP3'!$D$2:$D$692,'Infos Relatório'!$B$2,'Faturamento SP3'!$E$2:$E$692,'Infos Relatório'!$B8,'Faturamento SP3'!$Z$2:$Z$692,'Infos Relatório'!U$1) -> 0 | W8: =SUMIFS('Faturamento SP3'!$J$2:$J$692,'Faturamento SP3'!$D$2:$D$692,'Infos Relatório'!$B$2,'Faturamento SP3'!$E$2:$E$692,'Infos Relatório'!$B8,'Faturamento SP3'!$Z$2:$Z$692,'Infos Relatório'!U$1) -> 0 | X8: =SUMIFS('Faturamento SP3'!$O$2:$O$692,'Faturamento SP3'!$D$2:$D$692,'Infos Relatório'!$B$2,'Faturamento SP3'!$E$2:$E$692,'Infos Relatório'!$B8,'Faturamento SP3'!$Z$2:$Z$692,'Infos Relatório'!U$1,'Faturamento SP3'!$T$2:$T$692,"Sim")+SUMIFS('Faturamento SP3'!$P$2:$P$692,'Faturamento SP3'!$D$2:$D$692,'Infos Relatório'!$B$2,'Faturamento SP3'!$E$2:$E$692,'Infos Relatório'!$B8,'Faturamento SP3'!$Z$2:$Z$692,'Infos Relatório'!U$1,'Faturamento SP3'!$T$2:$T$692,"Sim") -> 0 | Y8: =X8/W8 -> #DIV/0! | Z8: =SUMIFS('Faturamento SP3'!$H$2:$H$692,'Faturamento SP3'!$D$2:$D$692,'Infos Relatório'!$B$2,'Faturamento SP3'!$E$2:$E$692,'Infos Relatório'!$B8,'Faturamento SP3'!$Z$2:$Z$692,'Infos Relatório'!U$1) -> 0 | AA8: =COUNTIFS('Faturamento SP3'!$D$2:$D$692,'Infos Relatório'!$B$2,'Faturamento SP3'!$E$2:$E$692,'Infos Relatório'!$B8,'Faturamento SP3'!$Z$2:$Z$692,'Infos Relatório'!AA$1) -> 0 | AB8: =SUMIFS('Faturamento SP3'!$G$2:$G$692,'Faturamento SP3'!$D$2:$D$692,'Infos Relatório'!$B$2,'Faturamento SP3'!$E$2:$E$692,'Infos Relatório'!$B8,'Faturamento SP3'!$Z$2:$Z$692,'Infos Relatório'!AA$1) -> 0 | AC8: =SUMIFS('Faturamento SP3'!$J$2:$J$692,'Faturamento SP3'!$D$2:$D$692,'Infos Relatório'!$B$2,'Faturamento SP3'!$E$2:$E$692,'Infos Relatório'!$B8,'Faturamento SP3'!$Z$2:$Z$692,'Infos Relatório'!AA$1) -> 0 | AD8: =SUMIFS('Faturamento SP3'!$O$2:$O$692,'Faturamento SP3'!$D$2:$D$692,'Infos Relatório'!$B$2,'Faturamento SP3'!$E$2:$E$692,'Infos Relatório'!$B8,'Faturamento SP3'!$Z$2:$Z$692,'Infos Relatório'!AA$1,'Faturamento SP3'!$T$2:$T$692,"Sim")+SUMIFS('Faturamento SP3'!$P$2:$P$692,'Faturamento SP3'!$D$2:$D$692,'Infos Relatório'!$B$2,'Faturamento SP3'!$E$2:$E$692,'Infos Relatório'!$B8,'Faturamento SP3'!$Z$2:$Z$692,'Infos Relatório'!AA$1,'Faturamento SP3'!$T$2:$T$692,"Sim") -> 0 | AE8: =AD8/AC8 -> #DIV/0! | AF8: =SUMIFS('Faturamento SP3'!$H$2:$H$692,'Faturamento SP3'!$D$2:$D$692,'Infos Relatório'!$B$2,'Faturamento SP3'!$E$2:$E$692,'Infos Relatório'!$B8,'Faturamento SP3'!$Z$2:$Z$692,'Infos Relatório'!AA$1) -> 0 | AG8: =COUNTIFS('Faturamento SP3'!$D$2:$D$692,'Infos Relatório'!$B$2,'Faturamento SP3'!$E$2:$E$692,'Infos Relatório'!$B8,'Faturamento SP3'!$Z$2:$Z$692,'Infos Relatório'!AG$1) -> 0 | AH8: =SUMIFS('Faturamento SP3'!$G$2:$G$692,'Faturamento SP3'!$D$2:$D$692,'Infos Relatório'!$B$2,'Faturamento SP3'!$E$2:$E$692,'Infos Relatório'!$B8,'Faturamento SP3'!$Z$2:$Z$692,'Infos Relatório'!AG$1) -> 0 | AI8: =SUMIFS('Faturamento SP3'!$J$2:$J$692,'Faturamento SP3'!$D$2:$D$692,'Infos Relatório'!$B$2,'Faturamento SP3'!$E$2:$E$692,'Infos Relatório'!$B8,'Faturamento SP3'!$Z$2:$Z$692,'Infos Relatório'!AG$1) -> 0 | AJ8: =SUMIFS('Faturamento SP3'!$O$2:$O$692,'Faturamento SP3'!$D$2:$D$692,'Infos Relatório'!$B$2,'Faturamento SP3'!$E$2:$E$692,'Infos Relatório'!$B8,'Faturamento SP3'!$Z$2:$Z$692,'Infos Relatório'!AG$1,'Faturamento SP3'!$T$2:$T$692,"Sim")+SUMIFS('Faturamento SP3'!$P$2:$P$692,'Faturamento SP3'!$D$2:$D$692,'Infos Relatório'!$B$2,'Faturamento SP3'!$E$2:$E$692,'Infos Relatório'!$B8,'Faturamento SP3'!$Z$2:$Z$692,'Infos Relatório'!AG$1,'Faturamento SP3'!$T$2:$T$692,"Sim") -> 0 | AK8: =AJ8/AI8 -> #DIV/0! | AL8: =SUMIFS('Faturamento SP3'!$H$2:$H$692,'Faturamento SP3'!$D$2:$D$692,'Infos Relatório'!$B$2,'Faturamento SP3'!$E$2:$E$692,'Infos Relatório'!$B8,'Faturamento SP3'!$Z$2:$Z$692,'Infos Relatório'!AG$1) -> 0 | AM8: =COUNTIFS('Faturamento SP3'!$D$2:$D$692,'Infos Relatório'!$B$2,'Faturamento SP3'!$E$2:$E$692,'Infos Relatório'!$B8,'Faturamento SP3'!$Z$2:$Z$692,'Infos Relatório'!AM$1) -> 0 | AN8: =SUMIFS('Faturamento SP3'!$G$2:$G$692,'Faturamento SP3'!$D$2:$D$692,'Infos Relatório'!$B$2,'Faturamento SP3'!$E$2:$E$692,'Infos Relatório'!$B8,'Faturamento SP3'!$Z$2:$Z$692,'Infos Relatório'!AM$1) -> 0 | AO8: =SUMIFS('Faturamento SP3'!$J$2:$J$692,'Faturamento SP3'!$D$2:$D$692,'Infos Relatório'!$B$2,'Faturamento SP3'!$E$2:$E$692,'Infos Relatório'!$B8,'Faturamento SP3'!$Z$2:$Z$692,'Infos Relatório'!AM$1) -> 0 | AP8: =SUMIFS('Faturamento SP3'!$O$2:$O$692,'Faturamento SP3'!$D$2:$D$692,'Infos Relatório'!$B$2,'Faturamento SP3'!$E$2:$E$692,'Infos Relatório'!$B8,'Faturamento SP3'!$Z$2:$Z$692,'Infos Relatório'!AM$1,'Faturamento SP3'!$T$2:$T$692,"Sim")+SUMIFS('Faturamento SP3'!$P$2:$P$692,'Faturamento SP3'!$D$2:$D$692,'Infos Relatório'!$B$2,'Faturamento SP3'!$E$2:$E$692,'Infos Relatório'!$B8,'Faturamento SP3'!$Z$2:$Z$692,'Infos Relatório'!AM$1,'Faturamento SP3'!$T$2:$T$692,"Sim") -> 0 | AQ8: =AP8/AO8 -> #DIV/0! | AR8: =SUMIFS('Faturamento SP3'!$H$2:$H$692,'Faturamento SP3'!$D$2:$D$692,'Infos Relatório'!$B$2,'Faturamento SP3'!$E$2:$E$692,'Infos Relatório'!$B8,'Faturamento SP3'!$Z$2:$Z$692,'Infos Relatório'!AM$1) -> 0 | AS8: =COUNTIFS('Faturamento SP3'!$D$2:$D$692,'Infos Relatório'!$B$2,'Faturamento SP3'!$E$2:$E$692,'Infos Relatório'!$B8,'Faturamento SP3'!$Z$2:$Z$692,'Infos Relatório'!AS$1) -> 0 | AT8: =SUMIFS('Faturamento SP3'!$G$2:$G$692,'Faturamento SP3'!$D$2:$D$692,'Infos Relatório'!$B$2,'Faturamento SP3'!$E$2:$E$692,'Infos Relatório'!$B8,'Faturamento SP3'!$Z$2:$Z$692,'Infos Relatório'!AS$1) -> 0 | AU8: =SUMIFS('Faturamento SP3'!$J$2:$J$692,'Faturamento SP3'!$D$2:$D$692,'Infos Relatório'!$B$2,'Faturamento SP3'!$E$2:$E$692,'Infos Relatório'!$B8,'Faturamento SP3'!$Z$2:$Z$692,'Infos Relatório'!AS$1) -> 0 | AV8: =SUMIFS('Faturamento SP3'!$O$2:$O$692,'Faturamento SP3'!$D$2:$D$692,'Infos Relatório'!$B$2,'Faturamento SP3'!$E$2:$E$692,'Infos Relatório'!$B8,'Faturamento SP3'!$Z$2:$Z$692,'Infos Relatório'!AS$1,'Faturamento SP3'!$T$2:$T$692,"Sim")+SUMIFS('Faturamento SP3'!$P$2:$P$692,'Faturamento SP3'!$D$2:$D$692,'Infos Relatório'!$B$2,'Faturamento SP3'!$E$2:$E$692,'Infos Relatório'!$B8,'Faturamento SP3'!$Z$2:$Z$692,'Infos Relatório'!AS$1,'Faturamento SP3'!$T$2:$T$692,"Sim") -> 0 | AW8: =AV8/AU8 -> #DIV/0! | AX8: =SUMIFS('Faturamento SP3'!$H$2:$H$692,'Faturamento SP3'!$D$2:$D$692,'Infos Relatório'!$B$2,'Faturamento SP3'!$E$2:$E$692,'Infos Relatório'!$B8,'Faturamento SP3'!$Z$2:$Z$692,'Infos Relatório'!AS$1) -> 0 | AY8: =COUNTIFS('Faturamento SP3'!$D$2:$D$692,'Infos Relatório'!$B$2,'Faturamento SP3'!$E$2:$E$692,'Infos Relatório'!$B8,'Faturamento SP3'!$Z$2:$Z$692,'Infos Relatório'!AY$1) -> 0 | AZ8: =SUMIFS('Faturamento SP3'!$G$2:$G$692,'Faturamento SP3'!$D$2:$D$692,'Infos Relatório'!$B$2,'Faturamento SP3'!$E$2:$E$692,'Infos Relatório'!$B8,'Faturamento SP3'!$Z$2:$Z$692,'Infos Relatório'!AY$1) -> 0 | BA8: =SUMIFS('Faturamento SP3'!$J$2:$J$692,'Faturamento SP3'!$D$2:$D$692,'Infos Relatório'!$B$2,'Faturamento SP3'!$E$2:$E$692,'Infos Relatório'!$B8,'Faturamento SP3'!$Z$2:$Z$692,'Infos Relatório'!AY$1) -> 0 | BB8: =SUMIFS('Faturamento SP3'!$O$2:$O$692,'Faturamento SP3'!$D$2:$D$692,'Infos Relatório'!$B$2,'Faturamento SP3'!$E$2:$E$692,'Infos Relatório'!$B8,'Faturamento SP3'!$Z$2:$Z$692,'Infos Relatório'!AY$1,'Faturamento SP3'!$T$2:$T$692,"Sim")+SUMIFS('Faturamento SP3'!$P$2:$P$692,'Faturamento SP3'!$D$2:$D$692,'Infos Relatório'!$B$2,'Faturamento SP3'!$E$2:$E$692,'Infos Relatório'!$B8,'Faturamento SP3'!$Z$2:$Z$692,'Infos Relatório'!AY$1,'Faturamento SP3'!$T$2:$T$692,"Sim") -> 0 | BC8: =BB8/BA8 -> #DIV/0! | BD8: =SUMIFS('Faturamento SP3'!$H$2:$H$692,'Faturamento SP3'!$D$2:$D$692,'Infos Relatório'!$B$2,'Faturamento SP3'!$E$2:$E$692,'Infos Relatório'!$B8,'Faturamento SP3'!$Z$2:$Z$692,'Infos Relatório'!AY$1) -> 0 | BE8: =COUNTIFS('Faturamento SP3'!$D$2:$D$692,'Infos Relatório'!$B$2,'Faturamento SP3'!$E$2:$E$692,'Infos Relatório'!$B8,'Faturamento SP3'!$Z$2:$Z$692,'Infos Relatório'!BE$1) -> 0 | BF8: =SUMIFS('Faturamento SP3'!$G$2:$G$692,'Faturamento SP3'!$D$2:$D$692,'Infos Relatório'!$B$2,'Faturamento SP3'!$E$2:$E$692,'Infos Relatório'!$B8,'Faturamento SP3'!$Z$2:$Z$692,'Infos Relatório'!BE$1) -> 0 | BG8: =SUMIFS('Faturamento SP3'!$J$2:$J$692,'Faturamento SP3'!$D$2:$D$692,'Infos Relatório'!$B$2,'Faturamento SP3'!$E$2:$E$692,'Infos Relatório'!$B8,'Faturamento SP3'!$Z$2:$Z$692,'Infos Relatório'!BE$1) -> 0 | BH8: =SUMIFS('Faturamento SP3'!$O$2:$O$692,'Faturamento SP3'!$D$2:$D$692,'Infos Relatório'!$B$2,'Faturamento SP3'!$E$2:$E$692,'Infos Relatório'!$B8,'Faturamento SP3'!$Z$2:$Z$692,'Infos Relatório'!BE$1,'Faturamento SP3'!$T$2:$T$692,"Sim")+SUMIFS('Faturamento SP3'!$P$2:$P$692,'Faturamento SP3'!$D$2:$D$692,'Infos Relatório'!$B$2,'Faturamento SP3'!$E$2:$E$692,'Infos Relatório'!$B8,'Faturamento SP3'!$Z$2:$Z$692,'Infos Relatório'!BE$1,'Faturamento SP3'!$T$2:$T$692,"Sim") -> 0 | BI8: =BH8/BG8 -> #DIV/0! | BJ8: =SUMIFS('Faturamento SP3'!$H$2:$H$692,'Faturamento SP3'!$D$2:$D$692,'Infos Relatório'!$B$2,'Faturamento SP3'!$E$2:$E$692,'Infos Relatório'!$B8,'Faturamento SP3'!$Z$2:$Z$692,'Infos Relatório'!BE$1) -> 0 | BK8: =COUNTIFS('Faturamento SP3'!$D$2:$D$692,'Infos Relatório'!$B$2,'Faturamento SP3'!$E$2:$E$692,'Infos Relatório'!$B8,'Faturamento SP3'!$Z$2:$Z$692,'Infos Relatório'!BK$1) -> 0 | BL8: =SUMIFS('Faturamento SP3'!$G$2:$G$692,'Faturamento SP3'!$D$2:$D$692,'Infos Relatório'!$B$2,'Faturamento SP3'!$E$2:$E$692,'Infos Relatório'!$B8,'Faturamento SP3'!$Z$2:$Z$692,'Infos Relatório'!BK$1) -> 0 | BM8: =SUMIFS('Faturamento SP3'!$J$2:$J$692,'Faturamento SP3'!$D$2:$D$692,'Infos Relatório'!$B$2,'Faturamento SP3'!$E$2:$E$692,'Infos Relatório'!$B8,'Faturamento SP3'!$Z$2:$Z$692,'Infos Relatório'!BK$1) -> 0 | BN8: =SUMIFS('Faturamento SP3'!$O$2:$O$692,'Faturamento SP3'!$D$2:$D$692,'Infos Relatório'!$B$2,'Faturamento SP3'!$E$2:$E$692,'Infos Relatório'!$B8,'Faturamento SP3'!$Z$2:$Z$692,'Infos Relatório'!BK$1,'Faturamento SP3'!$T$2:$T$692,"Sim")+SUMIFS('Faturamento SP3'!$P$2:$P$692,'Faturamento SP3'!$D$2:$D$692,'Infos Relatório'!$B$2,'Faturamento SP3'!$E$2:$E$692,'Infos Relatório'!$B8,'Faturamento SP3'!$Z$2:$Z$692,'Infos Relatório'!BK$1,'Faturamento SP3'!$T$2:$T$692,"Sim") -> 0 | BO8: =BN8/BM8 -> #DIV/0! | BP8: =SUMIFS('Faturamento SP3'!$H$2:$H$692,'Faturamento SP3'!$D$2:$D$692,'Infos Relatório'!$B$2,'Faturamento SP3'!$E$2:$E$692,'Infos Relatório'!$B8,'Faturamento SP3'!$Z$2:$Z$692,'Infos Relatório'!BK$1) -> 0 | BQ8: =COUNTIFS('Faturamento SP3'!$D$2:$D$692,'Infos Relatório'!$B$2,'Faturamento SP3'!$E$2:$E$692,'Infos Relatório'!$B8,'Faturamento SP3'!$Z$2:$Z$692,'Infos Relatório'!BQ$1) -> 0 | BR8: =SUMIFS('Faturamento SP3'!$G$2:$G$692,'Faturamento SP3'!$D$2:$D$692,'Infos Relatório'!$B$2,'Faturamento SP3'!$E$2:$E$692,'Infos Relatório'!$B8,'Faturamento SP3'!$Z$2:$Z$692,'Infos Relatório'!BQ$1) -> 0 | BS8: =SUMIFS('Faturamento SP3'!$J$2:$J$692,'Faturamento SP3'!$D$2:$D$692,'Infos Relatório'!$B$2,'Faturamento SP3'!$E$2:$E$692,'Infos Relatório'!$B8,'Faturamento SP3'!$Z$2:$Z$692,'Infos Relatório'!BQ$1) -> 0 | BT8: =SUMIFS('Faturamento SP3'!$O$2:$O$692,'Faturamento SP3'!$D$2:$D$692,'Infos Relatório'!$B$2,'Faturamento SP3'!$E$2:$E$692,'Infos Relatório'!$B8,'Faturamento SP3'!$Z$2:$Z$692,'Infos Relatório'!BQ$1,'Faturamento SP3'!$T$2:$T$692,"Sim")+SUMIFS('Faturamento SP3'!$P$2:$P$692,'Faturamento SP3'!$D$2:$D$692,'Infos Relatório'!$B$2,'Faturamento SP3'!$E$2:$E$692,'Infos Relatório'!$B8,'Faturamento SP3'!$Z$2:$Z$692,'Infos Relatório'!BQ$1,'Faturamento SP3'!$T$2:$T$692,"Sim") -> 0 | BU8: =BT8/BS8 -> #DIV/0! | BV8: =SUMIFS('Faturamento SP3'!$H$2:$H$692,'Faturamento SP3'!$D$2:$D$692,'Infos Relatório'!$B$2,'Faturamento SP3'!$E$2:$E$692,'Infos Relatório'!$B8,'Faturamento SP3'!$Z$2:$Z$692,'Infos Relatório'!BQ$1) -> 0
B9: Anjos da Vida | C9: =COUNTIFS('Faturamento SP3'!$D$2:$D$692,'Infos Relatório'!$B$2,'Faturamento SP3'!$E$2:$E$692,'Infos Relatório'!$B9,'Faturamento SP3'!$Z$2:$Z$692,'Infos Relatório'!C$1) -> 0 | D9: =SUMIFS('Faturamento SP3'!$G$2:$G$692,'Faturamento SP3'!$D$2:$D$692,'Infos Relatório'!$B$2,'Faturamento SP3'!$E$2:$E$692,'Infos Relatório'!$B9,'Faturamento SP3'!$Z$2:$Z$692,'Infos Relatório'!C$1) -> 0 | E9: =SUMIFS('Faturamento SP3'!$J$2:$J$692,'Faturamento SP3'!$D$2:$D$692,'Infos Relatório'!$B$2,'Faturamento SP3'!$E$2:$E$692,'Infos Relatório'!$B9,'Faturamento SP3'!$Z$2:$Z$692,'Infos Relatório'!C$1) -> 0 | F9: =SUMIFS('Faturamento SP3'!$O$2:$O$692,'Faturamento SP3'!$D$2:$D$692,'Infos Relatório'!$B$2,'Faturamento SP3'!$E$2:$E$692,'Infos Relatório'!$B9,'Faturamento SP3'!$Z$2:$Z$692,'Infos Relatório'!C$1,'Faturamento SP3'!$T$2:$T$692,"Sim")+SUMIFS('Faturamento SP3'!$P$2:$P$692,'Faturamento SP3'!$D$2:$D$692,'Infos Relatório'!$B$2,'Faturamento SP3'!$E$2:$E$692,'Infos Relatório'!$B9,'Faturamento SP3'!$Z$2:$Z$692,'Infos Relatório'!C$1,'Faturamento SP3'!$T$2:$T$692,"Sim") -> 0 | G9: =F9/E9 -> #DIV/0! | H9: =SUMIFS('Faturamento SP3'!$H$2:$H$692,'Faturamento SP3'!$D$2:$D$692,'Infos Relatório'!$B$2,'Faturamento SP3'!$E$2:$E$692,'Infos Relatório'!$B9,'Faturamento SP3'!$Z$2:$Z$692,'Infos Relatório'!C$1) -> 0 | I9: =COUNTIFS('Faturamento SP3'!$D$2:$D$692,'Infos Relatório'!$B$2,'Faturamento SP3'!$E$2:$E$692,'Infos Relatório'!$B9,'Faturamento SP3'!$Z$2:$Z$692,'Infos Relatório'!I$1) -> 0 | J9: =SUMIFS('Faturamento SP3'!$G$2:$G$692,'Faturamento SP3'!$D$2:$D$692,'Infos Relatório'!$B$2,'Faturamento SP3'!$E$2:$E$692,'Infos Relatório'!$B9,'Faturamento SP3'!$Z$2:$Z$692,'Infos Relatório'!I$1) -> 0 | K9: =SUMIFS('Faturamento SP3'!$J$2:$J$692,'Faturamento SP3'!$D$2:$D$692,'Infos Relatório'!$B$2,'Faturamento SP3'!$E$2:$E$692,'Infos Relatório'!$B9,'Faturamento SP3'!$Z$2:$Z$692,'Infos Relatório'!I$1) -> 0 | L9: =SUMIFS('Faturamento SP3'!$O$2:$O$692,'Faturamento SP3'!$D$2:$D$692,'Infos Relatório'!$B$2,'Faturamento SP3'!$E$2:$E$692,'Infos Relatório'!$B9,'Faturamento SP3'!$Z$2:$Z$692,'Infos Relatório'!I$1,'Faturamento SP3'!$T$2:$T$692,"Sim")+SUMIFS('Faturamento SP3'!$P$2:$P$692,'Faturamento SP3'!$D$2:$D$692,'Infos Relatório'!$B$2,'Faturamento SP3'!$E$2:$E$692,'Infos Relatório'!$B9,'Faturamento SP3'!$Z$2:$Z$692,'Infos Relatório'!I$1,'Faturamento SP3'!$T$2:$T$692,"Sim") -> 0 | M9: =L9/K9 -> #DIV/0! | N9: =SUMIFS('Faturamento SP3'!$H$2:$H$692,'Faturamento SP3'!$D$2:$D$692,'Infos Relatório'!$B$2,'Faturamento SP3'!$E$2:$E$692,'Infos Relatório'!$B9,'Faturamento SP3'!$Z$2:$Z$692,'Infos Relatório'!I$1) -> 0 | O9: =COUNTIFS('Faturamento SP3'!$D$2:$D$692,'Infos Relatório'!$B$2,'Faturamento SP3'!$E$2:$E$692,'Infos Relatório'!$B9,'Faturamento SP3'!$Z$2:$Z$692,'Infos Relatório'!O$1) -> 0 | P9: =SUMIFS('Faturamento SP3'!$G$2:$G$692,'Faturamento SP3'!$D$2:$D$692,'Infos Relatório'!$B$2,'Faturamento SP3'!$E$2:$E$692,'Infos Relatório'!$B9,'Faturamento SP3'!$Z$2:$Z$692,'Infos Relatório'!O$1) -> 0 | Q9: =SUMIFS('Faturamento SP3'!$J$2:$J$692,'Faturamento SP3'!$D$2:$D$692,'Infos Relatório'!$B$2,'Faturamento SP3'!$E$2:$E$692,'Infos Relatório'!$B9,'Faturamento SP3'!$Z$2:$Z$692,'Infos Relatório'!O$1) -> 0 | R9: =SUMIFS('Faturamento SP3'!$O$2:$O$692,'Faturamento SP3'!$D$2:$D$692,'Infos Relatório'!$B$2,'Faturamento SP3'!$E$2:$E$692,'Infos Relatório'!$B9,'Faturamento SP3'!$Z$2:$Z$692,'Infos Relatório'!O$1,'Faturamento SP3'!$T$2:$T$692,"Sim")+SUMIFS('Faturamento SP3'!$P$2:$P$692,'Faturamento SP3'!$D$2:$D$692,'Infos Relatório'!$B$2,'Faturamento SP3'!$E$2:$E$692,'Infos Relatório'!$B9,'Faturamento SP3'!$Z$2:$Z$692,'Infos Relatório'!O$1,'Faturamento SP3'!$T$2:$T$692,"Sim") -> 0 | S9: =R9/Q9 -> #DIV/0! | T9: =SUMIFS('Faturamento SP3'!$H$2:$H$692,'Faturamento SP3'!$D$2:$D$692,'Infos Relatório'!$B$2,'Faturamento SP3'!$E$2:$E$692,'Infos Relatório'!$B9,'Faturamento SP3'!$Z$2:$Z$692,'Infos Relatório'!O$1) -> 0 | U9: =COUNTIFS('Faturamento SP3'!$D$2:$D$692,'Infos Relatório'!$B$2,'Faturamento SP3'!$E$2:$E$692,'Infos Relatório'!$B9,'Faturamento SP3'!$Z$2:$Z$692,'Infos Relatório'!U$1) -> 0 | V9: =SUMIFS('Faturamento SP3'!$G$2:$G$692,'Faturamento SP3'!$D$2:$D$692,'Infos Relatório'!$B$2,'Faturamento SP3'!$E$2:$E$692,'Infos Relatório'!$B9,'Faturamento SP3'!$Z$2:$Z$692,'Infos Relatório'!U$1) -> 0 | W9: =SUMIFS('Faturamento SP3'!$J$2:$J$692,'Faturamento SP3'!$D$2:$D$692,'Infos Relatório'!$B$2,'Faturamento SP3'!$E$2:$E$692,'Infos Relatório'!$B9,'Faturamento SP3'!$Z$2:$Z$692,'Infos Relatório'!U$1) -> 0 | X9: =SUMIFS('Faturamento SP3'!$O$2:$O$692,'Faturamento SP3'!$D$2:$D$692,'Infos Relatório'!$B$2,'Faturamento SP3'!$E$2:$E$692,'Infos Relatório'!$B9,'Faturamento SP3'!$Z$2:$Z$692,'Infos Relatório'!U$1,'Faturamento SP3'!$T$2:$T$692,"Sim")+SUMIFS('Faturamento SP3'!$P$2:$P$692,'Faturamento SP3'!$D$2:$D$692,'Infos Relatório'!$B$2,'Faturamento SP3'!$E$2:$E$692,'Infos Relatório'!$B9,'Faturamento SP3'!$Z$2:$Z$692,'Infos Relatório'!U$1,'Faturamento SP3'!$T$2:$T$692,"Sim") -> 0 | Y9: =X9/W9 -> #DIV/0! | Z9: =SUMIFS('Faturamento SP3'!$H$2:$H$692,'Faturamento SP3'!$D$2:$D$692,'Infos Relatório'!$B$2,'Faturamento SP3'!$E$2:$E$692,'Infos Relatório'!$B9,'Faturamento SP3'!$Z$2:$Z$692,'Infos Relatório'!U$1) -> 0 | AA9: =COUNTIFS('Faturamento SP3'!$D$2:$D$692,'Infos Relatório'!$B$2,'Faturamento SP3'!$E$2:$E$692,'Infos Relatório'!$B9,'Faturamento SP3'!$Z$2:$Z$692,'Infos Relatório'!AA$1) -> 0 | AB9: =SUMIFS('Faturamento SP3'!$G$2:$G$692,'Faturamento SP3'!$D$2:$D$692,'Infos Relatório'!$B$2,'Faturamento SP3'!$E$2:$E$692,'Infos Relatório'!$B9,'Faturamento SP3'!$Z$2:$Z$692,'Infos Relatório'!AA$1) -> 0 | AC9: =SUMIFS('Faturamento SP3'!$J$2:$J$692,'Faturamento SP3'!$D$2:$D$692,'Infos Relatório'!$B$2,'Faturamento SP3'!$E$2:$E$692,'Infos Relatório'!$B9,'Faturamento SP3'!$Z$2:$Z$692,'Infos Relatório'!AA$1) -> 0 | AD9: =SUMIFS('Faturamento SP3'!$O$2:$O$692,'Faturamento SP3'!$D$2:$D$692,'Infos Relatório'!$B$2,'Faturamento SP3'!$E$2:$E$692,'Infos Relatório'!$B9,'Faturamento SP3'!$Z$2:$Z$692,'Infos Relatório'!AA$1,'Faturamento SP3'!$T$2:$T$692,"Sim")+SUMIFS('Faturamento SP3'!$P$2:$P$692,'Faturamento SP3'!$D$2:$D$692,'Infos Relatório'!$B$2,'Faturamento SP3'!$E$2:$E$692,'Infos Relatório'!$B9,'Faturamento SP3'!$Z$2:$Z$692,'Infos Relatório'!AA$1,'Faturamento SP3'!$T$2:$T$692,"Sim") -> 0 | AE9: =AD9/AC9 -> #DIV/0! | AF9: =SUMIFS('Faturamento SP3'!$H$2:$H$692,'Faturamento SP3'!$D$2:$D$692,'Infos Relatório'!$B$2,'Faturamento SP3'!$E$2:$E$692,'Infos Relatório'!$B9,'Faturamento SP3'!$Z$2:$Z$692,'Infos Relatório'!AA$1) -> 0 | AG9: =COUNTIFS('Faturamento SP3'!$D$2:$D$692,'Infos Relatório'!$B$2,'Faturamento SP3'!$E$2:$E$692,'Infos Relatório'!$B9,'Faturamento SP3'!$Z$2:$Z$692,'Infos Relatório'!AG$1) -> 0 | AH9: =SUMIFS('Faturamento SP3'!$G$2:$G$692,'Faturamento SP3'!$D$2:$D$692,'Infos Relatório'!$B$2,'Faturamento SP3'!$E$2:$E$692,'Infos Relatório'!$B9,'Faturamento SP3'!$Z$2:$Z$692,'Infos Relatório'!AG$1) -> 0 | AI9: =SUMIFS('Faturamento SP3'!$J$2:$J$692,'Faturamento SP3'!$D$2:$D$692,'Infos Relatório'!$B$2,'Faturamento SP3'!$E$2:$E$692,'Infos Relatório'!$B9,'Faturamento SP3'!$Z$2:$Z$692,'Infos Relatório'!AG$1) -> 0 | AJ9: =SUMIFS('Faturamento SP3'!$O$2:$O$692,'Faturamento SP3'!$D$2:$D$692,'Infos Relatório'!$B$2,'Faturamento SP3'!$E$2:$E$692,'Infos Relatório'!$B9,'Faturamento SP3'!$Z$2:$Z$692,'Infos Relatório'!AG$1,'Faturamento SP3'!$T$2:$T$692,"Sim")+SUMIFS('Faturamento SP3'!$P$2:$P$692,'Faturamento SP3'!$D$2:$D$692,'Infos Relatório'!$B$2,'Faturamento SP3'!$E$2:$E$692,'Infos Relatório'!$B9,'Faturamento SP3'!$Z$2:$Z$692,'Infos Relatório'!AG$1,'Faturamento SP3'!$T$2:$T$692,"Sim") -> 0 | AK9: =AJ9/AI9 -> #DIV/0! | AL9: =SUMIFS('Faturamento SP3'!$H$2:$H$692,'Faturamento SP3'!$D$2:$D$692,'Infos Relatório'!$B$2,'Faturamento SP3'!$E$2:$E$692,'Infos Relatório'!$B9,'Faturamento SP3'!$Z$2:$Z$692,'Infos Relatório'!AG$1) -> 0 | AM9: =COUNTIFS('Faturamento SP3'!$D$2:$D$692,'Infos Relatório'!$B$2,'Faturamento SP3'!$E$2:$E$692,'Infos Relatório'!$B9,'Faturamento SP3'!$Z$2:$Z$692,'Infos Relatório'!AM$1) -> 0 | AN9: =SUMIFS('Faturamento SP3'!$G$2:$G$692,'Faturamento SP3'!$D$2:$D$692,'Infos Relatório'!$B$2,'Faturamento SP3'!$E$2:$E$692,'Infos Relatório'!$B9,'Faturamento SP3'!$Z$2:$Z$692,'Infos Relatório'!AM$1) -> 0 | AO9: =SUMIFS('Faturamento SP3'!$J$2:$J$692,'Faturamento SP3'!$D$2:$D$692,'Infos Relatório'!$B$2,'Faturamento SP3'!$E$2:$E$692,'Infos Relatório'!$B9,'Faturamento SP3'!$Z$2:$Z$692,'Infos Relatório'!AM$1) -> 0 | AP9: =SUMIFS('Faturamento SP3'!$O$2:$O$692,'Faturamento SP3'!$D$2:$D$692,'Infos Relatório'!$B$2,'Faturamento SP3'!$E$2:$E$692,'Infos Relatório'!$B9,'Faturamento SP3'!$Z$2:$Z$692,'Infos Relatório'!AM$1,'Faturamento SP3'!$T$2:$T$692,"Sim")+SUMIFS('Faturamento SP3'!$P$2:$P$692,'Faturamento SP3'!$D$2:$D$692,'Infos Relatório'!$B$2,'Faturamento SP3'!$E$2:$E$692,'Infos Relatório'!$B9,'Faturamento SP3'!$Z$2:$Z$692,'Infos Relatório'!AM$1,'Faturamento SP3'!$T$2:$T$692,"Sim") -> 0 | AQ9: =AP9/AO9 -> #DIV/0! | AR9: =SUMIFS('Faturamento SP3'!$H$2:$H$692,'Faturamento SP3'!$D$2:$D$692,'Infos Relatório'!$B$2,'Faturamento SP3'!$E$2:$E$692,'Infos Relatório'!$B9,'Faturamento SP3'!$Z$2:$Z$692,'Infos Relatório'!AM$1) -> 0 | AS9: =COUNTIFS('Faturamento SP3'!$D$2:$D$692,'Infos Relatório'!$B$2,'Faturamento SP3'!$E$2:$E$692,'Infos Relatório'!$B9,'Faturamento SP3'!$Z$2:$Z$692,'Infos Relatório'!AS$1) -> 0 | AT9: =SUMIFS('Faturamento SP3'!$G$2:$G$692,'Faturamento SP3'!$D$2:$D$692,'Infos Relatório'!$B$2,'Faturamento SP3'!$E$2:$E$692,'Infos Relatório'!$B9,'Faturamento SP3'!$Z$2:$Z$692,'Infos Relatório'!AS$1) -> 0 | AU9: =SUMIFS('Faturamento SP3'!$J$2:$J$692,'Faturamento SP3'!$D$2:$D$692,'Infos Relatório'!$B$2,'Faturamento SP3'!$E$2:$E$692,'Infos Relatório'!$B9,'Faturamento SP3'!$Z$2:$Z$692,'Infos Relatório'!AS$1) -> 0 | AV9: =SUMIFS('Faturamento SP3'!$O$2:$O$692,'Faturamento SP3'!$D$2:$D$692,'Infos Relatório'!$B$2,'Faturamento SP3'!$E$2:$E$692,'Infos Relatório'!$B9,'Faturamento SP3'!$Z$2:$Z$692,'Infos Relatório'!AS$1,'Faturamento SP3'!$T$2:$T$692,"Sim")+SUMIFS('Faturamento SP3'!$P$2:$P$692,'Faturamento SP3'!$D$2:$D$692,'Infos Relatório'!$B$2,'Faturamento SP3'!$E$2:$E$692,'Infos Relatório'!$B9,'Faturamento SP3'!$Z$2:$Z$692,'Infos Relatório'!AS$1,'Faturamento SP3'!$T$2:$T$692,"Sim") -> 0 | AW9: =AV9/AU9 -> #DIV/0! | AX9: =SUMIFS('Faturamento SP3'!$H$2:$H$692,'Faturamento SP3'!$D$2:$D$692,'Infos Relatório'!$B$2,'Faturamento SP3'!$E$2:$E$692,'Infos Relatório'!$B9,'Faturamento SP3'!$Z$2:$Z$692,'Infos Relatório'!AS$1) -> 0 | AY9: =COUNTIFS('Faturamento SP3'!$D$2:$D$692,'Infos Relatório'!$B$2,'Faturamento SP3'!$E$2:$E$692,'Infos Relatório'!$B9,'Faturamento SP3'!$Z$2:$Z$692,'Infos Relatório'!AY$1) -> 0 | AZ9: =SUMIFS('Faturamento SP3'!$G$2:$G$692,'Faturamento SP3'!$D$2:$D$692,'Infos Relatório'!$B$2,'Faturamento SP3'!$E$2:$E$692,'Infos Relatório'!$B9,'Faturamento SP3'!$Z$2:$Z$692,'Infos Relatório'!AY$1) -> 0 | BA9: =SUMIFS('Faturamento SP3'!$J$2:$J$692,'Faturamento SP3'!$D$2:$D$692,'Infos Relatório'!$B$2,'Faturamento SP3'!$E$2:$E$692,'Infos Relatório'!$B9,'Faturamento SP3'!$Z$2:$Z$692,'Infos Relatório'!AY$1) -> 0 | BB9: =SUMIFS('Faturamento SP3'!$O$2:$O$692,'Faturamento SP3'!$D$2:$D$692,'Infos Relatório'!$B$2,'Faturamento SP3'!$E$2:$E$692,'Infos Relatório'!$B9,'Faturamento SP3'!$Z$2:$Z$692,'Infos Relatório'!AY$1,'Faturamento SP3'!$T$2:$T$692,"Sim")+SUMIFS('Faturamento SP3'!$P$2:$P$692,'Faturamento SP3'!$D$2:$D$692,'Infos Relatório'!$B$2,'Faturamento SP3'!$E$2:$E$692,'Infos Relatório'!$B9,'Faturamento SP3'!$Z$2:$Z$692,'Infos Relatório'!AY$1,'Faturamento SP3'!$T$2:$T$692,"Sim") -> 0 | BC9: =BB9/BA9 -> #DIV/0! | BD9: =SUMIFS('Faturamento SP3'!$H$2:$H$692,'Faturamento SP3'!$D$2:$D$692,'Infos Relatório'!$B$2,'Faturamento SP3'!$E$2:$E$692,'Infos Relatório'!$B9,'Faturamento SP3'!$Z$2:$Z$692,'Infos Relatório'!AY$1) -> 0 | BE9: =COUNTIFS('Faturamento SP3'!$D$2:$D$692,'Infos Relatório'!$B$2,'Faturamento SP3'!$E$2:$E$692,'Infos Relatório'!$B9,'Faturamento SP3'!$Z$2:$Z$692,'Infos Relatório'!BE$1) -> 0 | BF9: =SUMIFS('Faturamento SP3'!$G$2:$G$692,'Faturamento SP3'!$D$2:$D$692,'Infos Relatório'!$B$2,'Faturamento SP3'!$E$2:$E$692,'Infos Relatório'!$B9,'Faturamento SP3'!$Z$2:$Z$692,'Infos Relatório'!BE$1) -> 0 | BG9: =SUMIFS('Faturamento SP3'!$J$2:$J$692,'Faturamento SP3'!$D$2:$D$692,'Infos Relatório'!$B$2,'Faturamento SP3'!$E$2:$E$692,'Infos Relatório'!$B9,'Faturamento SP3'!$Z$2:$Z$692,'Infos Relatório'!BE$1) -> 0 | BH9: =SUMIFS('Faturamento SP3'!$O$2:$O$692,'Faturamento SP3'!$D$2:$D$692,'Infos Relatório'!$B$2,'Faturamento SP3'!$E$2:$E$692,'Infos Relatório'!$B9,'Faturamento SP3'!$Z$2:$Z$692,'Infos Relatório'!BE$1,'Faturamento SP3'!$T$2:$T$692,"Sim")+SUMIFS('Faturamento SP3'!$P$2:$P$692,'Faturamento SP3'!$D$2:$D$692,'Infos Relatório'!$B$2,'Faturamento SP3'!$E$2:$E$692,'Infos Relatório'!$B9,'Faturamento SP3'!$Z$2:$Z$692,'Infos Relatório'!BE$1,'Faturamento SP3'!$T$2:$T$692,"Sim") -> 0 | BI9: =BH9/BG9 -> #DIV/0! | BJ9: =SUMIFS('Faturamento SP3'!$H$2:$H$692,'Faturamento SP3'!$D$2:$D$692,'Infos Relatório'!$B$2,'Faturamento SP3'!$E$2:$E$692,'Infos Relatório'!$B9,'Faturamento SP3'!$Z$2:$Z$692,'Infos Relatório'!BE$1) -> 0 | BK9: =COUNTIFS('Faturamento SP3'!$D$2:$D$692,'Infos Relatório'!$B$2,'Faturamento SP3'!$E$2:$E$692,'Infos Relatório'!$B9,'Faturamento SP3'!$Z$2:$Z$692,'Infos Relatório'!BK$1) -> 0 | BL9: =SUMIFS('Faturamento SP3'!$G$2:$G$692,'Faturamento SP3'!$D$2:$D$692,'Infos Relatório'!$B$2,'Faturamento SP3'!$E$2:$E$692,'Infos Relatório'!$B9,'Faturamento SP3'!$Z$2:$Z$692,'Infos Relatório'!BK$1) -> 0 | BM9: =SUMIFS('Faturamento SP3'!$J$2:$J$692,'Faturamento SP3'!$D$2:$D$692,'Infos Relatório'!$B$2,'Faturamento SP3'!$E$2:$E$692,'Infos Relatório'!$B9,'Faturamento SP3'!$Z$2:$Z$692,'Infos Relatório'!BK$1) -> 0 | BN9: =SUMIFS('Faturamento SP3'!$O$2:$O$692,'Faturamento SP3'!$D$2:$D$692,'Infos Relatório'!$B$2,'Faturamento SP3'!$E$2:$E$692,'Infos Relatório'!$B9,'Faturamento SP3'!$Z$2:$Z$692,'Infos Relatório'!BK$1,'Faturamento SP3'!$T$2:$T$692,"Sim")+SUMIFS('Faturamento SP3'!$P$2:$P$692,'Faturamento SP3'!$D$2:$D$692,'Infos Relatório'!$B$2,'Faturamento SP3'!$E$2:$E$692,'Infos Relatório'!$B9,'Faturamento SP3'!$Z$2:$Z$692,'Infos Relatório'!BK$1,'Faturamento SP3'!$T$2:$T$692,"Sim") -> 0 | BO9: =BN9/BM9 -> #DIV/0! | BP9: =SUMIFS('Faturamento SP3'!$H$2:$H$692,'Faturamento SP3'!$D$2:$D$692,'Infos Relatório'!$B$2,'Faturamento SP3'!$E$2:$E$692,'Infos Relatório'!$B9,'Faturamento SP3'!$Z$2:$Z$692,'Infos Relatório'!BK$1) -> 0 | BQ9: =COUNTIFS('Faturamento SP3'!$D$2:$D$692,'Infos Relatório'!$B$2,'Faturamento SP3'!$E$2:$E$692,'Infos Relatório'!$B9,'Faturamento SP3'!$Z$2:$Z$692,'Infos Relatório'!BQ$1) -> 0 | BR9: =SUMIFS('Faturamento SP3'!$G$2:$G$692,'Faturamento SP3'!$D$2:$D$692,'Infos Relatório'!$B$2,'Faturamento SP3'!$E$2:$E$692,'Infos Relatório'!$B9,'Faturamento SP3'!$Z$2:$Z$692,'Infos Relatório'!BQ$1) -> 0 | BS9: =SUMIFS('Faturamento SP3'!$J$2:$J$692,'Faturamento SP3'!$D$2:$D$692,'Infos Relatório'!$B$2,'Faturamento SP3'!$E$2:$E$692,'Infos Relatório'!$B9,'Faturamento SP3'!$Z$2:$Z$692,'Infos Relatório'!BQ$1) -> 0 | BT9: =SUMIFS('Faturamento SP3'!$O$2:$O$692,'Faturamento SP3'!$D$2:$D$692,'Infos Relatório'!$B$2,'Faturamento SP3'!$E$2:$E$692,'Infos Relatório'!$B9,'Faturamento SP3'!$Z$2:$Z$692,'Infos Relatório'!BQ$1,'Faturamento SP3'!$T$2:$T$692,"Sim")+SUMIFS('Faturamento SP3'!$P$2:$P$692,'Faturamento SP3'!$D$2:$D$692,'Infos Relatório'!$B$2,'Faturamento SP3'!$E$2:$E$692,'Infos Relatório'!$B9,'Faturamento SP3'!$Z$2:$Z$692,'Infos Relatório'!BQ$1,'Faturamento SP3'!$T$2:$T$692,"Sim") -> 0 | BU9: =BT9/BS9 -> #DIV/0! | BV9: =SUMIFS('Faturamento SP3'!$H$2:$H$692,'Faturamento SP3'!$D$2:$D$692,'Infos Relatório'!$B$2,'Faturamento SP3'!$E$2:$E$692,'Infos Relatório'!$B9,'Faturamento SP3'!$Z$2:$Z$692,'Infos Relatório'!BQ$1) -> 0
B10: Art Garden | C10: =COUNTIFS('Faturamento SP3'!$D$2:$D$692,'Infos Relatório'!$B$2,'Faturamento SP3'!$E$2:$E$692,'Infos Relatório'!$B10,'Faturamento SP3'!$Z$2:$Z$692,'Infos Relatório'!C$1) -> 0 | D10: =SUMIFS('Faturamento SP3'!$G$2:$G$692,'Faturamento SP3'!$D$2:$D$692,'Infos Relatório'!$B$2,'Faturamento SP3'!$E$2:$E$692,'Infos Relatório'!$B10,'Faturamento SP3'!$Z$2:$Z$692,'Infos Relatório'!C$1) -> 0 | E10: =SUMIFS('Faturamento SP3'!$J$2:$J$692,'Faturamento SP3'!$D$2:$D$692,'Infos Relatório'!$B$2,'Faturamento SP3'!$E$2:$E$692,'Infos Relatório'!$B10,'Faturamento SP3'!$Z$2:$Z$692,'Infos Relatório'!C$1) -> 0 | F10: =SUMIFS('Faturamento SP3'!$O$2:$O$692,'Faturamento SP3'!$D$2:$D$692,'Infos Relatório'!$B$2,'Faturamento SP3'!$E$2:$E$692,'Infos Relatório'!$B10,'Faturamento SP3'!$Z$2:$Z$692,'Infos Relatório'!C$1,'Faturamento SP3'!$T$2:$T$692,"Sim")+SUMIFS('Faturamento SP3'!$P$2:$P$692,'Faturamento SP3'!$D$2:$D$692,'Infos Relatório'!$B$2,'Faturamento SP3'!$E$2:$E$692,'Infos Relatório'!$B10,'Faturamento SP3'!$Z$2:$Z$692,'Infos Relatório'!C$1,'Faturamento SP3'!$T$2:$T$692,"Sim") -> 0 | G10: =F10/E10 -> #DIV/0! | H10: =SUMIFS('Faturamento SP3'!$H$2:$H$692,'Faturamento SP3'!$D$2:$D$692,'Infos Relatório'!$B$2,'Faturamento SP3'!$E$2:$E$692,'Infos Relatório'!$B10,'Faturamento SP3'!$Z$2:$Z$692,'Infos Relatório'!C$1) -> 0 | I10: =COUNTIFS('Faturamento SP3'!$D$2:$D$692,'Infos Relatório'!$B$2,'Faturamento SP3'!$E$2:$E$692,'Infos Relatório'!$B10,'Faturamento SP3'!$Z$2:$Z$692,'Infos Relatório'!I$1) -> 0 | J10: =SUMIFS('Faturamento SP3'!$G$2:$G$692,'Faturamento SP3'!$D$2:$D$692,'Infos Relatório'!$B$2,'Faturamento SP3'!$E$2:$E$692,'Infos Relatório'!$B10,'Faturamento SP3'!$Z$2:$Z$692,'Infos Relatório'!I$1) -> 0 | K10: =SUMIFS('Faturamento SP3'!$J$2:$J$692,'Faturamento SP3'!$D$2:$D$692,'Infos Relatório'!$B$2,'Faturamento SP3'!$E$2:$E$692,'Infos Relatório'!$B10,'Faturamento SP3'!$Z$2:$Z$692,'Infos Relatório'!I$1) -> 0 | L10: =SUMIFS('Faturamento SP3'!$O$2:$O$692,'Faturamento SP3'!$D$2:$D$692,'Infos Relatório'!$B$2,'Faturamento SP3'!$E$2:$E$692,'Infos Relatório'!$B10,'Faturamento SP3'!$Z$2:$Z$692,'Infos Relatório'!I$1,'Faturamento SP3'!$T$2:$T$692,"Sim")+SUMIFS('Faturamento SP3'!$P$2:$P$692,'Faturamento SP3'!$D$2:$D$692,'Infos Relatório'!$B$2,'Faturamento SP3'!$E$2:$E$692,'Infos Relatório'!$B10,'Faturamento SP3'!$Z$2:$Z$692,'Infos Relatório'!I$1,'Faturamento SP3'!$T$2:$T$692,"Sim") -> 0 | M10: =L10/K10 -> #DIV/0! | N10: =SUMIFS('Faturamento SP3'!$H$2:$H$692,'Faturamento SP3'!$D$2:$D$692,'Infos Relatório'!$B$2,'Faturamento SP3'!$E$2:$E$692,'Infos Relatório'!$B10,'Faturamento SP3'!$Z$2:$Z$692,'Infos Relatório'!I$1) -> 0 | O10: =COUNTIFS('Faturamento SP3'!$D$2:$D$692,'Infos Relatório'!$B$2,'Faturamento SP3'!$E$2:$E$692,'Infos Relatório'!$B10,'Faturamento SP3'!$Z$2:$Z$692,'Infos Relatório'!O$1) -> 0 | P10: =SUMIFS('Faturamento SP3'!$G$2:$G$692,'Faturamento SP3'!$D$2:$D$692,'Infos Relatório'!$B$2,'Faturamento SP3'!$E$2:$E$692,'Infos Relatório'!$B10,'Faturamento SP3'!$Z$2:$Z$692,'Infos Relatório'!O$1) -> 0 | Q10: =SUMIFS('Faturamento SP3'!$J$2:$J$692,'Faturamento SP3'!$D$2:$D$692,'Infos Relatório'!$B$2,'Faturamento SP3'!$E$2:$E$692,'Infos Relatório'!$B10,'Faturamento SP3'!$Z$2:$Z$692,'Infos Relatório'!O$1) -> 0 | R10: =SUMIFS('Faturamento SP3'!$O$2:$O$692,'Faturamento SP3'!$D$2:$D$692,'Infos Relatório'!$B$2,'Faturamento SP3'!$E$2:$E$692,'Infos Relatório'!$B10,'Faturamento SP3'!$Z$2:$Z$692,'Infos Relatório'!O$1,'Faturamento SP3'!$T$2:$T$692,"Sim")+SUMIFS('Faturamento SP3'!$P$2:$P$692,'Faturamento SP3'!$D$2:$D$692,'Infos Relatório'!$B$2,'Faturamento SP3'!$E$2:$E$692,'Infos Relatório'!$B10,'Faturamento SP3'!$Z$2:$Z$692,'Infos Relatório'!O$1,'Faturamento SP3'!$T$2:$T$692,"Sim") -> 0 | S10: =R10/Q10 -> #DIV/0! | T10: =SUMIFS('Faturamento SP3'!$H$2:$H$692,'Faturamento SP3'!$D$2:$D$692,'Infos Relatório'!$B$2,'Faturamento SP3'!$E$2:$E$692,'Infos Relatório'!$B10,'Faturamento SP3'!$Z$2:$Z$692,'Infos Relatório'!O$1) -> 0 | U10: =COUNTIFS('Faturamento SP3'!$D$2:$D$692,'Infos Relatório'!$B$2,'Faturamento SP3'!$E$2:$E$692,'Infos Relatório'!$B10,'Faturamento SP3'!$Z$2:$Z$692,'Infos Relatório'!U$1) -> 0 | V10: =SUMIFS('Faturamento SP3'!$G$2:$G$692,'Faturamento SP3'!$D$2:$D$692,'Infos Relatório'!$B$2,'Faturamento SP3'!$E$2:$E$692,'Infos Relatório'!$B10,'Faturamento SP3'!$Z$2:$Z$692,'Infos Relatório'!U$1) -> 0 | W10: =SUMIFS('Faturamento SP3'!$J$2:$J$692,'Faturamento SP3'!$D$2:$D$692,'Infos Relatório'!$B$2,'Faturamento SP3'!$E$2:$E$692,'Infos Relatório'!$B10,'Faturamento SP3'!$Z$2:$Z$692,'Infos Relatório'!U$1) -> 0 | X10: =SUMIFS('Faturamento SP3'!$O$2:$O$692,'Faturamento SP3'!$D$2:$D$692,'Infos Relatório'!$B$2,'Faturamento SP3'!$E$2:$E$692,'Infos Relatório'!$B10,'Faturamento SP3'!$Z$2:$Z$692,'Infos Relatório'!U$1,'Faturamento SP3'!$T$2:$T$692,"Sim")+SUMIFS('Faturamento SP3'!$P$2:$P$692,'Faturamento SP3'!$D$2:$D$692,'Infos Relatório'!$B$2,'Faturamento SP3'!$E$2:$E$692,'Infos Relatório'!$B10,'Faturamento SP3'!$Z$2:$Z$692,'Infos Relatório'!U$1,'Faturamento SP3'!$T$2:$T$692,"Sim") -> 0 | Y10: =X10/W10 -> #DIV/0! | Z10: =SUMIFS('Faturamento SP3'!$H$2:$H$692,'Faturamento SP3'!$D$2:$D$692,'Infos Relatório'!$B$2,'Faturamento SP3'!$E$2:$E$692,'Infos Relatório'!$B10,'Faturamento SP3'!$Z$2:$Z$692,'Infos Relatório'!U$1) -> 0 | AA10: =COUNTIFS('Faturamento SP3'!$D$2:$D$692,'Infos Relatório'!$B$2,'Faturamento SP3'!$E$2:$E$692,'Infos Relatório'!$B10,'Faturamento SP3'!$Z$2:$Z$692,'Infos Relatório'!AA$1) -> 0 | AB10: =SUMIFS('Faturamento SP3'!$G$2:$G$692,'Faturamento SP3'!$D$2:$D$692,'Infos Relatório'!$B$2,'Faturamento SP3'!$E$2:$E$692,'Infos Relatório'!$B10,'Faturamento SP3'!$Z$2:$Z$692,'Infos Relatório'!AA$1) -> 0 | AC10: =SUMIFS('Faturamento SP3'!$J$2:$J$692,'Faturamento SP3'!$D$2:$D$692,'Infos Relatório'!$B$2,'Faturamento SP3'!$E$2:$E$692,'Infos Relatório'!$B10,'Faturamento SP3'!$Z$2:$Z$692,'Infos Relatório'!AA$1) -> 0 | AD10: =SUMIFS('Faturamento SP3'!$O$2:$O$692,'Faturamento SP3'!$D$2:$D$692,'Infos Relatório'!$B$2,'Faturamento SP3'!$E$2:$E$692,'Infos Relatório'!$B10,'Faturamento SP3'!$Z$2:$Z$692,'Infos Relatório'!AA$1,'Faturamento SP3'!$T$2:$T$692,"Sim")+SUMIFS('Faturamento SP3'!$P$2:$P$692,'Faturamento SP3'!$D$2:$D$692,'Infos Relatório'!$B$2,'Faturamento SP3'!$E$2:$E$692,'Infos Relatório'!$B10,'Faturamento SP3'!$Z$2:$Z$692,'Infos Relatório'!AA$1,'Faturamento SP3'!$T$2:$T$692,"Sim") -> 0 | AE10: =AD10/AC10 -> #DIV/0! | AF10: =SUMIFS('Faturamento SP3'!$H$2:$H$692,'Faturamento SP3'!$D$2:$D$692,'Infos Relatório'!$B$2,'Faturamento SP3'!$E$2:$E$692,'Infos Relatório'!$B10,'Faturamento SP3'!$Z$2:$Z$692,'Infos Relatório'!AA$1) -> 0 | AG10: =COUNTIFS('Faturamento SP3'!$D$2:$D$692,'Infos Relatório'!$B$2,'Faturamento SP3'!$E$2:$E$692,'Infos Relatório'!$B10,'Faturamento SP3'!$Z$2:$Z$692,'Infos Relatório'!AG$1) -> 0 | AH10: =SUMIFS('Faturamento SP3'!$G$2:$G$692,'Faturamento SP3'!$D$2:$D$692,'Infos Relatório'!$B$2,'Faturamento SP3'!$E$2:$E$692,'Infos Relatório'!$B10,'Faturamento SP3'!$Z$2:$Z$692,'Infos Relatório'!AG$1) -> 0 | AI10: =SUMIFS('Faturamento SP3'!$J$2:$J$692,'Faturamento SP3'!$D$2:$D$692,'Infos Relatório'!$B$2,'Faturamento SP3'!$E$2:$E$692,'Infos Relatório'!$B10,'Faturamento SP3'!$Z$2:$Z$692,'Infos Relatório'!AG$1) -> 0 | AJ10: =SUMIFS('Faturamento SP3'!$O$2:$O$692,'Faturamento SP3'!$D$2:$D$692,'Infos Relatório'!$B$2,'Faturamento SP3'!$E$2:$E$692,'Infos Relatório'!$B10,'Faturamento SP3'!$Z$2:$Z$692,'Infos Relatório'!AG$1,'Faturamento SP3'!$T$2:$T$692,"Sim")+SUMIFS('Faturamento SP3'!$P$2:$P$692,'Faturamento SP3'!$D$2:$D$692,'Infos Relatório'!$B$2,'Faturamento SP3'!$E$2:$E$692,'Infos Relatório'!$B10,'Faturamento SP3'!$Z$2:$Z$692,'Infos Relatório'!AG$1,'Faturamento SP3'!$T$2:$T$692,"Sim") -> 0 | AK10: =AJ10/AI10 -> #DIV/0! | AL10: =SUMIFS('Faturamento SP3'!$H$2:$H$692,'Faturamento SP3'!$D$2:$D$692,'Infos Relatório'!$B$2,'Faturamento SP3'!$E$2:$E$692,'Infos Relatório'!$B10,'Faturamento SP3'!$Z$2:$Z$692,'Infos Relatório'!AG$1) -> 0 | AM10: =COUNTIFS('Faturamento SP3'!$D$2:$D$692,'Infos Relatório'!$B$2,'Faturamento SP3'!$E$2:$E$692,'Infos Relatório'!$B10,'Faturamento SP3'!$Z$2:$Z$692,'Infos Relatório'!AM$1) -> 0 | AN10: =SUMIFS('Faturamento SP3'!$G$2:$G$692,'Faturamento SP3'!$D$2:$D$692,'Infos Relatório'!$B$2,'Faturamento SP3'!$E$2:$E$692,'Infos Relatório'!$B10,'Faturamento SP3'!$Z$2:$Z$692,'Infos Relatório'!AM$1) -> 0 | AO10: =SUMIFS('Faturamento SP3'!$J$2:$J$692,'Faturamento SP3'!$D$2:$D$692,'Infos Relatório'!$B$2,'Faturamento SP3'!$E$2:$E$692,'Infos Relatório'!$B10,'Faturamento SP3'!$Z$2:$Z$692,'Infos Relatório'!AM$1) -> 0 | AP10: =SUMIFS('Faturamento SP3'!$O$2:$O$692,'Faturamento SP3'!$D$2:$D$692,'Infos Relatório'!$B$2,'Faturamento SP3'!$E$2:$E$692,'Infos Relatório'!$B10,'Faturamento SP3'!$Z$2:$Z$692,'Infos Relatório'!AM$1,'Faturamento SP3'!$T$2:$T$692,"Sim")+SUMIFS('Faturamento SP3'!$P$2:$P$692,'Faturamento SP3'!$D$2:$D$692,'Infos Relatório'!$B$2,'Faturamento SP3'!$E$2:$E$692,'Infos Relatório'!$B10,'Faturamento SP3'!$Z$2:$Z$692,'Infos Relatório'!AM$1,'Faturamento SP3'!$T$2:$T$692,"Sim") -> 0 | AQ10: =AP10/AO10 -> #DIV/0! | AR10: =SUMIFS('Faturamento SP3'!$H$2:$H$692,'Faturamento SP3'!$D$2:$D$692,'Infos Relatório'!$B$2,'Faturamento SP3'!$E$2:$E$692,'Infos Relatório'!$B10,'Faturamento SP3'!$Z$2:$Z$692,'Infos Relatório'!AM$1) -> 0 | AS10: =COUNTIFS('Faturamento SP3'!$D$2:$D$692,'Infos Relatório'!$B$2,'Faturamento SP3'!$E$2:$E$692,'Infos Relatório'!$B10,'Faturamento SP3'!$Z$2:$Z$692,'Infos Relatório'!AS$1) -> 0 | AT10: =SUMIFS('Faturamento SP3'!$G$2:$G$692,'Faturamento SP3'!$D$2:$D$692,'Infos Relatório'!$B$2,'Faturamento SP3'!$E$2:$E$692,'Infos Relatório'!$B10,'Faturamento SP3'!$Z$2:$Z$692,'Infos Relatório'!AS$1) -> 0 | AU10: =SUMIFS('Faturamento SP3'!$J$2:$J$692,'Faturamento SP3'!$D$2:$D$692,'Infos Relatório'!$B$2,'Faturamento SP3'!$E$2:$E$692,'Infos Relatório'!$B10,'Faturamento SP3'!$Z$2:$Z$692,'Infos Relatório'!AS$1) -> 0 | AV10: =SUMIFS('Faturamento SP3'!$O$2:$O$692,'Faturamento SP3'!$D$2:$D$692,'Infos Relatório'!$B$2,'Faturamento SP3'!$E$2:$E$692,'Infos Relatório'!$B10,'Faturamento SP3'!$Z$2:$Z$692,'Infos Relatório'!AS$1,'Faturamento SP3'!$T$2:$T$692,"Sim")+SUMIFS('Faturamento SP3'!$P$2:$P$692,'Faturamento SP3'!$D$2:$D$692,'Infos Relatório'!$B$2,'Faturamento SP3'!$E$2:$E$692,'Infos Relatório'!$B10,'Faturamento SP3'!$Z$2:$Z$692,'Infos Relatório'!AS$1,'Faturamento SP3'!$T$2:$T$692,"Sim") -> 0 | AW10: =AV10/AU10 -> #DIV/0! | AX10: =SUMIFS('Faturamento SP3'!$H$2:$H$692,'Faturamento SP3'!$D$2:$D$692,'Infos Relatório'!$B$2,'Faturamento SP3'!$E$2:$E$692,'Infos Relatório'!$B10,'Faturamento SP3'!$Z$2:$Z$692,'Infos Relatório'!AS$1) -> 0 | AY10: =COUNTIFS('Faturamento SP3'!$D$2:$D$692,'Infos Relatório'!$B$2,'Faturamento SP3'!$E$2:$E$692,'Infos Relatório'!$B10,'Faturamento SP3'!$Z$2:$Z$692,'Infos Relatório'!AY$1) -> 0 | AZ10: =SUMIFS('Faturamento SP3'!$G$2:$G$692,'Faturamento SP3'!$D$2:$D$692,'Infos Relatório'!$B$2,'Faturamento SP3'!$E$2:$E$692,'Infos Relatório'!$B10,'Faturamento SP3'!$Z$2:$Z$692,'Infos Relatório'!AY$1) -> 0 | BA10: =SUMIFS('Faturamento SP3'!$J$2:$J$692,'Faturamento SP3'!$D$2:$D$692,'Infos Relatório'!$B$2,'Faturamento SP3'!$E$2:$E$692,'Infos Relatório'!$B10,'Faturamento SP3'!$Z$2:$Z$692,'Infos Relatório'!AY$1) -> 0 | BB10: =SUMIFS('Faturamento SP3'!$O$2:$O$692,'Faturamento SP3'!$D$2:$D$692,'Infos Relatório'!$B$2,'Faturamento SP3'!$E$2:$E$692,'Infos Relatório'!$B10,'Faturamento SP3'!$Z$2:$Z$692,'Infos Relatório'!AY$1,'Faturamento SP3'!$T$2:$T$692,"Sim")+SUMIFS('Faturamento SP3'!$P$2:$P$692,'Faturamento SP3'!$D$2:$D$692,'Infos Relatório'!$B$2,'Faturamento SP3'!$E$2:$E$692,'Infos Relatório'!$B10,'Faturamento SP3'!$Z$2:$Z$692,'Infos Relatório'!AY$1,'Faturamento SP3'!$T$2:$T$692,"Sim") -> 0 | BC10: =BB10/BA10 -> #DIV/0! | BD10: =SUMIFS('Faturamento SP3'!$H$2:$H$692,'Faturamento SP3'!$D$2:$D$692,'Infos Relatório'!$B$2,'Faturamento SP3'!$E$2:$E$692,'Infos Relatório'!$B10,'Faturamento SP3'!$Z$2:$Z$692,'Infos Relatório'!AY$1) -> 0 | BE10: =COUNTIFS('Faturamento SP3'!$D$2:$D$692,'Infos Relatório'!$B$2,'Faturamento SP3'!$E$2:$E$692,'Infos Relatório'!$B10,'Faturamento SP3'!$Z$2:$Z$692,'Infos Relatório'!BE$1) -> 0 | BF10: =SUMIFS('Faturamento SP3'!$G$2:$G$692,'Faturamento SP3'!$D$2:$D$692,'Infos Relatório'!$B$2,'Faturamento SP3'!$E$2:$E$692,'Infos Relatório'!$B10,'Faturamento SP3'!$Z$2:$Z$692,'Infos Relatório'!BE$1) -> 0 | BG10: =SUMIFS('Faturamento SP3'!$J$2:$J$692,'Faturamento SP3'!$D$2:$D$692,'Infos Relatório'!$B$2,'Faturamento SP3'!$E$2:$E$692,'Infos Relatório'!$B10,'Faturamento SP3'!$Z$2:$Z$692,'Infos Relatório'!BE$1) -> 0 | BH10: =SUMIFS('Faturamento SP3'!$O$2:$O$692,'Faturamento SP3'!$D$2:$D$692,'Infos Relatório'!$B$2,'Faturamento SP3'!$E$2:$E$692,'Infos Relatório'!$B10,'Faturamento SP3'!$Z$2:$Z$692,'Infos Relatório'!BE$1,'Faturamento SP3'!$T$2:$T$692,"Sim")+SUMIFS('Faturamento SP3'!$P$2:$P$692,'Faturamento SP3'!$D$2:$D$692,'Infos Relatório'!$B$2,'Faturamento SP3'!$E$2:$E$692,'Infos Relatório'!$B10,'Faturamento SP3'!$Z$2:$Z$692,'Infos Relatório'!BE$1,'Faturamento SP3'!$T$2:$T$692,"Sim") -> 0 | BI10: =BH10/BG10 -> #DIV/0! | BJ10: =SUMIFS('Faturamento SP3'!$H$2:$H$692,'Faturamento SP3'!$D$2:$D$692,'Infos Relatório'!$B$2,'Faturamento SP3'!$E$2:$E$692,'Infos Relatório'!$B10,'Faturamento SP3'!$Z$2:$Z$692,'Infos Relatório'!BE$1) -> 0 | BK10: =COUNTIFS('Faturamento SP3'!$D$2:$D$692,'Infos Relatório'!$B$2,'Faturamento SP3'!$E$2:$E$692,'Infos Relatório'!$B10,'Faturamento SP3'!$Z$2:$Z$692,'Infos Relatório'!BK$1) -> 0 | BL10: =SUMIFS('Faturamento SP3'!$G$2:$G$692,'Faturamento SP3'!$D$2:$D$692,'Infos Relatório'!$B$2,'Faturamento SP3'!$E$2:$E$692,'Infos Relatório'!$B10,'Faturamento SP3'!$Z$2:$Z$692,'Infos Relatório'!BK$1) -> 0 | BM10: =SUMIFS('Faturamento SP3'!$J$2:$J$692,'Faturamento SP3'!$D$2:$D$692,'Infos Relatório'!$B$2,'Faturamento SP3'!$E$2:$E$692,'Infos Relatório'!$B10,'Faturamento SP3'!$Z$2:$Z$692,'Infos Relatório'!BK$1) -> 0 | BN10: =SUMIFS('Faturamento SP3'!$O$2:$O$692,'Faturamento SP3'!$D$2:$D$692,'Infos Relatório'!$B$2,'Faturamento SP3'!$E$2:$E$692,'Infos Relatório'!$B10,'Faturamento SP3'!$Z$2:$Z$692,'Infos Relatório'!BK$1,'Faturamento SP3'!$T$2:$T$692,"Sim")+SUMIFS('Faturamento SP3'!$P$2:$P$692,'Faturamento SP3'!$D$2:$D$692,'Infos Relatório'!$B$2,'Faturamento SP3'!$E$2:$E$692,'Infos Relatório'!$B10,'Faturamento SP3'!$Z$2:$Z$692,'Infos Relatório'!BK$1,'Faturamento SP3'!$T$2:$T$692,"Sim") -> 0 | BO10: =BN10/BM10 -> #DIV/0! | BP10: =SUMIFS('Faturamento SP3'!$H$2:$H$692,'Faturamento SP3'!$D$2:$D$692,'Infos Relatório'!$B$2,'Faturamento SP3'!$E$2:$E$692,'Infos Relatório'!$B10,'Faturamento SP3'!$Z$2:$Z$692,'Infos Relatório'!BK$1) -> 0 | BQ10: =COUNTIFS('Faturamento SP3'!$D$2:$D$692,'Infos Relatório'!$B$2,'Faturamento SP3'!$E$2:$E$692,'Infos Relatório'!$B10,'Faturamento SP3'!$Z$2:$Z$692,'Infos Relatório'!BQ$1) -> 0 | BR10: =SUMIFS('Faturamento SP3'!$G$2:$G$692,'Faturamento SP3'!$D$2:$D$692,'Infos Relatório'!$B$2,'Faturamento SP3'!$E$2:$E$692,'Infos Relatório'!$B10,'Faturamento SP3'!$Z$2:$Z$692,'Infos Relatório'!BQ$1) -> 0 | BS10: =SUMIFS('Faturamento SP3'!$J$2:$J$692,'Faturamento SP3'!$D$2:$D$692,'Infos Relatório'!$B$2,'Faturamento SP3'!$E$2:$E$692,'Infos Relatório'!$B10,'Faturamento SP3'!$Z$2:$Z$692,'Infos Relatório'!BQ$1) -> 0 | BT10: =SUMIFS('Faturamento SP3'!$O$2:$O$692,'Faturamento SP3'!$D$2:$D$692,'Infos Relatório'!$B$2,'Faturamento SP3'!$E$2:$E$692,'Infos Relatório'!$B10,'Faturamento SP3'!$Z$2:$Z$692,'Infos Relatório'!BQ$1,'Faturamento SP3'!$T$2:$T$692,"Sim")+SUMIFS('Faturamento SP3'!$P$2:$P$692,'Faturamento SP3'!$D$2:$D$692,'Infos Relatório'!$B$2,'Faturamento SP3'!$E$2:$E$692,'Infos Relatório'!$B10,'Faturamento SP3'!$Z$2:$Z$692,'Infos Relatório'!BQ$1,'Faturamento SP3'!$T$2:$T$692,"Sim") -> 0 | BU10: =BT10/BS10 -> #DIV/0! | BV10: =SUMIFS('Faturamento SP3'!$H$2:$H$692,'Faturamento SP3'!$D$2:$D$692,'Infos Relatório'!$B$2,'Faturamento SP3'!$E$2:$E$692,'Infos Relatório'!$B10,'Faturamento SP3'!$Z$2:$Z$692,'Infos Relatório'!BQ$1) -> 0
B11: Artemp | C11: =COUNTIFS('Faturamento SP3'!$D$2:$D$692,'Infos Relatório'!$B$2,'Faturamento SP3'!$E$2:$E$692,'Infos Relatório'!$B11,'Faturamento SP3'!$Z$2:$Z$692,'Infos Relatório'!C$1) -> 0 | D11: =SUMIFS('Faturamento SP3'!$G$2:$G$692,'Faturamento SP3'!$D$2:$D$692,'Infos Relatório'!$B$2,'Faturamento SP3'!$E$2:$E$692,'Infos Relatório'!$B11,'Faturamento SP3'!$Z$2:$Z$692,'Infos Relatório'!C$1) -> 0 | E11: =SUMIFS('Faturamento SP3'!$J$2:$J$692,'Faturamento SP3'!$D$2:$D$692,'Infos Relatório'!$B$2,'Faturamento SP3'!$E$2:$E$692,'Infos Relatório'!$B11,'Faturamento SP3'!$Z$2:$Z$692,'Infos Relatório'!C$1) -> 0 | F11: =SUMIFS('Faturamento SP3'!$O$2:$O$692,'Faturamento SP3'!$D$2:$D$692,'Infos Relatório'!$B$2,'Faturamento SP3'!$E$2:$E$692,'Infos Relatório'!$B11,'Faturamento SP3'!$Z$2:$Z$692,'Infos Relatório'!C$1,'Faturamento SP3'!$T$2:$T$692,"Sim")+SUMIFS('Faturamento SP3'!$P$2:$P$692,'Faturamento SP3'!$D$2:$D$692,'Infos Relatório'!$B$2,'Faturamento SP3'!$E$2:$E$692,'Infos Relatório'!$B11,'Faturamento SP3'!$Z$2:$Z$692,'Infos Relatório'!C$1,'Faturamento SP3'!$T$2:$T$692,"Sim") -> 0 | G11: =F11/E11 -> #DIV/0! | H11: =SUMIFS('Faturamento SP3'!$H$2:$H$692,'Faturamento SP3'!$D$2:$D$692,'Infos Relatório'!$B$2,'Faturamento SP3'!$E$2:$E$692,'Infos Relatório'!$B11,'Faturamento SP3'!$Z$2:$Z$692,'Infos Relatório'!C$1) -> 0 | I11: =COUNTIFS('Faturamento SP3'!$D$2:$D$692,'Infos Relatório'!$B$2,'Faturamento SP3'!$E$2:$E$692,'Infos Relatório'!$B11,'Faturamento SP3'!$Z$2:$Z$692,'Infos Relatório'!I$1) -> 0 | J11: =SUMIFS('Faturamento SP3'!$G$2:$G$692,'Faturamento SP3'!$D$2:$D$692,'Infos Relatório'!$B$2,'Faturamento SP3'!$E$2:$E$692,'Infos Relatório'!$B11,'Faturamento SP3'!$Z$2:$Z$692,'Infos Relatório'!I$1) -> 0 | K11: =SUMIFS('Faturamento SP3'!$J$2:$J$692,'Faturamento SP3'!$D$2:$D$692,'Infos Relatório'!$B$2,'Faturamento SP3'!$E$2:$E$692,'Infos Relatório'!$B11,'Faturamento SP3'!$Z$2:$Z$692,'Infos Relatório'!I$1) -> 0 | L11: =SUMIFS('Faturamento SP3'!$O$2:$O$692,'Faturamento SP3'!$D$2:$D$692,'Infos Relatório'!$B$2,'Faturamento SP3'!$E$2:$E$692,'Infos Relatório'!$B11,'Faturamento SP3'!$Z$2:$Z$692,'Infos Relatório'!I$1,'Faturamento SP3'!$T$2:$T$692,"Sim")+SUMIFS('Faturamento SP3'!$P$2:$P$692,'Faturamento SP3'!$D$2:$D$692,'Infos Relatório'!$B$2,'Faturamento SP3'!$E$2:$E$692,'Infos Relatório'!$B11,'Faturamento SP3'!$Z$2:$Z$692,'Infos Relatório'!I$1,'Faturamento SP3'!$T$2:$T$692,"Sim") -> 0 | M11: =L11/K11 -> #DIV/0! | N11: =SUMIFS('Faturamento SP3'!$H$2:$H$692,'Faturamento SP3'!$D$2:$D$692,'Infos Relatório'!$B$2,'Faturamento SP3'!$E$2:$E$692,'Infos Relatório'!$B11,'Faturamento SP3'!$Z$2:$Z$692,'Infos Relatório'!I$1) -> 0 | O11: =COUNTIFS('Faturamento SP3'!$D$2:$D$692,'Infos Relatório'!$B$2,'Faturamento SP3'!$E$2:$E$692,'Infos Relatório'!$B11,'Faturamento SP3'!$Z$2:$Z$692,'Infos Relatório'!O$1) -> 0 | P11: =SUMIFS('Faturamento SP3'!$G$2:$G$692,'Faturamento SP3'!$D$2:$D$692,'Infos Relatório'!$B$2,'Faturamento SP3'!$E$2:$E$692,'Infos Relatório'!$B11,'Faturamento SP3'!$Z$2:$Z$692,'Infos Relatório'!O$1) -> 0 | Q11: =SUMIFS('Faturamento SP3'!$J$2:$J$692,'Faturamento SP3'!$D$2:$D$692,'Infos Relatório'!$B$2,'Faturamento SP3'!$E$2:$E$692,'Infos Relatório'!$B11,'Faturamento SP3'!$Z$2:$Z$692,'Infos Relatório'!O$1) -> 0 | R11: =SUMIFS('Faturamento SP3'!$O$2:$O$692,'Faturamento SP3'!$D$2:$D$692,'Infos Relatório'!$B$2,'Faturamento SP3'!$E$2:$E$692,'Infos Relatório'!$B11,'Faturamento SP3'!$Z$2:$Z$692,'Infos Relatório'!O$1,'Faturamento SP3'!$T$2:$T$692,"Sim")+SUMIFS('Faturamento SP3'!$P$2:$P$692,'Faturamento SP3'!$D$2:$D$692,'Infos Relatório'!$B$2,'Faturamento SP3'!$E$2:$E$692,'Infos Relatório'!$B11,'Faturamento SP3'!$Z$2:$Z$692,'Infos Relatório'!O$1,'Faturamento SP3'!$T$2:$T$692,"Sim") -> 0 | S11: =R11/Q11 -> #DIV/0! | T11: =SUMIFS('Faturamento SP3'!$H$2:$H$692,'Faturamento SP3'!$D$2:$D$692,'Infos Relatório'!$B$2,'Faturamento SP3'!$E$2:$E$692,'Infos Relatório'!$B11,'Faturamento SP3'!$Z$2:$Z$692,'Infos Relatório'!O$1) -> 0 | U11: =COUNTIFS('Faturamento SP3'!$D$2:$D$692,'Infos Relatório'!$B$2,'Faturamento SP3'!$E$2:$E$692,'Infos Relatório'!$B11,'Faturamento SP3'!$Z$2:$Z$692,'Infos Relatório'!U$1) -> 0 | V11: =SUMIFS('Faturamento SP3'!$G$2:$G$692,'Faturamento SP3'!$D$2:$D$692,'Infos Relatório'!$B$2,'Faturamento SP3'!$E$2:$E$692,'Infos Relatório'!$B11,'Faturamento SP3'!$Z$2:$Z$692,'Infos Relatório'!U$1) -> 0 | W11: =SUMIFS('Faturamento SP3'!$J$2:$J$692,'Faturamento SP3'!$D$2:$D$692,'Infos Relatório'!$B$2,'Faturamento SP3'!$E$2:$E$692,'Infos Relatório'!$B11,'Faturamento SP3'!$Z$2:$Z$692,'Infos Relatório'!U$1) -> 0 | X11: =SUMIFS('Faturamento SP3'!$O$2:$O$692,'Faturamento SP3'!$D$2:$D$692,'Infos Relatório'!$B$2,'Faturamento SP3'!$E$2:$E$692,'Infos Relatório'!$B11,'Faturamento SP3'!$Z$2:$Z$692,'Infos Relatório'!U$1,'Faturamento SP3'!$T$2:$T$692,"Sim")+SUMIFS('Faturamento SP3'!$P$2:$P$692,'Faturamento SP3'!$D$2:$D$692,'Infos Relatório'!$B$2,'Faturamento SP3'!$E$2:$E$692,'Infos Relatório'!$B11,'Faturamento SP3'!$Z$2:$Z$692,'Infos Relatório'!U$1,'Faturamento SP3'!$T$2:$T$692,"Sim") -> 0 | Y11: =X11/W11 -> #DIV/0! | Z11: =SUMIFS('Faturamento SP3'!$H$2:$H$692,'Faturamento SP3'!$D$2:$D$692,'Infos Relatório'!$B$2,'Faturamento SP3'!$E$2:$E$692,'Infos Relatório'!$B11,'Faturamento SP3'!$Z$2:$Z$692,'Infos Relatório'!U$1) -> 0 | AA11: =COUNTIFS('Faturamento SP3'!$D$2:$D$692,'Infos Relatório'!$B$2,'Faturamento SP3'!$E$2:$E$692,'Infos Relatório'!$B11,'Faturamento SP3'!$Z$2:$Z$692,'Infos Relatório'!AA$1) -> 0 | AB11: =SUMIFS('Faturamento SP3'!$G$2:$G$692,'Faturamento SP3'!$D$2:$D$692,'Infos Relatório'!$B$2,'Faturamento SP3'!$E$2:$E$692,'Infos Relatório'!$B11,'Faturamento SP3'!$Z$2:$Z$692,'Infos Relatório'!AA$1) -> 0 | AC11: =SUMIFS('Faturamento SP3'!$J$2:$J$692,'Faturamento SP3'!$D$2:$D$692,'Infos Relatório'!$B$2,'Faturamento SP3'!$E$2:$E$692,'Infos Relatório'!$B11,'Faturamento SP3'!$Z$2:$Z$692,'Infos Relatório'!AA$1) -> 0 | AD11: =SUMIFS('Faturamento SP3'!$O$2:$O$692,'Faturamento SP3'!$D$2:$D$692,'Infos Relatório'!$B$2,'Faturamento SP3'!$E$2:$E$692,'Infos Relatório'!$B11,'Faturamento SP3'!$Z$2:$Z$692,'Infos Relatório'!AA$1,'Faturamento SP3'!$T$2:$T$692,"Sim")+SUMIFS('Faturamento SP3'!$P$2:$P$692,'Faturamento SP3'!$D$2:$D$692,'Infos Relatório'!$B$2,'Faturamento SP3'!$E$2:$E$692,'Infos Relatório'!$B11,'Faturamento SP3'!$Z$2:$Z$692,'Infos Relatório'!AA$1,'Faturamento SP3'!$T$2:$T$692,"Sim") -> 0 | AE11: =AD11/AC11 -> #DIV/0! | AF11: =SUMIFS('Faturamento SP3'!$H$2:$H$692,'Faturamento SP3'!$D$2:$D$692,'Infos Relatório'!$B$2,'Faturamento SP3'!$E$2:$E$692,'Infos Relatório'!$B11,'Faturamento SP3'!$Z$2:$Z$692,'Infos Relatório'!AA$1) -> 0 | AG11: =COUNTIFS('Faturamento SP3'!$D$2:$D$692,'Infos Relatório'!$B$2,'Faturamento SP3'!$E$2:$E$692,'Infos Relatório'!$B11,'Faturamento SP3'!$Z$2:$Z$692,'Infos Relatório'!AG$1) -> 0 | AH11: =SUMIFS('Faturamento SP3'!$G$2:$G$692,'Faturamento SP3'!$D$2:$D$692,'Infos Relatório'!$B$2,'Faturamento SP3'!$E$2:$E$692,'Infos Relatório'!$B11,'Faturamento SP3'!$Z$2:$Z$692,'Infos Relatório'!AG$1) -> 0 | AI11: =SUMIFS('Faturamento SP3'!$J$2:$J$692,'Faturamento SP3'!$D$2:$D$692,'Infos Relatório'!$B$2,'Faturamento SP3'!$E$2:$E$692,'Infos Relatório'!$B11,'Faturamento SP3'!$Z$2:$Z$692,'Infos Relatório'!AG$1) -> 0 | AJ11: =SUMIFS('Faturamento SP3'!$O$2:$O$692,'Faturamento SP3'!$D$2:$D$692,'Infos Relatório'!$B$2,'Faturamento SP3'!$E$2:$E$692,'Infos Relatório'!$B11,'Faturamento SP3'!$Z$2:$Z$692,'Infos Relatório'!AG$1,'Faturamento SP3'!$T$2:$T$692,"Sim")+SUMIFS('Faturamento SP3'!$P$2:$P$692,'Faturamento SP3'!$D$2:$D$692,'Infos Relatório'!$B$2,'Faturamento SP3'!$E$2:$E$692,'Infos Relatório'!$B11,'Faturamento SP3'!$Z$2:$Z$692,'Infos Relatório'!AG$1,'Faturamento SP3'!$T$2:$T$692,"Sim") -> 0 | AK11: =AJ11/AI11 -> #DIV/0! | AL11: =SUMIFS('Faturamento SP3'!$H$2:$H$692,'Faturamento SP3'!$D$2:$D$692,'Infos Relatório'!$B$2,'Faturamento SP3'!$E$2:$E$692,'Infos Relatório'!$B11,'Faturamento SP3'!$Z$2:$Z$692,'Infos Relatório'!AG$1) -> 0 | AM11: =COUNTIFS('Faturamento SP3'!$D$2:$D$692,'Infos Relatório'!$B$2,'Faturamento SP3'!$E$2:$E$692,'Infos Relatório'!$B11,'Faturamento SP3'!$Z$2:$Z$692,'Infos Relatório'!AM$1) -> 0 | AN11: =SUMIFS('Faturamento SP3'!$G$2:$G$692,'Faturamento SP3'!$D$2:$D$692,'Infos Relatório'!$B$2,'Faturamento SP3'!$E$2:$E$692,'Infos Relatório'!$B11,'Faturamento SP3'!$Z$2:$Z$692,'Infos Relatório'!AM$1) -> 0 | AO11: =SUMIFS('Faturamento SP3'!$J$2:$J$692,'Faturamento SP3'!$D$2:$D$692,'Infos Relatório'!$B$2,'Faturamento SP3'!$E$2:$E$692,'Infos Relatório'!$B11,'Faturamento SP3'!$Z$2:$Z$692,'Infos Relatório'!AM$1) -> 0 | AP11: =SUMIFS('Faturamento SP3'!$O$2:$O$692,'Faturamento SP3'!$D$2:$D$692,'Infos Relatório'!$B$2,'Faturamento SP3'!$E$2:$E$692,'Infos Relatório'!$B11,'Faturamento SP3'!$Z$2:$Z$692,'Infos Relatório'!AM$1,'Faturamento SP3'!$T$2:$T$692,"Sim")+SUMIFS('Faturamento SP3'!$P$2:$P$692,'Faturamento SP3'!$D$2:$D$692,'Infos Relatório'!$B$2,'Faturamento SP3'!$E$2:$E$692,'Infos Relatório'!$B11,'Faturamento SP3'!$Z$2:$Z$692,'Infos Relatório'!AM$1,'Faturamento SP3'!$T$2:$T$692,"Sim") -> 0 | AQ11: =AP11/AO11 -> #DIV/0! | AR11: =SUMIFS('Faturamento SP3'!$H$2:$H$692,'Faturamento SP3'!$D$2:$D$692,'Infos Relatório'!$B$2,'Faturamento SP3'!$E$2:$E$692,'Infos Relatório'!$B11,'Faturamento SP3'!$Z$2:$Z$692,'Infos Relatório'!AM$1) -> 0 | AS11: =COUNTIFS('Faturamento SP3'!$D$2:$D$692,'Infos Relatório'!$B$2,'Faturamento SP3'!$E$2:$E$692,'Infos Relatório'!$B11,'Faturamento SP3'!$Z$2:$Z$692,'Infos Relatório'!AS$1) -> 0 | AT11: =SUMIFS('Faturamento SP3'!$G$2:$G$692,'Faturamento SP3'!$D$2:$D$692,'Infos Relatório'!$B$2,'Faturamento SP3'!$E$2:$E$692,'Infos Relatório'!$B11,'Faturamento SP3'!$Z$2:$Z$692,'Infos Relatório'!AS$1) -> 0 | AU11: =SUMIFS('Faturamento SP3'!$J$2:$J$692,'Faturamento SP3'!$D$2:$D$692,'Infos Relatório'!$B$2,'Faturamento SP3'!$E$2:$E$692,'Infos Relatório'!$B11,'Faturamento SP3'!$Z$2:$Z$692,'Infos Relatório'!AS$1) -> 0 | AV11: =SUMIFS('Faturamento SP3'!$O$2:$O$692,'Faturamento SP3'!$D$2:$D$692,'Infos Relatório'!$B$2,'Faturamento SP3'!$E$2:$E$692,'Infos Relatório'!$B11,'Faturamento SP3'!$Z$2:$Z$692,'Infos Relatório'!AS$1,'Faturamento SP3'!$T$2:$T$692,"Sim")+SUMIFS('Faturamento SP3'!$P$2:$P$692,'Faturamento SP3'!$D$2:$D$692,'Infos Relatório'!$B$2,'Faturamento SP3'!$E$2:$E$692,'Infos Relatório'!$B11,'Faturamento SP3'!$Z$2:$Z$692,'Infos Relatório'!AS$1,'Faturamento SP3'!$T$2:$T$692,"Sim") -> 0 | AW11: =AV11/AU11 -> #DIV/0! | AX11: =SUMIFS('Faturamento SP3'!$H$2:$H$692,'Faturamento SP3'!$D$2:$D$692,'Infos Relatório'!$B$2,'Faturamento SP3'!$E$2:$E$692,'Infos Relatório'!$B11,'Faturamento SP3'!$Z$2:$Z$692,'Infos Relatório'!AS$1) -> 0 | AY11: =COUNTIFS('Faturamento SP3'!$D$2:$D$692,'Infos Relatório'!$B$2,'Faturamento SP3'!$E$2:$E$692,'Infos Relatório'!$B11,'Faturamento SP3'!$Z$2:$Z$692,'Infos Relatório'!AY$1) -> 0 | AZ11: =SUMIFS('Faturamento SP3'!$G$2:$G$692,'Faturamento SP3'!$D$2:$D$692,'Infos Relatório'!$B$2,'Faturamento SP3'!$E$2:$E$692,'Infos Relatório'!$B11,'Faturamento SP3'!$Z$2:$Z$692,'Infos Relatório'!AY$1) -> 0 | BA11: =SUMIFS('Faturamento SP3'!$J$2:$J$692,'Faturamento SP3'!$D$2:$D$692,'Infos Relatório'!$B$2,'Faturamento SP3'!$E$2:$E$692,'Infos Relatório'!$B11,'Faturamento SP3'!$Z$2:$Z$692,'Infos Relatório'!AY$1) -> 0 | BB11: =SUMIFS('Faturamento SP3'!$O$2:$O$692,'Faturamento SP3'!$D$2:$D$692,'Infos Relatório'!$B$2,'Faturamento SP3'!$E$2:$E$692,'Infos Relatório'!$B11,'Faturamento SP3'!$Z$2:$Z$692,'Infos Relatório'!AY$1,'Faturamento SP3'!$T$2:$T$692,"Sim")+SUMIFS('Faturamento SP3'!$P$2:$P$692,'Faturamento SP3'!$D$2:$D$692,'Infos Relatório'!$B$2,'Faturamento SP3'!$E$2:$E$692,'Infos Relatório'!$B11,'Faturamento SP3'!$Z$2:$Z$692,'Infos Relatório'!AY$1,'Faturamento SP3'!$T$2:$T$692,"Sim") -> 0 | BC11: =BB11/BA11 -> #DIV/0! | BD11: =SUMIFS('Faturamento SP3'!$H$2:$H$692,'Faturamento SP3'!$D$2:$D$692,'Infos Relatório'!$B$2,'Faturamento SP3'!$E$2:$E$692,'Infos Relatório'!$B11,'Faturamento SP3'!$Z$2:$Z$692,'Infos Relatório'!AY$1) -> 0 | BE11: =COUNTIFS('Faturamento SP3'!$D$2:$D$692,'Infos Relatório'!$B$2,'Faturamento SP3'!$E$2:$E$692,'Infos Relatório'!$B11,'Faturamento SP3'!$Z$2:$Z$692,'Infos Relatório'!BE$1) -> 0 | BF11: =SUMIFS('Faturamento SP3'!$G$2:$G$692,'Faturamento SP3'!$D$2:$D$692,'Infos Relatório'!$B$2,'Faturamento SP3'!$E$2:$E$692,'Infos Relatório'!$B11,'Faturamento SP3'!$Z$2:$Z$692,'Infos Relatório'!BE$1) -> 0 | BG11: =SUMIFS('Faturamento SP3'!$J$2:$J$692,'Faturamento SP3'!$D$2:$D$692,'Infos Relatório'!$B$2,'Faturamento SP3'!$E$2:$E$692,'Infos Relatório'!$B11,'Faturamento SP3'!$Z$2:$Z$692,'Infos Relatório'!BE$1) -> 0 | BH11: =SUMIFS('Faturamento SP3'!$O$2:$O$692,'Faturamento SP3'!$D$2:$D$692,'Infos Relatório'!$B$2,'Faturamento SP3'!$E$2:$E$692,'Infos Relatório'!$B11,'Faturamento SP3'!$Z$2:$Z$692,'Infos Relatório'!BE$1,'Faturamento SP3'!$T$2:$T$692,"Sim")+SUMIFS('Faturamento SP3'!$P$2:$P$692,'Faturamento SP3'!$D$2:$D$692,'Infos Relatório'!$B$2,'Faturamento SP3'!$E$2:$E$692,'Infos Relatório'!$B11,'Faturamento SP3'!$Z$2:$Z$692,'Infos Relatório'!BE$1,'Faturamento SP3'!$T$2:$T$692,"Sim") -> 0 | BI11: =BH11/BG11 -> #DIV/0! | BJ11: =SUMIFS('Faturamento SP3'!$H$2:$H$692,'Faturamento SP3'!$D$2:$D$692,'Infos Relatório'!$B$2,'Faturamento SP3'!$E$2:$E$692,'Infos Relatório'!$B11,'Faturamento SP3'!$Z$2:$Z$692,'Infos Relatório'!BE$1) -> 0 | BK11: =COUNTIFS('Faturamento SP3'!$D$2:$D$692,'Infos Relatório'!$B$2,'Faturamento SP3'!$E$2:$E$692,'Infos Relatório'!$B11,'Faturamento SP3'!$Z$2:$Z$692,'Infos Relatório'!BK$1) -> 0 | BL11: =SUMIFS('Faturamento SP3'!$G$2:$G$692,'Faturamento SP3'!$D$2:$D$692,'Infos Relatório'!$B$2,'Faturamento SP3'!$E$2:$E$692,'Infos Relatório'!$B11,'Faturamento SP3'!$Z$2:$Z$692,'Infos Relatório'!BK$1) -> 0 | BM11: =SUMIFS('Faturamento SP3'!$J$2:$J$692,'Faturamento SP3'!$D$2:$D$692,'Infos Relatório'!$B$2,'Faturamento SP3'!$E$2:$E$692,'Infos Relatório'!$B11,'Faturamento SP3'!$Z$2:$Z$692,'Infos Relatório'!BK$1) -> 0 | BN11: =SUMIFS('Faturamento SP3'!$O$2:$O$692,'Faturamento SP3'!$D$2:$D$692,'Infos Relatório'!$B$2,'Faturamento SP3'!$E$2:$E$692,'Infos Relatório'!$B11,'Faturamento SP3'!$Z$2:$Z$692,'Infos Relatório'!BK$1,'Faturamento SP3'!$T$2:$T$692,"Sim")+SUMIFS('Faturamento SP3'!$P$2:$P$692,'Faturamento SP3'!$D$2:$D$692,'Infos Relatório'!$B$2,'Faturamento SP3'!$E$2:$E$692,'Infos Relatório'!$B11,'Faturamento SP3'!$Z$2:$Z$692,'Infos Relatório'!BK$1,'Faturamento SP3'!$T$2:$T$692,"Sim") -> 0 | BO11: =BN11/BM11 -> #DIV/0! | BP11: =SUMIFS('Faturamento SP3'!$H$2:$H$692,'Faturamento SP3'!$D$2:$D$692,'Infos Relatório'!$B$2,'Faturamento SP3'!$E$2:$E$692,'Infos Relatório'!$B11,'Faturamento SP3'!$Z$2:$Z$692,'Infos Relatório'!BK$1) -> 0 | BQ11: =COUNTIFS('Faturamento SP3'!$D$2:$D$692,'Infos Relatório'!$B$2,'Faturamento SP3'!$E$2:$E$692,'Infos Relatório'!$B11,'Faturamento SP3'!$Z$2:$Z$692,'Infos Relatório'!BQ$1) -> 0 | BR11: =SUMIFS('Faturamento SP3'!$G$2:$G$692,'Faturamento SP3'!$D$2:$D$692,'Infos Relatório'!$B$2,'Faturamento SP3'!$E$2:$E$692,'Infos Relatório'!$B11,'Faturamento SP3'!$Z$2:$Z$692,'Infos Relatório'!BQ$1) -> 0 | BS11: =SUMIFS('Faturamento SP3'!$J$2:$J$692,'Faturamento SP3'!$D$2:$D$692,'Infos Relatório'!$B$2,'Faturamento SP3'!$E$2:$E$692,'Infos Relatório'!$B11,'Faturamento SP3'!$Z$2:$Z$692,'Infos Relatório'!BQ$1) -> 0 | BT11: =SUMIFS('Faturamento SP3'!$O$2:$O$692,'Faturamento SP3'!$D$2:$D$692,'Infos Relatório'!$B$2,'Faturamento SP3'!$E$2:$E$692,'Infos Relatório'!$B11,'Faturamento SP3'!$Z$2:$Z$692,'Infos Relatório'!BQ$1,'Faturamento SP3'!$T$2:$T$692,"Sim")+SUMIFS('Faturamento SP3'!$P$2:$P$692,'Faturamento SP3'!$D$2:$D$692,'Infos Relatório'!$B$2,'Faturamento SP3'!$E$2:$E$692,'Infos Relatório'!$B11,'Faturamento SP3'!$Z$2:$Z$692,'Infos Relatório'!BQ$1,'Faturamento SP3'!$T$2:$T$692,"Sim") -> 0 | BU11: =BT11/BS11 -> #DIV/0! | BV11: =SUMIFS('Faturamento SP3'!$H$2:$H$692,'Faturamento SP3'!$D$2:$D$692,'Infos Relatório'!$B$2,'Faturamento SP3'!$E$2:$E$692,'Infos Relatório'!$B11,'Faturamento SP3'!$Z$2:$Z$692,'Infos Relatório'!BQ$1) -> 0
B12: BM Serviços de Jardinagem | C12: =COUNTIFS('Faturamento SP3'!$D$2:$D$692,'Infos Relatório'!$B$2,'Faturamento SP3'!$E$2:$E$692,'Infos Relatório'!$B12,'Faturamento SP3'!$Z$2:$Z$692,'Infos Relatório'!C$1) -> 0 | D12: =SUMIFS('Faturamento SP3'!$G$2:$G$692,'Faturamento SP3'!$D$2:$D$692,'Infos Relatório'!$B$2,'Faturamento SP3'!$E$2:$E$692,'Infos Relatório'!$B12,'Faturamento SP3'!$Z$2:$Z$692,'Infos Relatório'!C$1) -> 0 | E12: =SUMIFS('Faturamento SP3'!$J$2:$J$692,'Faturamento SP3'!$D$2:$D$692,'Infos Relatório'!$B$2,'Faturamento SP3'!$E$2:$E$692,'Infos Relatório'!$B12,'Faturamento SP3'!$Z$2:$Z$692,'Infos Relatório'!C$1) -> 0 | F12: =SUMIFS('Faturamento SP3'!$O$2:$O$692,'Faturamento SP3'!$D$2:$D$692,'Infos Relatório'!$B$2,'Faturamento SP3'!$E$2:$E$692,'Infos Relatório'!$B12,'Faturamento SP3'!$Z$2:$Z$692,'Infos Relatório'!C$1,'Faturamento SP3'!$T$2:$T$692,"Sim")+SUMIFS('Faturamento SP3'!$P$2:$P$692,'Faturamento SP3'!$D$2:$D$692,'Infos Relatório'!$B$2,'Faturamento SP3'!$E$2:$E$692,'Infos Relatório'!$B12,'Faturamento SP3'!$Z$2:$Z$692,'Infos Relatório'!C$1,'Faturamento SP3'!$T$2:$T$692,"Sim") -> 0 | G12: =F12/E12 -> #DIV/0! | H12: =SUMIFS('Faturamento SP3'!$H$2:$H$692,'Faturamento SP3'!$D$2:$D$692,'Infos Relatório'!$B$2,'Faturamento SP3'!$E$2:$E$692,'Infos Relatório'!$B12,'Faturamento SP3'!$Z$2:$Z$692,'Infos Relatório'!C$1) -> 0 | I12: =COUNTIFS('Faturamento SP3'!$D$2:$D$692,'Infos Relatório'!$B$2,'Faturamento SP3'!$E$2:$E$692,'Infos Relatório'!$B12,'Faturamento SP3'!$Z$2:$Z$692,'Infos Relatório'!I$1) -> 0 | J12: =SUMIFS('Faturamento SP3'!$G$2:$G$692,'Faturamento SP3'!$D$2:$D$692,'Infos Relatório'!$B$2,'Faturamento SP3'!$E$2:$E$692,'Infos Relatório'!$B12,'Faturamento SP3'!$Z$2:$Z$692,'Infos Relatório'!I$1) -> 0 | K12: =SUMIFS('Faturamento SP3'!$J$2:$J$692,'Faturamento SP3'!$D$2:$D$692,'Infos Relatório'!$B$2,'Faturamento SP3'!$E$2:$E$692,'Infos Relatório'!$B12,'Faturamento SP3'!$Z$2:$Z$692,'Infos Relatório'!I$1) -> 0 | L12: =SUMIFS('Faturamento SP3'!$O$2:$O$692,'Faturamento SP3'!$D$2:$D$692,'Infos Relatório'!$B$2,'Faturamento SP3'!$E$2:$E$692,'Infos Relatório'!$B12,'Faturamento SP3'!$Z$2:$Z$692,'Infos Relatório'!I$1,'Faturamento SP3'!$T$2:$T$692,"Sim")+SUMIFS('Faturamento SP3'!$P$2:$P$692,'Faturamento SP3'!$D$2:$D$692,'Infos Relatório'!$B$2,'Faturamento SP3'!$E$2:$E$692,'Infos Relatório'!$B12,'Faturamento SP3'!$Z$2:$Z$692,'Infos Relatório'!I$1,'Faturamento SP3'!$T$2:$T$692,"Sim") -> 0 | M12: =L12/K12 -> #DIV/0! | N12: =SUMIFS('Faturamento SP3'!$H$2:$H$692,'Faturamento SP3'!$D$2:$D$692,'Infos Relatório'!$B$2,'Faturamento SP3'!$E$2:$E$692,'Infos Relatório'!$B12,'Faturamento SP3'!$Z$2:$Z$692,'Infos Relatório'!I$1) -> 0 | O12: =COUNTIFS('Faturamento SP3'!$D$2:$D$692,'Infos Relatório'!$B$2,'Faturamento SP3'!$E$2:$E$692,'Infos Relatório'!$B12,'Faturamento SP3'!$Z$2:$Z$692,'Infos Relatório'!O$1) -> 0 | P12: =SUMIFS('Faturamento SP3'!$G$2:$G$692,'Faturamento SP3'!$D$2:$D$692,'Infos Relatório'!$B$2,'Faturamento SP3'!$E$2:$E$692,'Infos Relatório'!$B12,'Faturamento SP3'!$Z$2:$Z$692,'Infos Relatório'!O$1) -> 0 | Q12: =SUMIFS('Faturamento SP3'!$J$2:$J$692,'Faturamento SP3'!$D$2:$D$692,'Infos Relatório'!$B$2,'Faturamento SP3'!$E$2:$E$692,'Infos Relatório'!$B12,'Faturamento SP3'!$Z$2:$Z$692,'Infos Relatório'!O$1) -> 0 | R12: =SUMIFS('Faturamento SP3'!$O$2:$O$692,'Faturamento SP3'!$D$2:$D$692,'Infos Relatório'!$B$2,'Faturamento SP3'!$E$2:$E$692,'Infos Relatório'!$B12,'Faturamento SP3'!$Z$2:$Z$692,'Infos Relatório'!O$1,'Faturamento SP3'!$T$2:$T$692,"Sim")+SUMIFS('Faturamento SP3'!$P$2:$P$692,'Faturamento SP3'!$D$2:$D$692,'Infos Relatório'!$B$2,'Faturamento SP3'!$E$2:$E$692,'Infos Relatório'!$B12,'Faturamento SP3'!$Z$2:$Z$692,'Infos Relatório'!O$1,'Faturamento SP3'!$T$2:$T$692,"Sim") -> 0 | S12: =R12/Q12 -> #DIV/0! | T12: =SUMIFS('Faturamento SP3'!$H$2:$H$692,'Faturamento SP3'!$D$2:$D$692,'Infos Relatório'!$B$2,'Faturamento SP3'!$E$2:$E$692,'Infos Relatório'!$B12,'Faturamento SP3'!$Z$2:$Z$692,'Infos Relatório'!O$1) -> 0 | U12: =COUNTIFS('Faturamento SP3'!$D$2:$D$692,'Infos Relatório'!$B$2,'Faturamento SP3'!$E$2:$E$692,'Infos Relatório'!$B12,'Faturamento SP3'!$Z$2:$Z$692,'Infos Relatório'!U$1) -> 0 | V12: =SUMIFS('Faturamento SP3'!$G$2:$G$692,'Faturamento SP3'!$D$2:$D$692,'Infos Relatório'!$B$2,'Faturamento SP3'!$E$2:$E$692,'Infos Relatório'!$B12,'Faturamento SP3'!$Z$2:$Z$692,'Infos Relatório'!U$1) -> 0 | W12: =SUMIFS('Faturamento SP3'!$J$2:$J$692,'Faturamento SP3'!$D$2:$D$692,'Infos Relatório'!$B$2,'Faturamento SP3'!$E$2:$E$692,'Infos Relatório'!$B12,'Faturamento SP3'!$Z$2:$Z$692,'Infos Relatório'!U$1) -> 0 | X12: =SUMIFS('Faturamento SP3'!$O$2:$O$692,'Faturamento SP3'!$D$2:$D$692,'Infos Relatório'!$B$2,'Faturamento SP3'!$E$2:$E$692,'Infos Relatório'!$B12,'Faturamento SP3'!$Z$2:$Z$692,'Infos Relatório'!U$1,'Faturamento SP3'!$T$2:$T$692,"Sim")+SUMIFS('Faturamento SP3'!$P$2:$P$692,'Faturamento SP3'!$D$2:$D$692,'Infos Relatório'!$B$2,'Faturamento SP3'!$E$2:$E$692,'Infos Relatório'!$B12,'Faturamento SP3'!$Z$2:$Z$692,'Infos Relatório'!U$1,'Faturamento SP3'!$T$2:$T$692,"Sim") -> 0 | Y12: =X12/W12 -> #DIV/0! | Z12: =SUMIFS('Faturamento SP3'!$H$2:$H$692,'Faturamento SP3'!$D$2:$D$692,'Infos Relatório'!$B$2,'Faturamento SP3'!$E$2:$E$692,'Infos Relatório'!$B12,'Faturamento SP3'!$Z$2:$Z$692,'Infos Relatório'!U$1) -> 0 | AA12: =COUNTIFS('Faturamento SP3'!$D$2:$D$692,'Infos Relatório'!$B$2,'Faturamento SP3'!$E$2:$E$692,'Infos Relatório'!$B12,'Faturamento SP3'!$Z$2:$Z$692,'Infos Relatório'!AA$1) -> 0 | AB12: =SUMIFS('Faturamento SP3'!$G$2:$G$692,'Faturamento SP3'!$D$2:$D$692,'Infos Relatório'!$B$2,'Faturamento SP3'!$E$2:$E$692,'Infos Relatório'!$B12,'Faturamento SP3'!$Z$2:$Z$692,'Infos Relatório'!AA$1) -> 0 | AC12: =SUMIFS('Faturamento SP3'!$J$2:$J$692,'Faturamento SP3'!$D$2:$D$692,'Infos Relatório'!$B$2,'Faturamento SP3'!$E$2:$E$692,'Infos Relatório'!$B12,'Faturamento SP3'!$Z$2:$Z$692,'Infos Relatório'!AA$1) -> 0 | AD12: =SUMIFS('Faturamento SP3'!$O$2:$O$692,'Faturamento SP3'!$D$2:$D$692,'Infos Relatório'!$B$2,'Faturamento SP3'!$E$2:$E$692,'Infos Relatório'!$B12,'Faturamento SP3'!$Z$2:$Z$692,'Infos Relatório'!AA$1,'Faturamento SP3'!$T$2:$T$692,"Sim")+SUMIFS('Faturamento SP3'!$P$2:$P$692,'Faturamento SP3'!$D$2:$D$692,'Infos Relatório'!$B$2,'Faturamento SP3'!$E$2:$E$692,'Infos Relatório'!$B12,'Faturamento SP3'!$Z$2:$Z$692,'Infos Relatório'!AA$1,'Faturamento SP3'!$T$2:$T$692,"Sim") -> 0 | AE12: =AD12/AC12 -> #DIV/0! | AF12: =SUMIFS('Faturamento SP3'!$H$2:$H$692,'Faturamento SP3'!$D$2:$D$692,'Infos Relatório'!$B$2,'Faturamento SP3'!$E$2:$E$692,'Infos Relatório'!$B12,'Faturamento SP3'!$Z$2:$Z$692,'Infos Relatório'!AA$1) -> 0 | AG12: =COUNTIFS('Faturamento SP3'!$D$2:$D$692,'Infos Relatório'!$B$2,'Faturamento SP3'!$E$2:$E$692,'Infos Relatório'!$B12,'Faturamento SP3'!$Z$2:$Z$692,'Infos Relatório'!AG$1) -> 0 | AH12: =SUMIFS('Faturamento SP3'!$G$2:$G$692,'Faturamento SP3'!$D$2:$D$692,'Infos Relatório'!$B$2,'Faturamento SP3'!$E$2:$E$692,'Infos Relatório'!$B12,'Faturamento SP3'!$Z$2:$Z$692,'Infos Relatório'!AG$1) -> 0 | AI12: =SUMIFS('Faturamento SP3'!$J$2:$J$692,'Faturamento SP3'!$D$2:$D$692,'Infos Relatório'!$B$2,'Faturamento SP3'!$E$2:$E$692,'Infos Relatório'!$B12,'Faturamento SP3'!$Z$2:$Z$692,'Infos Relatório'!AG$1) -> 0 | AJ12: =SUMIFS('Faturamento SP3'!$O$2:$O$692,'Faturamento SP3'!$D$2:$D$692,'Infos Relatório'!$B$2,'Faturamento SP3'!$E$2:$E$692,'Infos Relatório'!$B12,'Faturamento SP3'!$Z$2:$Z$692,'Infos Relatório'!AG$1,'Faturamento SP3'!$T$2:$T$692,"Sim")+SUMIFS('Faturamento SP3'!$P$2:$P$692,'Faturamento SP3'!$D$2:$D$692,'Infos Relatório'!$B$2,'Faturamento SP3'!$E$2:$E$692,'Infos Relatório'!$B12,'Faturamento SP3'!$Z$2:$Z$692,'Infos Relatório'!AG$1,'Faturamento SP3'!$T$2:$T$692,"Sim") -> 0 | AK12: =AJ12/AI12 -> #DIV/0! | AL12: =SUMIFS('Faturamento SP3'!$H$2:$H$692,'Faturamento SP3'!$D$2:$D$692,'Infos Relatório'!$B$2,'Faturamento SP3'!$E$2:$E$692,'Infos Relatório'!$B12,'Faturamento SP3'!$Z$2:$Z$692,'Infos Relatório'!AG$1) -> 0 | AM12: =COUNTIFS('Faturamento SP3'!$D$2:$D$692,'Infos Relatório'!$B$2,'Faturamento SP3'!$E$2:$E$692,'Infos Relatório'!$B12,'Faturamento SP3'!$Z$2:$Z$692,'Infos Relatório'!AM$1) -> 0 | AN12: =SUMIFS('Faturamento SP3'!$G$2:$G$692,'Faturamento SP3'!$D$2:$D$692,'Infos Relatório'!$B$2,'Faturamento SP3'!$E$2:$E$692,'Infos Relatório'!$B12,'Faturamento SP3'!$Z$2:$Z$692,'Infos Relatório'!AM$1) -> 0 | AO12: =SUMIFS('Faturamento SP3'!$J$2:$J$692,'Faturamento SP3'!$D$2:$D$692,'Infos Relatório'!$B$2,'Faturamento SP3'!$E$2:$E$692,'Infos Relatório'!$B12,'Faturamento SP3'!$Z$2:$Z$692,'Infos Relatório'!AM$1) -> 0 | AP12: =SUMIFS('Faturamento SP3'!$O$2:$O$692,'Faturamento SP3'!$D$2:$D$692,'Infos Relatório'!$B$2,'Faturamento SP3'!$E$2:$E$692,'Infos Relatório'!$B12,'Faturamento SP3'!$Z$2:$Z$692,'Infos Relatório'!AM$1,'Faturamento SP3'!$T$2:$T$692,"Sim")+SUMIFS('Faturamento SP3'!$P$2:$P$692,'Faturamento SP3'!$D$2:$D$692,'Infos Relatório'!$B$2,'Faturamento SP3'!$E$2:$E$692,'Infos Relatório'!$B12,'Faturamento SP3'!$Z$2:$Z$692,'Infos Relatório'!AM$1,'Faturamento SP3'!$T$2:$T$692,"Sim") -> 0 | AQ12: =AP12/AO12 -> #DIV/0! | AR12: =SUMIFS('Faturamento SP3'!$H$2:$H$692,'Faturamento SP3'!$D$2:$D$692,'Infos Relatório'!$B$2,'Faturamento SP3'!$E$2:$E$692,'Infos Relatório'!$B12,'Faturamento SP3'!$Z$2:$Z$692,'Infos Relatório'!AM$1) -> 0 | AS12: =COUNTIFS('Faturamento SP3'!$D$2:$D$692,'Infos Relatório'!$B$2,'Faturamento SP3'!$E$2:$E$692,'Infos Relatório'!$B12,'Faturamento SP3'!$Z$2:$Z$692,'Infos Relatório'!AS$1) -> 0 | AT12: =SUMIFS('Faturamento SP3'!$G$2:$G$692,'Faturamento SP3'!$D$2:$D$692,'Infos Relatório'!$B$2,'Faturamento SP3'!$E$2:$E$692,'Infos Relatório'!$B12,'Faturamento SP3'!$Z$2:$Z$692,'Infos Relatório'!AS$1) -> 0 | AU12: =SUMIFS('Faturamento SP3'!$J$2:$J$692,'Faturamento SP3'!$D$2:$D$692,'Infos Relatório'!$B$2,'Faturamento SP3'!$E$2:$E$692,'Infos Relatório'!$B12,'Faturamento SP3'!$Z$2:$Z$692,'Infos Relatório'!AS$1) -> 0 | AV12: =SUMIFS('Faturamento SP3'!$O$2:$O$692,'Faturamento SP3'!$D$2:$D$692,'Infos Relatório'!$B$2,'Faturamento SP3'!$E$2:$E$692,'Infos Relatório'!$B12,'Faturamento SP3'!$Z$2:$Z$692,'Infos Relatório'!AS$1,'Faturamento SP3'!$T$2:$T$692,"Sim")+SUMIFS('Faturamento SP3'!$P$2:$P$692,'Faturamento SP3'!$D$2:$D$692,'Infos Relatório'!$B$2,'Faturamento SP3'!$E$2:$E$692,'Infos Relatório'!$B12,'Faturamento SP3'!$Z$2:$Z$692,'Infos Relatório'!AS$1,'Faturamento SP3'!$T$2:$T$692,"Sim") -> 0 | AW12: =AV12/AU12 -> #DIV/0! | AX12: =SUMIFS('Faturamento SP3'!$H$2:$H$692,'Faturamento SP3'!$D$2:$D$692,'Infos Relatório'!$B$2,'Faturamento SP3'!$E$2:$E$692,'Infos Relatório'!$B12,'Faturamento SP3'!$Z$2:$Z$692,'Infos Relatório'!AS$1) -> 0 | AY12: =COUNTIFS('Faturamento SP3'!$D$2:$D$692,'Infos Relatório'!$B$2,'Faturamento SP3'!$E$2:$E$692,'Infos Relatório'!$B12,'Faturamento SP3'!$Z$2:$Z$692,'Infos Relatório'!AY$1) -> 0 | AZ12: =SUMIFS('Faturamento SP3'!$G$2:$G$692,'Faturamento SP3'!$D$2:$D$692,'Infos Relatório'!$B$2,'Faturamento SP3'!$E$2:$E$692,'Infos Relatório'!$B12,'Faturamento SP3'!$Z$2:$Z$692,'Infos Relatório'!AY$1) -> 0 | BA12: =SUMIFS('Faturamento SP3'!$J$2:$J$692,'Faturamento SP3'!$D$2:$D$692,'Infos Relatório'!$B$2,'Faturamento SP3'!$E$2:$E$692,'Infos Relatório'!$B12,'Faturamento SP3'!$Z$2:$Z$692,'Infos Relatório'!AY$1) -> 0 | BB12: =SUMIFS('Faturamento SP3'!$O$2:$O$692,'Faturamento SP3'!$D$2:$D$692,'Infos Relatório'!$B$2,'Faturamento SP3'!$E$2:$E$692,'Infos Relatório'!$B12,'Faturamento SP3'!$Z$2:$Z$692,'Infos Relatório'!AY$1,'Faturamento SP3'!$T$2:$T$692,"Sim")+SUMIFS('Faturamento SP3'!$P$2:$P$692,'Faturamento SP3'!$D$2:$D$692,'Infos Relatório'!$B$2,'Faturamento SP3'!$E$2:$E$692,'Infos Relatório'!$B12,'Faturamento SP3'!$Z$2:$Z$692,'Infos Relatório'!AY$1,'Faturamento SP3'!$T$2:$T$692,"Sim") -> 0 | BC12: =BB12/BA12 -> #DIV/0! | BD12: =SUMIFS('Faturamento SP3'!$H$2:$H$692,'Faturamento SP3'!$D$2:$D$692,'Infos Relatório'!$B$2,'Faturamento SP3'!$E$2:$E$692,'Infos Relatório'!$B12,'Faturamento SP3'!$Z$2:$Z$692,'Infos Relatório'!AY$1) -> 0 | BE12: =COUNTIFS('Faturamento SP3'!$D$2:$D$692,'Infos Relatório'!$B$2,'Faturamento SP3'!$E$2:$E$692,'Infos Relatório'!$B12,'Faturamento SP3'!$Z$2:$Z$692,'Infos Relatório'!BE$1) -> 0 | BF12: =SUMIFS('Faturamento SP3'!$G$2:$G$692,'Faturamento SP3'!$D$2:$D$692,'Infos Relatório'!$B$2,'Faturamento SP3'!$E$2:$E$692,'Infos Relatório'!$B12,'Faturamento SP3'!$Z$2:$Z$692,'Infos Relatório'!BE$1) -> 0 | BG12: =SUMIFS('Faturamento SP3'!$J$2:$J$692,'Faturamento SP3'!$D$2:$D$692,'Infos Relatório'!$B$2,'Faturamento SP3'!$E$2:$E$692,'Infos Relatório'!$B12,'Faturamento SP3'!$Z$2:$Z$692,'Infos Relatório'!BE$1) -> 0 | BH12: =SUMIFS('Faturamento SP3'!$O$2:$O$692,'Faturamento SP3'!$D$2:$D$692,'Infos Relatório'!$B$2,'Faturamento SP3'!$E$2:$E$692,'Infos Relatório'!$B12,'Faturamento SP3'!$Z$2:$Z$692,'Infos Relatório'!BE$1,'Faturamento SP3'!$T$2:$T$692,"Sim")+SUMIFS('Faturamento SP3'!$P$2:$P$692,'Faturamento SP3'!$D$2:$D$692,'Infos Relatório'!$B$2,'Faturamento SP3'!$E$2:$E$692,'Infos Relatório'!$B12,'Faturamento SP3'!$Z$2:$Z$692,'Infos Relatório'!BE$1,'Faturamento SP3'!$T$2:$T$692,"Sim") -> 0 | BI12: =BH12/BG12 -> #DIV/0! | BJ12: =SUMIFS('Faturamento SP3'!$H$2:$H$692,'Faturamento SP3'!$D$2:$D$692,'Infos Relatório'!$B$2,'Faturamento SP3'!$E$2:$E$692,'Infos Relatório'!$B12,'Faturamento SP3'!$Z$2:$Z$692,'Infos Relatório'!BE$1) -> 0 | BK12: =COUNTIFS('Faturamento SP3'!$D$2:$D$692,'Infos Relatório'!$B$2,'Faturamento SP3'!$E$2:$E$692,'Infos Relatório'!$B12,'Faturamento SP3'!$Z$2:$Z$692,'Infos Relatório'!BK$1) -> 0 | BL12: =SUMIFS('Faturamento SP3'!$G$2:$G$692,'Faturamento SP3'!$D$2:$D$692,'Infos Relatório'!$B$2,'Faturamento SP3'!$E$2:$E$692,'Infos Relatório'!$B12,'Faturamento SP3'!$Z$2:$Z$692,'Infos Relatório'!BK$1) -> 0 | BM12: =SUMIFS('Faturamento SP3'!$J$2:$J$692,'Faturamento SP3'!$D$2:$D$692,'Infos Relatório'!$B$2,'Faturamento SP3'!$E$2:$E$692,'Infos Relatório'!$B12,'Faturamento SP3'!$Z$2:$Z$692,'Infos Relatório'!BK$1) -> 0 | BN12: =SUMIFS('Faturamento SP3'!$O$2:$O$692,'Faturamento SP3'!$D$2:$D$692,'Infos Relatório'!$B$2,'Faturamento SP3'!$E$2:$E$692,'Infos Relatório'!$B12,'Faturamento SP3'!$Z$2:$Z$692,'Infos Relatório'!BK$1,'Faturamento SP3'!$T$2:$T$692,"Sim")+SUMIFS('Faturamento SP3'!$P$2:$P$692,'Faturamento SP3'!$D$2:$D$692,'Infos Relatório'!$B$2,'Faturamento SP3'!$E$2:$E$692,'Infos Relatório'!$B12,'Faturamento SP3'!$Z$2:$Z$692,'Infos Relatório'!BK$1,'Faturamento SP3'!$T$2:$T$692,"Sim") -> 0 | BO12: =BN12/BM12 -> #DIV/0! | BP12: =SUMIFS('Faturamento SP3'!$H$2:$H$692,'Faturamento SP3'!$D$2:$D$692,'Infos Relatório'!$B$2,'Faturamento SP3'!$E$2:$E$692,'Infos Relatório'!$B12,'Faturamento SP3'!$Z$2:$Z$692,'Infos Relatório'!BK$1) -> 0 | BQ12: =COUNTIFS('Faturamento SP3'!$D$2:$D$692,'Infos Relatório'!$B$2,'Faturamento SP3'!$E$2:$E$692,'Infos Relatório'!$B12,'Faturamento SP3'!$Z$2:$Z$692,'Infos Relatório'!BQ$1) -> 0 | BR12: =SUMIFS('Faturamento SP3'!$G$2:$G$692,'Faturamento SP3'!$D$2:$D$692,'Infos Relatório'!$B$2,'Faturamento SP3'!$E$2:$E$692,'Infos Relatório'!$B12,'Faturamento SP3'!$Z$2:$Z$692,'Infos Relatório'!BQ$1) -> 0 | BS12: =SUMIFS('Faturamento SP3'!$J$2:$J$692,'Faturamento SP3'!$D$2:$D$692,'Infos Relatório'!$B$2,'Faturamento SP3'!$E$2:$E$692,'Infos Relatório'!$B12,'Faturamento SP3'!$Z$2:$Z$692,'Infos Relatório'!BQ$1) -> 0 | BT12: =SUMIFS('Faturamento SP3'!$O$2:$O$692,'Faturamento SP3'!$D$2:$D$692,'Infos Relatório'!$B$2,'Faturamento SP3'!$E$2:$E$692,'Infos Relatório'!$B12,'Faturamento SP3'!$Z$2:$Z$692,'Infos Relatório'!BQ$1,'Faturamento SP3'!$T$2:$T$692,"Sim")+SUMIFS('Faturamento SP3'!$P$2:$P$692,'Faturamento SP3'!$D$2:$D$692,'Infos Relatório'!$B$2,'Faturamento SP3'!$E$2:$E$692,'Infos Relatório'!$B12,'Faturamento SP3'!$Z$2:$Z$692,'Infos Relatório'!BQ$1,'Faturamento SP3'!$T$2:$T$692,"Sim") -> 0 | BU12: =BT12/BS12 -> #DIV/0! | BV12: =SUMIFS('Faturamento SP3'!$H$2:$H$692,'Faturamento SP3'!$D$2:$D$692,'Infos Relatório'!$B$2,'Faturamento SP3'!$E$2:$E$692,'Infos Relatório'!$B12,'Faturamento SP3'!$Z$2:$Z$692,'Infos Relatório'!BQ$1) -> 0
B13: Brasanitas | C13: =COUNTIFS('Faturamento SP3'!$D$2:$D$692,'Infos Relatório'!$B$2,'Faturamento SP3'!$E$2:$E$692,'Infos Relatório'!$B13,'Faturamento SP3'!$Z$2:$Z$692,'Infos Relatório'!C$1) -> 0 | D13: =SUMIFS('Faturamento SP3'!$G$2:$G$692,'Faturamento SP3'!$D$2:$D$692,'Infos Relatório'!$B$2,'Faturamento SP3'!$E$2:$E$692,'Infos Relatório'!$B13,'Faturamento SP3'!$Z$2:$Z$692,'Infos Relatório'!C$1) -> 0 | E13: =SUMIFS('Faturamento SP3'!$J$2:$J$692,'Faturamento SP3'!$D$2:$D$692,'Infos Relatório'!$B$2,'Faturamento SP3'!$E$2:$E$692,'Infos Relatório'!$B13,'Faturamento SP3'!$Z$2:$Z$692,'Infos Relatório'!C$1) -> 0 | F13: =SUMIFS('Faturamento SP3'!$O$2:$O$692,'Faturamento SP3'!$D$2:$D$692,'Infos Relatório'!$B$2,'Faturamento SP3'!$E$2:$E$692,'Infos Relatório'!$B13,'Faturamento SP3'!$Z$2:$Z$692,'Infos Relatório'!C$1,'Faturamento SP3'!$T$2:$T$692,"Sim")+SUMIFS('Faturamento SP3'!$P$2:$P$692,'Faturamento SP3'!$D$2:$D$692,'Infos Relatório'!$B$2,'Faturamento SP3'!$E$2:$E$692,'Infos Relatório'!$B13,'Faturamento SP3'!$Z$2:$Z$692,'Infos Relatório'!C$1,'Faturamento SP3'!$T$2:$T$692,"Sim") -> 0 | G13: =F13/E13 -> #DIV/0! | H13: =SUMIFS('Faturamento SP3'!$H$2:$H$692,'Faturamento SP3'!$D$2:$D$692,'Infos Relatório'!$B$2,'Faturamento SP3'!$E$2:$E$692,'Infos Relatório'!$B13,'Faturamento SP3'!$Z$2:$Z$692,'Infos Relatório'!C$1) -> 0 | I13: =COUNTIFS('Faturamento SP3'!$D$2:$D$692,'Infos Relatório'!$B$2,'Faturamento SP3'!$E$2:$E$692,'Infos Relatório'!$B13,'Faturamento SP3'!$Z$2:$Z$692,'Infos Relatório'!I$1) -> 0 | J13: =SUMIFS('Faturamento SP3'!$G$2:$G$692,'Faturamento SP3'!$D$2:$D$692,'Infos Relatório'!$B$2,'Faturamento SP3'!$E$2:$E$692,'Infos Relatório'!$B13,'Faturamento SP3'!$Z$2:$Z$692,'Infos Relatório'!I$1) -> 0 | K13: =SUMIFS('Faturamento SP3'!$J$2:$J$692,'Faturamento SP3'!$D$2:$D$692,'Infos Relatório'!$B$2,'Faturamento SP3'!$E$2:$E$692,'Infos Relatório'!$B13,'Faturamento SP3'!$Z$2:$Z$692,'Infos Relatório'!I$1) -> 0 | L13: =SUMIFS('Faturamento SP3'!$O$2:$O$692,'Faturamento SP3'!$D$2:$D$692,'Infos Relatório'!$B$2,'Faturamento SP3'!$E$2:$E$692,'Infos Relatório'!$B13,'Faturamento SP3'!$Z$2:$Z$692,'Infos Relatório'!I$1,'Faturamento SP3'!$T$2:$T$692,"Sim")+SUMIFS('Faturamento SP3'!$P$2:$P$692,'Faturamento SP3'!$D$2:$D$692,'Infos Relatório'!$B$2,'Faturamento SP3'!$E$2:$E$692,'Infos Relatório'!$B13,'Faturamento SP3'!$Z$2:$Z$692,'Infos Relatório'!I$1,'Faturamento SP3'!$T$2:$T$692,"Sim") -> 0 | M13: =L13/K13 -> #DIV/0! | N13: =SUMIFS('Faturamento SP3'!$H$2:$H$692,'Faturamento SP3'!$D$2:$D$692,'Infos Relatório'!$B$2,'Faturamento SP3'!$E$2:$E$692,'Infos Relatório'!$B13,'Faturamento SP3'!$Z$2:$Z$692,'Infos Relatório'!I$1) -> 0 | O13: =COUNTIFS('Faturamento SP3'!$D$2:$D$692,'Infos Relatório'!$B$2,'Faturamento SP3'!$E$2:$E$692,'Infos Relatório'!$B13,'Faturamento SP3'!$Z$2:$Z$692,'Infos Relatório'!O$1) -> 0 | P13: =SUMIFS('Faturamento SP3'!$G$2:$G$692,'Faturamento SP3'!$D$2:$D$692,'Infos Relatório'!$B$2,'Faturamento SP3'!$E$2:$E$692,'Infos Relatório'!$B13,'Faturamento SP3'!$Z$2:$Z$692,'Infos Relatório'!O$1) -> 0 | Q13: =SUMIFS('Faturamento SP3'!$J$2:$J$692,'Faturamento SP3'!$D$2:$D$692,'Infos Relatório'!$B$2,'Faturamento SP3'!$E$2:$E$692,'Infos Relatório'!$B13,'Faturamento SP3'!$Z$2:$Z$692,'Infos Relatório'!O$1) -> 0 | R13: =SUMIFS('Faturamento SP3'!$O$2:$O$692,'Faturamento SP3'!$D$2:$D$692,'Infos Relatório'!$B$2,'Faturamento SP3'!$E$2:$E$692,'Infos Relatório'!$B13,'Faturamento SP3'!$Z$2:$Z$692,'Infos Relatório'!O$1,'Faturamento SP3'!$T$2:$T$692,"Sim")+SUMIFS('Faturamento SP3'!$P$2:$P$692,'Faturamento SP3'!$D$2:$D$692,'Infos Relatório'!$B$2,'Faturamento SP3'!$E$2:$E$692,'Infos Relatório'!$B13,'Faturamento SP3'!$Z$2:$Z$692,'Infos Relatório'!O$1,'Faturamento SP3'!$T$2:$T$692,"Sim") -> 0 | S13: =R13/Q13 -> #DIV/0! | T13: =SUMIFS('Faturamento SP3'!$H$2:$H$692,'Faturamento SP3'!$D$2:$D$692,'Infos Relatório'!$B$2,'Faturamento SP3'!$E$2:$E$692,'Infos Relatório'!$B13,'Faturamento SP3'!$Z$2:$Z$692,'Infos Relatório'!O$1) -> 0 | U13: =COUNTIFS('Faturamento SP3'!$D$2:$D$692,'Infos Relatório'!$B$2,'Faturamento SP3'!$E$2:$E$692,'Infos Relatório'!$B13,'Faturamento SP3'!$Z$2:$Z$692,'Infos Relatório'!U$1) -> 0 | V13: =SUMIFS('Faturamento SP3'!$G$2:$G$692,'Faturamento SP3'!$D$2:$D$692,'Infos Relatório'!$B$2,'Faturamento SP3'!$E$2:$E$692,'Infos Relatório'!$B13,'Faturamento SP3'!$Z$2:$Z$692,'Infos Relatório'!U$1) -> 0 | W13: =SUMIFS('Faturamento SP3'!$J$2:$J$692,'Faturamento SP3'!$D$2:$D$692,'Infos Relatório'!$B$2,'Faturamento SP3'!$E$2:$E$692,'Infos Relatório'!$B13,'Faturamento SP3'!$Z$2:$Z$692,'Infos Relatório'!U$1) -> 0 | X13: =SUMIFS('Faturamento SP3'!$O$2:$O$692,'Faturamento SP3'!$D$2:$D$692,'Infos Relatório'!$B$2,'Faturamento SP3'!$E$2:$E$692,'Infos Relatório'!$B13,'Faturamento SP3'!$Z$2:$Z$692,'Infos Relatório'!U$1,'Faturamento SP3'!$T$2:$T$692,"Sim")+SUMIFS('Faturamento SP3'!$P$2:$P$692,'Faturamento SP3'!$D$2:$D$692,'Infos Relatório'!$B$2,'Faturamento SP3'!$E$2:$E$692,'Infos Relatório'!$B13,'Faturamento SP3'!$Z$2:$Z$692,'Infos Relatório'!U$1,'Faturamento SP3'!$T$2:$T$692,"Sim") -> 0 | Y13: =X13/W13 -> #DIV/0! | Z13: =SUMIFS('Faturamento SP3'!$H$2:$H$692,'Faturamento SP3'!$D$2:$D$692,'Infos Relatório'!$B$2,'Faturamento SP3'!$E$2:$E$692,'Infos Relatório'!$B13,'Faturamento SP3'!$Z$2:$Z$692,'Infos Relatório'!U$1) -> 0 | AA13: =COUNTIFS('Faturamento SP3'!$D$2:$D$692,'Infos Relatório'!$B$2,'Faturamento SP3'!$E$2:$E$692,'Infos Relatório'!$B13,'Faturamento SP3'!$Z$2:$Z$692,'Infos Relatório'!AA$1) -> 0 | AB13: =SUMIFS('Faturamento SP3'!$G$2:$G$692,'Faturamento SP3'!$D$2:$D$692,'Infos Relatório'!$B$2,'Faturamento SP3'!$E$2:$E$692,'Infos Relatório'!$B13,'Faturamento SP3'!$Z$2:$Z$692,'Infos Relatório'!AA$1) -> 0 | AC13: =SUMIFS('Faturamento SP3'!$J$2:$J$692,'Faturamento SP3'!$D$2:$D$692,'Infos Relatório'!$B$2,'Faturamento SP3'!$E$2:$E$692,'Infos Relatório'!$B13,'Faturamento SP3'!$Z$2:$Z$692,'Infos Relatório'!AA$1) -> 0 | AD13: =SUMIFS('Faturamento SP3'!$O$2:$O$692,'Faturamento SP3'!$D$2:$D$692,'Infos Relatório'!$B$2,'Faturamento SP3'!$E$2:$E$692,'Infos Relatório'!$B13,'Faturamento SP3'!$Z$2:$Z$692,'Infos Relatório'!AA$1,'Faturamento SP3'!$T$2:$T$692,"Sim")+SUMIFS('Faturamento SP3'!$P$2:$P$692,'Faturamento SP3'!$D$2:$D$692,'Infos Relatório'!$B$2,'Faturamento SP3'!$E$2:$E$692,'Infos Relatório'!$B13,'Faturamento SP3'!$Z$2:$Z$692,'Infos Relatório'!AA$1,'Faturamento SP3'!$T$2:$T$692,"Sim") -> 0 | AE13: =AD13/AC13 -> #DIV/0! | AF13: =SUMIFS('Faturamento SP3'!$H$2:$H$692,'Faturamento SP3'!$D$2:$D$692,'Infos Relatório'!$B$2,'Faturamento SP3'!$E$2:$E$692,'Infos Relatório'!$B13,'Faturamento SP3'!$Z$2:$Z$692,'Infos Relatório'!AA$1) -> 0 | AG13: =COUNTIFS('Faturamento SP3'!$D$2:$D$692,'Infos Relatório'!$B$2,'Faturamento SP3'!$E$2:$E$692,'Infos Relatório'!$B13,'Faturamento SP3'!$Z$2:$Z$692,'Infos Relatório'!AG$1) -> 0 | AH13: =SUMIFS('Faturamento SP3'!$G$2:$G$692,'Faturamento SP3'!$D$2:$D$692,'Infos Relatório'!$B$2,'Faturamento SP3'!$E$2:$E$692,'Infos Relatório'!$B13,'Faturamento SP3'!$Z$2:$Z$692,'Infos Relatório'!AG$1) -> 0 | AI13: =SUMIFS('Faturamento SP3'!$J$2:$J$692,'Faturamento SP3'!$D$2:$D$692,'Infos Relatório'!$B$2,'Faturamento SP3'!$E$2:$E$692,'Infos Relatório'!$B13,'Faturamento SP3'!$Z$2:$Z$692,'Infos Relatório'!AG$1) -> 0 | AJ13: =SUMIFS('Faturamento SP3'!$O$2:$O$692,'Faturamento SP3'!$D$2:$D$692,'Infos Relatório'!$B$2,'Faturamento SP3'!$E$2:$E$692,'Infos Relatório'!$B13,'Faturamento SP3'!$Z$2:$Z$692,'Infos Relatório'!AG$1,'Faturamento SP3'!$T$2:$T$692,"Sim")+SUMIFS('Faturamento SP3'!$P$2:$P$692,'Faturamento SP3'!$D$2:$D$692,'Infos Relatório'!$B$2,'Faturamento SP3'!$E$2:$E$692,'Infos Relatório'!$B13,'Faturamento SP3'!$Z$2:$Z$692,'Infos Relatório'!AG$1,'Faturamento SP3'!$T$2:$T$692,"Sim") -> 0 | AK13: =AJ13/AI13 -> #DIV/0! | AL13: =SUMIFS('Faturamento SP3'!$H$2:$H$692,'Faturamento SP3'!$D$2:$D$692,'Infos Relatório'!$B$2,'Faturamento SP3'!$E$2:$E$692,'Infos Relatório'!$B13,'Faturamento SP3'!$Z$2:$Z$692,'Infos Relatório'!AG$1) -> 0 | AM13: =COUNTIFS('Faturamento SP3'!$D$2:$D$692,'Infos Relatório'!$B$2,'Faturamento SP3'!$E$2:$E$692,'Infos Relatório'!$B13,'Faturamento SP3'!$Z$2:$Z$692,'Infos Relatório'!AM$1) -> 0 | AN13: =SUMIFS('Faturamento SP3'!$G$2:$G$692,'Faturamento SP3'!$D$2:$D$692,'Infos Relatório'!$B$2,'Faturamento SP3'!$E$2:$E$692,'Infos Relatório'!$B13,'Faturamento SP3'!$Z$2:$Z$692,'Infos Relatório'!AM$1) -> 0 | AO13: =SUMIFS('Faturamento SP3'!$J$2:$J$692,'Faturamento SP3'!$D$2:$D$692,'Infos Relatório'!$B$2,'Faturamento SP3'!$E$2:$E$692,'Infos Relatório'!$B13,'Faturamento SP3'!$Z$2:$Z$692,'Infos Relatório'!AM$1) -> 0 | AP13: =SUMIFS('Faturamento SP3'!$O$2:$O$692,'Faturamento SP3'!$D$2:$D$692,'Infos Relatório'!$B$2,'Faturamento SP3'!$E$2:$E$692,'Infos Relatório'!$B13,'Faturamento SP3'!$Z$2:$Z$692,'Infos Relatório'!AM$1,'Faturamento SP3'!$T$2:$T$692,"Sim")+SUMIFS('Faturamento SP3'!$P$2:$P$692,'Faturamento SP3'!$D$2:$D$692,'Infos Relatório'!$B$2,'Faturamento SP3'!$E$2:$E$692,'Infos Relatório'!$B13,'Faturamento SP3'!$Z$2:$Z$692,'Infos Relatório'!AM$1,'Faturamento SP3'!$T$2:$T$692,"Sim") -> 0 | AQ13: =AP13/AO13 -> #DIV/0! | AR13: =SUMIFS('Faturamento SP3'!$H$2:$H$692,'Faturamento SP3'!$D$2:$D$692,'Infos Relatório'!$B$2,'Faturamento SP3'!$E$2:$E$692,'Infos Relatório'!$B13,'Faturamento SP3'!$Z$2:$Z$692,'Infos Relatório'!AM$1) -> 0 | AS13: =COUNTIFS('Faturamento SP3'!$D$2:$D$692,'Infos Relatório'!$B$2,'Faturamento SP3'!$E$2:$E$692,'Infos Relatório'!$B13,'Faturamento SP3'!$Z$2:$Z$692,'Infos Relatório'!AS$1) -> 0 | AT13: =SUMIFS('Faturamento SP3'!$G$2:$G$692,'Faturamento SP3'!$D$2:$D$692,'Infos Relatório'!$B$2,'Faturamento SP3'!$E$2:$E$692,'Infos Relatório'!$B13,'Faturamento SP3'!$Z$2:$Z$692,'Infos Relatório'!AS$1) -> 0 | AU13: =SUMIFS('Faturamento SP3'!$J$2:$J$692,'Faturamento SP3'!$D$2:$D$692,'Infos Relatório'!$B$2,'Faturamento SP3'!$E$2:$E$692,'Infos Relatório'!$B13,'Faturamento SP3'!$Z$2:$Z$692,'Infos Relatório'!AS$1) -> 0 | AV13: =SUMIFS('Faturamento SP3'!$O$2:$O$692,'Faturamento SP3'!$D$2:$D$692,'Infos Relatório'!$B$2,'Faturamento SP3'!$E$2:$E$692,'Infos Relatório'!$B13,'Faturamento SP3'!$Z$2:$Z$692,'Infos Relatório'!AS$1,'Faturamento SP3'!$T$2:$T$692,"Sim")+SUMIFS('Faturamento SP3'!$P$2:$P$692,'Faturamento SP3'!$D$2:$D$692,'Infos Relatório'!$B$2,'Faturamento SP3'!$E$2:$E$692,'Infos Relatório'!$B13,'Faturamento SP3'!$Z$2:$Z$692,'Infos Relatório'!AS$1,'Faturamento SP3'!$T$2:$T$692,"Sim") -> 0 | AW13: =AV13/AU13 -> #DIV/0! | AX13: =SUMIFS('Faturamento SP3'!$H$2:$H$692,'Faturamento SP3'!$D$2:$D$692,'Infos Relatório'!$B$2,'Faturamento SP3'!$E$2:$E$692,'Infos Relatório'!$B13,'Faturamento SP3'!$Z$2:$Z$692,'Infos Relatório'!AS$1) -> 0 | AY13: =COUNTIFS('Faturamento SP3'!$D$2:$D$692,'Infos Relatório'!$B$2,'Faturamento SP3'!$E$2:$E$692,'Infos Relatório'!$B13,'Faturamento SP3'!$Z$2:$Z$692,'Infos Relatório'!AY$1) -> 0 | AZ13: =SUMIFS('Faturamento SP3'!$G$2:$G$692,'Faturamento SP3'!$D$2:$D$692,'Infos Relatório'!$B$2,'Faturamento SP3'!$E$2:$E$692,'Infos Relatório'!$B13,'Faturamento SP3'!$Z$2:$Z$692,'Infos Relatório'!AY$1) -> 0 | BA13: =SUMIFS('Faturamento SP3'!$J$2:$J$692,'Faturamento SP3'!$D$2:$D$692,'Infos Relatório'!$B$2,'Faturamento SP3'!$E$2:$E$692,'Infos Relatório'!$B13,'Faturamento SP3'!$Z$2:$Z$692,'Infos Relatório'!AY$1) -> 0 | BB13: =SUMIFS('Faturamento SP3'!$O$2:$O$692,'Faturamento SP3'!$D$2:$D$692,'Infos Relatório'!$B$2,'Faturamento SP3'!$E$2:$E$692,'Infos Relatório'!$B13,'Faturamento SP3'!$Z$2:$Z$692,'Infos Relatório'!AY$1,'Faturamento SP3'!$T$2:$T$692,"Sim")+SUMIFS('Faturamento SP3'!$P$2:$P$692,'Faturamento SP3'!$D$2:$D$692,'Infos Relatório'!$B$2,'Faturamento SP3'!$E$2:$E$692,'Infos Relatório'!$B13,'Faturamento SP3'!$Z$2:$Z$692,'Infos Relatório'!AY$1,'Faturamento SP3'!$T$2:$T$692,"Sim") -> 0 | BC13: =BB13/BA13 -> #DIV/0! | BD13: =SUMIFS('Faturamento SP3'!$H$2:$H$692,'Faturamento SP3'!$D$2:$D$692,'Infos Relatório'!$B$2,'Faturamento SP3'!$E$2:$E$692,'Infos Relatório'!$B13,'Faturamento SP3'!$Z$2:$Z$692,'Infos Relatório'!AY$1) -> 0 | BE13: =COUNTIFS('Faturamento SP3'!$D$2:$D$692,'Infos Relatório'!$B$2,'Faturamento SP3'!$E$2:$E$692,'Infos Relatório'!$B13,'Faturamento SP3'!$Z$2:$Z$692,'Infos Relatório'!BE$1) -> 0 | BF13: =SUMIFS('Faturamento SP3'!$G$2:$G$692,'Faturamento SP3'!$D$2:$D$692,'Infos Relatório'!$B$2,'Faturamento SP3'!$E$2:$E$692,'Infos Relatório'!$B13,'Faturamento SP3'!$Z$2:$Z$692,'Infos Relatório'!BE$1) -> 0 | BG13: =SUMIFS('Faturamento SP3'!$J$2:$J$692,'Faturamento SP3'!$D$2:$D$692,'Infos Relatório'!$B$2,'Faturamento SP3'!$E$2:$E$692,'Infos Relatório'!$B13,'Faturamento SP3'!$Z$2:$Z$692,'Infos Relatório'!BE$1) -> 0 | BH13: =SUMIFS('Faturamento SP3'!$O$2:$O$692,'Faturamento SP3'!$D$2:$D$692,'Infos Relatório'!$B$2,'Faturamento SP3'!$E$2:$E$692,'Infos Relatório'!$B13,'Faturamento SP3'!$Z$2:$Z$692,'Infos Relatório'!BE$1,'Faturamento SP3'!$T$2:$T$692,"Sim")+SUMIFS('Faturamento SP3'!$P$2:$P$692,'Faturamento SP3'!$D$2:$D$692,'Infos Relatório'!$B$2,'Faturamento SP3'!$E$2:$E$692,'Infos Relatório'!$B13,'Faturamento SP3'!$Z$2:$Z$692,'Infos Relatório'!BE$1,'Faturamento SP3'!$T$2:$T$692,"Sim") -> 0 | BI13: =BH13/BG13 -> #DIV/0! | BJ13: =SUMIFS('Faturamento SP3'!$H$2:$H$692,'Faturamento SP3'!$D$2:$D$692,'Infos Relatório'!$B$2,'Faturamento SP3'!$E$2:$E$692,'Infos Relatório'!$B13,'Faturamento SP3'!$Z$2:$Z$692,'Infos Relatório'!BE$1) -> 0 | BK13: =COUNTIFS('Faturamento SP3'!$D$2:$D$692,'Infos Relatório'!$B$2,'Faturamento SP3'!$E$2:$E$692,'Infos Relatório'!$B13,'Faturamento SP3'!$Z$2:$Z$692,'Infos Relatório'!BK$1) -> 0 | BL13: =SUMIFS('Faturamento SP3'!$G$2:$G$692,'Faturamento SP3'!$D$2:$D$692,'Infos Relatório'!$B$2,'Faturamento SP3'!$E$2:$E$692,'Infos Relatório'!$B13,'Faturamento SP3'!$Z$2:$Z$692,'Infos Relatório'!BK$1) -> 0 | BM13: =SUMIFS('Faturamento SP3'!$J$2:$J$692,'Faturamento SP3'!$D$2:$D$692,'Infos Relatório'!$B$2,'Faturamento SP3'!$E$2:$E$692,'Infos Relatório'!$B13,'Faturamento SP3'!$Z$2:$Z$692,'Infos Relatório'!BK$1) -> 0 | BN13: =SUMIFS('Faturamento SP3'!$O$2:$O$692,'Faturamento SP3'!$D$2:$D$692,'Infos Relatório'!$B$2,'Faturamento SP3'!$E$2:$E$692,'Infos Relatório'!$B13,'Faturamento SP3'!$Z$2:$Z$692,'Infos Relatório'!BK$1,'Faturamento SP3'!$T$2:$T$692,"Sim")+SUMIFS('Faturamento SP3'!$P$2:$P$692,'Faturamento SP3'!$D$2:$D$692,'Infos Relatório'!$B$2,'Faturamento SP3'!$E$2:$E$692,'Infos Relatório'!$B13,'Faturamento SP3'!$Z$2:$Z$692,'Infos Relatório'!BK$1,'Faturamento SP3'!$T$2:$T$692,"Sim") -> 0 | BO13: =BN13/BM13 -> #DIV/0! | BP13: =SUMIFS('Faturamento SP3'!$H$2:$H$692,'Faturamento SP3'!$D$2:$D$692,'Infos Relatório'!$B$2,'Faturamento SP3'!$E$2:$E$692,'Infos Relatório'!$B13,'Faturamento SP3'!$Z$2:$Z$692,'Infos Relatório'!BK$1) -> 0 | BQ13: =COUNTIFS('Faturamento SP3'!$D$2:$D$692,'Infos Relatório'!$B$2,'Faturamento SP3'!$E$2:$E$692,'Infos Relatório'!$B13,'Faturamento SP3'!$Z$2:$Z$692,'Infos Relatório'!BQ$1) -> 0 | BR13: =SUMIFS('Faturamento SP3'!$G$2:$G$692,'Faturamento SP3'!$D$2:$D$692,'Infos Relatório'!$B$2,'Faturamento SP3'!$E$2:$E$692,'Infos Relatório'!$B13,'Faturamento SP3'!$Z$2:$Z$692,'Infos Relatório'!BQ$1) -> 0 | BS13: =SUMIFS('Faturamento SP3'!$J$2:$J$692,'Faturamento SP3'!$D$2:$D$692,'Infos Relatório'!$B$2,'Faturamento SP3'!$E$2:$E$692,'Infos Relatório'!$B13,'Faturamento SP3'!$Z$2:$Z$692,'Infos Relatório'!BQ$1) -> 0 | BT13: =SUMIFS('Faturamento SP3'!$O$2:$O$692,'Faturamento SP3'!$D$2:$D$692,'Infos Relatório'!$B$2,'Faturamento SP3'!$E$2:$E$692,'Infos Relatório'!$B13,'Faturamento SP3'!$Z$2:$Z$692,'Infos Relatório'!BQ$1,'Faturamento SP3'!$T$2:$T$692,"Sim")+SUMIFS('Faturamento SP3'!$P$2:$P$692,'Faturamento SP3'!$D$2:$D$692,'Infos Relatório'!$B$2,'Faturamento SP3'!$E$2:$E$692,'Infos Relatório'!$B13,'Faturamento SP3'!$Z$2:$Z$692,'Infos Relatório'!BQ$1,'Faturamento SP3'!$T$2:$T$692,"Sim") -> 0 | BU13: =BT13/BS13 -> #DIV/0! | BV13: =SUMIFS('Faturamento SP3'!$H$2:$H$692,'Faturamento SP3'!$D$2:$D$692,'Infos Relatório'!$B$2,'Faturamento SP3'!$E$2:$E$692,'Infos Relatório'!$B13,'Faturamento SP3'!$Z$2:$Z$692,'Infos Relatório'!BQ$1) -> 0
B14: Brasil Gestão | C14: =COUNTIFS('Faturamento SP3'!$D$2:$D$692,'Infos Relatório'!$B$2,'Faturamento SP3'!$E$2:$E$692,'Infos Relatório'!$B14,'Faturamento SP3'!$Z$2:$Z$692,'Infos Relatório'!C$1) -> 0 | D14: =SUMIFS('Faturamento SP3'!$G$2:$G$692,'Faturamento SP3'!$D$2:$D$692,'Infos Relatório'!$B$2,'Faturamento SP3'!$E$2:$E$692,'Infos Relatório'!$B14,'Faturamento SP3'!$Z$2:$Z$692,'Infos Relatório'!C$1) -> 0 | E14: =SUMIFS('Faturamento SP3'!$J$2:$J$692,'Faturamento SP3'!$D$2:$D$692,'Infos Relatório'!$B$2,'Faturamento SP3'!$E$2:$E$692,'Infos Relatório'!$B14,'Faturamento SP3'!$Z$2:$Z$692,'Infos Relatório'!C$1) -> 0 | F14: =SUMIFS('Faturamento SP3'!$O$2:$O$692,'Faturamento SP3'!$D$2:$D$692,'Infos Relatório'!$B$2,'Faturamento SP3'!$E$2:$E$692,'Infos Relatório'!$B14,'Faturamento SP3'!$Z$2:$Z$692,'Infos Relatório'!C$1,'Faturamento SP3'!$T$2:$T$692,"Sim")+SUMIFS('Faturamento SP3'!$P$2:$P$692,'Faturamento SP3'!$D$2:$D$692,'Infos Relatório'!$B$2,'Faturamento SP3'!$E$2:$E$692,'Infos Relatório'!$B14,'Faturamento SP3'!$Z$2:$Z$692,'Infos Relatório'!C$1,'Faturamento SP3'!$T$2:$T$692,"Sim") -> 0 | G14: =F14/E14 -> #DIV/0! | H14: =SUMIFS('Faturamento SP3'!$H$2:$H$692,'Faturamento SP3'!$D$2:$D$692,'Infos Relatório'!$B$2,'Faturamento SP3'!$E$2:$E$692,'Infos Relatório'!$B14,'Faturamento SP3'!$Z$2:$Z$692,'Infos Relatório'!C$1) -> 0 | I14: =COUNTIFS('Faturamento SP3'!$D$2:$D$692,'Infos Relatório'!$B$2,'Faturamento SP3'!$E$2:$E$692,'Infos Relatório'!$B14,'Faturamento SP3'!$Z$2:$Z$692,'Infos Relatório'!I$1) -> 0 | J14: =SUMIFS('Faturamento SP3'!$G$2:$G$692,'Faturamento SP3'!$D$2:$D$692,'Infos Relatório'!$B$2,'Faturamento SP3'!$E$2:$E$692,'Infos Relatório'!$B14,'Faturamento SP3'!$Z$2:$Z$692,'Infos Relatório'!I$1) -> 0 | K14: =SUMIFS('Faturamento SP3'!$J$2:$J$692,'Faturamento SP3'!$D$2:$D$692,'Infos Relatório'!$B$2,'Faturamento SP3'!$E$2:$E$692,'Infos Relatório'!$B14,'Faturamento SP3'!$Z$2:$Z$692,'Infos Relatório'!I$1) -> 0 | L14: =SUMIFS('Faturamento SP3'!$O$2:$O$692,'Faturamento SP3'!$D$2:$D$692,'Infos Relatório'!$B$2,'Faturamento SP3'!$E$2:$E$692,'Infos Relatório'!$B14,'Faturamento SP3'!$Z$2:$Z$692,'Infos Relatório'!I$1,'Faturamento SP3'!$T$2:$T$692,"Sim")+SUMIFS('Faturamento SP3'!$P$2:$P$692,'Faturamento SP3'!$D$2:$D$692,'Infos Relatório'!$B$2,'Faturamento SP3'!$E$2:$E$692,'Infos Relatório'!$B14,'Faturamento SP3'!$Z$2:$Z$692,'Infos Relatório'!I$1,'Faturamento SP3'!$T$2:$T$692,"Sim") -> 0 | M14: =L14/K14 -> #DIV/0! | N14: =SUMIFS('Faturamento SP3'!$H$2:$H$692,'Faturamento SP3'!$D$2:$D$692,'Infos Relatório'!$B$2,'Faturamento SP3'!$E$2:$E$692,'Infos Relatório'!$B14,'Faturamento SP3'!$Z$2:$Z$692,'Infos Relatório'!I$1) -> 0 | O14: =COUNTIFS('Faturamento SP3'!$D$2:$D$692,'Infos Relatório'!$B$2,'Faturamento SP3'!$E$2:$E$692,'Infos Relatório'!$B14,'Faturamento SP3'!$Z$2:$Z$692,'Infos Relatório'!O$1) -> 0 | P14: =SUMIFS('Faturamento SP3'!$G$2:$G$692,'Faturamento SP3'!$D$2:$D$692,'Infos Relatório'!$B$2,'Faturamento SP3'!$E$2:$E$692,'Infos Relatório'!$B14,'Faturamento SP3'!$Z$2:$Z$692,'Infos Relatório'!O$1) -> 0 | Q14: =SUMIFS('Faturamento SP3'!$J$2:$J$692,'Faturamento SP3'!$D$2:$D$692,'Infos Relatório'!$B$2,'Faturamento SP3'!$E$2:$E$692,'Infos Relatório'!$B14,'Faturamento SP3'!$Z$2:$Z$692,'Infos Relatório'!O$1) -> 0 | R14: =SUMIFS('Faturamento SP3'!$O$2:$O$692,'Faturamento SP3'!$D$2:$D$692,'Infos Relatório'!$B$2,'Faturamento SP3'!$E$2:$E$692,'Infos Relatório'!$B14,'Faturamento SP3'!$Z$2:$Z$692,'Infos Relatório'!O$1,'Faturamento SP3'!$T$2:$T$692,"Sim")+SUMIFS('Faturamento SP3'!$P$2:$P$692,'Faturamento SP3'!$D$2:$D$692,'Infos Relatório'!$B$2,'Faturamento SP3'!$E$2:$E$692,'Infos Relatório'!$B14,'Faturamento SP3'!$Z$2:$Z$692,'Infos Relatório'!O$1,'Faturamento SP3'!$T$2:$T$692,"Sim") -> 0 | S14: =R14/Q14 -> #DIV/0! | T14: =SUMIFS('Faturamento SP3'!$H$2:$H$692,'Faturamento SP3'!$D$2:$D$692,'Infos Relatório'!$B$2,'Faturamento SP3'!$E$2:$E$692,'Infos Relatório'!$B14,'Faturamento SP3'!$Z$2:$Z$692,'Infos Relatório'!O$1) -> 0 | U14: =COUNTIFS('Faturamento SP3'!$D$2:$D$692,'Infos Relatório'!$B$2,'Faturamento SP3'!$E$2:$E$692,'Infos Relatório'!$B14,'Faturamento SP3'!$Z$2:$Z$692,'Infos Relatório'!U$1) -> 0 | V14: =SUMIFS('Faturamento SP3'!$G$2:$G$692,'Faturamento SP3'!$D$2:$D$692,'Infos Relatório'!$B$2,'Faturamento SP3'!$E$2:$E$692,'Infos Relatório'!$B14,'Faturamento SP3'!$Z$2:$Z$692,'Infos Relatório'!U$1) -> 0 | W14: =SUMIFS('Faturamento SP3'!$J$2:$J$692,'Faturamento SP3'!$D$2:$D$692,'Infos Relatório'!$B$2,'Faturamento SP3'!$E$2:$E$692,'Infos Relatório'!$B14,'Faturamento SP3'!$Z$2:$Z$692,'Infos Relatório'!U$1) -> 0 | X14: =SUMIFS('Faturamento SP3'!$O$2:$O$692,'Faturamento SP3'!$D$2:$D$692,'Infos Relatório'!$B$2,'Faturamento SP3'!$E$2:$E$692,'Infos Relatório'!$B14,'Faturamento SP3'!$Z$2:$Z$692,'Infos Relatório'!U$1,'Faturamento SP3'!$T$2:$T$692,"Sim")+SUMIFS('Faturamento SP3'!$P$2:$P$692,'Faturamento SP3'!$D$2:$D$692,'Infos Relatório'!$B$2,'Faturamento SP3'!$E$2:$E$692,'Infos Relatório'!$B14,'Faturamento SP3'!$Z$2:$Z$692,'Infos Relatório'!U$1,'Faturamento SP3'!$T$2:$T$692,"Sim") -> 0 | Y14: =X14/W14 -> #DIV/0! | Z14: =SUMIFS('Faturamento SP3'!$H$2:$H$692,'Faturamento SP3'!$D$2:$D$692,'Infos Relatório'!$B$2,'Faturamento SP3'!$E$2:$E$692,'Infos Relatório'!$B14,'Faturamento SP3'!$Z$2:$Z$692,'Infos Relatório'!U$1) -> 0 | AA14: =COUNTIFS('Faturamento SP3'!$D$2:$D$692,'Infos Relatório'!$B$2,'Faturamento SP3'!$E$2:$E$692,'Infos Relatório'!$B14,'Faturamento SP3'!$Z$2:$Z$692,'Infos Relatório'!AA$1) -> 0 | AB14: =SUMIFS('Faturamento SP3'!$G$2:$G$692,'Faturamento SP3'!$D$2:$D$692,'Infos Relatório'!$B$2,'Faturamento SP3'!$E$2:$E$692,'Infos Relatório'!$B14,'Faturamento SP3'!$Z$2:$Z$692,'Infos Relatório'!AA$1) -> 0 | AC14: =SUMIFS('Faturamento SP3'!$J$2:$J$692,'Faturamento SP3'!$D$2:$D$692,'Infos Relatório'!$B$2,'Faturamento SP3'!$E$2:$E$692,'Infos Relatório'!$B14,'Faturamento SP3'!$Z$2:$Z$692,'Infos Relatório'!AA$1) -> 0 | AD14: =SUMIFS('Faturamento SP3'!$O$2:$O$692,'Faturamento SP3'!$D$2:$D$692,'Infos Relatório'!$B$2,'Faturamento SP3'!$E$2:$E$692,'Infos Relatório'!$B14,'Faturamento SP3'!$Z$2:$Z$692,'Infos Relatório'!AA$1,'Faturamento SP3'!$T$2:$T$692,"Sim")+SUMIFS('Faturamento SP3'!$P$2:$P$692,'Faturamento SP3'!$D$2:$D$692,'Infos Relatório'!$B$2,'Faturamento SP3'!$E$2:$E$692,'Infos Relatório'!$B14,'Faturamento SP3'!$Z$2:$Z$692,'Infos Relatório'!AA$1,'Faturamento SP3'!$T$2:$T$692,"Sim") -> 0 | AE14: =AD14/AC14 -> #DIV/0! | AF14: =SUMIFS('Faturamento SP3'!$H$2:$H$692,'Faturamento SP3'!$D$2:$D$692,'Infos Relatório'!$B$2,'Faturamento SP3'!$E$2:$E$692,'Infos Relatório'!$B14,'Faturamento SP3'!$Z$2:$Z$692,'Infos Relatório'!AA$1) -> 0 | AG14: =COUNTIFS('Faturamento SP3'!$D$2:$D$692,'Infos Relatório'!$B$2,'Faturamento SP3'!$E$2:$E$692,'Infos Relatório'!$B14,'Faturamento SP3'!$Z$2:$Z$692,'Infos Relatório'!AG$1) -> 0 | AH14: =SUMIFS('Faturamento SP3'!$G$2:$G$692,'Faturamento SP3'!$D$2:$D$692,'Infos Relatório'!$B$2,'Faturamento SP3'!$E$2:$E$692,'Infos Relatório'!$B14,'Faturamento SP3'!$Z$2:$Z$692,'Infos Relatório'!AG$1) -> 0 | AI14: =SUMIFS('Faturamento SP3'!$J$2:$J$692,'Faturamento SP3'!$D$2:$D$692,'Infos Relatório'!$B$2,'Faturamento SP3'!$E$2:$E$692,'Infos Relatório'!$B14,'Faturamento SP3'!$Z$2:$Z$692,'Infos Relatório'!AG$1) -> 0 | AJ14: =SUMIFS('Faturamento SP3'!$O$2:$O$692,'Faturamento SP3'!$D$2:$D$692,'Infos Relatório'!$B$2,'Faturamento SP3'!$E$2:$E$692,'Infos Relatório'!$B14,'Faturamento SP3'!$Z$2:$Z$692,'Infos Relatório'!AG$1,'Faturamento SP3'!$T$2:$T$692,"Sim")+SUMIFS('Faturamento SP3'!$P$2:$P$692,'Faturamento SP3'!$D$2:$D$692,'Infos Relatório'!$B$2,'Faturamento SP3'!$E$2:$E$692,'Infos Relatório'!$B14,'Faturamento SP3'!$Z$2:$Z$692,'Infos Relatório'!AG$1,'Faturamento SP3'!$T$2:$T$692,"Sim") -> 0 | AK14: =AJ14/AI14 -> #DIV/0! | AL14: =SUMIFS('Faturamento SP3'!$H$2:$H$692,'Faturamento SP3'!$D$2:$D$692,'Infos Relatório'!$B$2,'Faturamento SP3'!$E$2:$E$692,'Infos Relatório'!$B14,'Faturamento SP3'!$Z$2:$Z$692,'Infos Relatório'!AG$1) -> 0 | AM14: =COUNTIFS('Faturamento SP3'!$D$2:$D$692,'Infos Relatório'!$B$2,'Faturamento SP3'!$E$2:$E$692,'Infos Relatório'!$B14,'Faturamento SP3'!$Z$2:$Z$692,'Infos Relatório'!AM$1) -> 0 | AN14: =SUMIFS('Faturamento SP3'!$G$2:$G$692,'Faturamento SP3'!$D$2:$D$692,'Infos Relatório'!$B$2,'Faturamento SP3'!$E$2:$E$692,'Infos Relatório'!$B14,'Faturamento SP3'!$Z$2:$Z$692,'Infos Relatório'!AM$1) -> 0 | AO14: =SUMIFS('Faturamento SP3'!$J$2:$J$692,'Faturamento SP3'!$D$2:$D$692,'Infos Relatório'!$B$2,'Faturamento SP3'!$E$2:$E$692,'Infos Relatório'!$B14,'Faturamento SP3'!$Z$2:$Z$692,'Infos Relatório'!AM$1) -> 0 | AP14: =SUMIFS('Faturamento SP3'!$O$2:$O$692,'Faturamento SP3'!$D$2:$D$692,'Infos Relatório'!$B$2,'Faturamento SP3'!$E$2:$E$692,'Infos Relatório'!$B14,'Faturamento SP3'!$Z$2:$Z$692,'Infos Relatório'!AM$1,'Faturamento SP3'!$T$2:$T$692,"Sim")+SUMIFS('Faturamento SP3'!$P$2:$P$692,'Faturamento SP3'!$D$2:$D$692,'Infos Relatório'!$B$2,'Faturamento SP3'!$E$2:$E$692,'Infos Relatório'!$B14,'Faturamento SP3'!$Z$2:$Z$692,'Infos Relatório'!AM$1,'Faturamento SP3'!$T$2:$T$692,"Sim") -> 0 | AQ14: =AP14/AO14 -> #DIV/0! | AR14: =SUMIFS('Faturamento SP3'!$H$2:$H$692,'Faturamento SP3'!$D$2:$D$692,'Infos Relatório'!$B$2,'Faturamento SP3'!$E$2:$E$692,'Infos Relatório'!$B14,'Faturamento SP3'!$Z$2:$Z$692,'Infos Relatório'!AM$1) -> 0 | AS14: =COUNTIFS('Faturamento SP3'!$D$2:$D$692,'Infos Relatório'!$B$2,'Faturamento SP3'!$E$2:$E$692,'Infos Relatório'!$B14,'Faturamento SP3'!$Z$2:$Z$692,'Infos Relatório'!AS$1) -> 0 | AT14: =SUMIFS('Faturamento SP3'!$G$2:$G$692,'Faturamento SP3'!$D$2:$D$692,'Infos Relatório'!$B$2,'Faturamento SP3'!$E$2:$E$692,'Infos Relatório'!$B14,'Faturamento SP3'!$Z$2:$Z$692,'Infos Relatório'!AS$1) -> 0 | AU14: =SUMIFS('Faturamento SP3'!$J$2:$J$692,'Faturamento SP3'!$D$2:$D$692,'Infos Relatório'!$B$2,'Faturamento SP3'!$E$2:$E$692,'Infos Relatório'!$B14,'Faturamento SP3'!$Z$2:$Z$692,'Infos Relatório'!AS$1) -> 0 | AV14: =SUMIFS('Faturamento SP3'!$O$2:$O$692,'Faturamento SP3'!$D$2:$D$692,'Infos Relatório'!$B$2,'Faturamento SP3'!$E$2:$E$692,'Infos Relatório'!$B14,'Faturamento SP3'!$Z$2:$Z$692,'Infos Relatório'!AS$1,'Faturamento SP3'!$T$2:$T$692,"Sim")+SUMIFS('Faturamento SP3'!$P$2:$P$692,'Faturamento SP3'!$D$2:$D$692,'Infos Relatório'!$B$2,'Faturamento SP3'!$E$2:$E$692,'Infos Relatório'!$B14,'Faturamento SP3'!$Z$2:$Z$692,'Infos Relatório'!AS$1,'Faturamento SP3'!$T$2:$T$692,"Sim") -> 0 | AW14: =AV14/AU14 -> #DIV/0! | AX14: =SUMIFS('Faturamento SP3'!$H$2:$H$692,'Faturamento SP3'!$D$2:$D$692,'Infos Relatório'!$B$2,'Faturamento SP3'!$E$2:$E$692,'Infos Relatório'!$B14,'Faturamento SP3'!$Z$2:$Z$692,'Infos Relatório'!AS$1) -> 0 | AY14: =COUNTIFS('Faturamento SP3'!$D$2:$D$692,'Infos Relatório'!$B$2,'Faturamento SP3'!$E$2:$E$692,'Infos Relatório'!$B14,'Faturamento SP3'!$Z$2:$Z$692,'Infos Relatório'!AY$1) -> 0 | AZ14: =SUMIFS('Faturamento SP3'!$G$2:$G$692,'Faturamento SP3'!$D$2:$D$692,'Infos Relatório'!$B$2,'Faturamento SP3'!$E$2:$E$692,'Infos Relatório'!$B14,'Faturamento SP3'!$Z$2:$Z$692,'Infos Relatório'!AY$1) -> 0 | BA14: =SUMIFS('Faturamento SP3'!$J$2:$J$692,'Faturamento SP3'!$D$2:$D$692,'Infos Relatório'!$B$2,'Faturamento SP3'!$E$2:$E$692,'Infos Relatório'!$B14,'Faturamento SP3'!$Z$2:$Z$692,'Infos Relatório'!AY$1) -> 0 | BB14: =SUMIFS('Faturamento SP3'!$O$2:$O$692,'Faturamento SP3'!$D$2:$D$692,'Infos Relatório'!$B$2,'Faturamento SP3'!$E$2:$E$692,'Infos Relatório'!$B14,'Faturamento SP3'!$Z$2:$Z$692,'Infos Relatório'!AY$1,'Faturamento SP3'!$T$2:$T$692,"Sim")+SUMIFS('Faturamento SP3'!$P$2:$P$692,'Faturamento SP3'!$D$2:$D$692,'Infos Relatório'!$B$2,'Faturamento SP3'!$E$2:$E$692,'Infos Relatório'!$B14,'Faturamento SP3'!$Z$2:$Z$692,'Infos Relatório'!AY$1,'Faturamento SP3'!$T$2:$T$692,"Sim") -> 0 | BC14: =BB14/BA14 -> #DIV/0! | BD14: =SUMIFS('Faturamento SP3'!$H$2:$H$692,'Faturamento SP3'!$D$2:$D$692,'Infos Relatório'!$B$2,'Faturamento SP3'!$E$2:$E$692,'Infos Relatório'!$B14,'Faturamento SP3'!$Z$2:$Z$692,'Infos Relatório'!AY$1) -> 0 | BE14: =COUNTIFS('Faturamento SP3'!$D$2:$D$692,'Infos Relatório'!$B$2,'Faturamento SP3'!$E$2:$E$692,'Infos Relatório'!$B14,'Faturamento SP3'!$Z$2:$Z$692,'Infos Relatório'!BE$1) -> 0 | BF14: =SUMIFS('Faturamento SP3'!$G$2:$G$692,'Faturamento SP3'!$D$2:$D$692,'Infos Relatório'!$B$2,'Faturamento SP3'!$E$2:$E$692,'Infos Relatório'!$B14,'Faturamento SP3'!$Z$2:$Z$692,'Infos Relatório'!BE$1) -> 0 | BG14: =SUMIFS('Faturamento SP3'!$J$2:$J$692,'Faturamento SP3'!$D$2:$D$692,'Infos Relatório'!$B$2,'Faturamento SP3'!$E$2:$E$692,'Infos Relatório'!$B14,'Faturamento SP3'!$Z$2:$Z$692,'Infos Relatório'!BE$1) -> 0 | BH14: =SUMIFS('Faturamento SP3'!$O$2:$O$692,'Faturamento SP3'!$D$2:$D$692,'Infos Relatório'!$B$2,'Faturamento SP3'!$E$2:$E$692,'Infos Relatório'!$B14,'Faturamento SP3'!$Z$2:$Z$692,'Infos Relatório'!BE$1,'Faturamento SP3'!$T$2:$T$692,"Sim")+SUMIFS('Faturamento SP3'!$P$2:$P$692,'Faturamento SP3'!$D$2:$D$692,'Infos Relatório'!$B$2,'Faturamento SP3'!$E$2:$E$692,'Infos Relatório'!$B14,'Faturamento SP3'!$Z$2:$Z$692,'Infos Relatório'!BE$1,'Faturamento SP3'!$T$2:$T$692,"Sim") -> 0 | BI14: =BH14/BG14 -> #DIV/0! | BJ14: =SUMIFS('Faturamento SP3'!$H$2:$H$692,'Faturamento SP3'!$D$2:$D$692,'Infos Relatório'!$B$2,'Faturamento SP3'!$E$2:$E$692,'Infos Relatório'!$B14,'Faturamento SP3'!$Z$2:$Z$692,'Infos Relatório'!BE$1) -> 0 | BK14: =COUNTIFS('Faturamento SP3'!$D$2:$D$692,'Infos Relatório'!$B$2,'Faturamento SP3'!$E$2:$E$692,'Infos Relatório'!$B14,'Faturamento SP3'!$Z$2:$Z$692,'Infos Relatório'!BK$1) -> 0 | BL14: =SUMIFS('Faturamento SP3'!$G$2:$G$692,'Faturamento SP3'!$D$2:$D$692,'Infos Relatório'!$B$2,'Faturamento SP3'!$E$2:$E$692,'Infos Relatório'!$B14,'Faturamento SP3'!$Z$2:$Z$692,'Infos Relatório'!BK$1) -> 0 | BM14: =SUMIFS('Faturamento SP3'!$J$2:$J$692,'Faturamento SP3'!$D$2:$D$692,'Infos Relatório'!$B$2,'Faturamento SP3'!$E$2:$E$692,'Infos Relatório'!$B14,'Faturamento SP3'!$Z$2:$Z$692,'Infos Relatório'!BK$1) -> 0 | BN14: =SUMIFS('Faturamento SP3'!$O$2:$O$692,'Faturamento SP3'!$D$2:$D$692,'Infos Relatório'!$B$2,'Faturamento SP3'!$E$2:$E$692,'Infos Relatório'!$B14,'Faturamento SP3'!$Z$2:$Z$692,'Infos Relatório'!BK$1,'Faturamento SP3'!$T$2:$T$692,"Sim")+SUMIFS('Faturamento SP3'!$P$2:$P$692,'Faturamento SP3'!$D$2:$D$692,'Infos Relatório'!$B$2,'Faturamento SP3'!$E$2:$E$692,'Infos Relatório'!$B14,'Faturamento SP3'!$Z$2:$Z$692,'Infos Relatório'!BK$1,'Faturamento SP3'!$T$2:$T$692,"Sim") -> 0 | BO14: =BN14/BM14 -> #DIV/0! | BP14: =SUMIFS('Faturamento SP3'!$H$2:$H$692,'Faturamento SP3'!$D$2:$D$692,'Infos Relatório'!$B$2,'Faturamento SP3'!$E$2:$E$692,'Infos Relatório'!$B14,'Faturamento SP3'!$Z$2:$Z$692,'Infos Relatório'!BK$1) -> 0 | BQ14: =COUNTIFS('Faturamento SP3'!$D$2:$D$692,'Infos Relatório'!$B$2,'Faturamento SP3'!$E$2:$E$692,'Infos Relatório'!$B14,'Faturamento SP3'!$Z$2:$Z$692,'Infos Relatório'!BQ$1) -> 0 | BR14: =SUMIFS('Faturamento SP3'!$G$2:$G$692,'Faturamento SP3'!$D$2:$D$692,'Infos Relatório'!$B$2,'Faturamento SP3'!$E$2:$E$692,'Infos Relatório'!$B14,'Faturamento SP3'!$Z$2:$Z$692,'Infos Relatório'!BQ$1) -> 0 | BS14: =SUMIFS('Faturamento SP3'!$J$2:$J$692,'Faturamento SP3'!$D$2:$D$692,'Infos Relatório'!$B$2,'Faturamento SP3'!$E$2:$E$692,'Infos Relatório'!$B14,'Faturamento SP3'!$Z$2:$Z$692,'Infos Relatório'!BQ$1) -> 0 | BT14: =SUMIFS('Faturamento SP3'!$O$2:$O$692,'Faturamento SP3'!$D$2:$D$692,'Infos Relatório'!$B$2,'Faturamento SP3'!$E$2:$E$692,'Infos Relatório'!$B14,'Faturamento SP3'!$Z$2:$Z$692,'Infos Relatório'!BQ$1,'Faturamento SP3'!$T$2:$T$692,"Sim")+SUMIFS('Faturamento SP3'!$P$2:$P$692,'Faturamento SP3'!$D$2:$D$692,'Infos Relatório'!$B$2,'Faturamento SP3'!$E$2:$E$692,'Infos Relatório'!$B14,'Faturamento SP3'!$Z$2:$Z$692,'Infos Relatório'!BQ$1,'Faturamento SP3'!$T$2:$T$692,"Sim") -> 0 | BU14: =BT14/BS14 -> #DIV/0! | BV14: =SUMIFS('Faturamento SP3'!$H$2:$H$692,'Faturamento SP3'!$D$2:$D$692,'Infos Relatório'!$B$2,'Faturamento SP3'!$E$2:$E$692,'Infos Relatório'!$B14,'Faturamento SP3'!$Z$2:$Z$692,'Infos Relatório'!BQ$1) -> 0
B15: Brasil Park | C15: =COUNTIFS('Faturamento SP3'!$D$2:$D$692,'Infos Relatório'!$B$2,'Faturamento SP3'!$E$2:$E$692,'Infos Relatório'!$B15,'Faturamento SP3'!$Z$2:$Z$692,'Infos Relatório'!C$1) -> 0 | D15: =SUMIFS('Faturamento SP3'!$G$2:$G$692,'Faturamento SP3'!$D$2:$D$692,'Infos Relatório'!$B$2,'Faturamento SP3'!$E$2:$E$692,'Infos Relatório'!$B15,'Faturamento SP3'!$Z$2:$Z$692,'Infos Relatório'!C$1) -> 0 | E15: =SUMIFS('Faturamento SP3'!$J$2:$J$692,'Faturamento SP3'!$D$2:$D$692,'Infos Relatório'!$B$2,'Faturamento SP3'!$E$2:$E$692,'Infos Relatório'!$B15,'Faturamento SP3'!$Z$2:$Z$692,'Infos Relatório'!C$1) -> 0 | F15: =SUMIFS('Faturamento SP3'!$O$2:$O$692,'Faturamento SP3'!$D$2:$D$692,'Infos Relatório'!$B$2,'Faturamento SP3'!$E$2:$E$692,'Infos Relatório'!$B15,'Faturamento SP3'!$Z$2:$Z$692,'Infos Relatório'!C$1,'Faturamento SP3'!$T$2:$T$692,"Sim")+SUMIFS('Faturamento SP3'!$P$2:$P$692,'Faturamento SP3'!$D$2:$D$692,'Infos Relatório'!$B$2,'Faturamento SP3'!$E$2:$E$692,'Infos Relatório'!$B15,'Faturamento SP3'!$Z$2:$Z$692,'Infos Relatório'!C$1,'Faturamento SP3'!$T$2:$T$692,"Sim") -> 0 | G15: =F15/E15 -> #DIV/0! | H15: =SUMIFS('Faturamento SP3'!$H$2:$H$692,'Faturamento SP3'!$D$2:$D$692,'Infos Relatório'!$B$2,'Faturamento SP3'!$E$2:$E$692,'Infos Relatório'!$B15,'Faturamento SP3'!$Z$2:$Z$692,'Infos Relatório'!C$1) -> 0 | I15: =COUNTIFS('Faturamento SP3'!$D$2:$D$692,'Infos Relatório'!$B$2,'Faturamento SP3'!$E$2:$E$692,'Infos Relatório'!$B15,'Faturamento SP3'!$Z$2:$Z$692,'Infos Relatório'!I$1) -> 0 | J15: =SUMIFS('Faturamento SP3'!$G$2:$G$692,'Faturamento SP3'!$D$2:$D$692,'Infos Relatório'!$B$2,'Faturamento SP3'!$E$2:$E$692,'Infos Relatório'!$B15,'Faturamento SP3'!$Z$2:$Z$692,'Infos Relatório'!I$1) -> 0 | K15: =SUMIFS('Faturamento SP3'!$J$2:$J$692,'Faturamento SP3'!$D$2:$D$692,'Infos Relatório'!$B$2,'Faturamento SP3'!$E$2:$E$692,'Infos Relatório'!$B15,'Faturamento SP3'!$Z$2:$Z$692,'Infos Relatório'!I$1) -> 0 | L15: =SUMIFS('Faturamento SP3'!$O$2:$O$692,'Faturamento SP3'!$D$2:$D$692,'Infos Relatório'!$B$2,'Faturamento SP3'!$E$2:$E$692,'Infos Relatório'!$B15,'Faturamento SP3'!$Z$2:$Z$692,'Infos Relatório'!I$1,'Faturamento SP3'!$T$2:$T$692,"Sim")+SUMIFS('Faturamento SP3'!$P$2:$P$692,'Faturamento SP3'!$D$2:$D$692,'Infos Relatório'!$B$2,'Faturamento SP3'!$E$2:$E$692,'Infos Relatório'!$B15,'Faturamento SP3'!$Z$2:$Z$692,'Infos Relatório'!I$1,'Faturamento SP3'!$T$2:$T$692,"Sim") -> 0 | M15: =L15/K15 -> #DIV/0! | N15: =SUMIFS('Faturamento SP3'!$H$2:$H$692,'Faturamento SP3'!$D$2:$D$692,'Infos Relatório'!$B$2,'Faturamento SP3'!$E$2:$E$692,'Infos Relatório'!$B15,'Faturamento SP3'!$Z$2:$Z$692,'Infos Relatório'!I$1) -> 0 | O15: =COUNTIFS('Faturamento SP3'!$D$2:$D$692,'Infos Relatório'!$B$2,'Faturamento SP3'!$E$2:$E$692,'Infos Relatório'!$B15,'Faturamento SP3'!$Z$2:$Z$692,'Infos Relatório'!O$1) -> 0 | P15: =SUMIFS('Faturamento SP3'!$G$2:$G$692,'Faturamento SP3'!$D$2:$D$692,'Infos Relatório'!$B$2,'Faturamento SP3'!$E$2:$E$692,'Infos Relatório'!$B15,'Faturamento SP3'!$Z$2:$Z$692,'Infos Relatório'!O$1) -> 0 | Q15: =SUMIFS('Faturamento SP3'!$J$2:$J$692,'Faturamento SP3'!$D$2:$D$692,'Infos Relatório'!$B$2,'Faturamento SP3'!$E$2:$E$692,'Infos Relatório'!$B15,'Faturamento SP3'!$Z$2:$Z$692,'Infos Relatório'!O$1) -> 0 | R15: =SUMIFS('Faturamento SP3'!$O$2:$O$692,'Faturamento SP3'!$D$2:$D$692,'Infos Relatório'!$B$2,'Faturamento SP3'!$E$2:$E$692,'Infos Relatório'!$B15,'Faturamento SP3'!$Z$2:$Z$692,'Infos Relatório'!O$1,'Faturamento SP3'!$T$2:$T$692,"Sim")+SUMIFS('Faturamento SP3'!$P$2:$P$692,'Faturamento SP3'!$D$2:$D$692,'Infos Relatório'!$B$2,'Faturamento SP3'!$E$2:$E$692,'Infos Relatório'!$B15,'Faturamento SP3'!$Z$2:$Z$692,'Infos Relatório'!O$1,'Faturamento SP3'!$T$2:$T$692,"Sim") -> 0 | S15: =R15/Q15 -> #DIV/0! | T15: =SUMIFS('Faturamento SP3'!$H$2:$H$692,'Faturamento SP3'!$D$2:$D$692,'Infos Relatório'!$B$2,'Faturamento SP3'!$E$2:$E$692,'Infos Relatório'!$B15,'Faturamento SP3'!$Z$2:$Z$692,'Infos Relatório'!O$1) -> 0 | U15: =COUNTIFS('Faturamento SP3'!$D$2:$D$692,'Infos Relatório'!$B$2,'Faturamento SP3'!$E$2:$E$692,'Infos Relatório'!$B15,'Faturamento SP3'!$Z$2:$Z$692,'Infos Relatório'!U$1) -> 0 | V15: =SUMIFS('Faturamento SP3'!$G$2:$G$692,'Faturamento SP3'!$D$2:$D$692,'Infos Relatório'!$B$2,'Faturamento SP3'!$E$2:$E$692,'Infos Relatório'!$B15,'Faturamento SP3'!$Z$2:$Z$692,'Infos Relatório'!U$1) -> 0 | W15: =SUMIFS('Faturamento SP3'!$J$2:$J$692,'Faturamento SP3'!$D$2:$D$692,'Infos Relatório'!$B$2,'Faturamento SP3'!$E$2:$E$692,'Infos Relatório'!$B15,'Faturamento SP3'!$Z$2:$Z$692,'Infos Relatório'!U$1) -> 0 | X15: =SUMIFS('Faturamento SP3'!$O$2:$O$692,'Faturamento SP3'!$D$2:$D$692,'Infos Relatório'!$B$2,'Faturamento SP3'!$E$2:$E$692,'Infos Relatório'!$B15,'Faturamento SP3'!$Z$2:$Z$692,'Infos Relatório'!U$1,'Faturamento SP3'!$T$2:$T$692,"Sim")+SUMIFS('Faturamento SP3'!$P$2:$P$692,'Faturamento SP3'!$D$2:$D$692,'Infos Relatório'!$B$2,'Faturamento SP3'!$E$2:$E$692,'Infos Relatório'!$B15,'Faturamento SP3'!$Z$2:$Z$692,'Infos Relatório'!U$1,'Faturamento SP3'!$T$2:$T$692,"Sim") -> 0 | Y15: =X15/W15 -> #DIV/0! | Z15: =SUMIFS('Faturamento SP3'!$H$2:$H$692,'Faturamento SP3'!$D$2:$D$692,'Infos Relatório'!$B$2,'Faturamento SP3'!$E$2:$E$692,'Infos Relatório'!$B15,'Faturamento SP3'!$Z$2:$Z$692,'Infos Relatório'!U$1) -> 0 | AA15: =COUNTIFS('Faturamento SP3'!$D$2:$D$692,'Infos Relatório'!$B$2,'Faturamento SP3'!$E$2:$E$692,'Infos Relatório'!$B15,'Faturamento SP3'!$Z$2:$Z$692,'Infos Relatório'!AA$1) -> 0 | AB15: =SUMIFS('Faturamento SP3'!$G$2:$G$692,'Faturamento SP3'!$D$2:$D$692,'Infos Relatório'!$B$2,'Faturamento SP3'!$E$2:$E$692,'Infos Relatório'!$B15,'Faturamento SP3'!$Z$2:$Z$692,'Infos Relatório'!AA$1) -> 0 | AC15: =SUMIFS('Faturamento SP3'!$J$2:$J$692,'Faturamento SP3'!$D$2:$D$692,'Infos Relatório'!$B$2,'Faturamento SP3'!$E$2:$E$692,'Infos Relatório'!$B15,'Faturamento SP3'!$Z$2:$Z$692,'Infos Relatório'!AA$1) -> 0 | AD15: =SUMIFS('Faturamento SP3'!$O$2:$O$692,'Faturamento SP3'!$D$2:$D$692,'Infos Relatório'!$B$2,'Faturamento SP3'!$E$2:$E$692,'Infos Relatório'!$B15,'Faturamento SP3'!$Z$2:$Z$692,'Infos Relatório'!AA$1,'Faturamento SP3'!$T$2:$T$692,"Sim")+SUMIFS('Faturamento SP3'!$P$2:$P$692,'Faturamento SP3'!$D$2:$D$692,'Infos Relatório'!$B$2,'Faturamento SP3'!$E$2:$E$692,'Infos Relatório'!$B15,'Faturamento SP3'!$Z$2:$Z$692,'Infos Relatório'!AA$1,'Faturamento SP3'!$T$2:$T$692,"Sim") -> 0 | AE15: =AD15/AC15 -> #DIV/0! | AF15: =SUMIFS('Faturamento SP3'!$H$2:$H$692,'Faturamento SP3'!$D$2:$D$692,'Infos Relatório'!$B$2,'Faturamento SP3'!$E$2:$E$692,'Infos Relatório'!$B15,'Faturamento SP3'!$Z$2:$Z$692,'Infos Relatório'!AA$1) -> 0 | AG15: =COUNTIFS('Faturamento SP3'!$D$2:$D$692,'Infos Relatório'!$B$2,'Faturamento SP3'!$E$2:$E$692,'Infos Relatório'!$B15,'Faturamento SP3'!$Z$2:$Z$692,'Infos Relatório'!AG$1) -> 0 | AH15: =SUMIFS('Faturamento SP3'!$G$2:$G$692,'Faturamento SP3'!$D$2:$D$692,'Infos Relatório'!$B$2,'Faturamento SP3'!$E$2:$E$692,'Infos Relatório'!$B15,'Faturamento SP3'!$Z$2:$Z$692,'Infos Relatório'!AG$1) -> 0 | AI15: =SUMIFS('Faturamento SP3'!$J$2:$J$692,'Faturamento SP3'!$D$2:$D$692,'Infos Relatório'!$B$2,'Faturamento SP3'!$E$2:$E$692,'Infos Relatório'!$B15,'Faturamento SP3'!$Z$2:$Z$692,'Infos Relatório'!AG$1) -> 0 | AJ15: =SUMIFS('Faturamento SP3'!$O$2:$O$692,'Faturamento SP3'!$D$2:$D$692,'Infos Relatório'!$B$2,'Faturamento SP3'!$E$2:$E$692,'Infos Relatório'!$B15,'Faturamento SP3'!$Z$2:$Z$692,'Infos Relatório'!AG$1,'Faturamento SP3'!$T$2:$T$692,"Sim")+SUMIFS('Faturamento SP3'!$P$2:$P$692,'Faturamento SP3'!$D$2:$D$692,'Infos Relatório'!$B$2,'Faturamento SP3'!$E$2:$E$692,'Infos Relatório'!$B15,'Faturamento SP3'!$Z$2:$Z$692,'Infos Relatório'!AG$1,'Faturamento SP3'!$T$2:$T$692,"Sim") -> 0 | AK15: =AJ15/AI15 -> #DIV/0! | AL15: =SUMIFS('Faturamento SP3'!$H$2:$H$692,'Faturamento SP3'!$D$2:$D$692,'Infos Relatório'!$B$2,'Faturamento SP3'!$E$2:$E$692,'Infos Relatório'!$B15,'Faturamento SP3'!$Z$2:$Z$692,'Infos Relatório'!AG$1) -> 0 | AM15: =COUNTIFS('Faturamento SP3'!$D$2:$D$692,'Infos Relatório'!$B$2,'Faturamento SP3'!$E$2:$E$692,'Infos Relatório'!$B15,'Faturamento SP3'!$Z$2:$Z$692,'Infos Relatório'!AM$1) -> 0 | AN15: =SUMIFS('Faturamento SP3'!$G$2:$G$692,'Faturamento SP3'!$D$2:$D$692,'Infos Relatório'!$B$2,'Faturamento SP3'!$E$2:$E$692,'Infos Relatório'!$B15,'Faturamento SP3'!$Z$2:$Z$692,'Infos Relatório'!AM$1) -> 0 | AO15: =SUMIFS('Faturamento SP3'!$J$2:$J$692,'Faturamento SP3'!$D$2:$D$692,'Infos Relatório'!$B$2,'Faturamento SP3'!$E$2:$E$692,'Infos Relatório'!$B15,'Faturamento SP3'!$Z$2:$Z$692,'Infos Relatório'!AM$1) -> 0 | AP15: =SUMIFS('Faturamento SP3'!$O$2:$O$692,'Faturamento SP3'!$D$2:$D$692,'Infos Relatório'!$B$2,'Faturamento SP3'!$E$2:$E$692,'Infos Relatório'!$B15,'Faturamento SP3'!$Z$2:$Z$692,'Infos Relatório'!AM$1,'Faturamento SP3'!$T$2:$T$692,"Sim")+SUMIFS('Faturamento SP3'!$P$2:$P$692,'Faturamento SP3'!$D$2:$D$692,'Infos Relatório'!$B$2,'Faturamento SP3'!$E$2:$E$692,'Infos Relatório'!$B15,'Faturamento SP3'!$Z$2:$Z$692,'Infos Relatório'!AM$1,'Faturamento SP3'!$T$2:$T$692,"Sim") -> 0 | AQ15: =AP15/AO15 -> #DIV/0! | AR15: =SUMIFS('Faturamento SP3'!$H$2:$H$692,'Faturamento SP3'!$D$2:$D$692,'Infos Relatório'!$B$2,'Faturamento SP3'!$E$2:$E$692,'Infos Relatório'!$B15,'Faturamento SP3'!$Z$2:$Z$692,'Infos Relatório'!AM$1) -> 0 | AS15: =COUNTIFS('Faturamento SP3'!$D$2:$D$692,'Infos Relatório'!$B$2,'Faturamento SP3'!$E$2:$E$692,'Infos Relatório'!$B15,'Faturamento SP3'!$Z$2:$Z$692,'Infos Relatório'!AS$1) -> 0 | AT15: =SUMIFS('Faturamento SP3'!$G$2:$G$692,'Faturamento SP3'!$D$2:$D$692,'Infos Relatório'!$B$2,'Faturamento SP3'!$E$2:$E$692,'Infos Relatório'!$B15,'Faturamento SP3'!$Z$2:$Z$692,'Infos Relatório'!AS$1) -> 0 | AU15: =SUMIFS('Faturamento SP3'!$J$2:$J$692,'Faturamento SP3'!$D$2:$D$692,'Infos Relatório'!$B$2,'Faturamento SP3'!$E$2:$E$692,'Infos Relatório'!$B15,'Faturamento SP3'!$Z$2:$Z$692,'Infos Relatório'!AS$1) -> 0 | AV15: =SUMIFS('Faturamento SP3'!$O$2:$O$692,'Faturamento SP3'!$D$2:$D$692,'Infos Relatório'!$B$2,'Faturamento SP3'!$E$2:$E$692,'Infos Relatório'!$B15,'Faturamento SP3'!$Z$2:$Z$692,'Infos Relatório'!AS$1,'Faturamento SP3'!$T$2:$T$692,"Sim")+SUMIFS('Faturamento SP3'!$P$2:$P$692,'Faturamento SP3'!$D$2:$D$692,'Infos Relatório'!$B$2,'Faturamento SP3'!$E$2:$E$692,'Infos Relatório'!$B15,'Faturamento SP3'!$Z$2:$Z$692,'Infos Relatório'!AS$1,'Faturamento SP3'!$T$2:$T$692,"Sim") -> 0 | AW15: =AV15/AU15 -> #DIV/0! | AX15: =SUMIFS('Faturamento SP3'!$H$2:$H$692,'Faturamento SP3'!$D$2:$D$692,'Infos Relatório'!$B$2,'Faturamento SP3'!$E$2:$E$692,'Infos Relatório'!$B15,'Faturamento SP3'!$Z$2:$Z$692,'Infos Relatório'!AS$1) -> 0 | AY15: =COUNTIFS('Faturamento SP3'!$D$2:$D$692,'Infos Relatório'!$B$2,'Faturamento SP3'!$E$2:$E$692,'Infos Relatório'!$B15,'Faturamento SP3'!$Z$2:$Z$692,'Infos Relatório'!AY$1) -> 0 | AZ15: =SUMIFS('Faturamento SP3'!$G$2:$G$692,'Faturamento SP3'!$D$2:$D$692,'Infos Relatório'!$B$2,'Faturamento SP3'!$E$2:$E$692,'Infos Relatório'!$B15,'Faturamento SP3'!$Z$2:$Z$692,'Infos Relatório'!AY$1) -> 0 | BA15: =SUMIFS('Faturamento SP3'!$J$2:$J$692,'Faturamento SP3'!$D$2:$D$692,'Infos Relatório'!$B$2,'Faturamento SP3'!$E$2:$E$692,'Infos Relatório'!$B15,'Faturamento SP3'!$Z$2:$Z$692,'Infos Relatório'!AY$1) -> 0 | BB15: =SUMIFS('Faturamento SP3'!$O$2:$O$692,'Faturamento SP3'!$D$2:$D$692,'Infos Relatório'!$B$2,'Faturamento SP3'!$E$2:$E$692,'Infos Relatório'!$B15,'Faturamento SP3'!$Z$2:$Z$692,'Infos Relatório'!AY$1,'Faturamento SP3'!$T$2:$T$692,"Sim")+SUMIFS('Faturamento SP3'!$P$2:$P$692,'Faturamento SP3'!$D$2:$D$692,'Infos Relatório'!$B$2,'Faturamento SP3'!$E$2:$E$692,'Infos Relatório'!$B15,'Faturamento SP3'!$Z$2:$Z$692,'Infos Relatório'!AY$1,'Faturamento SP3'!$T$2:$T$692,"Sim") -> 0 | BC15: =BB15/BA15 -> #DIV/0! | BD15: =SUMIFS('Faturamento SP3'!$H$2:$H$692,'Faturamento SP3'!$D$2:$D$692,'Infos Relatório'!$B$2,'Faturamento SP3'!$E$2:$E$692,'Infos Relatório'!$B15,'Faturamento SP3'!$Z$2:$Z$692,'Infos Relatório'!AY$1) -> 0 | BE15: =COUNTIFS('Faturamento SP3'!$D$2:$D$692,'Infos Relatório'!$B$2,'Faturamento SP3'!$E$2:$E$692,'Infos Relatório'!$B15,'Faturamento SP3'!$Z$2:$Z$692,'Infos Relatório'!BE$1) -> 0 | BF15: =SUMIFS('Faturamento SP3'!$G$2:$G$692,'Faturamento SP3'!$D$2:$D$692,'Infos Relatório'!$B$2,'Faturamento SP3'!$E$2:$E$692,'Infos Relatório'!$B15,'Faturamento SP3'!$Z$2:$Z$692,'Infos Relatório'!BE$1) -> 0 | BG15: =SUMIFS('Faturamento SP3'!$J$2:$J$692,'Faturamento SP3'!$D$2:$D$692,'Infos Relatório'!$B$2,'Faturamento SP3'!$E$2:$E$692,'Infos Relatório'!$B15,'Faturamento SP3'!$Z$2:$Z$692,'Infos Relatório'!BE$1) -> 0 | BH15: =SUMIFS('Faturamento SP3'!$O$2:$O$692,'Faturamento SP3'!$D$2:$D$692,'Infos Relatório'!$B$2,'Faturamento SP3'!$E$2:$E$692,'Infos Relatório'!$B15,'Faturamento SP3'!$Z$2:$Z$692,'Infos Relatório'!BE$1,'Faturamento SP3'!$T$2:$T$692,"Sim")+SUMIFS('Faturamento SP3'!$P$2:$P$692,'Faturamento SP3'!$D$2:$D$692,'Infos Relatório'!$B$2,'Faturamento SP3'!$E$2:$E$692,'Infos Relatório'!$B15,'Faturamento SP3'!$Z$2:$Z$692,'Infos Relatório'!BE$1,'Faturamento SP3'!$T$2:$T$692,"Sim") -> 0 | BI15: =BH15/BG15 -> #DIV/0! | BJ15: =SUMIFS('Faturamento SP3'!$H$2:$H$692,'Faturamento SP3'!$D$2:$D$692,'Infos Relatório'!$B$2,'Faturamento SP3'!$E$2:$E$692,'Infos Relatório'!$B15,'Faturamento SP3'!$Z$2:$Z$692,'Infos Relatório'!BE$1) -> 0 | BK15: =COUNTIFS('Faturamento SP3'!$D$2:$D$692,'Infos Relatório'!$B$2,'Faturamento SP3'!$E$2:$E$692,'Infos Relatório'!$B15,'Faturamento SP3'!$Z$2:$Z$692,'Infos Relatório'!BK$1) -> 0 | BL15: =SUMIFS('Faturamento SP3'!$G$2:$G$692,'Faturamento SP3'!$D$2:$D$692,'Infos Relatório'!$B$2,'Faturamento SP3'!$E$2:$E$692,'Infos Relatório'!$B15,'Faturamento SP3'!$Z$2:$Z$692,'Infos Relatório'!BK$1) -> 0 | BM15: =SUMIFS('Faturamento SP3'!$J$2:$J$692,'Faturamento SP3'!$D$2:$D$692,'Infos Relatório'!$B$2,'Faturamento SP3'!$E$2:$E$692,'Infos Relatório'!$B15,'Faturamento SP3'!$Z$2:$Z$692,'Infos Relatório'!BK$1) -> 0 | BN15: =SUMIFS('Faturamento SP3'!$O$2:$O$692,'Faturamento SP3'!$D$2:$D$692,'Infos Relatório'!$B$2,'Faturamento SP3'!$E$2:$E$692,'Infos Relatório'!$B15,'Faturamento SP3'!$Z$2:$Z$692,'Infos Relatório'!BK$1,'Faturamento SP3'!$T$2:$T$692,"Sim")+SUMIFS('Faturamento SP3'!$P$2:$P$692,'Faturamento SP3'!$D$2:$D$692,'Infos Relatório'!$B$2,'Faturamento SP3'!$E$2:$E$692,'Infos Relatório'!$B15,'Faturamento SP3'!$Z$2:$Z$692,'Infos Relatório'!BK$1,'Faturamento SP3'!$T$2:$T$692,"Sim") -> 0 | BO15: =BN15/BM15 -> #DIV/0! | BP15: =SUMIFS('Faturamento SP3'!$H$2:$H$692,'Faturamento SP3'!$D$2:$D$692,'Infos Relatório'!$B$2,'Faturamento SP3'!$E$2:$E$692,'Infos Relatório'!$B15,'Faturamento SP3'!$Z$2:$Z$692,'Infos Relatório'!BK$1) -> 0 | BQ15: =COUNTIFS('Faturamento SP3'!$D$2:$D$692,'Infos Relatório'!$B$2,'Faturamento SP3'!$E$2:$E$692,'Infos Relatório'!$B15,'Faturamento SP3'!$Z$2:$Z$692,'Infos Relatório'!BQ$1) -> 0 | BR15: =SUMIFS('Faturamento SP3'!$G$2:$G$692,'Faturamento SP3'!$D$2:$D$692,'Infos Relatório'!$B$2,'Faturamento SP3'!$E$2:$E$692,'Infos Relatório'!$B15,'Faturamento SP3'!$Z$2:$Z$692,'Infos Relatório'!BQ$1) -> 0 | BS15: =SUMIFS('Faturamento SP3'!$J$2:$J$692,'Faturamento SP3'!$D$2:$D$692,'Infos Relatório'!$B$2,'Faturamento SP3'!$E$2:$E$692,'Infos Relatório'!$B15,'Faturamento SP3'!$Z$2:$Z$692,'Infos Relatório'!BQ$1) -> 0 | BT15: =SUMIFS('Faturamento SP3'!$O$2:$O$692,'Faturamento SP3'!$D$2:$D$692,'Infos Relatório'!$B$2,'Faturamento SP3'!$E$2:$E$692,'Infos Relatório'!$B15,'Faturamento SP3'!$Z$2:$Z$692,'Infos Relatório'!BQ$1,'Faturamento SP3'!$T$2:$T$692,"Sim")+SUMIFS('Faturamento SP3'!$P$2:$P$692,'Faturamento SP3'!$D$2:$D$692,'Infos Relatório'!$B$2,'Faturamento SP3'!$E$2:$E$692,'Infos Relatório'!$B15,'Faturamento SP3'!$Z$2:$Z$692,'Infos Relatório'!BQ$1,'Faturamento SP3'!$T$2:$T$692,"Sim") -> 0 | BU15: =BT15/BS15 -> #DIV/0! | BV15: =SUMIFS('Faturamento SP3'!$H$2:$H$692,'Faturamento SP3'!$D$2:$D$692,'Infos Relatório'!$B$2,'Faturamento SP3'!$E$2:$E$692,'Infos Relatório'!$B15,'Faturamento SP3'!$Z$2:$Z$692,'Infos Relatório'!BQ$1) -> 0
